{
  "resume_id": "R0005",
  "content": "BEHAVIORAL HEALTHCARE HELP LINE AND PSYCHIATRIC EMERGENCY TEAM SUPERVISOR\nProfessional Overview\nSeasoned Licensed Clinical Social Worker dedicated to providing high quality, compassionate, and effective care in role of psychotherapist,\neducator, and manager.\nLicense\nLCS 18224\u00c2 \u00c2 \u00c2 \u00c2 \u00c2 \u00c2 \u00c2 \u00c2 \u00c2 \u00c2 \u00c2 \u00c2 \u00c2 \u00c2 \u00c2 \u00c2 \u00c2 \u00c2 \u00c2 \u00c2 \u00c2 \u00c2 \u00c2 \u00c2 \u00c2 \u00c2 \u00c2 \u00c2 \u00c2 \u00c2 \u00c2 \u00c2 \u00c2 \u00c2 \u00c2 \u00c2 \u00c2 \u00c2 \u00c2 \u00c2 \nCore Qualifications\nClinical acumen\nMulticuturally competent psychotherapist\nClinical supervision\nClient-centered care\nQuality care focused\nService oriented\nCommitted to personal and professional growth\nStrength based management style\nProgram development, design,\u00c2 training\nQuality review and process improvement\nRapport building\nContract, Criminal, Tort, Probate\u00c2 law familiarity\u00c2 \u00c2 \nEducation\nGlendale College of Law\n \nCity\n \n, \nState\nUniversity of Southern California\n \nCity\n \n, \nState\n \nMaster of Social Work\nGraduated with honors\nCalifornia State University, Northridge\n \nCity\n \n, \nState\n \nBachelor of Arts\n \n: \nPsychology\nGraduated with honors, member of Psi Chi, Golden Key National Honor Society, Tau Alpha Epsilon Honor Society\nAccomplishments\nClinical\nEstablished and operated private practice for 10 years\nDocumentation\nDocumentation Influenced creation, design, and reporting fields of patient charting system\nCreated, implemented system of documentation that resulted in 95% quality assurance scores for several consecutive years\nQuality\nStandardized chart documentation\nDeveloped telephonic, documentation, performance\u00c2 indicators\n?Training\nWrote training manual and organized resource material\nDeveloped curriculum, taught, and modeled desired skill/outcome\nProvided electronic medical record navigation and documentation training ?\n\u00c2 Marketing\nIncreased referrals via Physician Liaison Program, Elder Law attorneys, primary care physicians, psychiatry and addiction medicine\nproviders, law enforcement, EAP providers, community\nWorkflow Planning\nImplemented new work processes\u00c2 which increased efficiencies and productivity\nComputer Skills\nProficient: Epic, Word, Lotus, Interqual, NICE, Symposium, Foundations, AZZ cardfile\nFamiliar: Excel, PowerPoint, Visio\nExperience\n07/2002\n \n- \nCurrent\nCompany Name\n \n- \nCity\n \n, \nState\n \nBehavioral Healthcare Help Line and Psychiatric Emergency Team Supervisor\nClinical supervisor of\u00c2 24/7/365 psychiatric\u00c2 crisis call center\u00c2 and\u00c2 psychiatric emergency team; interim supervisor to Utilization Management\nand Bed Finding departments within a large\u00c2 care coordination center; hired, counseled, terminated staff; recorded, tracked,\ndeveloped\u00c2 performance indicators and performance\u00c2 criteria for evaluations; wrote and updated protocols,\u00c2 policy and procedures, quality\nreview indicators, training manual, meeting minutes, business\u00c2 reports; influenced development and re-design\u00c2 of electronic charting and reporting\nfields; organized and led new hire, clinical,\u00c2 Frequent Caller, computer, staff meetings/trainings, and\u00c2 holiday, retirement, Social Work\nMonth\u00c2 celebrations;\u00c2 performed web-based\u00c2 in-service work stoppage\u00c2 training to\u00c2 physicians, managers\u00c2 and successfully staffed\nthe\u00c2 crisis line for 48 consecutive\u00c2 hours with no abandoned calls;\u00c2 developed Frequent Caller treatment plan template for coordination and\ncontinuity of care; participated and presented\u00c2 statistical data\u00c2 at\u00c2 regional Department Administrators and regional Southern California Quality\nAssurance meetings; implemented interdepartmental cross training which increased efficiencies, productivity, staff development, and morale;\nrecorded, tracked, ensured\u00c2 staff\u00c2 license renewals, CEUs, mandated\u00c2 organizational classes were completed by due dates; completed bi-\nmonthly payroll and managed all leaves; completed staff scheduling every 6 weeks; decreased tardiness; responded to all IT concerns; reviewed,\nresearched, responded to all critical incidents and complaints; developed work flows that decreased time members spent in non-plan EDs\u00c2 with\nattention to high quality\u00c2 care and cost containment; answered crisis calls when short staffed; and,\u00c2 shared on-call responsibilities.\n03/1998\n \n- \n07/2002\nCompany Name\n \n- \nCity\n \n, \nState\n \nLicensed Clinical Social Worker/Care Coordinator\nPerformed biopsychosocial telephonic assessments, crisis intervention,\u00c2 and/or consultation for members, employees, purchaser groups,\nEmployee Assistance Professionals, \nmanagement, law enforcement, and emergency department physicians; determined appropriate levels of care;\nrepatriated or case managed\u00c2 members in non-plan hospitals; advocated for members needing psychiatric and/or addiction medicine\ntreatment;\u00c2 care coordinated with the member's treatment team; trained new staff;\u00c2 worked collaboratively on interdepartmental team and\ndeveloped work flows, procedures, and protocols that\u00c2 increased efficiencies, productivity, role clarity; developed documentation\nstandards;\u00c2 influenced the creation and development\u00c2 of departmental electronic database for charting case notes.\n04/1996\n \n- \n03/1998\nCompany Name\n ",
  "enriched_profile": {
    "fullName": "Seasoned Licensed Clinical Social Worker",
    "email": "",
    "phone": "",
    "location": "",
    "linkedin": "",
    "github": "",
    "portfolio": "",
    "summary": "Seasoned Licensed Clinical Social Worker dedicated to providing high quality, compassionate, and effective care in role of psychotherapist, educator, and manager.",
    "education": [
      {
        "school": "Glendale College of Law",
        "degree": "",
        "field": "",
        "startDate": "",
        "endDate": "",
        "gpa": ""
      },
      {
        "school": "University of Southern California",
        "degree": "Master of Social Work",
        "field": "",
        "startDate": "",
        "endDate": "",
        "gpa": ""
      },
      {
        "school": "California State University, Northridge",
        "degree": "Bachelor of Arts",
        "field": "Psychology",
        "startDate": "",
        "endDate": "",
        "gpa": ""
      }
    ],
    "experience": [
      {
        "company": "Behavioral Healthcare Help Line and Psychiatric Emergency Team",
        "position": "Supervisor",
        "startDate": "07/2002",
        "endDate": "Present",
        "description": "Clinical supervisor of 24/7/365 psychiatric crisis call center and psychiatric emergency team; interim supervisor to Utilization Management and Bed Finding departments within a large care coordination center; hired, counseled, terminated staff; recorded, tracked, developed performance indicators and performance criteria for evaluations; wrote and updated protocols, policy and procedures, quality review indicators, training manual, meeting minutes, business reports; influenced development and re-design of electronic charting and reporting fields; organized and led new hire, clinical, Frequent Caller, computer, staff meetings/trainings, and holiday, retirement, Social Work Month celebrations; performed web-based in-service work stoppage training to physicians, managers and successfully staffed the crisis line for 48 consecutive hours with no abandoned calls; developed Frequent Caller treatment plan template for coordination and continuity of care; participated and presented statistical data at regional Department Administrators and regional Southern California Quality Assurance meetings; implemented interdepartmental cross training which increased efficiencies, productivity, staff development, and morale; recorded, tracked, ensured staff license renewals, CEUs, mandated organizational classes were completed by due dates; completed bi-monthly payroll and managed all leaves; completed staff scheduling every 6 weeks; decreased tardiness; responded to all IT concerns; reviewed, researched, responded to all critical incidents and complaints; developed work flows that decreased time members spent in non-plan EDs with attention to high quality care and cost containment; answered crisis calls when short staffed; and, shared on-call responsibilities."
      },
      {
        "company": "Company Name",
        "position": "Licensed Clinical Social Worker/Care Coordinator",
        "startDate": "03/1998",
        "endDate": "07/2002",
        "description": "Performed biopsychosocial telephonic assessments, crisis intervention, and/or consultation for members, employees, purchaser groups, Employee Assistance Professionals, management, law enforcement, and emergency department physicians; determined appropriate levels of care; repatriated or case managed members in non-plan hospitals; advocated for members needing psychiatric and/or addiction medicine treatment; care coordinated with the member's treatment team; trained new staff; worked collaboratively on interdepartmental team and developed work flows, procedures, and protocols that increased efficiencies, productivity, role clarity; developed documentation standards; influenced the creation and development of departmental electronic database for charting case notes."
      },
      {
        "company": "Senior Care Network",
        "position": "Clinical Social Worker",
        "startDate": "04/1996",
        "endDate": "03/1998",
        "description": "Field based case management for disabled adults with chronic mental illness and older adults with co-occurring disorders. Completed in-home assessments and monthly monitoring; client and family counseling, education, and community referrals. Per attorney request, evaluated, wrote report, testified in court (became expert witness) for probate conservatorship hearings; marketed and managed the Physician Liaison program; lead weekly Caregiver support group; underwrote long-term care insurance assessments and benefit determination evaluations; became community resource specialist."
      },
      {
        "company": "Behavioral Science Faculty, Family Practice Residency Program",
        "position": "Social Work Associate",
        "startDate": "05/1992",
        "endDate": "08/1996",
        "description": "Social Work Associate in community medical clinic; interviewed prospective residents; developed curriculum, taught, and evaluated performance of Family Practice residents and medical students on the Substance Abuse and Psychiatry rotations; conducted lectures, presentations in class, 'Brown Bag lunches,' and off-site meetings; set up internal and external training sites and ensured learning objectives were met; education was focused on risk, substance abuse, and biopsychosocial assessments, active listening, interviewing skills, DSM diagnoses while on rounds, during home visits, and co-led therapy sessions; instilled confidence by demonstrating attunement to patient and self, assessment, treatment planning, rapport building skills, and provided after visit summarization/feedback; strengthened teamwork and resident and faculty relationships by incorporating team building activities into staff meetings; liaison to residents who needed psychiatric or health services; provided short/long term individual, couple, family therapy on complicated cases and provided feedback to the resident; and was a preceptor to other MSW students."
      },
      {
        "company": "Psychotherapist",
        "position": "",
        "startDate": "10/1991",
        "endDate": "10/2001",
        "description": "Individual, couple, family therapy with children, adolescents, adults, and older adults. Presenting problems were: depression, anxiety, panic attacks, insomnia, psychosis, explosive rage, adoption, foster care, grief and loss, truancy, trauma, self harm, substance abuse/addiction, gender dysphoria, domestic violence, homelessness, parenting concerns, care giver burn-out, and school/work stress. Clientele: ethnically, culturally, racially, and socioeconomically diverse."
      },
      {
        "company": "Employee Assistance Program/Mental Health Center",
        "position": "MSW Intern/Social Work Associate",
        "startDate": "10/1990",
        "endDate": "10/1991",
        "description": "Consultation provided to managers, employees, Human Resources regarding work place problems; Crisis Intervention, short and long-term therapy provided to contract and company employees, their families, and the community; taught series of classes on Stress Management and Memory Retention. Featured speaker at a 'Drugs in the Workplace' seminar; and taught substance abuse related classes and lead couples group therapy with addicts and co-addicts in an outpatient chemical dependency recovery program. Clientele: racially, ethnically, culturally, and socioeconomically diverse."
      },
      {
        "company": "Company Name",
        "position": "MSW Intern",
        "startDate": ""
      }
    ],
    "projects": [],
    "skills": [],
    "licenses": []
  }
}