{
  "resume_id": "R0007",
  "content": "CHIEF EXECUTIVE OFFICER\nSummary\nAward-winning executive and marketing professional experienced in high-volume, multi-unit, retail and business operations in the pharmaceutical,\nfinancial services, and food and beverage industries. Demonstrated expertise in brand development, territory management, sales operations,\nproduct launches, recruiting, and business development. Skilled in utilizing technology as a tool to improve organizational efficiency. Desires a high-\nlevel marketing position in a professional corporate environment.\nHighlights\nBrand Development\nProject Management\nRelationship Management\nTraining & Development\nSales Operations\nMerchandising\nAccomplishments\nIncreased annual sales to nearly $5.7 million through strategic marketing & sales campaigns.\nLaunched aggressive growth plans that helped increase customer base from 0 to 15,000 customers.\nCreated strategies to develop and expand existing customer sales, which resulted in a 200% sales growth in less than 12 months.\nGrew a targeted newsletter subscriber list from 0 to 6,000 members in just 12 months.\nEarned the Winner's Circle Award in 2008.\nExperience\n10/2008\n \nto \nCurrent\nChief Executive Officer\n \nCompany Name\n \n\u00ef\u00bc\u200b \nCity\n \n, \nState\nDeveloped and launched Greenie Tots ,a full-line of children's entrees, currently sold in mass retail including Whole Foods, Giant Eagle,\nSafeway , and independent grocery stores across the United States.\nHeaded online/retail marketing campaigns to drive traffic and business to our online website and into our retail stores.\nHired & trained all new brand ambassadors that marketed and sold the Greenie Tots brand to consumers & retail outlets.\nManaged production setup and distribution with the largest national natural products distributer UNFI.\nDeveloped company wide incentive performance plan which motivated staff and resulted in a 70% increase in sales.\nRolled out integrated advertising campaign across multiple media channels\nIncreased profits by 60% in one year through restructure of business line.\n08/2003\n \nto \n03/2013\nHealthcare Management Representative 2\n \nCompany Name\n \n\u00ef\u00bc\u200b \nCity\n \n, \nState\nResponsible for a portfolio of billion dollar revenue medications including Lipitor\u00c2\u00ae, Viagra\u00c2\u00ae, Celebrex\u00c2\u00ae, Lyrica\u00c2\u00ae, Chantix\u00c2\u00ae,\nToviaz\u00c2\u00ae, and Premarin\u00c2\u00ae to increase market base and change physician prescribing habits.\nIncreased sales in Fort Lauderdale, FL \nterritory by 67% reaching territory sales of $5.7 million\nDeveloped and maintained networks/partnerships with external partners such as physicians, hospitals, community advocacy groups,\npharmacies, and corporate employers.\nAssisted District Manager with the development and leadership for district strategy for product launches, sales initiatives, and team\nmotivational activities.\nDeveloped strategic pharmacy initiatives to foster customer relationships and positive formulary acceptance.\nSuccessfully launched Toviaz\u00c2\u00ae , Lyrica\u00c2\u00ae, & Exubera\u00c2\u00ae by prospecting, tar.\n01/2002\n \nto \n08/2002\nNational Healthcare Operations Intern\n \nCompany Name\n \n\u00ef\u00bc\u200b \nCity\n \n, \nState\nDeveloped and maintained monthly expense budget reports for entire Managed Care sales force (NHO) \nto evaluate budget spending &\nallocation of resources.\nUtilized Sherlock NHO software to analyze formulary status for the Cluster and created reports to emphasize formulary growth & decline.\nDeveloped & spearheaded a community health fair targeted at the Hispanic community in Harlem, NY to educate indigent patients on\nimproving their health.\nCollaborated with external partners including City of New York, Veritas, Local churches, & Media (Radio, Newspaper, &Television).\nSpearheaded the design, development, and implementation of branding the Manage Care division of Pfizer by developing a logo that\nrepresented the team.\nManaged outside advertising agency and directed internal focus panels to insure the logo represented the cluster\n05/2001\n \nto \n08/2001\nFinance Intern\n \nCompany Name\n \n\u00ef\u00bc\u200b \nCity\n \n, \nState\nMaintained partnerships with external customers such as school institutions, businesses, and Bank of America customers.\nDeveloped and maintained a customer database with current, client investment positions and future investment goals.\nCreated visual tools to assist the VP in presenting to external partners.\nRecruited and trained new intern hires on the Banc of America policies and procedures.\n10/1999\n \nto \n12/2000\nCustomer Development Intern\n \nCompany Name\n \n\u00ef\u00bc\u200b \nCity\n \n, \nState\nAnalyzed and developed industry reports using Information Resources Inc, for the Marketing and Sales department to track current product\nsales against previous sales performance.\nDeveloped a database system to track the positioning and sales of the newly launched product Rick's Spiked Lemonade.\nDesigned a tool to measure performance against competitive products in the categories of Wine Coolers, Beer, and Mixers.\nDeveloped presentations and presented to the marketing and sales VP's \nthe areas were our products could be better positioned in the ret",
  "enriched_profile": {
    "fullName": "Chief Executive Officer",
    "email": "",
    "phone": "",
    "location": "City, State",
    "linkedin": "",
    "github": "",
    "portfolio": "",
    "summary": "Award-winning executive with expertise in brand development, project management, relationship management, training & development, and sales operations. Increased annual sales to $5.7M through strategic marketing & sales campaigns. Grew customer base from 0 to 15,000 and expanded existing customer sales by 200% in less than 12 months. Earned the Winner's Circle Award in 2008.",
    "education": [
      {
        "school": "Florida A&M University",
        "degree": "MBA",
        "field": "Business Administration",
        "startDate": "August 2003",
        "endDate": "",
        "gpa": ""
      },
      {
        "school": "Florida A&M University",
        "degree": "BS",
        "field": "Business Administration",
        "startDate": "August 2003",
        "endDate": "",
        "gpa": ""
      }
    ],
    "experience": [
      {
        "company": "Company Name",
        "position": "Chief Executive Officer",
        "startDate": "10/2008",
        "endDate": "Current",
        "description": "Developed and launched Greenie Tots, a full-line of children's entrees. Headed online/retail marketing campaigns to drive traffic and business. Hired and trained all new brand ambassadors. Managed production setup and distribution with UNFI. Developed company-wide incentive performance plan. Rolled out integrated advertising campaign across multiple media channels. Increased profits by 60% in one year through restructure of business line."
      },
      {
        "company": "Company Name",
        "position": "Healthcare Management Representative 2",
        "startDate": "08/2003",
        "endDate": "03/2013",
        "description": "Responsible for a portfolio of billion dollar revenue medications. Increased sales in Fort Lauderdale, FL territory by 67%. Developed and maintained networks/partnerships with external partners. Assisted District Manager with the development and leadership for district strategy for product launches, sales initiatives, and team motivational activities. Developed strategic pharmacy initiatives to foster customer relationships and positive formulary acceptance. Successfully launched Toviaz\u00ae, Lyrica\u00ae, & Exubera\u00ae by prospecting."
      },
      {
        "company": "Company Name",
        "position": "National Healthcare Operations Intern",
        "startDate": "01/2002",
        "endDate": "08/2002",
        "description": "Developed and maintained monthly expense budget reports for the NHO sales force. Utilized Sherlock NHO software to analyze formulary status and create reports. Developed and spearheaded a community health fair targeted at the Hispanic community in Harlem, NY. Collaborated with external partners. Spearheaded the design, development, and implementation of branding the Managed Care division of Pfizer."
      },
      {
        "company": "Company Name",
        "position": "Finance Intern",
        "startDate": "05/2001",
        "endDate": "08/2001",
        "description": "Maintained partnerships with external customers. Developed and maintained a customer database. Created visual tools to assist in presenting to external partners. Recruited and trained new intern hires. Analyzed and developed industry reports for the Marketing and Sales department."
      },
      {
        "company": "Company Name",
        "position": "Customer Development Intern",
        "startDate": "10/1999",
        "endDate": "12/2000",
        "description": "Analyzed and developed industry reports for the Marketing and Sales department. Developed a database system to track the positioning and sales of the newly launched product. Designed a tool to measure performance against competitive products. Developed presentations and presented to marketing and sales VP's."
      }
    ],
    "projects": [],
    "skills": [
      "Microsoft Office (Excel, Power Point, and Access expertise)",
      "Internet",
      "PC/MAC software proficiency",
      "Microsoft Project",
      "Information Resources Inc",
      "Database",
      "CUE",
      "Quick Books"
    ],
    "licenses": []
  }
}