{
  "resume_id": "R0004",
  "content": "SR. ESTIMATOR-BAS CONSTRUCTION SALES\nSummary\n9+ years of professional working experience in energy solution consulting and performance contracting, HVAC estimating & designing in buildings\n& industrial sector. Experience of 3 years in project development, presenting and managing the implementation of innovative energy business\nsolutions. Working knowledge in designing & preparing energy solutions for large complex projects. Total projects worked for fiscal year 2014\nexceeds $30 million. Excellent working relationships within the different business units. Working knowledge of Variable Frequency drives, PLC\nsystems and other automations used in industry. Actively Involved in Networking Chapter in Boston area like National Association of Women In\nConstruction, Mass Building Congress, American Society for Precision Engineering Obtain a challenging position that will allow me to utilize my\neducational attainment and professional experience in Energy Engineering, Project Engineering, Building Energy Systems, Energy Conservation,\nRenewable Energy and Energy Management of residential, commercial, healthcare, data center and industrial facilities.\nAccomplishments\nAwarded as most interactive person across all business units in India by Schneider\nHoneywell's BRAVO Award for the successful commissioning of the Alarm Management Suite at IPCL, Baroda or the first time in India\nEnergy Management Professional Certified by Schneider University\nFramed out the processes and templates for new energy business unit in Schneider India\nActive Volunteer in CSR activities in Schneider for social cause\nInitiated selling of the energy conservation solutions to clients showing savings and ROI\nIndividually worked out and framed a clear- cut procedure for Installation & Commissioning of MS SQL based Alarm Management Suite\nand defined the procedure for healthy communication of Alarm Management Suite with Honeywell Systems & various Third Party DCS /\nPLC's\nExperience\nSr. Estimator-BAS Construction Sales\n \nAugust 2015\n \nto \nCurrent\n \nCompany Name\n \n\u00ef\u00bc\u200b \nCity\n \n, \nState\n- 01810, USA \u00e2\u017e\u00a2 Key responsible person for designing & estimating of HVAC proposals on Studio 360 related to capital construction and\nrenovation projects ($40M estimation volume YtD) by supporting Sales team and validating the proposals with operations teams \u00e2\u017e\u00a2 Generate an\naverage of $2M estimate per month for Building-Construction business \u00e2\u017e\u00a2 Responsible for negotiating with sub-contractors and vendors to\nensure accurate scope and cost projections. \u00e2\u017e\u00a2 Qualify engineering drawings & specifications. \u00e2\u017e\u00a2 Working with the operations team to validate\nproposed solutions and to develop Branch Estimate Library on Studio 360 \u00e2\u017e\u00a2 Produce accurate & through takeoffs, including pricing of work\nProject Engineer\n \nCompany Name\n \n\u00ef\u00bc\u200b \nCity\n \n, \nState\n \n56&57, Hadapsar Industrial Estate, Pune- 411 013, India \u00e2\u017e\u00a2 Responsible for Project Planning, Collection of\nUser requirements, System Design & Testing, Execution and System Maintenance. \u00e2\u017e\u00a2 Worked as Project engineering After Marketing Service\nGroup for projects involving Dual redundant and single system of Honeywell's DCS & PLC based control system for various process industries.\n\u00e2\u017e\u00a2 Responsible for design, Development and Testing of DCS, PLC, and SCADA programs for the Honeywell Systems. \u00e2\u017e\u00a2 Responsible for\nInstallation, Configuring and Maintenance of Real time Servers and Networking under Windows.\nSales Engineer\n \nCompany Name\n \n, Phase II, Gurgaon -122002, Haryana, India \u00e2\u017e\u00a2 Worked on energy performance contracts and energy proposals worth more\nthan 40 million dollars for various facilities including hospital, correctional facilities, office buildings, colleges, IT/ITES buildings, commercial\nbuildings, retail sector and industrial facilities. \u00e2\u017e\u00a2 Prepared energy solutions for more than 50 projects and surveyed almost 40 projects for\npreliminary & detailed energy assessment for identifying energy conservation measures (ECMS). \u00e2\u017e\u00a2 Prepared and helped the implementation\nteam in execution of Performance Contracting projects of values almost 5 million dollar. \u00e2\u017e\u00a2 Key responsible person for identifying, designing &\nimplementation of Energy Conservation Measures across 20 identified Schneider Offices in India. \u00e2\u017e\u00a2 Supported BD/Sales and energy auditors for\nsolution designing and development of standard energy conservation solutions for building & industrial sector. \u00e2\u017e\u00a2 Main responsibilities includes\nidentify the energy conservation measures, development of the detailed scope of work for each measures, walkthrough with vendors and\nsubcontractor to price each measures, preparation of the estimated costing and contract documents, preparation of the sequence of operation for\nthe retrofit equipment, review of all the submittals documents, provide technical assistance during the construction phase, commission of the system\nand measurement and verification of each measures. Siemens Building Technologies Pvt. Ltd., 49, Eldams Road, Teynampet, Chenn",
  "enriched_profile": {
    "fullName": "John Doe",
    "email": "",
    "phone": "",
    "location": "Boston area, USA",
    "linkedin": "",
    "github": "",
    "portfolio": "",
    "summary": "9+ years of professional experience in energy solution consulting, HVAC estimating & designing in buildings and industrial sector. Proven track record in project development, presenting and managing the implementation of innovative energy business solutions. Expertise in designing energy solutions for large complex projects. Strong relationships within various business units and working knowledge of automation systems.",
    "education": [
      {
        "school": "Maharishi Markendeshwar Engineering College",
        "degree": "Bachelor of Instrumentation Engineering",
        "field": "Instrumentation Engineering",
        "startDate": "2002-05-09",
        "endDate": "2006-07-21",
        "gpa": ""
      }
    ],
    "experience": [
      {
        "company": "Company Name",
        "position": "Sr. Estimator-BAS Construction Sales",
        "startDate": "2015-08",
        "endDate": "",
        "description": "Key responsible person for designing & estimating of HVAC proposals on Studio 360 related to capital construction and renovation projects. Generate an average of $2M estimate per month for Building-Construction business. Responsible for negotiating with sub-contractors and vendors to ensure accurate scope and cost projections."
      },
      {
        "company": "Company Name",
        "position": "Project Engineer",
        "startDate": "",
        "endDate": "",
        "description": "Responsible for Project Planning, Collection of User requirements, System Design & Testing, Execution and System Maintenance. Worked on Honeywell's DCS & PLC based control system for various process industries."
      },
      {
        "company": "Company Name",
        "position": "Sales Engineer",
        "startDate": "",
        "endDate": "",
        "description": "Worked on energy performance contracts and energy proposals worth more than 40 million dollars for various facilities. Prepared energy solutions for more than 50 projects and surveyed almost 40 projects for preliminary & detailed energy assessment for identifying energy conservation measures (ECMS)."
      }
    ],
    "projects": [
      {
        "name": "",
        "techStack": "",
        "description": "",
        "link": ""
      }
    ],
    "skills": [
      "Sales",
      "Proposals",
      "Solutions",
      "Commercial Buildings",
      "Million",
      "Sales And Contracts",
      "Ecms",
      "Energy Conservation",
      "Energy Solutions",
      "Industrial Facilities",
      "Retail",
      "Retail Marketing",
      "Retrofit",
      "Technical Assistance",
      "Instrumentation",
      "Long-term Disability",
      "Ltd",
      "Engineer",
      "Hvac",
      "Collection",
      "Maintenance",
      "Marketing",
      "Networking",
      "Project Engineer",
      "Project Planning",
      "Real Time",
      "Scada",
      "Testing",
      "Estimating",
      "Estimation",
      "Estimator",
      "Operations",
      "Pricing",
      "Sales Team",
      "Takeoffs",
      "Fire Protection",
      "Front End",
      "Quotations",
      "Relationship Building",
      "Sales Activities",
      "Sales Engineer",
      "Security",
      "Siemens",
      "Award",
      "Clients",
      "Csr",
      "Energy Management",
      "Project Development",
      "Roi",
      "Selling Of",
      "Sql"
    ],
    "licenses": [
      {
        "title": "Energy Management Professional",
        "description": "Certified by Schneider University",
        "issueDate": "",
        "expiryDate": ""
      }
    ]
  }
}