{
  "resume_id": "R0002",
  "content": "MEDIA ACTIVITIES SPECIALIST\nSummary\nMulti-Tasking \nMedia Relations \nResults-oriented\nStrategic Initiatives \nEvent Planning \nWriter & Editor\nManager/Supervisor \nFlexibility \nAdaptable\nHighlights\nGreatly improved media coverage of press\nconferences and other events on campus\nIncreased the frequency of newspaper, radio and\ntelevision interviews featuring Chattanooga State\nadministrators, faculty and staff\nHosted popular television show that focused on\ncampus and community events (1997-2004)\nCommissioned by local State Representative to produce a historical\ndocumentary on African American in the Tennessee Legislature from\nReconstruction to Modern Times (2004)\nCreated on-site Spanish language classes for Emergency Room personnel in\nlocal hospitals when Spanish speaking population began to expand in the\narea (1995)\nAccomplishments\nLed Chattanooga State to receive \nNational Awards, the \nBronze Paragon Award\n \nin \n2012\n \nfrom the National Council for Marketing and Public\nRelations (NCMPR) for \nDegrees That Work 1 & 2\n \nin the Radio/Advertisement/PSA Series category\nSilver Paragon Award \nin \n2011\n \nfrom NCMPR for \nThe Power of Achievement\n \nin the Electronic Viewbook category\nWrote and produced \n2010\n \nNCMPR District level winners, \nOnline Orientation\n \nin the Online Services category won the \nGold Medallion\n ; \nThe\nEarly College Video\n \nin theCollege Promotional Video category won the \nSilver Medallion\n ; the five commercial series,\n Thanks\n , won the\nBronze Medallion \nin the Video Advertisement/PSA Series category\nExperience\n09/2013\n \nto \nCurrent\nMedia Activities Specialist\n \nCompany Name\n \n\u00ef\u00bc\u200b \nCity\n \n, \nState\nOrganize major campus events by overseeing security, media services, food services, and marketing.\nNotable speakers in the past have included Neil de Grasse Tyson, host of Cosmos: A Spacetime Odyssey, and theoretical physicist,\nDr.Michio Kaku.\nAssisting academic departments with minor events such as conferences and speakers that require smaller venues.\nCreate videos for various departments on campus for academic and recruitment purposes.\n03/1996\n \nto \n08/2013\nMarketing Coordinator\nEngaged in strategic planning with deans and department heads to increase enrollment \nand public awareness of new academic programs\nUtilized focus groups, surveys, and other market research and analysis tools to develop strategy\nSupported branding via press releases, copy for radio and TV ads, extensive website content and print ads, brochures, fliers, posters, and\nbillboards\nManaged advertising budget for print and electronic media up to $500,000.\nProofed and edited materials for publication\nSupervised staff of seven comprised of three graphic artists, three web designers, and the office manager\nRecruited and mentored students who represented the college at special events\nWrote scripts and recruited talent for the College's radio and television commercials\nWorked with local production companies to create commercials for TV and radio\nDeveloped scripts for recruitment and instructional videos for various academic departments\nProduced a series of \"How To\" videos to guide students through the registration process for the Student Services department\nCommissioned by local state representative to produce a historical documentary on African Americans in the Tennessee Legislature\nIncreased media presence at press conferences and other campus events\nHosted television show that focused on campus and community events on cable channel dedicated to education\nIncreased the frequency of newspaper, radio and television interviews featuring administrators, faculty, and staff members\nDesignated as the contact for area journalists and served as spokesperson when needed.\n03/1994\n \nto \n03/1996\nContinuing Education Coordinator\nCreated personal interest classes that appealed to and met the needs of the community.\nRecruited instructors, organized schedule, and marketed courses.\nOrganized first Spanish language classes for ER personnel in local hospitals.\nSkills\nacademic, ads, advertising, banners, brochures, budget, conferences, special events, market research, marketing, materials, newspaper, office\nmanager, personnel, press, press releases, publication, radio, recruitment, scripts, \nstrategy, strategic planning, television, website content\nProfessional Affiliations\nNational Council for Marketing and Public Relations (NCMPR)\nTennessee College Public Relations Association (TCPRA)\nLookout Chapter of the Public Relations Society of America American (PRSA)\nAdvertising Federation Chattanooga (Ad Fed)\nTennessee Screenwriters Association\nEducation\n1994\nMaster of Arts\n \n: \nRadio, Television & Motion Pictures\n \nUniversity of North Carolina\n \n\u00ef\u00bc\u200b \nCity\n \n,\n \nState\nRadio, Television & Motion Pictures\nWriters Guild of America Internship, \nStar Trek: Deep Space 9\n , Paramount Pictures, Los Angeles California, Summer 1993\n1975\nBachelor of Arts\n \n: \nHuman Services\n \nUniversity of Tennessee\n \n\u00ef\u00bc\u200b \nCity\n \n, \nState\nHuman Services\nM\n ortar Board Senior Citation, Academic ",
  "enriched_profile": {
    "fullName": "John Doe",
    "email": "",
    "phone": "",
    "location": "City, State",
    "linkedin": "",
    "github": "",
    "portfolio": "",
    "summary": "Results-oriented Media Activities Specialist with expertise in media relations, event planning, and content creation. Proven track record of improving media coverage and public awareness of academic programs. Skilled in strategic initiatives, adaptability, and leadership.",
    "education": [
      {
        "school": "University of North Carolina",
        "degree": "Master of Arts",
        "field": "Radio, Television & Motion Pictures",
        "startDate": "1992",
        "endDate": "1994",
        "gpa": ""
      },
      {
        "school": "University of Tennessee",
        "degree": "Bachelor of Arts",
        "field": "Human Services",
        "startDate": "1971",
        "endDate": "1975",
        "gpa": ""
      }
    ],
    "experience": [
      {
        "company": "Company Name",
        "position": "Media Activities Specialist",
        "startDate": "09/2013",
        "endDate": "Present",
        "description": "Organize major campus events, oversee security, media services, food services, and marketing. Create videos for various departments on campus for academic and recruitment purposes."
      },
      {
        "company": "",
        "position": "Marketing Coordinator",
        "startDate": "03/1996",
        "endDate": "08/2013",
        "description": "Engaged in strategic planning with deans and department heads to increase enrollment and public awareness of new academic programs. Utilized market research and analysis tools to develop strategy. Managed advertising budget for print and electronic media. Proofed and edited materials for publication. Supervised staff of seven."
      }
    ],
    "projects": [
      {
        "name": "Degrees That Work 1 & 2",
        "techStack": "Radio/Advertisement/PSA Series",
        "description": "National Awards winner in the Radio/Advertisement/PSA Series category by NCMPR in 2012",
        "link": ""
      },
      {
        "name": "The Power of Achievement",
        "techStack": "Electronic Viewbook",
        "description": "Silver Paragon Award winner in the Electronic Viewbook category by NCMPR in 2011",
        "link": ""
      }
    ],
    "skills": [
      "academic",
      "ads",
      "advertising",
      "banners",
      "brochures",
      "budget",
      "conferences",
      "special events",
      "market research",
      "marketing",
      "materials",
      "newspaper",
      "office manager",
      "personnel",
      "press",
      "press releases",
      "publication",
      "radio",
      "recruitment",
      "scripts",
      "strategy",
      "strategic planning",
      "television",
      "website content"
    ],
    "licenses": []
  }
}