{
  "resume_id": "R0001",
  "content": "SOUS CHEF\nWork Experience\nSous Chef\n \nJul 2010\n \nCompany Name\n \n\u00ef\u00bc\u200b \nCity\n \n, \nState\nAssisted cooks in the preparation of green salads, fruit salads and pasta salads.\nWorked the saut\u00c3\u00a9 and fry stations.\nPlated and distributed completed dishes to waiters.\nImproved the accuracy of filled orders by changing the procedure of sharing tickets.\nTook inventory and placed orders, assisted in the food and beverage operations.\nFront Desk Agent\n \nCompany Name\n \n\u00ef\u00bc\u200b \nCity\n \n, \nState\nAssisted the Property Coordinator with daily tasks and worked on hotel computer programming systems Worked with HR department to\ncontrol staffing and perform employee performance evaluations.\nHandled property functions on daily basis to ensure best performance and persistent upgrading in customer service, employee proficiency,\nperformance, marketing, property ambience and income.\nHandled room reservation Adjusted auditing reports Received and send telephone messages and facsimiles.\nFront Desk Manager\n \nJan 2013\n \nto \nJan 2014\n \nCompany Name\n \n\u00ef\u00bc\u200b \nCity\n \n, \nState\nProcess guest registration including calculation and collection of payment Conduct night audit as assigned Processed all financial transactions\nincluding the verification and processing of credit card transactions in accordance with company policies and procedures and complete shift\nreports Maintain room status inventory Respond to guest inquires and request regarding hotel services, reservations, local attractions,\ndirections, etc.\nEfficient in several software systems PBX and OPERA Perform work duties in accordance with safety and security policies and procedures\nGuest Service Recovery- Night Audit IHG Rewards Gold Level Rewards Champion Kept track of all enrollments for reward members\nMaintained excellence according to IHG's standards for monthly enrollments Completed several IHG Rewards Compliance training\nseminars.\nBaquet- Front desk\n \nJan 2010\n \nto \nJan 2013\n \nCompany Name\n \n\u00ef\u00bc\u200b \nCity\n \n, \nState\nAssisted with administration work, contracts, contract changes, certificates.\nPrepared access cards, ordered products.\nSelected the right candidates for the company's needs.\nBecame familiar with various laws such as ADA, FMLA, and Workers Compensation.\nFront Desk Agent\n \nJan 2011\n \nto \nJan 2012\n \nCompany Name\n \n\u00ef\u00bc\u200b \nCity\n \n, \nState\nAccomplished appointment scheduling, data entry and revenue management, met sales goals.\nInteract with customers on a daily basis via face to face or multi-line phone Prep Cook (Banquet Upheld Department of Health policies by\nmaintaining a sanitary and pleasant dining environment Prepared meals to customer satisfaction and performed inventory management.\nShift Supervisor/ Host\n \nJun 2007\n \nto \nDec 2007\n \nCompany Name\n \n\u00ef\u00bc\u200b \nCity\n \n, \nState\nIn charge of all hosts/ hostesses during my time as shift supervisor, responsible for the front of the house.\nChecked time sheets to ensure employees were clocking out properly, trained new employees on POS system.\nPerform work duties in accordance with regulations such as OSHA, HAZCOM, and Blood Borne Illnesses.\nCareer Overview\nA highly- motivated, productive and customer-focused team player with strong communication, interpersonal, organizational, time management,\nanalytical and problem solving skills. Reliable and dedicated with the ability to grasp and apply new procedures quickly; organize and prioritize\ntasks to meet deadlines and adapt readily to new challenges.\nCore Strengths\nPromoting hotel facilities Customer service Hospitality\nSupervising\nResolving guest disputes\nProject Management\nMarketing\nExperienced in multiple reservation systems\nStrong influencing & communication skills.\nIn-depth knowledge of the hotel, hospitality, leisure and service sector.\nAble to identify, understand and give priority to urgent issues.\nWorking long hours, under pressure and tight deadlines.\nAccounting\nRevenue Management\nAccomplishments\nHilton Garden Inn Opening Team Member\nWoodbridge, Virginia\nEducational Background\nMaster's\n \n, \nBusiness Administration\n \n2015\n \nStratford University\n \n\u00ef\u00bc\u200b \nCity\n \n, \nState\n \nGPA: \nGPA: 3.8 Magna Cum Lade\n \nBusiness Administration GPA: 3.8\nMagna Cum Lade\nBachelors of Arts\n \n, \nHospitality Management\n \n2013\n \nStratford University\n \n\u00ef\u00bc\u200b \nCity\n \n, \nState\n \n, \nUSA\nHospitality Management\nAssociate of Applied Science\n \n, \nAdvanced Culinary Arts\n \n2010\n \nStratford\n \n\u00ef\u00bc\u200b \nCity\n \n, \nState\n \n, \nUSA\nAdvanced Culinary Arts (C.C.)\nCertifications and Trainings\n \nCity\n \n, \nState\nTIPS certified\nCPR-AED Certified\nCertified Food Handler, State of Virginia\nFood Management Professional, State of Virginia\nIHG Training\nOnQ Training\nCertified Culinarian 2010\nSkills\nADA compliance, auditing, computer programming, contracts, CPR, credit, customer satisfaction, customer\nservice, data entry, Department of Health, financial, HR, inventory management, Cost accounting, marketing, access, PBX, policies, POS, safety,\nsales, scheduling, seminars, staffing, supervisor,",
  "enriched_profile": {
    "fullName": "John Doe",
    "email": "",
    "phone": "",
    "location": "City, State",
    "linkedin": "",
    "github": "",
    "portfolio": "",
    "summary": "Highly-motivated team player with strong communication, interpersonal, organizational, time management, analytical, and problem-solving skills. Experienced in hotel facilities promotion, customer service, supervising, resolving guest disputes, project management, marketing, and accounting. Hilton Garden Inn Opening Team Member.",
    "education": [
      {
        "school": "Stratford University",
        "degree": "Master's",
        "field": "Business Administration",
        "startDate": "2015",
        "endDate": "",
        "gpa": "3.8 (Magna Cum Lade)"
      },
      {
        "school": "Stratford University",
        "degree": "Bachelor of Arts",
        "field": "Hospitality Management",
        "startDate": "2013",
        "endDate": "",
        "gpa": ""
      },
      {
        "school": "Stratford",
        "degree": "Associate of Applied Science",
        "field": "Advanced Culinary Arts",
        "startDate": "2010",
        "endDate": "",
        "gpa": ""
      }
    ],
    "experience": [
      {
        "company": "Company Name",
        "position": "Front Desk Manager",
        "startDate": "Jan 2013",
        "endDate": "Jan 2014",
        "description": "Processed guest registration, conducted night audit, processed financial transactions, maintained room status inventory, responded to guest inquiries, and performed work duties in accordance with safety and security policies."
      },
      {
        "company": "Company Name",
        "position": "Baquet - Front Desk",
        "startDate": "Jan 2010",
        "endDate": "Jan 2013",
        "description": "Assisted with administration work, contracts, contract changes, certificates, prepared access cards, ordered products, selected candidates, and became familiar with various laws."
      },
      {
        "company": "Company Name",
        "position": "Front Desk Agent",
        "startDate": "Jan 2011",
        "endDate": "Jan 2012",
        "description": "Accomplished appointment scheduling, data entry, and revenue management, interacted with customers, and performed work duties in accordance with regulations."
      },
      {
        "company": "Company Name",
        "position": "Prep Cook (Banquet)",
        "startDate": "",
        "endDate": "",
        "description": "Upheld Department of Health policies, prepared meals to customer satisfaction, and performed inventory management."
      },
      {
        "company": "Company Name",
        "position": "Shift Supervisor/Host",
        "startDate": "Jun 2007",
        "endDate": "Dec 2007",
        "description": "Managed hosts/hostesses, checked time sheets, trained new employees, and performed work duties in accordance with regulations."
      }
    ],
    "projects": [],
    "skills": [
      "ADA compliance",
      "auditing",
      "computer programming",
      "contracts",
      "CPR",
      "credit",
      "customer satisfaction",
      "customer service",
      "data entry",
      "Department of Health",
      "financial",
      "HR",
      "inventory management",
      "Cost accounting",
      "marketing",
      "access",
      "PBX",
      "policies",
      "POS",
      "safety",
      "sales",
      "scheduling",
      "seminars",
      "staffing",
      "supervisor",
      "TIPS certified",
      "CPR-AED Certified",
      "Certified Food Handler, State of Virginia",
      "Food Management Professional, State of Virginia",
      "IHG Training",
      "OnQ Training",
      "Certified Culinarian 2010"
    ],
    "licenses": []
  }
}