{
  "resume_id": "R0018",
  "content": "BUSINESS DEVELOPMENT MANAGER/STAFFING MANAGER\nProfessional Summary\nInnovative Manager seeks position offering opportunities for new professional and personal challenges. Self-starter with a positive, can-do attitude\nwho is driven to learn, improve and succeed. Over 10 years of proactive and indirect diverse recruiting and staffing experience.\nEducation and Training\n2003\nBachelor of Science\n \n: \nHealth Science option in Health Management and Marketing\n \nCalifornia State University of Hayward\n \n\u00ef\u00bc\u200b \nCity\n \n, \nState\n \n, \nUnited\nStates\nSkill Highlights\nStaffing management ability\nProven patience and self-discipline\nRelationship and team building\nStaff training and development\nCritical thinking proficiency\nCompensation/benefits administration\nSkilled negotiator\nAccount management\nExcellent written and verbal communicator\nEnthusiastic team player\nProblem solving\nBilling\nAttention to detail\nRecruiting and selection techniques\nProficient communicator\nContract review\nCold calling\nHiring recommendations\nInterviewing\nStrategic planning\nMulti-tasking ability\nSkills\n\u00c2 Proficient with Microsoft Word, Excel, PowerPoint, Access and Outlook Express. \u00c2 Optimizer, WFX, Stafferlink, Healthtrust, and Bullhorn.\nMaintaining active databases of various hospital proprietary software technology systems.\nProfessional Experience\n08/2006\n \nto \nCurrent\nBusiness Development Manager/Staffing Manager\n \nCompany Name\n \n\u00ef\u00bc\u200b \nCity\n \n, \nState\n \nManage full cycle staffing, recruiting, and maintain a database\nof clients and applicants that is aligned to the business opportunity in the market for recruitment, staffing, and placement . Responsible for job\npostings, hiring, interviewing, and training new employees.\u00c2 \n Generate new accounts by implementing effective networking and content marketing\nstrategies. \nManage budget forecasting, goal setting and performance reporting for all accounts. \nNegotiate rates to cut costs and benefit corporate\npartnerships\n \n.\u00c2 \n \nDemonstrate knowledge of HIPAA Privacy and Security Regulations. \nConduct reference and background checks on all job\napplicants. \nDeveloped creative recruiting strategies that met anticipated staffing needs. \nCommunicate the duties, compensation, benefits and\nworking conditions to all potential candidates.\n \nContact all job applicants to inform them of their application status. Work with Director of Nursing\nand Human Resource Directors to ensure all healthcare organization is able to support business growth. Coach and counsel employees regarding\nattendance & performance; mediate employee disputes and complaints.\u00c2 \n Respond \nOnboard new employees in the time reporting and payroll\nsystems\n \n. \nManage payroll and time and attendance systems.\n05/2003\n \nto \n08/2008\nStaffing Coordinator\n \nCompany Name\n \n\u00ef\u00bc\u200b \nCity\n \n, \nState\n \nCreated and maintained all absentee calendars, agency nurse schedules and staff meeting\nminutes. \nMaintained all confidential personnel files, licensing and CPR compliance records. Develop computerized schedules for assigned nursing\nunits based on established staffing patterns, policies, approved employee preferences, and managers' requests. Revises and adjusts unit schedules\nas needed in consultation with nurse managers.\u00c2 Proactively adjusts and allocates core, registry, and float nursing personnel to provide adequate\ncoverage to clinics and inpatient areas to strategically meet real-time staffing requirements in the most cost-effective manner\n05/2003\n \nto \n08/2008\nStaffing Manager\n \nCompany Name\n \n\u00ef\u00bc\u200b \nCity\n \n, \nState\n \nManage full cycle staffing, recruiting, and maintain a database of clients and applicants that is\naligned to the business opportunity in the market for recruitment, staffing, and placement . Responsible for job postings, hiring, interviewing, and\ntraining new employees.\u00c2 Generate new accounts by implementing effective networking and content marketing strategies.Manage budget\nforecasting, goal setting and performance reporting for all accounts.\u00c2 Negotiate rates to cut costs and benefit corporate\npartnerships.\u00c2 Demonstrate knowledge of HIPAA Privacy and Security Regulations.\u00c2 Conduct reference and background checks on all job\napplicants.\u00c2 Developed creative recruiting strategies that met anticipated staffing needs.\u00c2 Communicate the duties, compensation, benefits and\nworking conditions to all potential candidates.\u00c2 Contact all job applicants to inform them of their application status. Work with Director of Nursing\nand Human Resource Directors to ensure all healthcare organization is able to support business growth. Coach and counsel employees regarding\nattendance & performance; mediate employee disputes and complaints.\u00c2 Respond\u00c2 Onboard new employees in the time reporting and payroll\nsystems\u00c2 .\u00c2 Manage payroll and time and attendance systems.",
  "enriched_profile": {
    "fullName": "Innovative Manager",
    "email": "",
    "phone": "",
    "location": "City, State, United States",
    "linkedin": "",
    "github": "",
    "portfolio": "",
    "summary": "Self-starter with 10+ years of recruiting and staffing experience seeking new professional and personal challenges. Skilled in staffing management, relationship building, staff training, critical thinking, compensation administration, negotiation, account management, communication, problem solving, and recruiting.",
    "education": [
      {
        "school": "California State University of Hayward",
        "degree": "Bachelor of Science",
        "field": "Health Science, option in Health Management and Marketing",
        "startDate": "2003",
        "endDate": "",
        "gpa": ""
      }
    ],
    "experience": [
      {
        "company": "Company Name",
        "position": "Business Development Manager/Staffing Manager",
        "startDate": "08/2006",
        "endDate": "Present",
        "description": "Manage full cycle staffing, recruiting, and maintain a database of clients and applicants. Responsible for job postings, hiring, interviewing, and training new employees. Generate new accounts, manage budget forecasting, goal setting and performance reporting for all accounts. Negotiate rates, demonstrate knowledge of HIPAA Privacy and Security Regulations, and conduct reference and background checks on all job applicants."
      },
      {
        "company": "Company Name",
        "position": "Staffing Coordinator",
        "startDate": "05/2003",
        "endDate": "08/2008",
        "description": "Created and maintained all absentee calendars, agency nurse schedules and staff meeting minutes. Maintained confidential personnel files, licensing and CPR compliance records. Developed computerized schedules for assigned nursing units based on established staffing patterns, policies, approved employee preferences, and managers' requests."
      },
      {
        "company": "Company Name",
        "position": "Staffing Manager",
        "startDate": "05/2003",
        "endDate": "08/2008",
        "description": "Manage full cycle staffing, recruiting, and maintain a database of clients and applicants. Responsible for job postings, hiring, interviewing, and training new employees. Generate new accounts, manage budget forecasting, goal setting and performance reporting for all accounts. Negotiate rates, demonstrate knowledge of HIPAA Privacy and Security Regulations, and conduct reference and background checks on all job applicants."
      }
    ],
    "projects": [],
    "skills": [
      "Staffing management",
      "Relationship building",
      "Staff training",
      "Critical thinking",
      "Compensation administration",
      "Negotiation",
      "Account management",
      "Communication",
      "Problem solving",
      "Recruiting",
      "Microsoft Word, Excel, PowerPoint, Access and Outlook Express proficiency",
      "Optimizer, WFX, Stafferlink, Healthtrust, and Bullhorn proficiency"
    ],
    "licenses": []
  }
}