{
  "resume_id": "R0015",
  "content": "CHILD FAMILY ADVOCATE\nProfessional Profile\nTalented administrative professional with background in accounting and finance. Extensive knowledge of AR/AP, Microsoft Excel and Quick\nBooks-software skills. Fearless Child Family Advocate comfortable taking a stand against threats to a child's safety or well-being. Works directly\nwith government officials, children and families to find the best care possible for every child.\nQualifications\nAttentive listener\nSensitive\nFamily maintenance\nDetail-oriented\nExcellent interpersonal skills\nTeam player\nStaff development\nRelevant Experience\nServed many program participants who went on to earn high school diplomas or GEDs.\nIncreased office organization by developing more efficient filing system and customer database protocols.\nLed support groups to help parents regain and improve their parent-child bond.\nExperience\nChild Family Advocate\n \nAugust 2013\n \nto \nCurrent\n \nCompany Name\n \n\u00ef\u00bc\u200b \nCity\n \n, \nState\nCollaborated with community members to educate the public regarding issues such as drug abuse prevention and traffic safety.\nCollaborated with community leaders, organizations and public agencies to promote the organizations community service programs.\nMaintained daily records of children's individual activities, behaviors, meals and naps.\nCreated and implemented developmentally-appropriate curriculum that addressed all learning styles.\nEstablished a safe play environment for the children.\nSupervised children on field trips to local parks, fire stations and zoos.\nDirected all protective placement, case management, parent education and family reunification activities.\nAdvised patients on community resources, made referrals and devised realistic treatment plans.Communicated with public social and welfare\nagencies to obtain and provide information.\nCustomer Services Team Lead\n \nOctober 2010\n \nto \nMarch 2013\n \nCompany Name\n \n\u00ef\u00bc\u200b \nCity\n \n, \nState\nSurpassed revenue goals in four consecutive quarters.\nCreated training manuals targeted at resolving even the most difficult customer issues.\nDeveloped, implemented and monitored programs to maximize customer satisfaction.\nInterviewed, hired and trained new quality customer service representatives.\nDeveloped and implemented policies, procedures and process improvement initiatives to improve retention rates and increase customer\nsatisfaction.\nCustomer Service/Banking \nNovember 2007\n \nto \nMarch 2009\n \nCompany Name\n \n\u00ef\u00bc\u200b \nCity\n \n, \nState\nCollected customer feedback and made process changes to exceed customer satisfaction goals.\nDeveloped process improvements to enhance efficiency and effectiveness of inter-department call center operations.\nOpened new customer accounts, including checking, savings and lines of credit.\nExamined checks for identification and endorsement.\nProcessed treasury, tax and loan payments.\nAdministrative Assistant\n \nAugust 2007\n \nto \nNovember 2007\n \nCompany Name\n \n\u00ef\u00bc\u200b \nCity\n \n, \nState\nManaged the receptionist area, including greeting visitors and responding to telephone and in-person requests for information.\nDispersed incoming mail to correct recipients throughout the office.\nCreated and maintained spreadsheets using advanced Excel functions and calculations to develop reports and lists.\nReceived and distributed faxes and mail in a timely manner.\nCall Center/Phone Representative/Collector\n \nAugust 2005\n \nto \nNovember 2007\n \nCompany Name\n \n\u00ef\u00bc\u200b \nCity\n \n, \nState\nComputed accurate sales prices for purchase transactions.\nEliminated outdated records by sending the records to be scanned.\nIdentified and resolved system and account issues.\nVerified and logged in deadlines forresponding to daily inquiries.\nEducation\nl Coursework in Organizational Behavior, Compensation, Labor Relations and Recruitment \nl Continuing education in Human Services\n \nGreenville\nCollege \nl Desktop publishing workshop\n \n\u00ef\u00bc\u200b \nCity\n \n, \nState\nSkills\nscheduling appointments\nAS 400, budgets\ncall center\nCustomer service\nfinancial, funds\nLabor Relations\nLeadership\nSales",
  "enriched_profile": {
    "fullName": "Talented Administrative Professional",
    "email": "",
    "phone": "",
    "location": "City, State",
    "linkedin": "",
    "github": "",
    "portfolio": "",
    "summary": "Experienced administrative professional with a background in accounting and finance. Skilled in AR/AP, Microsoft Excel, and QuickBooks. Passionate Child Family Advocate with excellent interpersonal skills, detail-oriented, and a team player.",
    "education": [
      {
        "school": "Greenville College",
        "degree": "",
        "field": "",
        "startDate": "",
        "endDate": "",
        "gpa": ""
      },
      {
        "school": "",
        "degree": "",
        "field": "Organizational Behavior, Compensation, Labor Relations, and Recruitment",
        "startDate": "",
        "endDate": "",
        "gpa": ""
      },
      {
        "school": "",
        "degree": "",
        "field": "Human Services",
        "startDate": "",
        "endDate": "",
        "gpa": ""
      },
      {
        "school": "",
        "degree": "",
        "field": "Desktop Publishing",
        "startDate": "",
        "endDate": "",
        "gpa": ""
      }
    ],
    "experience": [
      {
        "company": "Company Name",
        "position": "Child Family Advocate",
        "startDate": "August 2013",
        "endDate": "Present",
        "description": "Collaborated with community members, created and implemented developmentally-appropriate curriculum, established a safe play environment, supervised children on field trips, and directed all protective placement, case management, parent education, and family reunification activities."
      },
      {
        "company": "Company Name",
        "position": "Customer Services Team Lead",
        "startDate": "October 2010",
        "endDate": "March 2013",
        "description": "Surpassed revenue goals in four consecutive quarters, created training manuals, developed and implemented programs to maximize customer satisfaction, interviewed, hired, and trained new quality customer service representatives, and developed and implemented policies, procedures, and process improvement initiatives to improve retention rates and increase customer satisfaction."
      },
      {
        "company": "Company Name",
        "position": "Customer Service/Banking",
        "startDate": "November 2007",
        "endDate": "March 2009",
        "description": "Collected customer feedback, developed process improvements, opened new customer accounts, examined checks for identification and endorsement, and processed treasury, tax, and loan payments."
      },
      {
        "company": "Company Name",
        "position": "Administrative Assistant",
        "startDate": "August 2007",
        "endDate": "November 2007",
        "description": "Managed the receptionist area, dispersed incoming mail, created and maintained spreadsheets, received and distributed faxes and mail in a timely manner."
      },
      {
        "company": "Company Name",
        "position": "Call Center/Phone Representative/Collector",
        "startDate": "August 2005",
        "endDate": "November 2007",
        "description": "Computed accurate sales prices, eliminated outdated records, identified and resolved system and account issues, and verified and logged in deadlines for responding to daily inquiries."
      }
    ],
    "projects": [],
    "skills": [
      "scheduling appointments",
      "AS 400",
      "budgets",
      "call center",
      "Customer service",
      "financial",
      "funds",
      "Labor Relations",
      "Leadership",
      "Sales"
    ],
    "licenses": []
  }
}