{
  "resume_id": "R0013",
  "content": "AVIATION ELECTRONICS TECHNICIAN\nSummary\nSeeking a challenging position where my existing skills and experience contribute to your company while expanding my technical abilities.\nHighlights\nProficient with maintenance tracking software, Prezi and Microsoft Office Programs such as Word, Excel, PowerPoint, Outlook, Adobe,\nAccess, Auto CAD, Commercial Multi-Engine and Single-Engine Pilot, Airline Dispatcher Certified, FAA Class 1 Medical, MATLAB,\nlabVIEW\nExperience\n01/2013\n \nto \n01/2015\nCompany Name\nUsed the instructional design process to plan and develop online courses in partnership with faculty SMEs, then building courses using a\nstandardized template in the Blackboard LMS environment.\nUtilized a variety of technology tools, including Canvas, Blackboard, Respondus, StudyMate, TurnItIn, SnagIt, Camtasia, HTML and\nothers to create instructional media.\nFacilitated in the transfer and development of online courses from Blackboard LMS to Canvas LMS.\nCollaborated with remote faculty to prepare high-quality, interactive online courses, for academic and non-credit delivery.\nConducted quality assurance reviews of courses and other instructional materials Edited and organized electronic information to create high-\nquality course content that is suited to the adult online learner.\nWorked with Blackboard System Administrators to troubleshoot issues with online courses in the LMS system, prepare for system\nupgrades by testing the LMS on staging servers.\n01/2008\n \nto \nCurrent\nAviation Electronics Technician\n \nCompany Name\nTroubleshoot radar systems, communication systems, navigation equipment, radar altimeter warning systems, instrument landing system\nequipment, electronic support measure systems, electro-optical sensors (IR turret), search radar and synthetic aperture radar.\nTest electronic circuits using commercial and industry-standard equipment, such as oscilloscopes, digital multi-meters, logic analyzers, DAC\nconverters, spectrum analyzers and signal generators and time delay reflectometers to isolate faults and defects.\nWork side by side with Quality assurance as a collateral duty inspector, responsible for writing quality deficiency reports, technical\ndiscrepancies and engineering investigations.\nMaintain and repair in-flight navigation and detection systems on aircrafts , radar systems, radar and tactical displays, IFF/SIF equipment,\nradar altimeters, Doppler navigation equipment, radio navigation systems, analog computing devices, electronic countermeasures equipment,\nlaser and fiber-optic infrared devices, digital recorder systems and aircraft digital systems, use basic RF electronic test equipment and\nspecialized system test equipment.\nCompleted maintenance action forms, keep an inventory of parts and supplies, maintain a technical library and perform avionics corrosion\ncontrol.\nTroubleshoot and repair antisubmarine warfare sensors, electronic warfare, data link, fire control and tactical displays with associated\nequipment, UHF and VHF receivers and transmitters, made repairs on antennas, repair and install electrical connectors, inspect and install\npressurized equipment, waveguide components, avionics gaskets and seals, calibrate test equipment, interpret computer languages and\ncomputer equipment.\n01/2003\n \nto \n01/2007\nAviation Electronics Technician\n \nCompany Name\nWorked in the Navy's largest intermediate maintenance department providing component level repair exceeding 260,000 components\nannually and valued at $557 million.\nIncorporated and ensured strict attention to detail in repairing electrical aircraft systems using commercial and industry-standard equipment,\nsuch as oscilloscopes, digital multi-meters, logic analyzers, DAC converters, spectrum analyzers and signal generators all while contributing\nto 55% percent reduction in backlog.\nAnalyzed and resolved intricate automated test equipment problems and debugged complex computer generated data all while supporting\n19 F/A-18 squadrons and 11 aircraft carriers.\nAssembled, checked, handled, inspected, maintained, operated, reprogrammed, repaired and processed over 2,900 maintenance actions\nannually on classified F/A-18 specialized repair assemblies all while maintaining a 95% ready for issue rate.\nUtilized technical manuals, wiring schematics, block diagrams, electrical schematics and drawings to rapidly isolate malfunctions in system\nwiring, sub assemblies and other components.\nEducation\nMay 2016\nBachelors of Science\n \n: \nAeronautical Science Applied Meteorology\n \nEmbry-Riddle Aeronautical University\n \n\u00ef\u00bc\u200b \nCity\n \n, \nState\n \nGPA: \nGPA: 3.23/4.0\nAeronautical Science Applied Meteorology GPA: 3.23/4.0\nMay 2008\nAssociate of Science\n \n: \nElectronic Engineering Technology\n \nTidewater Community College\n \n\u00ef\u00bc\u200b \nCity\n \n, \nState\n \nGPA: \nGPA: 3.85/4.0 Summa Cum Laude\nElectronic Engineering Technology GPA: 3.85/4.0 Summa Cum Laude\nLanguages\nBilingual fluent in Spanish and English\nSkills\nacademic, Adobe, Articulate, attention to detail, Auto CAD, basic, calibration, C",
  "enriched_profile": {
    "fullName": "Aviation Electronics Technician",
    "email": "",
    "phone": "",
    "location": "",
    "linkedin": "",
    "github": "",
    "portfolio": "",
    "summary": "Seeking a challenging position to contribute to a company with existing skills and experience while expanding technical abilities.",
    "education": [
      {
        "school": "Embry-Riddle Aeronautical University",
        "degree": "Bachelor of Science",
        "field": "Aeronautical Science Applied Meteorology",
        "startDate": "May 2016",
        "endDate": "",
        "gpa": "3.23/4.0"
      },
      {
        "school": "Tidewater Community College",
        "degree": "Associate of Science",
        "field": "Electronic Engineering Technology",
        "startDate": "May 2008",
        "endDate": "",
        "gpa": "3.85/4.0 Summa Cum Laude"
      }
    ],
    "experience": [
      {
        "company": "Company Name",
        "position": "Instructional Designer",
        "startDate": "01/2013",
        "endDate": "01/2015",
        "description": "Planned and developed online courses in partnership with faculty SMEs, built courses using a standardized template in the Blackboard LMS environment, utilized technology tools to create instructional media, collaborated with remote faculty, conducted quality assurance reviews, and edited electronic information."
      },
      {
        "company": "Company Name",
        "position": "Aviation Electronics Technician",
        "startDate": "01/2008",
        "endDate": "Current",
        "description": "Troubleshot radar systems, communication systems, navigation equipment, radar altimeter warning systems, instrument landing system equipment, electronic support measure systems, electro-optical sensors, search radar and synthetic aperture radar, maintained and repaired in-flight navigation and detection systems on aircrafts, repaired antisubmarine warfare sensors, electronic warfare, data link, fire control and tactical displays with associated equipment, UHF and VHF receivers and transmitters, made repairs on antennas, repaired and installed electrical connectors, inspected and installed pressurized equipment, waveguide components, avionics gaskets and seals, calibrated test equipment, interpreted computer languages and computer equipment, completed maintenance action forms, kept an inventory of parts and supplies, maintained a technical library and performed avionics corrosion control."
      },
      {
        "company": "Company Name",
        "position": "Aviation Electronics Technician",
        "startDate": "01/2003",
        "endDate": "01/2007",
        "description": "Repaired electrical aircraft systems, contributed to 55% reduction in backlog, analyzed and resolved intricate automated test equipment problems, debugged complex computer generated data, assembled, checked, handled, inspected, maintained, operated, reprogrammed, repaired and processed over 2,900 maintenance actions annually on classified F/A-18 specialized repair assemblies, utilized technical manuals, wiring schematics, block diagrams, electrical schematics and drawings to rapidly isolate malfunctions in system wiring, sub assemblies and other components."
      }
    ],
    "projects": [],
    "skills": [
      "academic",
      "Adobe",
      "Articulate",
      "attention to detail",
      "Auto CAD",
      "calibration",
      "Canvas",
      "content",
      "credit",
      "delivery",
      "electrical schematics",
      "English",
      "forms",
      "HTML",
      "inspect",
      "inspector",
      "instructional design",
      "inventory",
      "labVIEW",
      "laser",
      "logic",
      "materials",
      "MATLAB",
      "Access",
      "Excel",
      "Microsoft Office Programs",
      "Outlook",
      "PowerPoint",
      "Word",
      "radar",
      "multi-meters",
      "Navy",
      "communicator",
      "navigation",
      "organizational",
      "oscilloscopes",
      "problem solver",
      "quality",
      "quality assurance",
      "radio",
      "recording",
      "repairs",
      "repairing",
      "schematics",
      "servers",
      "signal generators",
      "Spanish",
      "technical manuals",
      "test equipment",
      "troubleshoot",
      "troubleshooting",
      "UHF",
      "upgrades",
      "VHF",
      "wiring"
    ],
    "licenses": [
      {
        "title": "Active DOD secret clearance",
        "description": "",
        "issueDate": "",
        "expiryDate": ""
      }
    ]
  }
}