{
  "resume_id": "R0021",
  "content": "INFORMATION TECHNOLOGY MANAGER\nProfessional Summary\nPossesses an extensive background in Information Technology Management, along with a Masters of Science degree and multiple certifications.\nExcels in planning, implementing, and evaluating the systems, infrastructure, and staffing necessary to execute complex initiatives and meet\ndeadlines in dynamic, fast-paced environments; adept at overseeing and participating in the installation, configuration, maintenance, and upgrade of\nnetworks, hardware, servers, and peripherals. \nDetail-oriented and decisive; applies communication and leadership skills to interface effectively with\nall levels of an organization. \nExpertise spans: \nNetwork Engineering, Helpdesk Administration, Software Licensing, Disaster Recovery,\nBackup/Restore \nOperations/Project Management, Strategic Planning/Analysis, Budgeting, TeamBuilding/Training, Vendor Relations\nPolicy/Procedure Development, Quality Assurance, Troubleshooting, Problem Solving, Process Improvement.\nExperience\n04/2013\n \nto \nCurrent\nInformation Technology Manager\n \nCompany Name\n \n\u00ef\u00bc\u200b \nCity\n \n, \nState\nA bankruptcy Trustee office handling Chapter 13 and Chapter 12 cases for the Northern District of Georgia Manages application\ndatabase/hardware systems used to track Chapter 13 bankruptcy cases, all office technologies,, information systems, and anti-spam/anti-\nvirus servers.\nEvaluates, recommends, implements, supports, and troubleshoots hardware and software.\nMaintains LAN/WAN infrastructure, connectivity, and security as well as LAN user documentation.\nPerforms disaster recovery planning.\nAdministers licenses and service contracts; schedules service visits from vendors and suppliers.\nDefines, documents, assesses, and updates IT-related procedures as needed.\nCreates and maintains user accounts, including email.\nInspects all employees' computers quarterly to ensure compliance of configuration and settings with office policies.\nCoordinates special projects.\nDesigned and implemented network infrastructure enhancements to improve performance, security, remote access, and connectivity.\nStandardized hardware, peripherals, and software.\nEstablished a helpdesk support system for monitoring, prioritizing, and scheduling requests.\nSpearheaded the deployment of a new tracking system that provided performance metrics used to identify where additional training and\nresources were required.\nResearched, installed, and configured an enterprise backup solution for disaster recovery that included features to allow users to recover\ndeleted items without the need to recover from DR backups.\nDoubled WAN bandwidth and propelled LAN and WLAN performance to 100% or higher through WAN, LAN, and WLAN\nreconfiguration.\nImproved accuracy, more than doubled efficiency from 35% to 87%, and increased cost savings from $250/quarter to $2,500/quarter by\ndeveloping an automated script for retrieving data from an outside server.\nAutomated asset tracking by employing a hand scanner and database system to improve efficiency and accuracy.\n08/1987\n \nto \n06/2012\nNetwork Analyst\n \nCompany Name\n \n\u00ef\u00bc\u200b \nCity\n \n, \nState\nA $1B+ global manufacturer of equipment for precision material dispensing, testing, inspection, surface preparation, and curing Fueled a\n1,000% improvement in LAN performance by replacing the existing network, which entailed changing software and LAN cabling for 20\nexisting switches, including reconfiguring the core switch with remote wiring closets with multiple stack units.\nLed a team of five network and equipment support specialists.Configured, maintained, analyzed, and troubleshot Nortel and Juniper\nnetworks, systems, and equipment (WAN/LAN/WLAN infrastructure, servers, PCs, notebooks, thin clients, printers, and other\nperipherals) used by 600 workers in Georgia.Supported 200 units configured for operation through client servers.Advanced global\ncompany objectives through participation in IT and telecom design and implementation.Advanced to this role through promotions from\nMechanical Drafter, Engineering Checker, Mechanical Designer, and Network Administrator.Slashed support requests 75%, cut equipment\ncosts 50%, and boosted work productivity 30% by applying near-zero configuration to develop, install, and implement a thin client solution\nfor 90 plant manufacturing cells.\nReduced standard company imaging and system deployment time 60% before station-specific customization by replacing and/or refreshing\n40 PCs each quarter, 100% on schedule.\nPlanned, designed, installed, configured, and tested wireless networks (WLAN from Cisco, Nortel, and Meraki) in multiple facilities;\ndocumented standards for US operations; trained users; and monitored performance.\nReplaced 125 field and service laptops by programming standard images and custom configurations on each machine, completing the six-\nweek project on schedule despite disruption of parts availability due to a tsunami.\nChampioned the use of computers in manufacturing cells to provide drawings and also facili",
  "enriched_profile": {
    "fullName": "John Doe",
    "email": "",
    "phone": "",
    "location": "City, State",
    "linkedin": "",
    "github": "",
    "portfolio": "",
    "summary": "Information Technology Manager with extensive background in IT management, network engineering, helpdesk administration, and project management. Proficient in planning, implementing, and evaluating systems, infrastructure, and staffing for complex initiatives in dynamic environments. Skilled in communication, leadership, and decisive problem-solving.",
    "education": [
      {
        "school": "Walden University",
        "degree": "Master of Science",
        "field": "Leadership",
        "startDate": "2015",
        "endDate": "",
        "gpa": ""
      },
      {
        "school": "Walden University",
        "degree": "Master of Science",
        "field": "Information Systems Management Project Management",
        "startDate": "2013",
        "endDate": "",
        "gpa": ""
      },
      {
        "school": "Walden University",
        "degree": "Bachelor of Science",
        "field": "Information Systems Management Mechanical Engineering",
        "startDate": "",
        "endDate": "",
        "gpa": ""
      }
    ],
    "experience": [
      {
        "company": "Bankruptcy Trustee office",
        "position": "Information Technology Manager",
        "startDate": "04/2013",
        "endDate": "Current",
        "description": "Managed application database/hardware systems for Chapter 13 bankruptcy cases, oversaw office technologies, information systems, and anti-spam/anti-virus servers. Evaluated, recommended, implemented, supported, and troubleshot hardware and software. Maintained LAN/WAN infrastructure, connectivity, and security. Performed disaster recovery planning. Administered licenses and service contracts. Defined, documented, assessed, and updated IT-related procedures. Created and maintained user accounts, including email. Inspected all employees' computers quarterly to ensure compliance of configuration and settings with office policies. Coordinated special projects."
      },
      {
        "company": "Company Name",
        "position": "Network Analyst",
        "startDate": "08/1987",
        "endDate": "06/2012",
        "description": "Fueled a 1,000% improvement in LAN performance by replacing the existing network, led a team of five network and equipment support specialists, configured, maintained, analyzed, and troubleshot Nortel and Juniper networks, systems, and equipment. Advanced global company objectives through participation in IT and telecom design and implementation. Slashed support requests 75%, cut equipment costs 50%, and boosted work productivity 30% by applying near-zero configuration to develop, install, and implement a thin client solution. Reduced standard company imaging and system deployment time 60% before station-specific customization. Planned, designed, installed, configured, and tested wireless networks in multiple facilities. Replaced 125 field and service laptops by programming standard images and custom configurations on each machine. Championed the use of computers in manufacturing cells to provide drawings and facilitate order tracking in conjunction with the ERP system."
      }
    ],
    "projects": [
      {
        "name": "Network Infrastructure Enhancements",
        "techStack": "Network Engineering",
        "description": "Designed and implemented network infrastructure enhancements to improve performance, security, remote access, and connectivity. Standardized hardware, peripherals, and software.",
        "link": ""
      }
    ],
    "skills": [
      "Network Engineering",
      "Helpdesk Administration",
      "Project Management",
      "Disaster Recovery",
      "Backup/Restore",
      "Strategic Planning",
      "Budgeting",
      "Team Building",
      "Vendor Relations",
      "Policy/Procedure Development",
      "Quality Assurance",
      "Troubleshooting",
      "Problem Solving",
      "Process Improvement",
      "Cisco",
      "Nortel",
      "Windows",
      "OSX",
      "IOS",
      "Hardware"
    ],
    "licenses": []
  }
}