{
  "resume_id": "R0022",
  "content": "CORPORATE ADMINISTRATOR\nSummary\nSuccessful administrative professional with 15 years of experience.\nSkills\nOrganized\nDetail oriented\nEfficient\nPrioritize multiple deadlines\nWork well independently\nCollaborate with others\nSoftware\nMicrosoft Word\nExcel\nPowerPoint\nOutlook\nAdobe Acrobat\nMultiple project software websites\nGeneral Clerical\nType 75 WPM\nMultiline phones\nExperience\nCorporate Administrator\n \nJanuary 2009\n \nto \nJanuary 2017\n \nCompany Name\n \n\u00ef\u00bc\u200b \nCity\n \n, \nState\nLight accounting/bookkeeping Travel arrangements Meeting agendas and minutes Editing/Proofreading Meticulously proofread Ensure\nconsistency in content \nStructure Revise for clarity Review style format Bidding Administration Prepare \"front-end docs\" Familiar with\nvarious loaning agency requirements Know and able to carry out bid process from start to finish Construction Administration Assist\napproximately 15 engineers in our water/wastewater department working on multi-million dollar projects.\nRequires great attention to detail while meeting multiple deadlines simultaneously.\nSpecific duties include:.\nDocument Processing - Proofread, revise, format, PDF, and produce master plans, planning studies, specifications and plans, technical\nmemos, letters, meeting minutes, and O&M manuals for municipalities and cities.\nBidding Administration - Distribute plans and specifications, maintain planholders' lists, issue and confirm receipt of addenda, and complete\nbid tabulations.\nConstruction Administration - Prepare contract documents.\nReceive and return submittals and RFIs; maintain logs.\nAssisted approximately 18 engineers in the water/wastewater department working on multi-million dollar projects.\nRequired great attention to detail while meeting multiple deadlines simultaneously.\nCoordinated with clients, contractors, subconsultants, and internal drafters to help keep projects running smoothly.\nSpecific duties included: Document Processing - Proofread, edited, formatted, PDF'd, and produced master plans, predesign reports,\nspecifications, technical memos, letters, meeting minutes, and O&M manuals for municipalities and cities.\nBidding Administration - Handled bidding phase from start to finish.\nSubmitted public notice to newspaper for publishing; assisted in preparing, then produced and distributed plans and specifications;\nmaintained planholders' list; prepared, issued, and confirmed receipt of addenda; and completed bid tabulation.\nConstruction Administration - Prepared and reviewed contract documents.\nReceived and returned submittals and RFIs; maintained logs.\nBefore shifting my focus solely on project-related tasks for our water/wastewater department, I previously also provided general support to\nour firm.\nAdditional tasks completed during this time included making travel arrangements; coordinating lunch and learns; and conference and\nworkshop registration and tracking.\nAlso responsible for the following tasks: \nMake travel arrangements and assign company vehicles.\nDownload and log digital photos.\nCoordinate lunch and learns.\nRegister engineers for conferences, workshops, and webinars.\nAs part of the master specifications/standards committee, create monthly meeting agendas and minutes.\nLog, track, and implement master specification change requests.\nAnswer and route phone calls.\nDistribute incoming mail.\nPrepare outgoing mail and UPS packages.\nRun company errands.\nCustomer Service Representative\n \nJanuary 2006\n \nto \nJanuary 2009\n \nCompany Name\n \n\u00ef\u00bc\u200b \nCity\n \n, \nState\nProvided full account servicing for the Sears Credit Cards Portfolio via incoming calls, including billing and payment inquiries and disputes,\nProvided full account servicing for the Sears Credit Cards Portfolio via incoming calls, including billing and payment inquiries and disputes,\naccount maintenance, and lost/stolen cards.\nConsistently met and exceeded quality and sales goals.\nAdministrative Assistant/Bookkeeper \nAddus HealthCare\n \nJanuary 2000\n \nto \nJanuary 2003\n \nCity\n \n, \nState\nCompleted monthly billing reports and Branch Manager's Report.\nBilled over $500,000 monthly to contracting state agencies and clients.\nReconciled billing, posted payments to clients' accounts, and prepared deposits.\nPrepared and approved accounts payable bills.\nCreated documents, spreadsheets, and monthly newsletters; included developing new spreadsheets for A/R and A/P purposes.\nCompleted several processes of payroll.\nAssisted in planning company functions.\nProvided support to the area manager, branch manager, and 12 other branches throughout Washington and Oregon.\nSupervised part-time assistant.\nEducation and Training\nCompleted 45 credits in various courses including Logic, Ethics, Philosophy of Science, Precalculus, and C Programming.\n \nBoise State University\n\u00ef\u00bc\u200b \nCity\n \n, \nState\nHigh School Diploma\n \nKuna High School\n \n\u00ef\u00bc\u200b \nCity\n \n, \nState\n \nGraduated with Highest Honors 3.97 Received Ambassador Award in Business\nProfessionals of America.\nSkills\naccounting, accounts payable, Adobe Acrobat, A/P, agency, a",
  "enriched_profile": {
    "fullName": "Successful Administrative Professional",
    "email": "",
    "phone": "",
    "location": "City, State",
    "linkedin": "",
    "github": "",
    "portfolio": "",
    "summary": "Successful administrative professional with 15 years of experience, skilled in organization, attention to detail, efficiency, and collaboration.",
    "education": [
      {
        "school": "Boise State University",
        "degree": "",
        "field": "",
        "startDate": "",
        "endDate": "",
        "gpa": ""
      },
      {
        "school": "Kuna High School",
        "degree": "High School Diploma",
        "field": "",
        "startDate": "",
        "endDate": "",
        "gpa": ""
      }
    ],
    "experience": [
      {
        "company": "Company Name",
        "position": "Corporate Administrator",
        "startDate": "January 2009",
        "endDate": "January 2017",
        "description": "Provided administrative support to approximately 15 engineers in the water/wastewater department working on multi-million dollar projects. Performed document processing, bidding administration, and construction administration. Coordinated with clients, contractors, subconsultants, and internal drafters to help keep projects running smoothly."
      },
      {
        "company": "Company Name",
        "position": "Customer Service Representative",
        "startDate": "January 2006",
        "endDate": "January 2009",
        "description": "Provided full account servicing for the Sears Credit Cards Portfolio via incoming calls, including billing and payment inquiries and disputes, account maintenance, and lost/stolen cards. Consistently met and exceeded quality and sales goals."
      },
      {
        "company": "Addus HealthCare",
        "position": "Administrative Assistant/Bookkeeper",
        "startDate": "January 2000",
        "endDate": "January 2003",
        "description": "Completed monthly billing reports and Branch Manager's Report. Billed over $500,000 monthly to contracting state agencies and clients. Reconciled billing, posted payments to clients' accounts, and prepared deposits. Prepared and approved accounts payable bills. Created documents, spreadsheets, and monthly newsletters; completed several processes of payroll. Assisted in planning company functions. Provided support to the area manager, branch manager, and 12 other branches throughout Washington and Oregon. Supervised part-time assistant."
      }
    ],
    "projects": [],
    "skills": [
      "Organized",
      "Detail oriented",
      "Efficient",
      "Prioritize multiple deadlines",
      "Work well independently",
      "Collaborate with others",
      "Microsoft Word",
      "Excel",
      "PowerPoint",
      "Outlook",
      "Adobe Acrobat",
      "Type 75 WPM",
      "Multiline phones",
      "Accounting",
      "Bookkeeping",
      "C Programming",
      "Adobe Acrobat",
      "Content creation",
      "Editing",
      "Email management",
      "Event planning",
      "Logic",
      "Newsletter creation",
      "Newspaper publishing",
      "Payroll processing",
      "Phone handling",
      "Spreadsheet creation",
      "Travel arrangement",
      "Website management"
    ],
    "licenses": []
  }
}