{
  "resume_id": "R0020",
  "content": "FITNESS INSTRUCTOR\nProfessional Summary\nDynamic, entrepreneurial sales executive with a record of achievement and success driving sales growth in highly competitive markets. Solid\nbackground securing key clients and increasing product distribution to grow market share. Steadfast in building new business, securing customer\nloyalty, and developing strong relationships with external business partners. Well organized with a track record that demonstrates self-motivation,\ncreativity and the initiative to achieve both personal and corporate goals.\nSkills\nSales Management\nAccount Management\nProgram Management\nClient Relationships\nProduct Marketing\nCustomer Retention\nDistribution Strategies\nTeam Leadership\nWine & Spirits/Beverage Industry\nExperience\nFitness Instructor\n \n, \n02/2013\n \nto \nCurrent\n \nCompany Name\n \n\u00e2\u20ac\u201c \nCity\n \n, \nState\n \nTeach energetic workouts that are challenging and motivating, yet safe. Provide students individualized hands-on adjustment throughout class.\nAddress each student by name during class and cultivate long term relationships. Organized the 2014 Fitness Kick-off Challenge in which local\nvendors provided educational seminars/products to inspire a commitment to a healthier lifestyle. Assist clients of all ages and fitness levels in\nimproving health and wellness.\nOwner\n \n, \n01/2011\n \nto \nCurrent\n \nCompany Name\n \n\u00e2\u20ac\u201c \nCity\n \n, \nState\n \nFounder of a stand up paddle board business consisting of retail sales, rentals and lessons. Hands on involvement from lease contract negotiations\nto build-out, to website development and marketing strategy. On site management of all daily operations as well as recruiting, hiring and training\nstaff. Responsible for all aspects of business including inventory management, product education, payroll, and social media outreach. Organized\ncorporate outings and charity fundraisers. Became the first and only Austin stand up paddle board company to offer online reservations for clients.\nAchieved an overall 5 star rating on YELP within the first year of business. The company is closing October 31, 2014.\nCentral Regional Manager\n \n, \n10/2008\n \nto \n03/2011\n \nCompany Name\n \n\u00e2\u20ac\u201c \nCity\n \n, \nState\n \nSuccessfully executed sales and managed an eight state region consisting of two distributors/brokers, with a combined total sales of approximately\n$2.7 million. Developed and implemented a promotional calendar for regional locations of national food stores. Collaborated with corporate\nbuyers on private label product development and program management. Worked as a team with distributor management and staff to educate and\ndevelop programs for increasing product knowledge, market presence and sales. Monthly conference calls with broker principals to review\nperformance, goals and opportunities. Conducted educational tea classes for retail sales partners as well as consumers.\nFine Wine Specialist\n \n, \n2008\n \nto \n2008\n \nCompany Name\n \n\u00e2\u20ac\u201c \nCity\n \n, \nState\n \nDeveloped relationships with on/off premise accounts to identify opportunities for product placement. Conducted wait staff training seminars and\ndesigned wine by the glass programs to support the Diamond portfolio. Assisted with inventory management and stock rotation. Set shelf space,\ncold box and built displays to support supplier promotions and incentive programs. Demonstrated sales abilities through successful presentation\nand promotion of new and existing products and the expansion of business. Met or exceeded assigned monthly quotas and placement objectives.\nWestern Regional Sales Manager\n \n, \n2005\n \nto \n2008\n \nCompany Name\n \n\u00e2\u20ac\u201c \nCity\n \n, \nState\n \nProficiently managed sales in a six state region comprised of eight different distributors/brokers, with combined total sales of approximately\n$1million. Interfaced directly with buyers, distributor management, sales representatives and marketing associates located throughout the territory.\nConducted regular reviews with distributor management to ensure consistent performance to goal. Attended distributor sales meetings to present\nand educate representatives on new and existing products. Designed and implemented various sales incentives with a focus on elevating\nperformance. Provided product training and promotional strategies to sales representatives and restaurant and retail staff. Developed Excel\nprogram to track monthly performance to goal.Increased overall sales in region by 9.5%.\nCalifornia Area Sales Manager\n \n, \n2002\n \nto \n2004\n \nCompany Name\n \n\u00e2\u20ac\u201c \nCity\n \n, \nState\n \nInterfaced with key on/off-premise accounts, working in partnership with the distributor sales force to promote brand building and line expansion\nof existing brands within the portfolio. Conducted trade and public tastings, special promotions and wine maker dinners. Achieved growth in 13\nfocus brands resulting in a 24% increase in sales.\nWine Steward/Educator\n \n, \n2001\n \nto \n2002\n \nCompany Name\n \n\u00e2\u20ac\u201c \nCity\n \n, \nState\n \nInstrumental in developing and implementing the bi-monthly wine class for consumers. Created con",
  "enriched_profile": {
    "fullName": "John Doe",
    "email": "",
    "phone": "",
    "location": "City, State",
    "linkedin": "",
    "github": "",
    "portfolio": "",
    "summary": "Dynamic, entrepreneurial sales executive with a record of achievement and success driving sales growth in highly competitive markets. Solid background securing key clients and increasing product distribution to grow market share. Steadfast in building new business, securing customer loyalty, and developing strong relationships with external business partners. Well organized with a track record that demonstrates self-motivation, creativity and the initiative to achieve both personal and corporate goals.",
    "education": [],
    "experience": [
      {
        "company": "Fitness Instructor",
        "position": "",
        "startDate": "02/2013",
        "endDate": "Current",
        "description": "Teach energetic workouts that are challenging and motivating, yet safe. Provide students individualized hands-on adjustment throughout class. Address each student by name during class and cultivate long term relationships. Organized the 2014 Fitness Kick-off Challenge in which local vendors provided educational seminars/products to inspire a commitment to a healthier lifestyle. Assist clients of all ages and fitness levels in improving health and wellness."
      },
      {
        "company": "Company Name",
        "position": "Owner",
        "startDate": "01/2011",
        "endDate": "Current",
        "description": "Founder of a stand up paddle board business consisting of retail sales, rentals and lessons. Hands on involvement from lease contract negotiations to build-out, to website development and marketing strategy. On site management of all daily operations as well as recruiting, hiring and training staff. Responsible for all aspects of business including inventory management, product education, payroll, and social media outreach. Organized corporate outings and charity fundraisers. Became the first and only Austin stand up paddle board company to offer online reservations for clients. Achieved an overall 5 star rating on YELP within the first year of business. The company is closing October 31, 2014."
      },
      {
        "company": "Company Name",
        "position": "Central Regional Manager",
        "startDate": "10/2008",
        "endDate": "03/2011",
        "description": "Successfully executed sales and managed an eight state region consisting of two distributors/brokers, with a combined total sales of approximately $2.7 million. Developed and implemented a promotional calendar for regional locations of national food stores. Collaborated with corporate buyers on private label product development and program management. Worked as a team with distributor management and staff to educate and develop programs for increasing product knowledge, market presence and sales. Monthly conference calls with broker principals to review performance, goals and opportunities. Conducted educational tea classes for retail sales partners as well as consumers."
      },
      {
        "company": "Company Name",
        "position": "Fine Wine Specialist",
        "startDate": "2008",
        "endDate": "2008",
        "description": "Developed relationships with on/off premise accounts to identify opportunities for product placement. Conducted wait staff training seminars and designed wine by the glass programs to support the Diamond portfolio. Assisted with inventory management and stock rotation. Set shelf space, cold box and built displays to support supplier promotions and incentive programs. Demonstrated sales abilities through successful presentation and promotion of new and existing products and the expansion of business. Met or exceeded assigned monthly quotas and placement objectives."
      },
      {
        "company": "Company Name",
        "position": "Western Regional Sales Manager",
        "startDate": "2005",
        "endDate": "2008",
        "description": "Proficiently managed sales in a six state region comprised of eight different distributors/brokers, with combined total sales of approximately $1million. Interfaced directly with buyers, distributor management, sales representatives and marketing associates located throughout the territory. Conducted regular reviews with distributor management to ensure consistent performance to goal. Attended distributor sales meetings to present and educate representatives on new and existing products. Designed and implemented various sales incentives with a focus on elevating performance. Provided product training and promotional strategies to sales representatives and restaurant and retail staff. Developed Excel program to track monthly performance to goal. Increased overall sales in region by 9.5%."
      },
      {
        "company": "Company Name",
        "position": "California Area Sales Manager",
        "startDate": "2002",
        "endDate": "2004",
        "description": "Interfaced with key on/off-premise accounts, working in partnership with the distributor sales force to promote brand building and line expansion of existing brands within the portfolio. Conducted trade and public tastings, special promotions and wine maker dinners. Achieved growth in 13 focus brands resulting in a 24% increase in sales."
      },
      {
        "company": "Company Name",
        "position": "Wine Steward/Educator",
        "startDate": "2001",
        "endDate": "2002",
        "description": "Instrumental in developing and implementing the bi-monthly wine class for consumers. Created content and format of class material and presented it in a manner that was informative yet fun. As head of the wine department, responsible for driving sales, monthly promotions and all merchandising. Operated in a management capacity when opening or closing the store. Managed staff, reconciled all bank transactions, generated reports and ensured the store was properly stocked and detailed. Provided assistance to customers with wine selections and food/wine pairing, made product recommendations and developed rapport to promote customer loyalty and repeat business."
      },
      {
        "company": "Company Name",
        "position": "Wine Educator",
        "startDate": "2000",
        "endDate": "2001",
        "description": "Responsible for daily operation of the Terrace Wine Bar at the Golden Vine Winery, hosted by Robert Mondavi at Disney's California Adventure. Conducted guided wine tastings for guests and educational seminars and tastings for the restaurant staff."
      }
    ],
    "projects": [],
    "skills": [
      "Sales Management",
      "Account Management",
      "Program Management",
      "Client Relationships",
      "Product Marketing",
      "Customer Retention",
      "Distribution Strategies",
      "Team Leadership",
      "Wine & Spirits/Beverage Industry"
    ],
    "licenses": [
      {
        "title": "2013 Certified Bar Method Fitness Instructor",
        "description": "",
        "issueDate": "2013",
        "expiryDate": ""
      },
      {
        "title": "2012 Certified Power Yoga and Yoga Sculpt Instructor",
        "description": "",
        "issueDate": "2012",
        "expiryDate": ""
      },
      {
        "title": "2002 Court of Masters Sommelier -Level One Certification",
        "description": "",
        "issueDate": "2002",
        "expiryDate": ""
      }
    ]
  }
}