{
  "resume_id": "R0025",
  "content": "FOOD PREP CHEF\nSkills\nHighly skilled in cooking and preparing a variety of cuisines\nInborn ability to explore new cooking avenues\nThorough understanding of sanitation needs of the kitchen\nOperate kitchen equipment such as ovens and grills for cooking purposes\nMaintain knowledge of all recipes so that the Head Chef's place can be filled in effectively in case of absenteeism\nSummary\nExceptional culinary insight.\nKnowledge of standard food preparation\nAbility to work in a high volume environment\nChef in preparing exceptional meals\nMotivated food serving professional with 5+ years food and beverage experience in casual and fine dining.\nHighlights\nKitchen productivity\nBasic knife skills\nUses proper sanitation practices\nAble to regularly lift/move up to 25-50 lbs\nPreparation of various food items\nGood personal hygiene\nTeam-oriented\nWell groomed\nHigh level of cleanly kitchen maintenance\nTeam-oriented\nSandwich preparation experience\nKnowledge of basic food preparation\nFood handling knowledge\nItalian cuisine\nAmerican cuisine\nEthnic foods preparation\nPlate presentation skills\nBanquet operations and off-site catering expert\nAccomplishments\nServe Safe 2015\nSeasoned and cooked food according to recipes or personal judgment and experience.\nEnsured consistent high quality of plate presentation.\nMaintained contact with kitchen staff, management, serving staff and customers.\nBaked, roasted, broiled, and steamed meats, fish, vegetables and other foods.\nSupported all kitchen operations when chef was absent.\nExperience\n09/2010\n \n- \n04/2011\nCompany Name\n \n\u00ef\u00bc\u200b \nCity\n \n, \nState\n \nFood Prep Chef\nFollowed all established restaurant practices and procedures.\nCarefully maintained sanitation, health and safety standards in all work areas.\nPrepared items according to written or verbal orders, working on several different orders simultaneously.\n06/2011\n \n- \n11/2012\nCompany Name\n \n\u00ef\u00bc\u200b \nCity\n \n, \nState\n \nCook\nFollowed all established restaurant practices and procedures.\nMaintained a neat, well groomed appearance including impeccable personal hygiene, hair restraint and minimal jewelry that\nmet company standards.\nClosely followed standard procedures for safe food preparation, assembly and presentation to ensure customer satisfaction.\nCut and chopped food items and cooked on a grill or in fryers.\n12/2012\n \n- \n03/2013\nCompany Name\n \n\u00ef\u00bc\u200b \nCity\n \n, \nState\n \nCook\nOperated large-volume cooking equipment such as grills, deep-fat fryers and griddles.\nTook necessary steps to meet customer needs and effectively resolve food or service issues.\nServed fresh, hot food with a smile in a timely manner.\nAccurately measured ingredients required for specific food items.\nFollowed all established restaurant practices and procedures.\n02/2013\n \n- \n06/2013\nCompany Name\n \n\u00ef\u00bc\u200b \nCity\n \n, \nState\n \nCook\nAssisted co-workers.\nAssisted co-workers.\nCooked food properly and in a timely fashion, using safety precautions\nWeighed, measured, and mixed ingredients according to recipes using various kitchen utensils and equipment\nCleaned and prepared various foods for cooking or serving\n06/2014\n \n- \n11/2014\nCompany Name\n \n\u00ef\u00bc\u200b \nCity\n \n, \nState\n \nChef\nDeveloped strategies to enhance catering and retail food service revenue and productivity goals.\nPrepared healthy, enjoyable breakfasts and dinners for diners.\nEffectively managed and assisted kitchen staff in producing food for banquets, catered events and member dining areas.\nEffectively used items in stock to decrease waste and profit loss.\nEnsured consistent high quality of plate presentation\nSeasoned and cooked food according to recipes or personal judgment and experience\nCreated and explored new cuisines\nInstructed cooks and other workers in the preparation, cooking, garnishing, and presentation of food\nCooked food properly and in a timely fashion, using safety precautions\nUsed all food handling standards\n01/2014\n \n- \n12/2014\nCompany Name\n \n\u00ef\u00bc\u200b \nCity\n \n, \nState\n \nFood Service Cook /Temp\nAssisted co-workers.\nPerformed kitchen maintenance for a private facility.\nResponsible for daily set up of five stations.\nStocked and rotated products, stocked supplies, and paper goods in a timely basis\nStored clean equipment and utensils\nSupervised and coordinated activities of cooks and workers engaged in food preparation\nUsed all food handling standards\nCleaned, cut, and cooked meat, fish, or poultry\nComplied with scheduled kitchen sanitation and ensured all standards and practices were met\nCooked food properly and in a timely fashion, using safety precautions\n01/2015\n \n- \n05/2015\nCompany Name\n \n\u00ef\u00bc\u200b \nCity\n \n, \nState\n \nLine Cook\nConsistently verified that kitchen staff followed all recipes and portioned serving guidelines correctly.\nConsistently kept a clean and safe environment by adhering to all federal, state and local sanitation and safety requirements.\nCommunicated clearly and positively with co-workers and management.\nWorked well with teammates and openly invited coaching from the management team.\nFollowed all established restaurant pr",
  "enriched_profile": {
    "fullName": "John Doe",
    "email": "",
    "phone": "",
    "location": "City, State",
    "linkedin": "",
    "github": "",
    "portfolio": "",
    "summary": "Motivated food serving professional with 5+ years of food and beverage experience in casual and fine dining. Exceptional culinary insight, knowledge of standard food preparation, and ability to work in a high volume environment. Skilled in preparing exceptional meals, kitchen productivity, and team-oriented ethics.",
    "education": [
      {
        "school": "William M Davies Career & Tech",
        "degree": "High School Diploma",
        "field": "Culinary/ Auto Body",
        "startDate": "2011",
        "endDate": "",
        "gpa": ""
      }
    ],
    "experience": [
      {
        "company": "Company Name",
        "position": "Food Prep Chef",
        "startDate": "09/2010",
        "endDate": "04/2011",
        "description": "Followed all established restaurant practices and procedures. Maintained sanitation, health, and safety standards in all work areas. Prepared items according to written or verbal orders, working on several different orders simultaneously."
      },
      {
        "company": "Company Name",
        "position": "Cook",
        "startDate": "06/2011",
        "endDate": "11/2012",
        "description": "Followed all established restaurant practices and procedures. Maintained a neat, well-groomed appearance. Closely followed standard procedures for safe food preparation, assembly, and presentation to ensure customer satisfaction. Cut and chopped food items and cooked on a grill or in fryers."
      },
      {
        "company": "Company Name",
        "position": "Cook",
        "startDate": "12/2012",
        "endDate": "03/2013",
        "description": "Operated large-volume cooking equipment such as grills, deep-fat fryers, and griddles. Took necessary steps to meet customer needs and effectively resolve food or service issues. Served fresh, hot food with a smile in a timely manner."
      },
      {
        "company": "Company Name",
        "position": "Cook",
        "startDate": "02/2013",
        "endDate": "06/2013",
        "description": "Assisted co-workers. Weighed, measured, and mixed ingredients according to recipes using various kitchen utensils and equipment. Cleaned and prepared various foods for cooking or serving."
      },
      {
        "company": "Company Name",
        "position": "Chef",
        "startDate": "06/2014",
        "endDate": "11/2014",
        "description": "Developed strategies to enhance catering and retail food service revenue and productivity goals. Prepared healthy, enjoyable breakfasts and dinners for diners. Effectively managed and assisted kitchen staff in producing food for banquets, catered events and member dining areas."
      },
      {
        "company": "Company Name",
        "position": "Food Service Cook /Temp",
        "startDate": "01/2014",
        "endDate": "12/2014",
        "description": "Assisted co-workers. Performed kitchen maintenance for a private facility. Responsible for daily set up of five stations. Stocked and rotated products, stocked supplies, and paper goods in a timely basis."
      },
      {
        "company": "Company Name",
        "position": "Line Cook",
        "startDate": "01/2015",
        "endDate": "05/2015",
        "description": "Consistently verified that kitchen staff followed all recipes and portioned serving guidelines correctly. Consistently kept a clean and safe environment by adhering to all federal, state and local sanitation and safety requirements."
      }
    ],
    "projects": [
      {
        "name": "",
        "techStack": "",
        "description": "",
        "link": ""
      }
    ],
    "skills": [
      "Kitchen productivity",
      "Basic knife skills",
      "Sanitation practices",
      "Food handling knowledge",
      "Plate presentation skills",
      "Banquet operations",
      "Catering expertise"
    ],
    "licenses": [
      {
        "title": "Serve Safe 2015",
        "description": "",
        "issueDate": "2015",
        "expiryDate": ""
      }
    ]
  }
}