{
  "resume_id": "R0029",
  "content": "CONSULTANT\nProfessional Summary\nAstute and innovative attorney with strong ability to develop and implement effective litigation case strategies and write persuasive motions. Proven\nability to resolve complex cases in clients' favor.\u00c2  Meticulous, conscientious, tenacious, organized, analytical, and able to thrive in dynamic\nenvironments.\u00c2 \u00c2  \nSkills\nCourt Procedures\nLegal Document Preparation\nStrong Researcher\nStrong Negotiator\nOrganization\nCommunication\nLeadership\nTeam Player\nLitigation Management\nDetailed-Oriented \u00c2  \u00c2  \u00c2  \u00c2  \u00c2 \u00c2 \nDue Dilligence\nDeposition\nMotion Practice\u00c2 \nRegulatory Compliance\nRisk Management\nStrong Writer\nCivil Litigation\nQuality Assurance\nProfessional and Personable\nAnalytical\nWork History\nConsultant\n \n06/2014\n \nto \nCurrent\n \nCompany Name\n \n\u00e2\u20ac\u201c \nCity\n \n, \nState\n \nServe as consultant attorney to major Virgin Islands' law firm that represents individuals, classes, and organizations in plaintiff-side civil litigation,\ninvolving areas of contracts, commercial transactions, trusts, bankruptcy, personal injury, and discrimination on the basis of race, national origin,\nsex, disability, and age.\u00e2\u20ac\u2039\u00c2 \nConduct legal research in complex litigation matters.\nDraft pleadings, oppositions to motion to dismiss, summary judgment, daubert motions, and appellate briefs.\nConduct discovery.\nInterpret laws, rulings and regulations for individuals and businesses.\nSpecial Assistant Corporation Counsel\n \n03/2011\n \nto \n05/2014\n \nCompany Name\n \n\u00e2\u20ac\u201c \nCity\n \n, \nState\n \nServed as Special Assistant Corporation Counsel in the Special Federal Litigation Division, a specialized division created to defend the City and its\nofficials in civil rights cases brought exclusively in federal courts pursuant to the United States Constitution and 42 U.S.C. Section 1983, in which\nmisconduct was claimed against the\u00c2 police, District Attorney, correction officer, and the Mayor of the City of New York.\nMade frequent appearances in federal courts and managed heavy caseload.\nEvaluated cases and negotiated settlements.\nRepresented clients at settlement conferences and mediations.\nDrafted pleadings, memoranda, settlement agreements, motions, interrogatories and requests for production of documents, initial disclosures, joint\npre-trial orders, and letters.\nDeveloped and executed investigative strategies.\nConducted discovery, including taking and defending depositions, and prepared cases for trial.\nInvestigated alleged criminal and constitutional law violations.\nConducted legal research and analysis.\nInterviewed clients and witnesses.\nMade presentations to division attorneys and supervisors regarding case developments and strategies.\nDeveloped strategies and arguments in preparation for presentation of cases.\nInterpreted laws, rulings and regulations for clients.\nAttorney\n \n01/2010\n \nto \n01/2011\n \nCompany Name\n \n\u00e2\u20ac\u201c \nCity\n \n, \nState\n \nServed as principal attorney in practice primarily focused \n\u00c2 on family and immigration laws.\nCounseled clients on a variety of matters including compliance with various regulations and codes.\nConducted factual and legal investigations.\nDrafted pleadings and motions.\nFiled and argued motions.\nDesigned discovery plans and conducted discovery.\nDeveloped and successfully implemented case strategies.\nNegotiated and drafted settlement and commercial lease agreements.\nRepresented client at hearings.\nConsultant Attorney\n \n12/2005\n \nto \n12/2009\n \nCompany Name\n \n\u00e2\u20ac\u201c \nCity\n \n, \nState\n \nServed as Consultant Attorney by Assisting several law firms during \u00c2 civil litigation, white collar criminal litigation, and SEC and DOJ\ninvestigations regarding matters involving allegations of fraud, anti-money laundering violations, and antiitrust violations.\nAnalyzed financial documentation and communications such risk alerts and Suspicious Activity Reports (SAR) to identify regulatory risks and\nwhether company exceeded its risk appetite in violation of company's own procedures. \u00c2 \nReviewed transactions and communications for fraud, \u00c2 illegal wire transfers, suspicious activities, breach of contract, breach of\u00c2  fiduciary duties,\nand regulatory violations. \u00c2 \nPerformed second level and quality control review to ensure documentation was correctly annotated and categorized prior to production to\ngovernment regulators, and adverse parties. \u00e2\u20ac\u00a8\nReviewed and analyzed documents to determine if method of calculating out-of-network benefits violated ERISA, RICO, the Sherman Act and\nstate law. \u00c2  \u00c2  \u00c2  \u00c2 \nConducted due diligence to ensure merger/acquisition did not violate U.S. antitrust law. \nConducted legal research, developed case theories, and drafted memoranda.\nAssisted in deposition and trial preparation by drafting privilege logs.\nFirms:\n \nJenner & Block; Arkin, Kaplan & Rice; Debevoise & Plimpton.\nEducation\nJ.D.\n \n: \nLaw\n \nMay 2005\n \nFordham University School of Law\n \n- \nCity\n \n, \nState\n \nGPA: \nFordham Journal of Corporate and Financial Law, Staff Member *Dean's recognition for successfully representing client in immigration case\n*",
  "enriched_profile": {
    "fullName": "Astute Consultant",
    "email": "",
    "phone": "",
    "location": "City, State",
    "linkedin": "",
    "github": "",
    "portfolio": "",
    "summary": "Astute and innovative attorney with strong ability to develop and implement effective litigation case strategies and write persuasive motions. Proven ability to resolve complex cases in clients' favor. Meticulous, conscientious, tenacious, organized, analytical, and able to thrive in dynamic environments. Strong researcher, negotiator, communicator, leader, team player, litigation manager, and writer.",
    "education": [
      {
        "school": "Fordham University School of Law",
        "degree": "J.D.",
        "field": "Law",
        "startDate": "May 2005",
        "endDate": "",
        "gpa": ""
      },
      {
        "school": "John Jay College of Criminal Justice",
        "degree": "Bachelor of Arts",
        "field": "Criminal Justice",
        "startDate": "May 2000",
        "endDate": "",
        "gpa": "Magna Cum Laude"
      }
    ],
    "experience": [
      {
        "company": "Company Name",
        "position": "Consultant",
        "startDate": "06/2014",
        "endDate": "Current",
        "description": "Serve as consultant attorney to major Virgin Islands' law firm that represents individuals, classes, and organizations in plaintiff-side civil litigation, involving areas of contracts, commercial transactions, trusts, bankruptcy, personal injury, and discrimination on the basis of race, national origin, sex, disability, and age. Conduct legal research in complex litigation matters. Draft pleadings, oppositions to motion to dismiss, summary judgment, daubert motions, and appellate briefs. Conduct discovery. Interpret laws, rulings and regulations for individuals and businesses."
      },
      {
        "company": "Company Name",
        "position": "Special Assistant Corporation Counsel",
        "startDate": "03/2011",
        "endDate": "05/2014",
        "description": "Served as Special Assistant Corporation Counsel in the Special Federal Litigation Division, a specialized division created to defend the City and its officials in civil rights cases brought exclusively in federal courts pursuant to the United States Constitution and 42 U.S.C. Section 1983, in which misconduct was claimed against the police, District Attorney, correction officer, and the Mayor of the City of New York. Made frequent appearances in federal courts and managed heavy caseload. Evaluated cases and negotiated settlements. Represented clients at settlement conferences and mediations. Drafted pleadings, memoranda, settlement agreements, motions, interrogatories and requests for production of documents, initial disclosures, joint pre-trial orders, and letters. Developed and executed investigative strategies. Conducted discovery, including taking and defending depositions, and prepared cases for trial. Investigated alleged criminal and constitutional law violations. Conducted legal research and analysis. Interviewed clients and witnesses. Made presentations to division attorneys and supervisors regarding case developments and strategies. Developed strategies and arguments in preparation for presentation of cases. Interpreted laws, rulings and regulations for clients."
      },
      {
        "company": "Company Name",
        "position": "Attorney",
        "startDate": "01/2010",
        "endDate": "01/2011",
        "description": "Served as principal attorney in practice primarily focused on family and immigration laws. Counseled clients on a variety of matters including compliance with various regulations and codes. Conducted factual and legal investigations. Drafted pleadings and motions. Filed and argued motions. Designed discovery plans and conducted discovery. Developed and successfully implemented case strategies. Negotiated and drafted settlement and commercial lease agreements. Represented client at hearings."
      },
      {
        "company": "Company Name",
        "position": "Consultant Attorney",
        "startDate": "12/2005",
        "endDate": "12/2009",
        "description": "Served as Consultant Attorney by Assisting several law firms during civil litigation, white collar criminal litigation, and SEC and DOJ investigations regarding matters involving allegations of fraud, anti-money laundering violations, and antiitrust violations. Analyzed financial documentation and communications such risk alerts and Suspicious Activity Reports (SAR) to identify regulatory risks and whether company exceeded its risk appetite in violation of company's own procedures. Reviewed transactions and communications for fraud, illegal wire transfers, suspicious activities, breach of contract, breach of fiduciary duties, and regulatory violations. Performed second level and quality control review to ensure documentation was correctly annotated and categorized prior to production to government regulators, and adverse parties. Reviewed and analyzed documents to determine if method of calculating out-of-network benefits violated ERISA, RICO, the Sherman Act and state law. Conducted due diligence to ensure merger/acquisition did not violate U.S. antitrust law. Conducted legal research, developed case theories, and drafted memoranda. Assisted in deposition and trial preparation by drafting privilege logs. Firms: Jenner & Block; Arkin, Kaplan & Rice; Debevoise & Plimpton."
      }
    ],
    "projects": [],
    "skills": [
      "Court Procedures",
      "Legal Document Preparation",
      "Strong Researcher",
      "Strong Negotiator",
      "Organization",
      "Communication",
      "Leadership",
      "Team Player",
      "Litigation Management",
      "Detailed-Oriented",
      "Due Dilligence",
      "Deposition",
      "Motion Practice",
      "Regulatory Compliance",
      "Risk Management",
      "Quality Assurance",
      "Professional and Personable",
      "Analytical"
    ],
    "licenses": []
  }
}