{
  "resume_id": "R0027",
  "content": "BUSINESS DEVELOPMENT DIRECTOR\nSummary\nI collaborate with multiple stakeholders to determine audience needs, quickly developing strategic plans that align with my clients business priorities\nand strategies.\nExperience\nBusiness Development Director\n \n05/1997\n \nto \nCurrent\n \nCompany Name\n \nCity\n \n, \nState\nProducing measurable results for my clients by designing unique engagement initiatives for employees, sales channel partners and consumers\ngroups. Sales of performance improvement products, most being intangible services to Fortune 500 clients. Success at discovering and growing\nmy business with customers who have the potential to spend more than $1 million with me each year.\nI have designed innovative solutions, customized to each customers various objectives and end result needs.\nManaging my internal teams to develop, design and operate complex custom projects ranging in value at least $150,000 to millions.\nTitles called on include the entire C suite, CEO, COO, CFO, CMO, President, EVP's of Marketing, Sales, Human Resources & Finance.\nDefine business issues to improve revenue and penetrating existing accounts and opening new.\nSold 17 new accounts while in current position, managed sales volume and profit margin with long sales cycle.\nManaged and hired staff of 4 to work with my major global account travel & meetings business over 8 years.\nTotal book of business constantly over $2.5 million each year.\nNearly twice the entertainment activity of other BDD's with similar tenure.\nAchieved over $6 million in sales twice, becoming a trusted partner to my clients, customers want me to Win!\nAccount Territory & District Sales Manager / National Account Sales\n \n08/1989\n \nto \n04/1997\n \nCompany Name\n \nCity\n \n, \nState\nResponsible for growth of distributor sales volume, product mix and motivation of DSR sales forces.\nDeveloped my own custom local training and marketing materials, which were later adopted by the Nestle corporate.\nDistributor and chain accounts accounted for over $11 million in sales.\nIncreased my chain accounts by over 75% while with national accounts.\nCreated sales forecasts, developed budgets, strategic plans and managed entire regional office staff. Working with my team we grew\nbusiness at Nestle largest US account by nearly double.\nSurpassed sales, budget goals every year as manager and twice led company nationally in new product introductions.\nDistrict sales grew from $16 million to over $22 million as district manager. Hired five salespeople and 4 direct reports were promoted,\nmanaged up to eight account managers at a time.\nDeveloped new reports, marketing and promotional strategies for the field. Designed account reviews process, management and field\ntraining programs for the entire company.\nSold small business owners and managed distributor sales accounts, using strategic planning, innovative programming and by cultivating\nstrong personal relationships. Took area territory sales from $500,000 to $2.9 million, with a mature company in an industry with an\naverage annual increase of only 3-5%.\nFinancial Operations Executive and Department Merchandising Manager\n \n04/1988\n \nto \n08/1989\n \nCompany Name\n \nCity\n \n, \nState\n \nFinancial Operations\nExecutive for the South Bend store. Volunteered to be merchandise manager for the stores largest department. While in this role the department\nhad the highest per foot sales volume of any department in the entire corporation during the 4th quarter of 1988.\nAccomplishments\n4 times President Achievement Guild Award winner, award for sales volume and profit.\n3 times President Achievement Award winner, award for sales volume and profit.\n4 times Achievement Guild winner, for leadership in 3 year running combined volume.\nTop travel and meetings sales several times since with BIW.\nNational sales contest \"the 1993 Superbowl\".\nTwice awarded \"The Over Achiever of the Year\" by my most profitable direct customer.\nReviewed consistently by management throughout career as \"Outstanding or Exceeding Expectations\".\nCollege: elected to executive positions with both Finance Club and Resident Housing Association.\nSkills\nSales, Business Development, Distributor Sales, Territory Sales, District Sales, Sales of Solutions, Sales Teams, Sales Accounts, National\nAccounts, Sales Management, Strategic Accounts, Sales Promotions, Travel & Meeting Sales, Technology Application Sales, Clients\nManagement, Marketing, Budget, Budgets, Forecasts, Promotional, Travel & Meeting Operations, Strategic Planning, Training, Training\nDevelopment, Financial Operations, Merchandising, Corporate Operations, Employee Engagement, Managing Existing Accounts, Forecasting,\nHuman Resources, Finding New Accounts, Relationship Building and Strategic Direction.\nEducation\nBachelor of Business Administration\n \n: \nFinance, General Business\n \n1988\n \nWestern Michigan University\n \nCity\n \n, \nState\n \n, \nUS\nEarned over 85% of all educational/living costs. Jobs worked while in college, industrial heavy construction, excelled at sev",
  "enriched_profile": {
    "fullName": "BUSINESS DEVELOPMENT DIRECTOR",
    "email": "",
    "phone": "",
    "location": "City, State",
    "linkedin": "",
    "github": "",
    "portfolio": "",
    "summary": "Collaborates with stakeholders to determine audience needs and develop strategic plans aligning with business priorities. Proven track record in sales, business development, sales management, and strategic planning.",
    "education": [
      {
        "school": "Western Michigan University",
        "degree": "Bachelor of Business Administration",
        "field": "Finance, General Business",
        "startDate": "1984",
        "endDate": "1988",
        "gpa": ""
      }
    ],
    "experience": [
      {
        "company": "Company Name",
        "position": "Business Development Director",
        "startDate": "05/1997",
        "endDate": "Present",
        "description": "Produce measurable results for clients by designing unique engagement initiatives for employees, sales channel partners, and consumer groups. Sold 17 new accounts, managed sales volume and profit margin, and managed a staff of 4."
      },
      {
        "company": "Company Name",
        "position": "Account Territory & District Sales Manager / National Account Sales",
        "startDate": "08/1989",
        "endDate": "04/1997",
        "description": "Responsible for growth of distributor sales volume, product mix, and motivation of DSR sales forces. Increased chain accounts by over 75% and surpassed sales, budget goals every year as manager."
      },
      {
        "company": "Company Name",
        "position": "Financial Operations Executive and Department Merchandising Manager",
        "startDate": "04/1988",
        "endDate": "08/1989",
        "description": "Financial Operations Executive for the South Bend store and volunteered to be merchandise manager for the stores largest department."
      }
    ],
    "projects": [],
    "skills": [
      "Sales",
      "Business Development",
      "Distributor Sales",
      "Territory Sales",
      "District Sales",
      "Sales of Solutions",
      "Sales Teams",
      "Sales Accounts",
      "National Accounts",
      "Sales Management",
      "Strategic Accounts",
      "Sales Promotions",
      "Travel & Meeting Sales",
      "Technology Application Sales",
      "Clients Management",
      "Marketing",
      "Budget",
      "Forecasts",
      "Promotional",
      "Travel & Meeting Operations",
      "Strategic Planning",
      "Training",
      "Training Development",
      "Financial Operations",
      "Merchandising",
      "Corporate Operations",
      "Employee Engagement",
      "Managing Existing Accounts",
      "Forecasting",
      "Human Resources",
      "Finding New Accounts",
      "Relationship Building",
      "Strategic Direction"
    ],
    "licenses": []
  }
}