{
  "resume_id": "R0023",
  "content": "WORKING RF SYSTEMS ENGINEER\nQualifications\nMicrosoft office/Office for Mac, pages, numbers, keynote \u00c2\u00b7 RF/Microwave software: Ansoft Designer, AWR Microwave Office. \u00c2\u00b7 RF test\ninstruments: Spectrum analyzer, Vector Network/Signal Analyzer, Logic Analyzer, etc. \u00c2\u00b7 Programming language: C/C++, Python, Java,\nMatlab, and LabView \u00c2\u00b7 Circuit design software: SPICE, NI Multisim \u00c2\u00b7 PCB design software: Eagle, PCB Artiest\nExperience\nWorking \nRF Systems Engineer\n \nMay 2014\n \nto \nCurrent\n \nCompany Name\nQualification \n\u00c2\u00b7 Multidisciplinary background: RF hardware designs, manufacturing operations and data analyst.\nSummary \n\u00c2\u00b7 Experienced in developing hardware's DFM procedures, checklists and requirements to subcontractors \u00c2\u00b7 Perform EVT,\nDVT, PVT verifications and utilize FA process to drive root cause from system to unit level \u00c2\u00b7 Team leader on multiple end-to-end\ntechnical project design, development, testing and validation \u00c2\u00b7 Manage Test/Production readiness reviews and drives quality requirement\nfor post-ramp qualification \u00c2\u00b7 Ability to manage multiple projects simultaneously, self-starter with innovation and sharp attention to details\nExperiences \n- New RF systems introduction on satellite communication architecture designs and proposals - Define RF hardware unit DFM\nprocedures and requirements for Antenna, receivers, filters, and amplifiers - Lead suppliers by providing technical design specifications and\ntesting requirements to meet SSL standards - Utilize FA process to monitor overall project field performance.\nAudits and DFM reviews on-site with suppliers - Investigated the algorithm to optimize the overall RF system performance for design,\nmanufacturing and testing - Perform EVT, DVT and PVT validations and quality measurements for satellite assembly at system and unit\nlevels - Drive and track closure on any RF components and modules NCs and issues impact to production readiness - Work with cross-\nfunctional teams to execute completion of satellite system design to fulfill contract requirement - Generate cascade RF performance\nprediction analyses (i.e.\nNF, Gain, IP3, 1dB-Comp, spurious, etc) - Exercises independent judgment in developing methods, techniques, and evaluation criterion for\nobtaining results - Monitor and measure manufacturing processes to reduce losses, decrease time span and improve quality.\nSystem Data Analyst\n \nAugust 2011\n \nto \nDecember 2013\n \nCompany Name\nPrioritize and extract big data from Purdue University's SQL database and maintain its accuracy and completeness - Develop and\nimplement data collection systems strategies that optimize statistical efficiency and data quality - Data manipulation language SQL\ncommands and utilize statistical tools including Excel, SAS, and SPSS.\nCreate complex charts and temporarily databases, perform data mining, and develop pivot tables for publication - Design and customize\nreports based upon data structure and determine additional data collection requirements - Provide documentation based on audit and report\ncriteria to investigators and research staff - Serve as a resource for non-routine inquiries such as requests for statistics or surveys.\nElectrical/Validation Engineer\n \nMay 2011\n \nto \nAugust 2011\n \nCompany Name\nDevelop and maintain data requirement for PCBA EVT, DVT, and PVT assembly for touch-pads - Design and implement automated test\nfor sensitivity, packrat, hovering, profiles, ripple, GSM, EMI, and ESD - Monitor manufacturer IC packaging test yields and field return\nfailure data to identify root cause - Develop in-depth reliability testing procedures: storage, thermal stock, drop and tap tests - Perform\ndebug and troubleshooting of product in house and at contract manufacturer site for support - Contribute in manufacturing diagnostic\nreviews to improve overall debug process more efficiently and effectively - Support internal and external customer related to lab data\ncollection and verification of an application issue.\nEducation\nM.S\n \n: \nElectrical and Computer Engineering\n \n, \nDec. 2013\n \nPURDUE UNIVERSITY\n \nGPA: \nGPA: 3.9/4.0\n \nElectrical and Computer Engineering GPA:\n3.9/4.0\nB.S\n \n: \nElectrical and Computer Engineering\n \n, \nDec. 2011\n \nGPA: \nGPA: 3.2/4.0\n \nElectrical and Computer Engineering GPA: 3.2/4.0 Thesis \nThe Design\nand Evaluation of a 5.8 GHz Laptop-Based Radar System Publication \n\u00c2\u00b7 Innovative laptop radar design to operate in both FMCW and CW\nmode \u00c2\u00b7 Doppler shift (DTI), ranging (RTI), and SAR measurement capability \u00c2\u00b7 Operate in ISM frequency band with +13dBm transmitting\npower \u00c2\u00b7 Data acquisition and signal processing using Matlab\nSkills\nbig data, C, C++, charts, Circuit design, hardware, Data acquisition, data analyst, data collection, data mining, databases, database, dBm, DTI,\ndesign software, documentation, functional, GSM, innovation, Java, LabView, Team leader, Logic Analyzer, Mac, manufacturing processes,\nMatlab, Excel, Microsoft office, Office, Microwave, Radar, NCs, Network, dB, packaging, pivot tables, Programming, proje",
  "enriched_profile": {
    "fullName": "John Doe",
    "email": "",
    "phone": "",
    "location": "City, State",
    "linkedin": "linkedin.com/in/john-doe",
    "github": "github.com/johndoe",
    "portfolio": "",
    "summary": "Experienced RF Systems Engineer with a multidisciplinary background in hardware designs, manufacturing operations, and data analysis. Skilled in developing DFM procedures, FA process, and leading technical projects. Also experienced as a System Data Analyst and Electrical/Validation Engineer.",
    "education": [
      {
        "school": "Purdue University",
        "degree": "M.S.",
        "field": "Electrical and Computer Engineering",
        "startDate": "August 2011",
        "endDate": "Dec. 2013",
        "gpa": "3.9/4.0"
      },
      {
        "school": "Purdue University",
        "degree": "B.S.",
        "field": "Electrical and Computer Engineering",
        "startDate": "Dec. 2011",
        "endDate": "",
        "gpa": "3.2/4.0"
      }
    ],
    "experience": [
      {
        "company": "Company Name",
        "position": "RF Systems Engineer",
        "startDate": "May 2014",
        "endDate": "Current",
        "description": "Experienced in developing hardware's DFM procedures, checklists and requirements to subcontractors. Perform EVT, DVT, PVT verifications and utilize FA process to drive root cause from system to unit level. Team leader on multiple end-to-end technical project design, development, testing and validation. Manage Test/Production readiness reviews and drives quality requirement for post-ramp qualification. Ability to manage multiple projects simultaneously, self-starter with innovation and sharp attention to details."
      },
      {
        "company": "Company Name",
        "position": "System Data Analyst",
        "startDate": "August 2011",
        "endDate": "December 2013",
        "description": "Prioritize and extract big data from Purdue University's SQL database and maintain its accuracy and completeness. Develop and implement data collection systems strategies that optimize statistical efficiency and data quality. Data manipulation language SQL commands and utilize statistical tools including Excel, SAS, and SPSS. Create complex charts and temporarily databases, perform data mining, and develop pivot tables for publication."
      },
      {
        "company": "Company Name",
        "position": "Electrical/Validation Engineer",
        "startDate": "May 2011",
        "endDate": "August 2011",
        "description": "Develop and maintain data requirement for PCBA EVT, DVT, and PVT assembly for touch-pads. Design and implement automated test for sensitivity, packrat, hovering, profiles, ripple, GSM, EMI, and ESD. Monitor manufacturer IC packaging test yields and field return failure data to identify root cause. Develop in-depth reliability testing procedures: storage, thermal stock, drop and tap tests. Perform debug and troubleshooting of product in house and at contract manufacturer site for support."
      }
    ],
    "projects": [
      {
        "name": "The Design and Evaluation of a 5.8 GHz Laptop-Based Radar System",
        "techStack": "Matlab, FMCW, CW, Doppler shift (DTI), ranging (RTI), SAR measurement capability, ISM frequency band, data acquisition, signal processing",
        "description": "Innovative laptop radar design to operate in both FMCW and CW mode. Doppler shift (DTI), ranging (RTI), and SAR measurement capability. Operate in ISM frequency band with +13dBm transmitting power. Data acquisition and signal processing using Matlab.",
        "link": ""
      }
    ],
    "skills": [
      "big data",
      "C",
      "C++",
      "charts",
      "Circuit design",
      "hardware",
      "Data acquisition",
      "data analyst",
      "data collection",
      "data mining",
      "databases",
      "database",
      "dBm",
      "DTI",
      "design software",
      "documentation",
      "functional",
      "GSM",
      "innovation",
      "Java",
      "LabView",
      "Team leader",
      "Logic Analyzer",
      "Mac",
      "manufacturing processes",
      "Matlab",
      "Excel",
      "Microsoft office",
      "Office",
      "Microwave",
      "Radar",
      "NCs",
      "Network",
      "dB",
      "packaging",
      "pivot tables",
      "Programming",
      "project design",
      "proposals",
      "Publication",
      "Python",
      "quality",
      "requirement",
      "research",
      "SAS",
      "self-starter",
      "Spectrum analyzer",
      "SPSS",
      "SQL",
      "SSL",
      "statistics",
      "surveys",
      "system design",
      "troubleshooting",
      "validation"
    ],
    "licenses": []
  }
}