{
  "resume_id": "R0026",
  "content": "CONSTRUCTION SITE MANAGER\nSummary\nsupervising and overseeing the direction of the project (or a package), ensuring that the client's specifications and requirements are met, reviewing\nprogress and liaising with quantity surveyors to monitor costs\nliaising with the client, other construction professionals and, sometimes, members of the public\ncoordinating and supervising construction workers\nselecting tools and materials\nmaking safety inspections and ensuring construction and site safety\nchecking and preparing site reports, designs and drawings\nmaintaining quality control procedures\nfinding ways to prevent problems and to solve any that crop up\nassessing and minimising risk\nwriting reports and keeping on top of paperwork\nhelping to negotiating contracts and securing permits and licences\nAs construction managers work on site wherever that site is, be prepared to relocate or face a longer commute as and when required.\nSkills\nGood communication skills\nProblem solving skills\nDecision-making ability\nCommercial awareness\nAbility to motivate other\nTeamworking skills\nGood knowledge of building methods and regulations\nCustomer service\nAccount management\nBusiness-to-business background\nCapital planning\nStaff training\nContract negotiation\nNetworking ability\nLead development\nProduct expertise\nCrisis communications\nMarketing\nBlueprint reading\nRegulation and compliance\nExcellent driving record\nDetail-oriented\nGood mechanical aptitude\nProduction line/assembly line forklift experience\nGood verbal/written communication skills\nEstablishing goals and setting priorities\nExperience\n03/2006\n \nto \n12/2012\nConstruction site manager\n \nCompany Name\n \n\u00ef\u00bc\u200b \nCity\n \n, \nState\nConferred with sales and marketing teams to ensure consistency in messaging and communication with business partners and customers, and\nto relay insight from data collected to shape successful marketing campaigns.\nConducted strengths, weakness, opportunities and threats (SWOT) analyses to develop strategic plans for corporate level and business\nunits.\nWorked with current clients to assess needs and develop improvement plans.\nStayed current on company products and services to provide top-notch expertise to customers.\nSet up potential client contacts, cultivated relationships and followed through all service needs.\nPut together contracts and completed sales with new and existing clients.\n02/2003\n \nto \n06/2006\nConstruction Superintendent\n \nCompany Name\n \n\u00ef\u00bc\u200b \nCity\n \n, \nState\nMaintained a written daily log of activities on the job site.\nReviewed project drawings to perform \u00c2 materials purchasing\u00c2 \nReviewed project drawings to perform \u00c2 materials\n\u00c2 Evaluated plans architectural plans and consulted with \u00c2 Subcontractors \u00c2 to gain a deep understanding of project &\nProvided equipment installations for a developing residential community of 40 units, working successfully according to project plans and\nquality standards.\nReviewed engineering documentation to determine order of construction operations.\nAssisted skilled workers with construction projects in all phases of rough and finish carpentry.\nConducted site pre-inspections and coordinated post-construction audits.\nManaged work with little supervision.\nTroubleshooted electrical and mechanical defects for residential, commercial and industrial sites.\nEnsured customer satisfaction by providing highest quality of products by ensuring all equipment was \u00c2 properly installed and working\ncorrectly.\n07/2011\n \nto \n10/2017\nSite Supervisor/Foreman\n \nCompany Name\n \n\u00ef\u00bc\u200b \nCity\n \n, \nState\nKept track of all inventory, including supplies and materials to help ensure against loss.\nGathered project material submittals and maintained records of approvals.\nMonitored project expenses and developed pre-construction estimates.\nMaintained a written daily log of activities on the job site.\nReviewed project drawings to perform installation activities according to specifications.\nEvaluated plans architectural plans and consulted with clients to gain a deep understanding of project plan and objectives.\nEducation and Training\n1997\nAssociate of Arts\n \n: \nCriminal Justice\n \nTallahassee Community College\n \n\u00ef\u00bc\u200b \nCity\n \n, \nState\n2020\nAssociate of Science\n \n: \nGraphic Design\n \nAcademy of Art University\n \n\u00ef\u00bc\u200b \nCity\n \n, \nState\nActivities and Honors\nClass\nExperience\nWorked closely with construction teams at a variety of work sites.\nResponsible for daily reporting on production equipment, including parts produced, downtime minutes, and any quality concerns.\nBlueprint Reading\nRead blueprints, work orders, and production schedules to accurately determine job instructions and specifications.\nProblem Diagnosis\n \nUsed operational knowledge of systems, parts and components to solve problems that arose during construction\u00c2 \nInspection\n \nInspected electrical systems, equipment, and fixtures to identify safety hazards for replacement or repair.\u00c2 \nProject Planning\nProvided project controls, cost estimation, and other business support services to technical line management.\nS",
  "enriched_profile": {
    "fullName": "John Doe",
    "email": "",
    "phone": "",
    "location": "City, State",
    "linkedin": "",
    "github": "",
    "portfolio": "",
    "summary": "Experienced Construction Site Manager with a proven track record of supervising and overseeing projects, liaising with clients and professionals, coordinating and supervising workers, and maintaining quality control. Skilled in communication, problem-solving, decision-making, commercial awareness, teamwork, and safety inspections.",
    "education": [
      {
        "school": "Tallahassee Community College",
        "degree": "Associate of Arts",
        "field": "Criminal Justice",
        "startDate": "1997",
        "endDate": "",
        "gpa": ""
      },
      {
        "school": "Academy of Art University",
        "degree": "Associate of Science",
        "field": "Graphic Design",
        "startDate": "2020",
        "endDate": "",
        "gpa": ""
      }
    ],
    "experience": [
      {
        "company": "Company Name",
        "position": "Construction Site Manager",
        "startDate": "03/2006",
        "endDate": "12/2012",
        "description": "Conferred with sales and marketing teams to ensure consistency in messaging and communication. Conducted SWOT analyses to develop strategic plans. Worked with clients to assess needs and develop improvement plans. Stayed current on company products and services. Set up potential client contacts and followed through on service needs. Put together contracts and completed sales with new and existing clients."
      },
      {
        "company": "Company Name",
        "position": "Construction Superintendent",
        "startDate": "02/2003",
        "endDate": "06/2006",
        "description": "Maintained a written daily log of activities. Reviewed project drawings for materials purchasing and installation activities. Evaluated architectural plans and consulted with subcontractors to gain a deep understanding of project plans. Assisted skilled workers with construction projects. Conducted site pre-inspections and coordinated post-construction audits. Managed work with little supervision. Troubleshot electrical and mechanical defects. Ensured customer satisfaction by providing properly installed and working equipment."
      },
      {
        "company": "Company Name",
        "position": "Site Supervisor/Foreman",
        "startDate": "07/2011",
        "endDate": "10/2017",
        "description": "Kept track of inventory, gathered project material submittals, monitored project expenses, reviewed project drawings, evaluated plans, and consulted with clients. Maintained a written daily log of activities."
      }
    ],
    "projects": [],
    "skills": [
      "Good communication skills",
      "Problem solving skills",
      "Decision-making ability",
      "Commercial awareness",
      "Ability to motivate others",
      "Teamworking skills",
      "Good knowledge of building methods and regulations",
      "Customer service",
      "Account management",
      "Business-to-business background",
      "Capital planning",
      "Staff training",
      "Contract negotiation",
      "Networking ability",
      "Lead development",
      "Product expertise",
      "Crisis communications",
      "Marketing",
      "Blueprint reading",
      "Regulation and compliance",
      "Establishing goals and setting priorities"
    ],
    "licenses": []
  }
}