{
  "resume_id": "R0024",
  "content": "FITNESS ATTENDANT\nSummary\nHighly-motivated Nutritionist with a masters degree seeking a career position in the healthcare field. Goal-oriented and high-achieving professional\nwith advanced knowledge and skills in nutrition. Hi\n ghly effective at evaluating the nutritional needs of both adults and children with various\ndiseases.\u00c2 Self-starter, energetic, enthusiastic and dependable individual with outstanding leadership and management skills. A creative and\norganized key team player with strong interpersonal and communication skills.\u00c2 \nHighlights\nGenetic nutrition\u00c2 \n background\nAdult, adolescent and child nutrition\nUse of\u00c2 \n \nanthropometric measurements\nEffectively influences other\nProficient speaker of Arabic\u00c2 and English\nMicrosoft Word, Excel, PowerPoint\nTeam leadership\nConfident public speaker\nAccomplishments\nCompletion\u00c2 of Masters' Thesis, The effect of Curcumin to help reduce the risk and development\u00c2 of Type 2 diabetes on a genetic level\u00c2 \nGranted the Key Player Award of the year on outstanding performance as a fitness attendant\nTraining and supervision of new employees\u00c2 \nElected from VP of finance to President of a graduate club at University of New Haven due to excellence in leadership and\nmanagement\u00c2 skills\nOur club ESM was granted Trailblazer Graduate Club of the year award\nAssessed and helped almost 5,000 patients with their nutrition and eating habits,\u00c2 resulting in a high percent success and a\ntangible\u00c2 positive feedback\nRequested personally by pediatricians due to professionalism in nutritional knowledge and communication skills\nPresented nutrition lecture for 300 elementary students at the American School in Jordan.\nRepresented nutrition as a career to senior students on Career Day at the American School in Jordan.\nExperience\nFitness Attendant \nMarch 2014\n \nto \nMay 2015\n \nCompany Name\n \n\u00ef\u00bc\u200b \nCity\n \n, \nState\nSupervised and\n \u00c2 guided members in safe exercise and use of machines\nContributed to the operation of a clean, friendly and well-maintained\u00c2 recreation center\nEncouraged and motivated members to attend group fitness classes\nContributed in selecting, interviewing and training\u00c2 of new employees\nWork evaluation improved from 3.36/4 to 3.79/4\nNutritionist \nJuly 2012\n \nto \nJuly 2013\n \nCompany Name\n \n\u00ef\u00bc\u200b \nCity\n \n, \nState\nAssessed almost 5,000 patients' overall physical health with body composition scale measurements and\u00c2 \n \nIn Body Machine.\nRecommended appropriate feeding schedules and methods to meet nutritional needs\u00c2 \n in line with patients' age, gender, diagnosis, cultural\nbackground and religious practices.\nEncouraged patients and caregivers to follow recommended food guidelines for well-balanced diets.\nConsulted regularly with physicians on patients' weight and r\n ecommended specialized laboratory tests to assess and monitor nutritional\nstatus\nCounseled more than 800 postpartum patients regarding special dietary needs to enhance recovery and\u00c2 \n \nefficient breastfeeding\nCoordinated successful school and other public events to increase health awareness and marketing of nutrition supplements\nEmphasized nutrition supplements' features to pharmacists to increase awareness and sales of product\nTrainee in food services and in healthy and therapeutic nutrition\n \nFebruary 2012\n \nto \nMarch 2012\n \nCompany Name\n \n\u00ef\u00bc\u200b \nCity\n \n, \nState\nManage tray line, checking and setting up trays to ensure patient food orders are correct according to their dietary need and disease status\nUtilize sanitation procedures at all times with food interaction and handling\nWork with specialized diets, kidney dialysis patients\nScreen all newly admitted patients for nutrition concerns\nDaily round on patients for nutrition concerns and risks\nProvide special diet menu options for inpatients\u00c2 \nEducation\nMaster of Science\n \n: \nHuman Nutrition\n \n, \n2015\n \nUniversity of New Haven\n \n\u00ef\u00bc\u200b \nCity\n \n, \nState\n \n, \nUSA\nMinor in Nutritional Genomics\nThesis submitted in partial fulfillment \nof requirements for degree\u00c2 \n3.8 GPA\nBachelor of Science\n \n: \nHuman Nutrition and Dietetics\n \n, \n2012\n \nUniversity of Jordan\n \n\u00ef\u00bc\u200b \nCity\n \n, \nJordan\n \n3.02 GPA\nOrganizations\nPresident, Engineering Smart Management (ESM)\n \u00c2  \u00c2  \u00c2  \u00c2  \u00c2  \u00c2  \u00c2  \u00c2 Jan 2015 - June 2015\u00c2 \nRepresented the organization with setting a leadership role model\nMonitor E-board duties and delegated authorities\u00c2 \nPlanned, organized and managed clubs events with E-board members\nActive member of the Graduate Student Council\nEstablish meetings guidelines and agendas on weekly basis\nVP of Finance, Engineering Smart Management(ESM)\n \n\u00c2  \u00c2  \u00c2  \u00c2  \u00c2 Sept 2014 - Jan 2015\nCreated annual budget for the academic year\u00c2 \nProcessed funds, payments, and all financial paperwork\nReported all receipts and expenditures on monthly basis\nGranted Trailblazer Graduate Club of the year award for outstanding and successful events\nVolunteered in Feeding Children Everywhere, packaged 2,150 meals. CT, June 2015 \u00c2  \u00c2  \u00c2  \u00c2  \u00c2  \u00c2  \u00c2  \u00c2  \u00c2  \u00c2  \u00c2  \u00c2  \u00c2  \u00c2  \u00c2  \u00c2  \u00c2  \u00c2  \u00c2 \n\u00c2  \u00c2  \u00c2  \u00c2  \u00c2  \u00c2  \u00c2  \u00c2  \u00c2  \u00c2  \u00c2  \u00c2  \u00c2  \u00c2  \u00c2  \u00c2  \u00c2  ",
  "enriched_profile": {
    "fullName": "Highly-motivated Nutritionist",
    "email": "",
    "phone": "",
    "location": "",
    "linkedin": "",
    "github": "",
    "portfolio": "",
    "summary": "Highly-motivated Nutritionist with a masters degree seeking a career position in the healthcare field. Goal-oriented and high-achieving professional with advanced knowledge and skills in nutrition. Effectively influences others and has excellent leadership and management skills. Proficient in Arabic and English.",
    "education": [
      {
        "school": "University of New Haven",
        "degree": "Master of Science",
        "field": "Human Nutrition",
        "startDate": "2015",
        "endDate": "",
        "gpa": "3.8"
      },
      {
        "school": "University of Jordan",
        "degree": "Bachelor of Science",
        "field": "Human Nutrition and Dietetics",
        "startDate": "2012",
        "endDate": "",
        "gpa": "3.02"
      }
    ],
    "experience": [
      {
        "company": "Company Name",
        "position": "Fitness Attendant",
        "startDate": "March 2014",
        "endDate": "May 2015",
        "description": "Supervised and guided members in safe exercise and use of machines. Contributed to the operation of a clean, friendly and well-maintained recreation center. Encouraged and motivated members to attend group fitness classes. Contributed in selecting, interviewing and training of new employees."
      },
      {
        "company": "Company Name",
        "position": "Nutritionist",
        "startDate": "July 2012",
        "endDate": "July 2013",
        "description": "Assessed patients' overall physical health with body composition scale measurements and In Body Machine. Recommended appropriate feeding schedules and methods to meet nutritional needs. Encouraged patients and caregivers to follow recommended food guidelines for well-balanced diets. Counseled postpartum patients regarding special dietary needs to enhance recovery and efficient breastfeeding."
      }
    ],
    "projects": [],
    "skills": [
      "Nutrition",
      "Leadership",
      "Management",
      "Public Speaking",
      "Microsoft Office"
    ],
    "licenses": []
  }
}