{
  "resume_id": "R0028",
  "content": "REGISTERED CLIENT SERVICE ASSOCIATE\nSummary\nTo obtain a position where my years of experience in the client support environment and proven track record of maintaining and developing new\nbusinesses can be fully utilized. Results-oriented, high-energy, hands-on professional, with a successful record of accomplishments in client\nsupport. \nMajor strengths include strong leadership, excellent communication skills, strong team player, attention to detail, compliance in all\nregulated environment and supervisory skills.\nSkills\nMicrosoft Word for Windows, Excel, Power Point, Access, Adobe PageMaker 6.5, Adobe Photoshop, Dreamweaver, Visio, Unix, Oracle 9i\nand Developer 2000.\nExperience\nRegistered Client Service Associate\n \n06/2012\n \nto \nCurrent\n \nCompany Name\n \nCity\n \n, \nState\nServe as primary contact to investment clients and prospects.\nProvide all operational services and support for client accounts.\nProvide Financial Advisors with presentations and seminars, aide in the implementation of marketing materials for prospects.\nReferring clients to other lines of banking division to enhance the relationship.\nWork with Financial Advisors to efficiently manage their book of business to increase their revenue for the bank.\nConduct monthly audits to make sure that client objectives are in consideration with the investments being offered by the brokers.\nWork directly with the Financial Advisors to manage their book of business worth 40 million.\nRelationship Banker II\n \n06/2004\n \nto \n06/2012\n \nCompany Name\n \nCity\n \n, \nState\nServe as primary contact to retail, commercial, and prospect clients.\nNew account opening and cross sale of other banking products and services.\nReferring identified client needs to other lines of banking divisions.\nProactively cold calling the clients to introduce the new products and services to increase branch revenue.\nConduct meetings with commercial bankers and introduce the banking products to the commercial clients to enhance the banking\nrelationship.\nAccomplishments.\nRanked in top 10 among 82 reps for 7 straight years, exceeding sales quotas a month.\nWinner of best sales representative of the year reward 3 straight years and first quarter in 2011.\nIncreased branch non-interest income by 10% with the sale of banking products and excellent client service skills.\nIncreased the loan portfolio for the branch by $800,000 within 7 months.\nIncreased net deposit portfolio for the branch by $1.7 million for the quarter by proven sales skills.\nTraining new hires and branch personals to be experts in their job performance to be successful in the company.\nPrivate Banker\n \n01/2003\n \nto \n01/2004\n \nCompany Name\n \nCity\n \n, \nState\nConduct outside sales calls to bring in new business.\nPerforming operational tasks of the branch that includes reconciliation and monitoring of Federal Reserve account.\nOpening new consumer, business accounts and creating CIF's, entering new accounts in the system using Impact.\nPerforming many tasks using Impact such as change of address, customer account information, posting stop payments, and loan information.\nAssisted in reception handling high volume customer calls.\nTechnical Writer/ Web Developer\n \n01/2000\n \nto \n01/2002\n \nCompany Name\n \nCity\n \n, \nState\nResponsibilities include creating, editing and verifying product and service documentation.\nDocumentation types include: hardware and software user and service manuals, online help and tutorials,\nprogramming/configuration/installation documents, requirement documents and reference documents.\nWork out various researches for giving the accurate description of the erection, installation, removal as well as maintenance of different\ngenres of hardware.\nSupply wiring figures outlines along with part breakdown sketches for illustrations.\nScripting interactive on-line help and tutorial packages.\nInstallation and maintenance of computer, security, and telecommunications systems.\nEducation and Training\nB.S\n \n: \nComputer Information Systems\n \n2001\n \nStrayer University\n \nComputer Information Systems\n1997\n \nNorthern Virginia Community College\n \nDBA Training, Completed First DBA exam in India\nSeries 7-General Securities Registered Representative\n \n2016\nSkills\nDreamweaver, Adobe PageMaker 6.5, Adobe Photoshop, banking, book, cold calling, hardware, client, clients, DBA, Documentation, editing,\nFinancial, investments, marketing materials, meetings, Access, Excel, Power Point, Windows, Microsoft Word, online help, Oracle 9, Developer\n2000, outside sales, presentations, programming, reception, requirement, retail, sales skills, sales, Securities, seminars, Scripting,\ntelecommunications, Unix, Visio, wiring",
  "enriched_profile": {
    "fullName": "John Doe",
    "email": "",
    "phone": "",
    "location": "City, State",
    "linkedin": "",
    "github": "",
    "portfolio": "",
    "summary": "Results-oriented professional with years of experience in client support, strong leadership, excellent communication skills, and a successful track record in developing new businesses.",
    "education": [
      {
        "school": "Strayer University",
        "degree": "B.S.",
        "field": "Computer Information Systems",
        "startDate": "2001",
        "endDate": "",
        "gpa": ""
      },
      {
        "school": "Northern Virginia Community College",
        "degree": "",
        "field": "Computer Information Systems",
        "startDate": "1997",
        "endDate": "",
        "gpa": ""
      }
    ],
    "experience": [
      {
        "company": "Company Name",
        "position": "Registered Client Service Associate",
        "startDate": "06/2012",
        "endDate": "Present",
        "description": "Serve as primary contact to investment clients and prospects. Provide operational services and support for client accounts. Assist Financial Advisors with presentations and seminars, and aide in the implementation of marketing materials for prospects. Refer clients to other lines of banking division to enhance the relationship. Conduct monthly audits to ensure client objectives align with investments being offered by brokers."
      },
      {
        "company": "Company Name",
        "position": "Relationship Banker II",
        "startDate": "06/2004",
        "endDate": "06/2012",
        "description": "Serve as primary contact to retail, commercial, and prospect clients. Perform new account opening and cross-sale of other banking products and services. Refer identified client needs to other lines of banking divisions. Proactively cold call clients to introduce new products and services to increase branch revenue. Conduct meetings with commercial bankers and introduce banking products to commercial clients to enhance the banking relationship."
      }
    ],
    "projects": [],
    "skills": [
      "Microsoft Word for Windows",
      "Excel",
      "Power Point",
      "Access",
      "Adobe PageMaker 6.5",
      "Adobe Photoshop",
      "Dreamweaver",
      "Visio",
      "Unix",
      "Oracle 9i and Developer 2000",
      "banking",
      "book",
      "cold calling",
      "client",
      "client management",
      "Dreamweaver",
      "Adobe PageMaker 6.5",
      "Adobe Photoshop",
      "Presentations",
      "programming",
      "reception",
      "requirement",
      "retail",
      "sales skills",
      "sales",
      "securities",
      "seminars",
      "scripting",
      "telecommunications",
      "Unix",
      "Visio",
      "wiring"
    ],
    "licenses": [
      {
        "title": "Series 7-General Securities Registered Representative",
        "description": "",
        "issueDate": "2016",
        "expiryDate": ""
      }
    ]
  }
}