{
  "resume_id": "R0035",
  "content": "RECREATION & SPORTS COORDINATOR\nObjective\nTo gain a Recreation Supervisor position so that I can provide support to professional and part time staff. I am looking for the opportunity to guide\nday to day operations of high quality, community recreation facilities. I hope to provide the type of support and management conducive to a healthy\nwork environment so that all staff can not only complete their roles & responsibilities, but also provide a facility that runs efficiently and offers\nexceptional service to members.\nQualifications\nACSM Exercise Physiologist\nTRX Qualified Instructor\n\u00c2 \nPersonal Trainer\nAHA CPR/AED & First Aid\nExperience\nCompany Name\n \nCity\n \n, \nState\n \nRecreation & Sports Coordinator\n \n03/2015\n \nto \nCurrent\nAssisted in daily supervision and administration of facility and interacted with members to ensure programs were carried out in a safe and\neffective manner.\nPlanned, organized and implemented recreation leagues and events throughout the calendar year.\nSupervised recreation programs, resolving any issues or disputes that may arise.\nEnforced safety and administered first aid to participants when required.\nAssisted supervisor in developing budget and developed innovative ways to increase revenue.\nResponsible for financial transactions including daily cash deposits and purchasing responsibilities including maintaining a purchasing card\nand receipt of sale.\nCompany Name\n \nCity\n \n, \nState\n \nSenior Health & Fitness Specialist Contractor\n \n02/2013\n \nto \n03/2015\nDeveloped and implemented programs to assess and increase the health and physical activity levels of various populations.\nManaged HealthCalc software program through the enrollment of new clients and maintained private records.\nConducted health and wellness assessments for clients and assisted them with goal setting and strategies to improve and maintain their health\nand worksite wellness.\nCompany Name\n \nCity\n \n, \nState\n \nHealth and Fitness Specialist\n \n08/2012\n \nto \n02/2013\nDeveloped and utilized special programs to connect with various health and wellness populations.\nMaintained great rapport with all customers ensuring all needs were handled in a timely manner.\nEntered appropriate documents into software database ensuring each participant was safe for physical activity assessments and\nparticipation.\nCompany Name\n \nCity\n \n, \nState\n \nFacility Manager\n \n01/2010\n \nto \n05/2012\nSupervised 40 \nstaff at the university's 100,000 square foot facility and assisted in the new hire recruitment and training procedures.\nProvided exceptional customer service to all members and prepared daily reports recording any issues within the facility.\nAdministrative support by assisting with budget preparation, financial reports, membership sales, payment records, account charges,\ncollections and deposits Leadership ....................................\n2014- Lead over 250 employees at The Center for Disease Control and Prevention's (CDC) \"Healthiest Center Institute Office (CIO)\"\nannual program and more than doubled their participation rate from the two previous years.\nMember of Center for Disease Control and Prevention Wellness on Worksite committee.\n2012-Only intern hired to become part of the Progressive Exercise Specialist team based off of performance, professionalism, and\ndedication shown during internship.\nEducation\nBachelor of Science\n \n:\n \nKinesiology\n \n2012\n \nEast Carolina University\n \n, \nCity\n \n, \nState\nSkills\nMicrosoft Office Programs\nBudget Allocation\nGood interpersonal skills that can help in building a strong team for the growth of the organization.\nAbility to handle different projects for the organization effectively.\n\u00c2 ",
  "enriched_profile": {
    "fullName": "John Doe",
    "email": "",
    "phone": "",
    "location": "City, State",
    "linkedin": "",
    "github": "",
    "portfolio": "",
    "summary": "Recreation & Sports Coordinator with experience in daily supervision, administration, and budget development. Skilled in leading teams, handling projects, and providing exceptional customer service.",
    "education": [
      {
        "school": "East Carolina University",
        "degree": "Bachelor of Science",
        "field": "Kinesiology",
        "startDate": "2008",
        "endDate": "2012",
        "gpa": ""
      }
    ],
    "experience": [
      {
        "company": "Company Name",
        "position": "Recreation & Sports Coordinator",
        "startDate": "03/2015",
        "endDate": "Present",
        "description": "Assisted in daily supervision and administration of facility, planned and organized recreation leagues and events, supervised recreation programs, enforced safety, assisted in budget development, and managed financial transactions."
      },
      {
        "company": "Company Name",
        "position": "Senior Health & Fitness Specialist Contractor",
        "startDate": "02/2013",
        "endDate": "03/2015",
        "description": "Developed and implemented programs to assess and increase the health and physical activity levels of various populations, managed HealthCalc software program, and conducted health and wellness assessments for clients."
      },
      {
        "company": "Company Name",
        "position": "Health and Fitness Specialist",
        "startDate": "08/2012",
        "endDate": "02/2013",
        "description": "Developed and utilized special programs to connect with various health and wellness populations, maintained great rapport with all customers, and ensured each participant was safe for physical activity assessments and participation."
      },
      {
        "company": "Company Name",
        "position": "Facility Manager",
        "startDate": "01/2010",
        "endDate": "05/2012",
        "description": "Supervised 40 staff at the university's 100,000 square foot facility, provided exceptional customer service, and assisted with budget preparation, financial reports, membership sales, payment records, account charges, collections and deposits."
      }
    ],
    "projects": [],
    "skills": [
      "Microsoft Office Programs",
      "Budget Allocation",
      "Interpersonal Skills",
      "Project Management"
    ],
    "licenses": []
  }
}