{
  "resume_id": "R0034",
  "content": "HR PERSONNEL ASSISTANT\nSummary\nI am a U.S. citizen who is authorized to work in the US for any employer. I have worked 8 years as an Office Clerk, 2 years as a Student\nIntern/Office Assistant, and 4 years as a Contractor. I am applying for the Data Entry Clerk position (Advert ID# 224278 Advert ID# 224278).\nMy skills and experiences include: Administrative Support, Auditing, File Management, Meeting Facilitation, Office Materials Management, &\nInventory Management.\nHighlights\nCOMPUTER SKILLS: Microsoft Word, MS Excel, MS Outlook, MS PowerPoint, PeopleSoft. TYPING SKILLS: 40-60 WPM.\nADDITIONAL SKILLS: Administrative Support, Auditing, Clerical, Copy, Customer Service, Data Entry, Delivery, Documentation, Fax, File\nManagement, Letters, Meeting Facilitation, Organizational Skills, Proofreading, Receptionist, Research, Scanning, Scheduling, Secretarial,\nTelephone Skills, Office Equipment Maintenance, and Inventory Management.\nExperience\nCompany Name\n \nCity\n \n, \nState\n \nHR Personnel Assistant\n \n03/2013\n \nto \n04/2014\nSupported human resources staff with new hire orientations and monthly departmental meetings.\nEntered updated personnel and subcontractor data into a central database.\nReviewed human resource paperwork for accuracy and completeness by verifying, collecting and correcting additional employee data.\nComposed and drafted all outgoing correspondence and reports for managers.\nAnswered and managed incoming and outgoing calls while recording accurate messages.\nMaintained Heavy Filing of HR Personnel Action Forms to include new hire letters, awards, certifications and promotions, providing a\nstronger framework for consistency and detail.\nAssisted Senior Personnel supervisors in Coordinating and conducted new hire pre-interviews.\nDeveloped and maintained an internal new hire filing system.\nReceived, maintained and filed appropriate paperwork as back up for all HR Office transactions.\nTyped memorandums, forms, and letters using software applications to complete HR office assignments and projects given on a regular\nbasis.\nUtilized and Navigated PeopleSoft (HRS) to input, manage and research data.\nOperated fax and copy machines to complete tasks as needed.\nInitiated and maintained email correspondence with teachers, principals, VPs, and other members of NPS regarding personal ID\ninformation, teaching background & certification info, and criminal history clearance.\nCompany Name\n \nCity\n \n, \nState\n \nAssistant Store Clerk\n \n05/2011\n \nto \n01/2012\nSelling merchandise and providing customer services for patrons.\nMonitoring patrons to assist the store in loss and theft prevention.\nRestocking shelves.\nImproving data maintenance of produce inventory.\nMaintaining the appearance of the store.\nAssisting with maintenance of produce inventory\nCompany Name\n \nCity\n \n, \nState\n \nOffice Clerk/ Federal Contractor\n \n06/2008\n \nto \n10/2009\nChecking and validating Retirement & NRC files in NFTS and CIS systems.\nCalling Applicant to Counter Window to Sign Certificate.\nCompleting File Maintenance of Riders, Mergers, and Certificates.\nFinishing and documenting 3-Box Audit for Weekly Systems Update.\nFiling of FBI background report on Applicants.\nAssign scheduled appointments to appointed legal officers.\nClerical Reception of Scheduled Applicants.\nAuditing Confidential Department Files.\nComposing & Mailing out appointment letters.\nFinalizing Pick list Printouts for Examinations/Cases.\nCompleting NFTS Data Systems updates.\nPerforming Clerical tasks regarding Naturalization ceremonies, including: A. Scheduling, Preparing, and Distribution of Certificates. B.\nRetrieval of Documentation from Applicants.\nUsing Computer Terminal to update DHS Automated Systems.\nProviding Administrative Support in Processing.\nPerforming Daily tasks of filing, recording, copying, and maintaining records.\nCompany Name\n \nCity\n \n, \nState\n \nOffice Clerk/Federal Contractor\n \n07/2005\n \nto \n01/2007\nPerforming Data Entry of Legal Documents and Court Case Dates.\nMail Clerk and Online Mail Information Updating\nSetting Schedules for Staff or Private Meetings\nFiling and Faxing of Confidential Court Documents\nMetering outgoing and stamping incoming mail\nReestablishing protocols for office supplies storage and maintenance\nProviding clerical support to Office administrators & Managers.\nEducation\nBachelor's of Arts\n \n:\n \nPolitical Science and Law\n \n2007\n \nMontclair State University\n \n, \nCity\n \n, \nState\n \n, \nUS\n \nBachelor's of Arts Degree in Political Science\nand Law Montclair State University - Upper Montclair, NJ 1998 to 2007\nHigh School Diploma\n \n1998\n \nOur Lady of Good Counsel High School\n \n, \nCity\n \n, \nState\n \n, \nUS\n \nHigh School Diploma Our Lady of Good Counsel High\nSchool - Newark, NJ 1995 to 1998\nSkills\nFiling, Clerk, Maintenance, Clerical, Office Clerk, Clerical Support, Data Entry, Faxing, Incoming Mail, Legal Documents, Mail Clerk, Office\nSupplies, Stamping, Administrative Support, Audit, Auditing, Cases, Copying, Documentation, Documenting, Fbi, File, Finishing, Nrc, Sche",
  "enriched_profile": {
    "fullName": "HR Personnel Assistant",
    "email": "",
    "phone": "",
    "location": "",
    "linkedin": "",
    "github": "",
    "portfolio": "",
    "summary": "U.S. citizen with 8 years of experience as an Office Clerk, 2 years as a Student Intern/Office Assistant, and 4 years as a Contractor. Skilled in administrative support, auditing, file management, meeting facilitation, and inventory management.",
    "education": [
      {
        "school": "Montclair State University",
        "degree": "Bachelor's of Arts",
        "field": "Political Science and Law",
        "startDate": "2007",
        "endDate": "",
        "gpa": ""
      },
      {
        "school": "Our Lady of Good Counsel High School",
        "degree": "High School Diploma",
        "field": "",
        "startDate": "1998",
        "endDate": "",
        "gpa": ""
      }
    ],
    "experience": [
      {
        "company": "HR Personnel Assistant",
        "position": "",
        "startDate": "03/2013",
        "endDate": "04/2014",
        "description": "Supported human resources staff with new hire orientations and monthly departmental meetings. Entered updated personnel and subcontractor data into a central database. Reviewed human resource paperwork for accuracy and completeness. Composed and drafted all outgoing correspondence and reports for managers. Answered and managed incoming and outgoing calls. Maintained heavy filing of HR personnel action forms. Assisted Senior Personnel supervisors in coordinating and conducted new hire pre-interviews. Developed and maintained an internal new hire filing system. Received, maintained and filed appropriate paperwork as back up for all HR Office transactions. Typed memorandums, forms, and letters using software applications. Operated fax and copy machines to complete tasks as needed. Initiated and maintained email correspondence with teachers, principals, VPs, and other members of NPS regarding personal ID information, teaching background & certification info, and criminal history clearance."
      },
      {
        "company": "Assistant Store Clerk",
        "position": "",
        "startDate": "05/2011",
        "endDate": "01/2012",
        "description": "Selling merchandise and providing customer services for patrons. Monitored patrons to assist the store in loss and theft prevention. Restocking shelves. Improving data maintenance of produce inventory. Maintaining the appearance of the store. Assisting with maintenance of produce inventory."
      },
      {
        "company": "Office Clerk/ Federal Contractor",
        "position": "",
        "startDate": "06/2008",
        "endDate": "10/2009",
        "description": "Checking and validating Retirement & NRC files in NFTS and CIS systems. Calling Applicant to Counter Window to Sign Certificate. Completing File Maintenance of Riders, Mergers, and Certificates. Finishing and documenting 3-Box Audit for Weekly Systems Update. Filing of FBI background report on Applicants. Assign scheduled appointments to appointed legal officers. Clerical Reception of Scheduled Applicants. Auditing Confidential Department Files. Composing & Mailing out appointment letters. Finalizing Pick list Printouts for Examinations/Cases. Completing NFTS Data Systems updates. Performing Clerical tasks regarding Naturalization ceremonies, including: A. Scheduling, Preparing, and Distribution of Certificates. B. Retrieval of Documentation from Applicants. Using Computer Terminal to update DHS Automated Systems. Providing Administrative Support in Processing. Performing Daily tasks of filing, recording, copying, and maintaining records."
      },
      {
        "company": "Office Clerk/Federal Contractor",
        "position": "",
        "startDate": "07/2005",
        "endDate": "01/2007",
        "description": "Performing Data Entry of Legal Documents and Court Case Dates. Mail Clerk and Online Mail Information Updating Setting Schedules for Staff or Private Meetings Filing and Faxing of Confidential Court Documents Metering outgoing and stamping incoming mail Reestablishing protocols for office supplies storage and maintenance Providing clerical support to Office administrators & Managers."
      }
    ],
    "projects": [],
    "skills": [
      "Filing",
      "Clerk",
      "Maintenance",
      "Clerical",
      "Office Clerk",
      "Clerical Support",
      "Data Entry",
      "Faxing",
      "Incoming Mail",
      "Legal Documents",
      "Mail Clerk",
      "Office Supplies",
      "Stamping",
      "Administrative Support",
      "Audit",
      "Auditing",
      "Cases",
      "Copying",
      "Documentation",
      "Documenting",
      "Fbi",
      "File",
      "Finishing",
      "Nrc",
      "Scheduling",
      "Basis",
      "Correspondence",
      "Database",
      "Hr",
      "Human Resources",
      "Peoplesoft",
      "Teaching",
      "Inventory",
      "60 Wpm",
      "Customer Service",
      "Equipment Maintenance",
      "Excel",
      "File Management",
      "Materials Management",
      "Microsoft Word",
      "Ms Excel",
      "Ms Outlook",
      "Ms Powerpoint",
      "Office Assistant",
      "Organizational Skills",
      "Outlook",
      "Powerpoint",
      "Proofreading",
      "Receptionist",
      "Retail Sales",
      "Scanning",
      "Secretarial",
      "Telephone",
      "Telephone Skills",
      "Typing",
      "Word"
    ],
    "licenses": []
  }
}