{
  "resume_id": "R0037",
  "content": "PHARMACEUTICAL SALES REPRESENTATIVE, WOMEN'S HEALTHCARE SPECIALIST\nProfessional Summary\nSkills\nPROVEN ADMINISTRATIVE HIGHLY ORGANIZED\nLEADERSHIP SUPPORT EVENT PLANNING\nENTREPRENEURIAL CONFLICT PUBLIC SPEAKING\nMINDSET RESOLUTION PROJECT STAFFING\nTEAM LEADERSHIP REPORTING AND\nSELF DIRECTED DOCUMENTATION\nOUTBOUND CALLING PROSPECTING\nAccount Management\nAcquisitions\nADMINISTRATIVE\nContracts\nClientele\nCustomer satisfaction\nCustomer\nSsatisfaction\nDecision making\nDOCUMENTATION\nEVENT PLANNING\nInventory\nTEAM LEADERSHIP\nLEADERSHIP\nDirector\nManaging\nMarketing plans\nMarketing\nMarket\nMergers\nCommunicator\nOrganizational skills\nProblem-solving\nPUBLIC SPEAKING\nRecruitment\nRelationship-building\nREPORTING\nSales\nSTAFFING\nStrategic\nStrategic planning\nTeam player\nWork History\nPHARMACEUTICAL SALES REPRESENTATIVE, Women's Healthcare Specialist\n \nCompany Name\n \n\u00e2\u20ac\u201c \nCity\n \n, \nState\n \nDoubled membership in an environment where acquisitions and mergers by National \nchain accounts directly affected potential membership\nrecruitment.\nInvestigated and resolved customer inquiries and complaints in a timely and empathetic \nmanner.\nResponded to all customer inquiries thoroughly and professionally.\nProvided an elevated customer experience to generate a loyal clientele \nResolved all customer complaints in a professional manner while\nprioritizing customer \nsatisfaction.\nSet up and explained new membership contracts.\nEffectively communicated with and supported sales, marketing and administrative teams \non a daily basis.\nAssisted in creating pre-season marketing plans to support department and divisional \nStrategies.\nCommunicated with vendors regarding backorder availability, future inventory and \nspecial orders.\nDeveloped Account Management Program that focused on maintaining existing account \nbase while using referral and reference systems to\nattract new accounts.\nOrganized new member marketing program including identifying potential target \naccounts, developing high touch outreach plans, incentive\npackages, and growth \nObjectives.\nSuccessfully managed acquisition of a New England Association and increased \nmembership by 50% within the first two years.\nAsked appropriate open-ended questions to discover prospects' needs and \nrequirements.\nRepresentative of the year 2003 \nSuccessfully launched new products and rapidly gained market share.\nMaintained an extensive knowledge of competitors, their offerings and their presence in \nassigned territory.\nServiced accounts on a regular basis to propose new products or services and maximize \nrevenue.\nIdentified and qualified accounts to assess market potential.\nConsistently hit and exceeded quarterly sales goals.\nIdentified and analyzed key competitors and related products.\nContacted customers as soon as issues arose to immediately find resolution before the \nproblems escalated.\nCommunicated regularly with territory, regional and strategic managers for daily support \nand strategic planning for accounts.\nSuccessfully sold brand name products, while competing with the generic medicine.\nCommunicated regularly with territory, regional and strategic managers for daily support \nand strategic planning for accounts.\nVisited customer locations to determine needs, set up contracts and provide training.\nEducation\nBachelor of Arts\n \n: \nBusiness Administration And Public Relations\n \n, \n1995\n \nHeidelberg College\n \n- \nCity\n \n, \nState\n \nWork History\nPHARMACEUTICAL SALES REPRESENTATIVE, Women's Healthcare Specialist\n \n, \nCompany Name\n \n\u00e2\u20ac\u201c \nCity\n \n, \nState\n \nDoubled membership in an environment where acquisitions and mergers by National \nchain accounts directly affected potential membership\nrecruitment.\nInvestigated and resolved customer inquiries and complaints in a timely and empathetic \nmanner.\nResponded to all customer inquiries thoroughly and professionally.\nProvided an elevated customer experience to generate a loyal clientele \nResolved all customer complaints in a professional manner while\nprioritizing customer \nsatisfaction.\nSet up and explained new membership contracts.\nEffectively communicated with and supported sales, marketing and administrative teams \non a daily basis.\nAssisted in creating pre-season marketing plans to support department and divisional \nStrategies.\nCommunicated with vendors regarding backorder availability, future inventory and \nspecial orders.\nDeveloped Account Management Program that focused on maintaining existing account \nbase while using referral and reference systems to\nattract new accounts.\nOrganized new member marketing program including identifying potential target \naccounts, developing high touch outreach plans, incentive\npackages, and growth \nObjectives.\nSuccessfully managed acquisition of a New England Association and increased \nmembership by 50% within the first two years.\nAsked appropriate open-ended questions to discover prospects' needs and \nrequirements.\nRepresentative of the year 2003 \nSuccessfully launched new products and rapidly gained market share.\nMaintained an extensive",
  "enriched_profile": {
    "fullName": "PHARMACEUTICAL SALES REPRESENTATIVE, Women's Healthcare Specialist",
    "email": "",
    "phone": "",
    "location": "",
    "linkedin": "",
    "github": "",
    "portfolio": "",
    "summary": "Experienced, multi-faceted business professional with ability to quickly generate business results. Seeking a position with Abbott for the Territory Sales Position in Tacoma,WA. Adept at attending job related conventions and managing special company events to attract candidates. Top-notch skills in relationship-building, problem-solving and decision making. Open and clear communicator with collaborative and hardworking style. Membership Enrollment Director excelling at customer satisfaction and retention. Flexible and hardworking in deadline driven environments. Energetic team player with top launch organizational skills.",
    "education": [
      {
        "school": "Heidelberg College",
        "degree": "Bachelor of Arts",
        "field": "Business Administration And Public Relations",
        "startDate": "1995",
        "endDate": "",
        "gpa": ""
      }
    ],
    "experience": [
      {
        "company": "Company Name",
        "position": "PHARMACEUTICAL SALES REPRESENTATIVE, Women's Healthcare Specialist",
        "startDate": "",
        "endDate": "",
        "description": "Doubled membership in an environment where acquisitions and mergers by National chain accounts directly affected potential membership recruitment. Investigated and resolved customer inquiries and complaints in a timely and empathetic manner. Responded to all customer inquiries thoroughly and professionally. Provided an elevated customer experience to generate a loyal clientele. Resolved all customer complaints in a professional manner while prioritizing customer satisfaction. Set up and explained new membership contracts. Effectively communicated with and supported sales, marketing and administrative teams on a daily basis. Assisted in creating pre-season marketing plans to support department and divisional strategies. Communicated with vendors regarding backorder availability, future inventory and special orders. Developed Account Management Program that focused on maintaining existing account base while using referral and reference systems to attract new accounts. Organized new member marketing program including identifying potential target accounts, developing high touch outreach plans, incentive packages, and growth objectives. Successfully managed acquisition of a New England Association and increased membership by 50% within the first two years. Asked appropriate open-ended questions to discover prospects' needs and requirements. Representative of the year 2003. Successfully launched new products and rapidly gained market share. Maintained an extensive knowledge of competitors, their offerings and their presence in assigned territory. Serviced accounts on a regular basis to propose new products or services and maximize revenue. Identified and qualified accounts to assess market potential. Consistently hit and exceeded quarterly sales goals. Identified and analyzed key competitors and related products. Contacted customers as soon as issues arose to immediately find resolution before the problems escalated. Communicated regularly with territory, regional and strategic managers for daily support and strategic planning for accounts. Successfully sold brand name products, while competing with the generic medicine. Visited customer locations to determine needs, set up contracts and provide training."
      }
    ],
    "projects": [],
    "skills": [
      "Account Management",
      "acquisitions",
      "ADMINISTRATIVE",
      "contracts",
      "clientele",
      "customer satisfaction",
      "customer Ssatisfaction",
      "decision making",
      "DOCUMENTATION",
      "EVENT PLANNING",
      "inventory",
      "TEAM LEADERSHIP",
      "LEADERSHIP",
      "Director",
      "managing",
      "marketing plans",
      "marketing",
      "market",
      "mergers",
      "communicator",
      "organizational skills",
      "problem-solving",
      "PUBLIC SPEAKING",
      "recruitment",
      "relationship-building",
      "REPORTING",
      "Sales",
      "STAFFING",
      "strategic",
      "strategic planning",
      "team player"
    ],
    "licenses": []
  }
}