{
  "resume_id": "R0031",
  "content": "GENERAL MANAGER / EXECUTIVE CHEF\nSummary\nDedicated leader with over 15-year track record as an organized administrative professional with hands-on experience supporting business areas\nsuch as accounting, database management and human resources. Collaborative team player with strong communication, decision-making and time\nmanagement abilities.\n \u00c2 \nHighlights\nReport writing\nComputer proficiency\nService-minded\nHuman resource knowledge\nAbility to prioritize\nMotivational leadership style\nInventory control\nProfessional demeanor\nSelf-directed\nTime management ability\nAccomplishments\nScheduling\n \u00c2 \nFacilitated onboarding of new employees by scheduling training, answering questions and processing paperwork.\nProcess Improvement\n \u00c2 \nOversaw implementation of new phone system which resulted in more cost-effective service.\nResearch\n \u00c2 \nInvestigated and analyzed client complaints to identify and resolve issues.\nAdministration\n \u00c2 \nPerformed administration tasks such as filing, developing spreadsheets, faxing reports, photocopying collateral and scanning documents for\ninter-departmental use.\nTraining\n \u00c2 \nSuccessfully trained staff in all office systems and databases, policies and procedures while focusing on minimizing errors and generating\nsuperior results.\nPayroll Assistance\n \u00c2 \nAssisted with payroll preparation and entered data into cumulative payroll document.\nExperience\nJune 2014\n \nto \nOctober 2015\nCompany Name\n \nCity\n \n, \nState\n \nGeneral Manager / Executive Chef\nCoordinated all department functions for restaurant staff.\nUpdated employee paperwork and time records.\nLiaised directly with customers to meet needs and maintain satisfaction.\nMaintained detailed administrative and procedural processes to improve accuracy and efficiency.\nAchieved notable successes in cost control, revenue generation and marketing effectiveness.\nMay 2013\n \nto \nMay 2014\nCompany Name\n \nCity\n \n, \nState\n \nSales Consultant\nMet incoming customers and provided immediate assistance.\nListened to customer needs and preferences to provide accurate advice.\nSolicited referrals from satisfied clients.\nAnswered incoming telephone calls with professional and knowledgeable responses.\nProvided expert product and service information.\nSeptember 2012\n \nto \nApril 2013\nCompany Name\n \nCity\n \n, \nState\n \nSales Consultant / Service Technician\nCold-called prospective customers to build relationship.\nFilled out expense reports for accounting.Updated database with customer and sales information.\nEstablished new customer accounts.Evaluated competitors and performed market research.\nWorked as technician cleaning up after different biological hazards including crime scene cleanup, flooding, and fire restoration.\nJune 2012\n \nto \nAugust 2012\nCompany Name\n \nCity\n \n, \nState\n \nForklift Driver\nTransported construction and scaffolding materials for a turnaraound in a chemical plant with large forklift\nTransported employees around job site using passenger vehicles, trucks and vans.\nMaintained strict adherence to safety protocols required by client.\nApril 2011\n \nto \nMay 2012\nCompany Name\n \nCity\n \n, \nState\n \nOperations Manager\nOversaw the development and launch of customer database\nBoosted company efficiency through technology upgrades and process improvements.\nOptimized the overall customer experience through establishing procedures for handling issues over the phone.\nIdentified inefficiencies and made recommendations for process improvements.\nNovember 2009\n \nto \nMarch 2012\nCompany Name\n \nCity\n \n, \nState\n \nGeneral Manager and Trainer for New Restaurant Openings\nContinually monitored restaurant and took appropriate action to ensure food quality and service standards were consistently met.\nExhibited thorough knowledge of foods, beverages, supervisory duties, service techniques, and guest interactions.\nOptimized profits by controlling food, beverage and labor costs on a daily basis.\nCommunicated well and used strong interpersonal skills to establish positive relationships with guests and employees.\nMarch 2009\n \nto \nOctober 2009\nCompany Name\n \nCity\n \n, \nState\n \nSwing Manager\nScheduled and directed staff in daily work assignments to maximize productivity.Efficiently resolved problems or concerns to the satisfaction\nof all involved parties.Continually monitored restaurant and took appropriate action to ensure food quality and service standards were\nconsistently met.Assigned tasks and oversaw the direction of employees to ensure compliance with food safety procedures and quality\ncontrol guidelines.\nEducation\n1988\nGED\n \nCity\n \n, \nState\n \n, \nUnited States\n \nGED\nI grew up in Guadalajara, Mexico and attended home school taught by my mother. \nI later received my GED. I also have the following training.\nBasic Vocational Certificate: Restaurant Operations\nBasic Vocational Certificate: Culinary Management\nCoursework in Business, Restaurant and Hotel Management\n.\nInterests\nCooking, computers, sailing, golf, travel, working, and family.\nAdditional Information\nI am fluent in Spanish. \nI believe that ha",
  "enriched_profile": {
    "fullName": "Dedicated Leader",
    "email": "",
    "phone": "",
    "location": "",
    "linkedin": "",
    "github": "",
    "portfolio": "",
    "summary": "Dedicated leader with over 15-year track record as an organized administrative professional with hands-on experience supporting business areas such as accounting, database management and human resources. Collaborative team player with strong communication, decision-making and time management abilities.",
    "education": [
      {
        "school": "Home school (taught by mother)",
        "degree": "GED",
        "field": "",
        "startDate": "1988",
        "endDate": "",
        "gpa": ""
      }
    ],
    "experience": [
      {
        "company": "Company Name",
        "position": "General Manager / Executive Chef",
        "startDate": "June 2014",
        "endDate": "October 2015",
        "description": "Coordinated all department functions for restaurant staff. Updated employee paperwork and time records. Liaised directly with customers to meet needs and maintain satisfaction. Maintained detailed administrative and procedural processes to improve accuracy and efficiency. Achieved notable successes in cost control, revenue generation and marketing effectiveness."
      },
      {
        "company": "Company Name",
        "position": "Sales Consultant",
        "startDate": "May 2013",
        "endDate": "May 2014",
        "description": "Met incoming customers and provided immediate assistance. Listened to customer needs and preferences to provide accurate advice. Solicited referrals from satisfied clients. Answered incoming telephone calls with professional and knowledgeable responses. Provided expert product and service information."
      },
      {
        "company": "Company Name",
        "position": "Sales Consultant / Service Technician",
        "startDate": "September 2012",
        "endDate": "April 2013",
        "description": "Cold-called prospective customers to build relationship. Filled out expense reports for accounting. Updated database with customer and sales information. Established new customer accounts. Evaluated competitors and performed market research. Worked as technician cleaning up after different biological hazards including crime scene cleanup, flooding, and fire restoration."
      },
      {
        "company": "Company Name",
        "position": "Forklift Driver",
        "startDate": "June 2012",
        "endDate": "August 2012",
        "description": "Transported construction and scaffolding materials for a turnaround in a chemical plant with large forklift. Transported employees around job site using passenger vehicles, trucks and vans. Maintained strict adherence to safety protocols required by client."
      },
      {
        "company": "Company Name",
        "position": "Operations Manager",
        "startDate": "April 2011",
        "endDate": "May 2012",
        "description": "Oversaw the development and launch of customer database. Boosted company efficiency through technology upgrades and process improvements. Optimized the overall customer experience through establishing procedures for handling issues over the phone. Identified inefficiencies and made recommendations for process improvements."
      },
      {
        "company": "Company Name",
        "position": "General Manager and Trainer for New Restaurant Openings",
        "startDate": "November 2009",
        "endDate": "March 2012",
        "description": "Continually monitored restaurant and took appropriate action to ensure food quality and service standards were consistently met. Exhibited thorough knowledge of foods, beverages, supervisory duties, service techniques, and guest interactions. Optimized profits by controlling food, beverage and labor costs on a daily basis. Communicated well and used strong interpersonal skills to establish positive relationships with guests and employees."
      },
      {
        "company": "Company Name",
        "position": "Swing Manager",
        "startDate": "March 2009",
        "endDate": "October 2009",
        "description": "Scheduled and directed staff in daily work assignments to maximize productivity. Efficiently resolved problems or concerns to the satisfaction of all involved parties. Continually monitored restaurant and took appropriate action to ensure food quality and service standards were consistently met. Assigned tasks and oversaw the direction of employees to ensure compliance with food safety procedures and quality control guidelines."
      }
    ],
    "projects": [],
    "skills": [
      "Advertising",
      "Automobiles",
      "Consultant",
      "Customer Relations",
      "Data Management",
      "Financial Planning",
      "Food safety",
      "Hiring",
      "Inventory Control",
      "Inventory Management",
      "Managing",
      "marketing",
      "materials",
      "Network design",
      "Network",
      "New Construction",
      "Payroll",
      "Performance Appraisals",
      "Personnel",
      "Policies",
      "Project Management",
      "Restaurant Operations",
      "Retail",
      "Safety",
      "Sales",
      "Spanish Speaking",
      "Supervision",
      "Telecommunications.",
      "Equipment Operations and Maintenance."
    ],
    "licenses": []
  }
}