{
  "resume_id": "R0047",
  "content": "WARD CLERK UNIT SECRETARY ADMISSIONS AND DISPOSITIONS CLERK 3RD PARTY LIABILITY CLERK PATIENT\nExecutive Summary\nSeeking a part-time nonmedical/retail position that will afford me the opportunity to use my various social and professional skills. strong\norganizational and problem-solving abilities, demonstrating sound judgment in establishing priorities and making decisions. *Well-Developed\ninterpersonal skills; interact effectively with people on all levels; remain calm during stressful situations. *innovative and resourceful, with the ability\nto recognize valuable applications for new ideas and a talent for successful implementation. \n*Conscientious and quality-oriented with an earned\nreputation for dependability, efficiency and professionalism.\nCore Qualifications\nMS Word\nMS Excel\nMS Powerpoint\nSOX (Sarbanes-Oxley Compliance) Training\nAdult CPR/AED Certification\nProfessional Experience\nWard Clerk, / Unit Secretary, Admissions and Dispositions Clerk, 3rd Party Liability Clerk, Patient Eligibility Clerk, Public Relations Assistant\n \nAs Supplemental/Cooperative Care Clerk, initiated and tracked a program to conclusion with an annual budget of $700,00 for over 40,000\nbeneficiaries.\nMaintained outpatient health records, determining eligibility of patients.\nSingle-handedly overhauled a repository of 1,000 specialized records, receiving consecutive superior ratings.\nCompany Name\n \nJanuary 2012\n \nto \nCurrent\n \nHR/Payroll Supervisor \nAccounting Apprentice\n \nCity\n \n, \nState\nPrepares payroll, taking into consideration non-standard shifts and overtime pay Process Out of Cycle check requests as needed Compute\nvacation, holiday and sick time Process weekly payroll following the guidelines of the Collective Bargaining Agreement Respond to requests\nfor income verification and/or employment verification Respond to associates questions/concerns in a courteous, pleasant manner Maintain\npayroll files Monthly reporting and reconciliation Implement payroll policies Determines payroll liabilities by calculating employee federal and\nstate income and social security taxes and employer's social security, unemployment, and workers compensation payments Respond to\nunemployment Insurance claims Pull queries for various monthly reports, reconcile and process check request for Conducts monthly SOX\naudits Check and audit timekeeping records and master file changes for compliance with established standards Update rates of pay and\ncalculate retroactive pay Respond to inquiries in a timely manner Preparation of weekly financial reporting for multi-sites and multi-states\nPerform various accounts payable and accounts receivable functions Month-end closing - preparation of P&L Statement and balance sheet\nFinancial forecasting and analysis Back-up HR Manager in all facets of HR duties.\nCompany Name\n \nOctober 1993\n \nto \nJanuary 2012\n \nShipping and Receiving Clerk/Scheduling Clerk/Inventory Control Clerk/Customer Service\nRepresentative/Payroll Administrator\n \nCity\n \n, \nState\nVerified and kept records on incoming and outgoing shipments Prepared items for shipment Received items into warehouse Compared\nidentifying information for incoming and outgoing shipments to verify information against bills of lading, invoices, orders, or other records\nScheduled appointments for product to be delivered to the warehouse as well as shipped out of the warehouse taking into consideration\ndelivery times and warehouse availability for product Complied and maintained records of quantity, type and value of material, equipment,\nmerchandise or supplies stocked in establishment Counted merchandise in stock and posted totals to inventory records via computer\nProvided information to customer by verifying understanding of requests and answering questions Resolved billing problems by identifying\nthe problem; explaining the procedure and forwarding the required adjustments Maintained payroll information by collecting, calculating and\nentering data Updated payroll records by entering changes in exemptions, insurance coverage, savings deductions and job title and\ndepartment transfers Resolved payroll discrepancies by collecting and analyzing information Provided payroll information by answering\nquestions and requests Maintained payroll operations by following policies and procedures; reporting needed changes Maintained employee\nconfidence and protected payroll operations by keeping information confidential.\nCompany Name\n \nJanuary 1983\n \nto \nJune 1992\n \nAssistant Supervisor, Air Evacuation Clerk/Assistant Supervisor, Inpatient Records Clerk/Supervisor\nMedical Service Accounts Officer/Patient Affairs Clerk/Hospital Outpatient Records Clerk\n \nSupervised a support staff of six in managing all administrative functions related to patients using air evacuation services.\nCoded each diagnosis and prepared concise medical histories to be entered into computer for patient's Aerovac Medical Record.\nPersonally managed difficult non-medical attendant issues directly with stateside facilitie",
  "enriched_profile": {
    "fullName": "WARD CLERK",
    "email": "",
    "phone": "",
    "location": "",
    "linkedin": "",
    "github": "",
    "portfolio": "",
    "summary": "Seeking a part-time nonmedical/retail position, I offer strong organizational and problem-solving abilities, demonstrated interpersonal skills, innovation, and resourcefulness. I have a reputation for dependability, efficiency, and professionalism.",
    "education": [
      {
        "school": "University of North Carolina",
        "degree": "Bachelors of Arts",
        "field": "Sociology",
        "startDate": "1982",
        "endDate": "",
        "gpa": ""
      }
    ],
    "experience": [
      {
        "company": "Company Name",
        "position": "HR/Payroll Supervisor",
        "startDate": "January 2012",
        "endDate": "Current",
        "description": "Prepares payroll, processes out of cycle check requests, computes vacation, holiday and sick time, responds to requests for income verification and/or employment verification, maintains payroll files, conducts monthly SOX audits, checks and audits timekeeping records and master file changes for compliance with established standards, updates rates of pay and calculates retroactive pay, responds to inquiries in a timely manner, performs various accounts payable and accounts receivable functions, and conducts month-end closing - preparation of P&L Statement and balance sheet."
      },
      {
        "company": "Company Name",
        "position": "Shipping and Receiving Clerk/Scheduling Clerk/Inventory Control Clerk/Customer Service Representative/Payroll Administrator",
        "startDate": "October 1993",
        "endDate": "January 2012",
        "description": "Verified and kept records on incoming and outgoing shipments, prepared items for shipment, received items into warehouse, compared identifying information for incoming and outgoing shipments to verify information against bills of lading, invoices, orders, or other records, scheduled appointments for product to be delivered to the warehouse as well as shipped out of the warehouse, maintained records of quantity, type and value of material, equipment, merchandise or supplies stocked in establishment, counted merchandise in stock and posted totals to inventory records via computer, provided information to customer by verifying understanding of requests and answering questions, resolved billing problems by identifying the problem; explaining the procedure and forwarding the required adjustments, maintained payroll information by collecting, calculating and entering data, updated payroll records by entering changes in exemptions, insurance coverage, savings deductions and job title and department transfers, resolved payroll discrepancies by collecting and analyzing information, provided payroll information by answering questions and requests, maintained payroll operations by following policies and procedures; reporting needed changes, maintained employee confidence and protected payroll operations by keeping information confidential."
      },
      {
        "company": "Company Name",
        "position": "Assistant Supervisor, Air Evacuation Clerk/Assistant Supervisor, Inpatient Records Clerk/Supervisor, Medical Service Accounts Officer/Patient Affairs Clerk/Hospital Outpatient Records Clerk",
        "startDate": "January 1983",
        "endDate": "June 1992",
        "description": "Supervised a support staff of six in managing all administrative functions related to patients using air evacuation services, coded each diagnosis and prepared concise medical histories to be entered into computer for patient's Aerovac Medical Record, personally managed difficult non-medical attendant issues directly with stateside facilities, entered discharge diagnosis and procedures into computer for all inpatient and ambulatory surgeries (3,000 cases annually) generated by 60 providers, ensuring that the proper paperwork was accurate and complete, obtained and compiled records for various audits, reviews and committees, assisted in pulling and screening more than 1,800 medical inpatient and outpatient records in support of JCAHO, upgraded several deficient functions within Inpatient Records; corrected discrepancies dating back three years, managed the hospital leave program, as well as mail and distribution program, significantly upgraded hospital's Regulation Program, resulting in elevation from a marginal to outstanding rating, drafted and implemented several innovative proposals to improve administrative efficiency, developed updated operating procedures for Mail & Distribution Office ensuring prompt and error-free service to 80+ departments, responsible for collecting cash, posting of ledgers and maintaining accountability for the Medical Service account, prepared billings; maintained files and ensured security of cashier's cage, restructured hospital's insurance billing and accounts receivable system, resulting in outstanding ratings."
      }
    ],
    "projects": [],
    "skills": [
      "accounts payable",
      "accounts receivable",
      "administrative",
      "Back-up",
      "balance sheet",
      "billing",
      "budget",
      "cashier",
      "CPR",
      "delivery",
      "diagnosis",
      "Financial forecasting",
      "financial reporting",
      "HR",
      "Insurance",
      "inventory",
      "managing",
      "MS Excel",
      "Mail",
      "Office",
      "MS Powerpoint",
      "MS Word",
      "Month-end closing",
      "payroll",
      "policies",
      "proposals",
      "receiving",
      "reporting",
      "Sarbanes-Oxley",
      "taxes",
      "type"
    ],
    "licenses": []
  }
}