{
  "resume_id": "R0042",
  "content": "DIGITAL MEDIA SALES CONSULTANT\nSummary\nDedicated and highly seasoned advertising employee with over 19 years of inside and outside newspaper sales experience in both the print and\ndigital realms. My goal is to be an asset to The Augusta Chronicle and to utilize my abilities and experience to further my personal growth.\nHighlights\nExcellent communication skills\nDetail oriented\nExcellent organizational skills\nGreat follow through\nRelationship building\nSolution focused\nNew Business Development\nCold Calling\nSkilled at understanding customers' needs and building campaigns focused on those needs\nAccomplishments\nCircle of Excellence, 2010 - The Augusta Chronicle\nAdvertising Salesperson of the Month, September 2010 - The Augusta Chronicle\nAdvertising Salesperson of the Month, January 2005 - The Savannah Morning News\nEmployee of the Month, March 2003- The Savannah Morning News\nAdvertising Employee of First Quarter 2000- The Fayetteville Observer\nExperience\nDigital Media Sales Consultant\n \nMar 2012\n \nto \nCurrent\n \nCompany Name\n \n\u00ef\u00bc\u200b \nCity\n \n, \nState\nResponsible for working alongside all advertising personnel to grow digital sales and serve as a source of reference for all members of the\nadvertising staff.\nWork with advertising sales representatives to build proposals for businesses and present solutions to companies for advertising needs.\nPrepare and analyze needs analysis to build customized proposals.\nOvercome customer objections.\nRun, analyze, and explain advertising reports.\nRecruitment Advertising Representative\n \nJan 2011\n \nto \nFeb 2012\n \nCompany Name\n \n\u00ef\u00bc\u200b \nCity\n \n, \nState\nService assigned and unassigned transient and monthly recruitment calls.\nFocus on the up-selling of monster.com products and Top Jobs.\nUtilize Ranger Data to complete callbacks.\nSell accounts into job fairs.\nEstablish new monthly recruitment accounts and contracts.\nHandle incoming Online Ads.\nPromote special pages and sections.\nQuote current recruitment and national rates.\nAutomotive Multi-media Account Executive\n \nJan 2007\n \nto \nJan 2011\n \nCompany Name\n \n\u00ef\u00bc\u200b \nCity\n \n, \nState\nService assigned and unassigned transient and monthly automotive dealers.\nFocus on building new ad campaigns and up-sell online products to direct traffic to the customers' lot.\nPull monthly reports and handle monthly projections.\nQuote current automotive rates.\nRecruitment Advertising Representative\n \nJan 2005\n \nto \nJan 2007\n \nCompany Name\n \n\u00ef\u00bc\u200b \nCity\n \n, \nState\nService assigned and unassigned transient and monthly recruitment calls.\nFocus on the up-selling of career builder.com and Top Jobs.\nUtilize Ranger Data to complete callbacks.\nSell accounts into Fall & Spring Job Fairs.\nEstablish new monthly recruitment accounts and contracts.\nHandle all incoming Classified Plus Ads, Place Ads and Ad Order Entry Ads and distribute them to recruitment and private party team\nmembers.\nPromote special pages and sections.\nQuote current recruitment and national rates.\nClassified Private Party Rep\n \nJan 2001\n \nto \nJan 2005\n \nCompany Name\n \n\u00ef\u00bc\u200b \nCity\n \n, \nState\nService assigned, unassigned, transient and commercial sales calls.\nPromote special pages and sections.\nQuote current classified rates.\nCold calling.\nHelp with weddings and obituaries as needed.\nFill in for sales supervisor as needed.\nSpecial Occasions Representative\n \nJan 2000\n \nto \nJan 2001\n \nCompany Name\n \n\u00ef\u00bc\u200b \nCity\n \n, \nState\nService assigned, unassigned, and transient sales calls.\nPromote special pages and sections.\nQuote current classified rates.\nCold calling.\nTyping and answering all wedding announcements and questions, special occasion announcements and assist in typing obituaries as needed.\nClassified Commercial Representative\n \nJan 1997\n \nto \nJan 2000\n \nCompany Name\n \n\u00ef\u00bc\u200b \nCity\n \n, \nState\nService assigned, unassigned, transient and commercial sales calls.\nEstablish new monthly accounts and contracts.\nPromote special pages and sections.\nQuote current classified rates.\nCold calling.\nComplete appropriate reports and billings.\nClassified Private Party Rep\n \nJan 1995\n \nto \nJan 1997\n \nCompany Name\n \n\u00ef\u00bc\u200b \nCity\n \n, \nState\nService assigned, unassigned, and transient sales calls.\nPromote Special pages and sections.\nQuote current classified rates.\nCold calling.\nComplete appropriate reports and billings.\nEducation\nMarketing\n \nAugusta State University\n \n\u00ef\u00bc\u200b \nCity\n \n, \nState\n1994-1997\nBachelors of Science\n \n, \nPsychology\n \n2012\n \nUniversity of Phoenix\n \n\u00ef\u00bc\u200b \nCity\n \n, \nState\nPsychology\nMaster of Science\n \n, \nCounseling and Clinical Psychology\n \nTroy University\n \n\u00ef\u00bc\u200b \nCity\n \n, \nState\nExpected graduation: 2016\nAdditional Information\nAdditional Skill-Building Training:\nLandy Chase Value-Based Selling- The Augusta Chronicle,\n2010 Franklin Covey- The Savannah Morning News,\n2005 Telephone Selling- The Savannah Morning News,\n2003 Customer Service Training- The Savannah Morning News,\n2003 Telephone Selling- The Savannah Morning News,\n2002 Advertising Legal Issues Training Class- The Augusta Chronicle,\n2001 CARE (Communication Actions that Re",
  "enriched_profile": {
    "fullName": "John Doe",
    "email": "",
    "phone": "",
    "location": "City, State",
    "linkedin": "",
    "github": "",
    "portfolio": "",
    "summary": "Dedicated advertising professional with 19+ years of experience in newspaper sales, both print and digital realms. Strong communication, organizational, and relationship building skills. Solution-focused and skilled in new business development, proposals, and understanding customer needs.",
    "education": [
      {
        "school": "Augusta State University",
        "degree": "Bachelors of Science",
        "field": "Marketing",
        "startDate": "1994",
        "endDate": "1997",
        "gpa": ""
      },
      {
        "school": "University of Phoenix",
        "degree": "Master of Science",
        "field": "Counseling and Clinical Psychology",
        "startDate": "",
        "endDate": "",
        "gpa": ""
      },
      {
        "school": "Troy University",
        "degree": "",
        "field": "Counseling and Clinical Psychology",
        "startDate": "",
        "endDate": "Expected 2016",
        "gpa": ""
      }
    ],
    "experience": [
      {
        "company": "Company Name",
        "position": "Digital Media Sales Consultant",
        "startDate": "Mar 2012",
        "endDate": "Present",
        "description": "Work alongside advertising personnel to grow digital sales, build proposals, overcome objections, and analyze reports."
      },
      {
        "company": "Company Name",
        "position": "Recruitment Advertising Representative",
        "startDate": "Jan 2011",
        "endDate": "Feb 2012",
        "description": "Service assigned and unassigned transient and monthly recruitment calls, up-sell Monster.com products, and handle incoming Online Ads."
      },
      {
        "company": "Company Name",
        "position": "Automotive Multi-media Account Executive",
        "startDate": "Jan 2007",
        "endDate": "Jan 2011",
        "description": "Service assigned and unassigned transient and monthly automotive dealers, build new ad campaigns, and handle monthly projections."
      },
      {
        "company": "Company Name",
        "position": "Recruitment Advertising Representative",
        "startDate": "Jan 2005",
        "endDate": "Jan 2007",
        "description": "Service assigned and unassigned transient and monthly recruitment calls, up-sell Career Builder.com, and handle Classified Plus Ads."
      },
      {
        "company": "Company Name",
        "position": "Classified Private Party Rep",
        "startDate": "Jan 1995",
        "endDate": "Jan 1997",
        "description": "Service assigned, unassigned, transient and commercial sales calls, promote special pages and sections, and quote classified rates."
      }
    ],
    "projects": [],
    "skills": [
      "Ad Building",
      "Ad Order Entry",
      "Advertising",
      "Advertising sales",
      "Automotive advertising",
      "Billing",
      "Cold calling",
      "Contract negotiation",
      "Customer Service",
      "Digital advertising",
      "Needs analysis",
      "Proposal Generation",
      "Recruitment advertising",
      "Telephone Skills"
    ],
    "licenses": []
  }
}