{
  "resume_id": "R0045",
  "content": "FINANCE MANAGER/ OPERATIONS MANAGER\nCareer Overview\nTo obtain a full time position in Management Information Systems with emphasis on business analysis where I can demonstrate excellent\nleadership, business and team work skills to produce effective results.\nQualifications\nTechnical help desk experience\nStrong analytical skills\nStrong collaborative skills\nDocument management\nExcellent problem solving skills\nStrong Communication Skills\nCustomer needs assessment\nRequirements Analysis\nRequirements Gathering\nC++\nJava\nCICS\nWindows Networks\nW-LAN\nTechnical Support\nSwitches, Bridges\nSoftware Development Life Cycle\nSystems Applications\nSystems Development\nSystems Implementation\nSystems Integration\nPC DOS\nPersonal Computers\nProblem Analysis and Resolution\nProcess Improvements\nProduct Life Cycle Management\nProduct Management\nProduct Research\nProject Quality Control\nQA\nQuality and Productivity Improvement\nTechnical Skills\nSkills\nExperience\nTotal Years\nLast Used\nAccomplishments\nIT Training\n \u00c2 \nSuccessfully trained 25 employees to use new operating system.\nNetwork Security\n \u00c2 \nPlanned, installed, maintained and optimized documentation of all LAN/WAN/VPN network hardware and software, security systems and\ncommunication links.\nManaged all clients network LAN/WAN hardware including routers, switches, load balancers and wireless networking equipment.\nNetwork Support\n \u00c2 \nActed as first point of contact for all major technical issues, including power outages, system failures and disaster recovery.\nOversaw infrastructure of three offices and acted as support for help-desk technicians and IT Department.\nWork Experience\nFinance Manager/ Operations Manager\n \nJuly 2004\n \nto \nCurrent\n \nCompany Name\n \n\u00ef\u00bc\u200b \nCity\n \n, \nState\nOversees all aspects of the organization's quality or business improvement efforts, such as developing and administrating the program,\ntraining and coaching employees, and facilitating change throughout the organization.\nResponsible for establishing strategic plans, policies, and procedures at all levels so quality improvement efforts will meet or exceed internal\nand external customers' needs and expectations.\nImplemented a new sales-tracking POS system to replace a manual form writing process to increase efficiency. Provided employee training\nfor POS system.\nRecruited, hired, trained, developed, and directed retail sales teams for two retail Wireless Nation dealer stores.\nOversaw client relations, new account development, and customer service.\nSupervised administrative functions, inventory, cash flow, merchandising, and operations. Generated monthly and annual sales reports.\nConducted ongoing staff development and personal growth planning for employees.\nDoubled annual sales by developing innovative and effective marketing programs. Created a team spirit within the stores that resulted in\nincreased sales, long-term employees, and customer satisfaction.\nAchieved 150% of quota and grew number of customers by 200% \nwithin the first year as Sales Manager.\nLed sales calls with team members to establish sales and customer retention goals. Determined merchandise price schedules and discount\nrates. Monitored customer preferences to determine focus of sales efforts.\nShared product knowledge with customers while making personal recommendations.Maintained friendly and professional customer\ninteractions.\nNegotiated and closed contracts with Fortune 500 companies, including Sprint Wireless, T-mobile and AT&T.\nComputer Information Systems Specialist II\n \nSeptember 1999\n \nto \nJuly 2004\n \nCompany Name\n \n\u00ef\u00bc\u200b \nCity\n \n, \nState\nAdministered the installation, configuration and continued maintenance of network equipment including servers, storage devices, routers,\nhubs, switches, and printers.\nTroubleshoots and resolves network connectivity and network related hardware/software problems. Processed an average of 20-30\ninbound and outbound technical support calls.\nReviews new hardware and software specifications and recommends products for procurement.\nInstall, configure, and optimize network communication hardware and client software. Referred difficult issues to upper management while\nmaintaining positive rapport with customer.\nCreate users, assigns privileges, and provides ongoing user support. Researched issues on various computer systems and databases to\nresolve complaints and answer inquiries.\nRespond to connectivity related help desk requests. Maintained composure and patience in face of difficult customer situations.\nRuns backup and recovery operations.\nProvides support and assistance to staff. Resolved customer complaints and concerns with strong verbal and negotiation skills. Displayed\ncourtesy and strong interpersonal skills with all customer interactions.\nCompletes archiving of network data and completes appropriate documentation.\nCollaborates with teachers and coordinators to assess and evaluate educational software to project future needs. Built and maintained\nsuccessful relationships with service providers, dealers and consu",
  "enriched_profile": {
    "fullName": "Finance Manager/ Operations Manager",
    "email": "",
    "phone": "",
    "location": "City, State",
    "linkedin": "",
    "github": "",
    "portfolio": "",
    "summary": "To obtain a full-time position in Management Information Systems with emphasis on business analysis, demonstrating excellent leadership, business, and teamwork skills to produce effective results.",
    "education": [
      {
        "school": "Bowie State University",
        "degree": "Master of Science",
        "field": "Information Systems",
        "startDate": "",
        "endDate": "2016",
        "gpa": "4.0"
      },
      {
        "school": "University of Maryland, University College",
        "degree": "Bachelor of Science",
        "field": "Information Systems",
        "startDate": "",
        "endDate": "2001",
        "gpa": ""
      }
    ],
    "experience": [
      {
        "company": "Company Name",
        "position": "Finance Manager/ Operations Manager",
        "startDate": "July 2004",
        "endDate": "",
        "description": "Oversees all aspects of the organization's quality or business improvement efforts, establishing strategic plans, policies, and procedures at all levels, implementing sales-tracking POS systems, recruiting, hiring, training, and developing retail sales teams, and conducting ongoing staff development and personal growth planning for employees."
      },
      {
        "company": "Company Name",
        "position": "Computer Information Systems Specialist II",
        "startDate": "September 1999",
        "endDate": "July 2004",
        "description": "Administered the installation, configuration, and maintenance of network equipment, troubleshot and resolved network connectivity and network-related hardware/software problems, reviewed new hardware and software specifications, installed, configured, and optimized network communication hardware and client software, created users, assigned privileges, and provided ongoing user support, responded to connectivity-related help desk requests, and completed archiving of network data."
      }
    ],
    "projects": [],
    "skills": [
      "administrative",
      "backup",
      "cash flow",
      "coaching",
      "hardware",
      "client",
      "client relations",
      "customer satisfaction",
      "customer service",
      "documentation",
      "help desk",
      "hubs",
      "inventory",
      "marketing",
      "merchandising",
      "network",
      "policies",
      "POS",
      "printers",
      "procurement",
      "quality",
      "quality improvement",
      "retail",
      "retail sales",
      "routers",
      "sales",
      "servers",
      "staff development",
      "strategic plans",
      "switches",
      "user support",
      "employee training"
    ],
    "licenses": []
  }
}