{
  "resume_id": "R0048",
  "content": "ACCOUNTANT\nSummary\nFinancial Accountant specializing in financial planning, reporting and analysis within the Department of Defense.\nHighlights\nAccount reconciliations\nResults-oriented\nFinancial reporting\nCritical thinking\nAccounting operations professional\nAnalysis of financial systems\nERP (Enterprise Resource Planning) software.\nExcellent facilitator\nAccomplishments\nServed on a tiger team which identified and resolved General Ledger postings in DEAMS totaling $360B in accounting adjustments. This allowed\nfor the first successful fiscal year-end close for 2012.\nIn collaboration with DFAS Europe, developed an automated tool that identified duplicate obligations. This tool allowed HQ USAFE to\ndeobligate over $5M in duplicate obligations.\nExperience\nCompany Name\n \nJuly 2011\n \nto \nNovember 2012\n \nAccountant\n \nCity\n \n, \nState\nEnterprise Resource Planning Office (ERO)\nIn this position as an Accountant assigned to the Defense Enterprise Accounting and Management System (DEAMS) ERO I was\nresponsible for identifying and resolving issues affecting the DEAMS General Ledger.\nI worked with teammates from the Procure to Pay, Orders to Cash, and Budget to Report areas to resolve daily challenges encountered\nwith the deployment of DEAMS to additional customers and when system change requests were promoted to production.\nI supported the testing of scripts, patches, and system change requests ensuring any anomalies were identified to the DEAMS Functional\nManagement Office for action by the DEAMS Program Management Office and/or the System Integrator.\nIn addition, I served on a tiger team designed to identify and resolve General Ledger posting differences and supported the development of\n$360B in accounting adjustments allowing for the first successful fiscal year-end close in 2012.\nThese actions also allowed for the reconciliation and closure of fiscal year 2010 and 2011 accounting adjustments ensuring that all DEAMS\nfiscal year-end requirements were completed.\nThese actions were recognized as critical to the successful review report issued by the Air Force Operational Test and Evaluation Center\n(AFOTEC) resulting in the Air Force receiving the authority to continue with the deployment of DEAMS.\nCompany Name\n \nApril 2010\n \nto \nJune 2011\n \nResource Advisor\n \nCity\n \n, \nState\nIn this position as Resource Advisor for the 1st Air Communications Operation Squadron (1ACOS) I was responsible for providing\nfinancial advice and decision support to the Commander.\nI was responsible for coordinating a $4.6M budget between four funding sources.\nI coordinated with USAFE Directorate of Intelligence (USAFE/A2), USAFE Directorate of Air and Space Operations (USAFE/A3),\nUSAFE Directorate of Communications (USAFE/A6) and the 435th Air Ground Operations Wing to ensure 1ACOS meets its mission\nrequirements.\nI consistently managed three separate timelines for providing budget/unfunded requirements, providing documentation and various reports in\nthe required format for each organization.\nI discussed the outcome of the Group and Directorate budget meetings providing feedback the same day to the Flight Chiefs and CC any\nissue which affects 1ACOS directly.\nI monitored the Defense Travel System (DTS) daily and identify orders and authorizations needing approval and provided notification to the\nappropriate Reviewing Officials and Approvers.\nUtilizing DTS and the General Accounting and Finance System I reviewed status reports to identify anomalies in obligations and have\nidentified those orders which require correction prior to payment.\nI provided Government Purchase Card (GPC) status reports the same day they are requested and in addition, communicated with the\nappropriate cardholders when changes were required to support their program.\nI identified cardholder training requirements and monitored these requirements to ensure all required training was completed in support of\nthis mission critical program.\nI developed guidance for the GPC cardholders on procedures for requesting training for the squadron and in addition I provided answers to\ncardholder questions on unique or non-standard issues/concerns.\nAssumed the role of the Billing Official during my final rating period and completed a self inspection of the program for the Management\nControl Program, zero findings.\nDuring yearly audit by 700th CONS received zero findings.\nCompany Name\n \nJuly 2008\n \nto \nApril 2010\n \nStaff Accountant\n \nCity\n \n, \nState\nIn my position as the Staff Accountant for HQ USAFE I was responsible for providing accounting and financial oversight and advice to\ncustomers throughout the Command in support of the USAFE Comptroller.\nI was responsible for performing ongoing analysis of financial programs to identify negative trends and weaknesses, ensured specific\nweaknesses were corrected, and determined whether systemic or repeat issues were identified and adequately addressed.\nI was required to apply a comprehensive knowledge of analysis/reporting requirements and data produced to re",
  "enriched_profile": {
    "fullName": "ACCOUNTANT",
    "email": "",
    "phone": "",
    "location": "",
    "linkedin": "",
    "github": "",
    "portfolio": "",
    "summary": "Financial Accountant specializing in financial planning, reporting and analysis within the Department of Defense. Highlights: Account reconciliations, Results-oriented, Financial reporting, Critical thinking, Accounting operations professional, Analysis of financial systems, ERP (Enterprise Resource Planning) software, Excellent facilitator.",
    "education": [
      {
        "school": "Northern Maine Community College",
        "degree": "Associate",
        "field": "Accounting",
        "startDate": "1994",
        "endDate": "",
        "gpa": "3.41"
      }
    ],
    "experience": [
      {
        "company": "Enterprise Resource Planning Office (ERO)",
        "position": "Accountant",
        "startDate": "July 2011",
        "endDate": "November 2012",
        "description": "Responsible for identifying and resolving issues affecting the DEAMS General Ledger. Worked with teammates to resolve daily challenges and supported the testing of scripts, patches, and system change requests."
      },
      {
        "company": "1st Air Communications Operation Squadron (1ACOS)",
        "position": "Resource Advisor",
        "startDate": "April 2010",
        "endDate": "June 2011",
        "description": "Provided financial advice and decision support to the Commander. Coordinated a $4.6M budget between four funding sources and monitored the Defense Travel System daily."
      }
    ],
    "projects": [
      {
        "name": "",
        "techStack": "",
        "description": "",
        "link": ""
      }
    ],
    "skills": [
      "Accounting",
      "General Accounting",
      "Accounts Payable",
      "Program Management"
    ],
    "licenses": []
  }
}