{
  "resume_id": "R0044",
  "content": "BUSINESS DEVELOPMENT REGIONAL MANAGER\nSummary\nResponsible for exhibiting value of the company's brand, through the delivery of expansion, recruitment, mobility, conflict resolution, and workforce\nmanagement services and solutions with Store level managers with customers, employee, management, and vendors.\u00c2 \nSkills\nProblem Solving\nTime Management\nPOS and Inventory Training\nInternal Conflict Resolution\nTraining and Development\nMarketing\nBudgets & Cost Reduction\nClient Retention\nBusiness Development\nPOS applications/software QuickBooks POS, Pacific Amber POS, and Lightspeed POS\nProficient in software such as QuickBooks and Microsoft Office applications.\u00c2 \nAdvanced use of the Windows XP, Windows 8, and Windows 10 operating systems.\nExperience\nJanuary 2013\n \nto \nCurrent\nCompany Name\n \nCity\n \n, \nState\n \nBusiness Development Regional Manager\nDeveloped, implemented, and improved inventory process and procedures resulting in reducing inventory loss throughout the company to\nbelow 5%.\nDeveloped and approve all company policies and procedures for inventory management and audits for POS (Point of Sale) and general\nstore functions.\nUtilizing Excel spreadsheets observations, system testing, and statistical reports for inventory and profit and loss.\nResponsible for marketing strategies and campaigns each quarter.\nProduce engaging online marketing campaigns and contests though the use of social media sites and search engines.\nPlan and schedule internal meetings, conference calls and web based presentations while utilizing most effective communication options to\nexplain new policies and procedures including but not limited to text and PowerPoint.\nPlan and schedule internal meetings, conference calls and web based presentations for notify and assist Human Resources and CEO, via\nAudits and \nindividual reviews, in a timely manner of all personnel-related changes involving branch office staff, including branch hierarchy\nreporting relationships, terminations and status changes.\nCross-trained and provided back-up support for multiple positions within the company.\nSpear headed a junior leadership program which increased employee retention.\nTested and selected POS software that was implemented throughout the company.\nPOS set up such as new product entry, employee set up, Transaction corrections, Inventory adjustments and customized reporting.\nUtilized most effective communication options to explain new policies and procedures including email, text, social (digital media),\nPowerPoint.\nAssisted Customers with complaints or concerns about the service or product received.\nCommunicated directly with vendors to insure inventory stock levels were adequately maintained and quality of product was approved and\nmaintained.\nResponsible for resolving internal conflicts with both mangers and employees to ensure a productive work environment.\nRecruitment of top talent for both entry level and management positions with a variety of different sourcing techniques including social media,\nUniversity Recruiting, referrals, and job boards.\nNotify Human Resources and CEO, via Audits and individual reviews, in a timely manner of all personnel-related changes involving branch\noffice staff, including branch hierarchy reporting relationships, terminations and status changes.\nProvide administrative support which includes, includes: answering phones, ordering supplies, preparing expense reimbursements, and\nassisting with events, presentations and report preparation.\nDrafted biweekly time sheets for over 20 executives and employees.\nJanuary 2012\n \nto \nJanuary 2013\nCompany Name\n \nCity\n \n, \nState\n \nSocial Media and PR Manager\nCreated a social media strategy that collaborates with marketing, PR and advertising campaigns.\nResearched top influencers, competitors, and trends in clients' industries; create timely and engaging content optimized for platform used and\nintended audience.\nMonitored sites for customer service opportunities and initiate conversations on behalf of the client.\nPlanned and managed the public relations programs designed to create and maintain a favorable public image for Fortune 500 companies.\nUtilized marketing software that measured marketing efforts and measure ROI on events and campaigns.\nCreated company literature and other forms of communication; helped design marketing and promotional materials, both print and\nelectronic.\nWorked with advertisers and editors for timely and useable ad and article submissions.\nPartnered with each manager in each department to determine event budget and expenses.\nJanuary 2011\n \nto \nJanuary 2013\nCompany Name\n \nCity\n \n, \nState\n \nTeacher/Receptionist\nInstructed students on the fundamentals of Cheerleading, Ballet, tap, Jazz and modern.\nInstructed students on the fundamentals of Cheerleading, Ballet, tap, Jazz and modern.\nManaged the receptionist area; which included greeting visitors and responding to telephone and in person request for academia or\nadministrative request.\nMaintained electronic and paper files; c",
  "enriched_profile": {
    "fullName": "Business Development Regional Manager",
    "email": "",
    "phone": "",
    "location": "City, State",
    "linkedin": "",
    "github": "",
    "portfolio": "",
    "summary": "Experienced Business Development Regional Manager responsible for exhibiting company's brand value, delivering expansion, recruitment, conflict resolution, and workforce management services. Proficient in QuickBooks, Microsoft Office, and various POS systems.",
    "education": [
      {
        "school": "Darton State College",
        "degree": "Associate of Applied Science",
        "field": "Business Administration",
        "startDate": "2017",
        "endDate": "",
        "gpa": ""
      },
      {
        "school": "Arabia Mountain High School",
        "degree": "High School Diploma",
        "field": "",
        "startDate": "May 2012",
        "endDate": "",
        "gpa": "Top 15% of my class 3.7"
      }
    ],
    "experience": [
      {
        "company": "Company Name",
        "position": "Business Development Regional Manager",
        "startDate": "January 2013",
        "endDate": "Current",
        "description": "Developed, implemented, and improved inventory process and procedures, reducing inventory loss throughout the company to below 5%. Utilized Excel spreadsheets, system testing, and statistical reports for inventory and profit and loss. Responsible for marketing strategies and campaigns each quarter. Assisted Customers with complaints or concerns about the service or product received. Communicated directly with vendors to insure inventory stock levels were adequately maintained and quality of product was approved and maintained. Responsible for resolving internal conflicts with both mangers and employees."
      },
      {
        "company": "Company Name",
        "position": "Social Media and PR Manager",
        "startDate": "January 2012",
        "endDate": "January 2013",
        "description": "Created a social media strategy that collaborates with marketing, PR and advertising campaigns. Researched top influencers, competitors, and trends in clients' industries; create timely and engaging content optimized for platform used and intended audience. Monitored sites for customer service opportunities and initiate conversations on behalf of the client. Planned and managed the public relations programs designed to create and maintain a favorable public image for Fortune 500 companies."
      },
      {
        "company": "Company Name",
        "position": "Teacher/Receptionist",
        "startDate": "January 2011",
        "endDate": "January 2013",
        "description": "Instructed students on the fundamentals of Cheerleading, Ballet, tap, Jazz and modern. Managed the receptionist area; which included greeting visitors and responding to telephone and in person request for academia or administrative request. Maintained electronic and paper files; created and maintained spreadsheets utilizing excel functions, pivot tables. Created customize reports that help minimize month end reporting for the leadership team."
      }
    ],
    "projects": [],
    "skills": [
      "administrative",
      "administrative support",
      "ad",
      "advertising",
      "back-up",
      "Budgets",
      "budget",
      "Business Development",
      "conflict resolution",
      "content",
      "Cost Reduction",
      "Client",
      "clients",
      "customer service",
      "delivery",
      "email",
      "forms",
      "Human Resources",
      "image",
      "inventory management",
      "Inventory",
      "leadership",
      "Managment",
      "marketing strategies",
      "marketing",
      "meetings",
      "Excel spreadsheets",
      "excel",
      "Microsoft Office applications",
      "office",
      "PowerPoint",
      "Windows 8",
      "Windows",
      "Windows XP",
      "online marketing",
      "search engines",
      "operating systems",
      "personnel",
      "pivot tables",
      "policies",
      "POS",
      "presentations",
      "PR",
      "Problem Solving",
      "profit and loss",
      "promotional materials",
      "public relations",
      "quality",
      "QuickBooks",
      "receptionist",
      "Recruiting",
      "Recruitment",
      "reporting",
      "spreadsheets",
      "strategy",
      "telephone",
      "answering phones"
    ],
    "licenses": []
  }
}