{
  "resume_id": "R0040",
  "content": "BUSINESS DEVELOPMENT REPRESENTATIVE\nAccomplishments\nAchievement driven and results-oriented individual interested in working in Business Management or Sales.\nSUMMARY: Youthful yet very mature; willing to learn and grow; excited about finding a challenging position that gives me an opportunity\nto contribute.\nQuick learner with attention to detail.\nExcellent ability to think out of the box and solve problems.\nSuperb leadership, intrapersonal, and people skills.\nFlexible and open to new challenges.\nProfessional Summary\nAchievement driven and results-oriented individual interested in working in Business Management or Sales.\nSkills\nMS Office Suite\nSalesForce.com\nPipedrive.com\nBirst/Intradiem Reports\nCPR Certification, 2012\nMS Office Suite\nSalesForce.com\nPipedrive.com\nBirst/Intradiem Reports\nCPR Certification, 2012\nSelf-motivated\nDedicated team player\nHighly competitive\nInterpersonal skills\nSalesForce.com\nPipedrive.com\nBirst/Intradiem Reports\nMS Office Suite\nSelf-motivated\nDedicated team player\nHighly competitive\nInterpersonal skills\nSalesForce.com\nPipedrive.com\nBirst/Intradiem Reports\nMS Office Suite\nMailchimp.com\nSelf-motivated\nDedicated team player\nHighly competitive\nInterpersonal skills\nWork History\nBusiness Development Representative\n \n05/2017\n \nto \nCurrent\n \nCompany Name\n \n\u00e2\u20ac\u201c \nCity\n \n, \nState\n \nIncreased gross revenue by 6% per month.\nGenerate new business by adding new retailers and working with existing retailers to strengthen and grow the relationship.\nDevelop relationships with retailers via outbound cold calls and email campaigns to decision makers.\nFollow 7 touches in 7 days plan for new prospects to set appointments.\nStrengthen existing accounts by growing product feed and improving pricing.\nDemonstrate solution and configure website integration.\nSales Development Representative\n \n09/2017\n \nto \nCurrent\n \nCompany Name\n \n\u00e2\u20ac\u201c \nCity\n \n, \nState\n \nMaintain positive energy on the sales floor.\nAchieved 160% of monthly quota and grew sales to $90K during Q1, earning title as top SDR globally in revenue and demos generated Q1\n2018.\u00c2 \nCompleted 130+ daily cold calls, with an average of 2.5 hours talk time.\nIncreased KPI's 2 fold month to month during first 90 days of employment.\nParticipate in all training and continuing education opportunities offered by management.\nSenior Sales Producer\n \n02/2015\n \nto \n05/2017\n \nCompany Name\n \n\u00e2\u20ac\u201c \nCity\n \n, \nState\n \nConsistently surpassed the agency standard of 20 policies per month.\nEstablish a referral network based on loan originators, real estate agents, new/used car and motorsports salesmen and my own personal\nnetwork.\nDeveloped marketing and partnership campaigns using a mix of targeted mailers, telemarketing and email drip campaigns.\nFollowed typical sales procedures on both internet and inbound sales leads.\nProbed for life and financial service opportunities for all customers.\nProvided customers with the utmost understanding during a loss and stood as a liaison between the customer and the claims department.\nCompleted all customer service requests in a timely manner.\nSolved underwriting obstacles for customers and new business.\nBusiness Development\n \n03/2017\n \nto \n08/2017\n \nCompany Name\n \n\u00e2\u20ac\u201c \nCity\n \n, \nState\n \nSuccessfully implemented company wide business development process, which led to a 6% per month increase in gross revenue. (target set\nby CEO was 2.5%)\nProspect for new retailers via outbound cold calls and email campaigns to decision makers. Met quota of on-boarding 2 new vendors per\nmonth.\nStrengthen existing accounts by proactively growing vendor product feed and improving pricing.\nFollowed call and email cadence throughout the entire sales cycle. \u00c2 \nDemonstrate solution and configure website integration.\nSenior Sales Producer\n \n02/2015\n \nto \n03/2017\n \nCompany Name\n \n\u00e2\u20ac\u201c \nCity\n \n, \nState\n \nConsistently surpassed the agency standard of 20 policies per month.\nEstablish a referral network based on loan originators, real estate agents, new/used car and motorsports salesmen and my own personal\nnetwork.\nDeveloped marketing and partnership campaigns using a mix of targeted mailers, telemarketing and email drip campaigns.\nFollowed typical sales procedures on both internet and inbound sales leads.\nProbed for life and financial service opportunities for all customers.\nProvided customers with the utmost understanding during a loss and stood as a liaison between the customer and the claims department.\nCompleted all customer service requests in a timely manner.\nSolved underwriting obstacles for customers and new business.\nSuccess Management and Reporting Analyst\n \n12/2012\n \nto \n02/2015\n \nCompany Name\n \n\u00e2\u20ac\u201c \nCity\n \n, \nState\n \nDocumented new reports engine data dictionary and report content.\nRan monthly and weekly adoption reports for upper management review.\nRan reports and organized data into a presentable document for client meetings.\nUpload weekly reports to Salesforce.com for companywide viewing.\nConducted classroom training on reporting system.\nCreated web help vide",
  "enriched_profile": {
    "fullName": "John Doe",
    "email": "",
    "phone": "",
    "location": "City, State",
    "linkedin": "",
    "github": "",
    "portfolio": "",
    "summary": "Achievement driven and results-oriented individual interested in working in Business Management or Sales. Quick learner with attention to detail. Excellent ability to think out of the box and solve problems. Superb leadership, intrapersonal, and people skills. Flexible and open to new challenges.",
    "education": [
      {
        "school": "Kennesaw State University, Coles College of Business",
        "degree": "Ph.D.",
        "field": "Professional Sales",
        "startDate": "2012",
        "endDate": "2019",
        "gpa": ""
      },
      {
        "school": "Kennesaw State University, Coles College of Business",
        "degree": "Bachelors",
        "field": "",
        "startDate": "December 2017",
        "endDate": "",
        "gpa": ""
      }
    ],
    "experience": [
      {
        "company": "Company Name",
        "position": "Business Development Representative",
        "startDate": "05/2017",
        "endDate": "Present",
        "description": "Increased gross revenue by 6% per month. Generate new business by adding new retailers and working with existing retailers to strengthen and grow the relationship. Develop relationships with retailers via outbound cold calls and email campaigns to decision makers. Follow 7 touches in 7 days plan for new prospects to set appointments. Strengthen existing accounts by growing product feed and improving pricing. Demonstrate solution and configure website integration."
      },
      {
        "company": "Company Name",
        "position": "Sales Development Representative",
        "startDate": "09/2017",
        "endDate": "Present",
        "description": "Maintain positive energy on the sales floor. Achieved 160% of monthly quota and grew sales to $90K during Q1, earning title as top SDR globally in revenue and demos generated Q1 2018. Completed 130+ daily cold calls, with an average of 2.5 hours talk time. Increased KPI's 2 fold month to month during first 90 days of employment. Participate in all training and continuing education opportunities offered by management."
      },
      {
        "company": "Company Name",
        "position": "Senior Sales Producer",
        "startDate": "02/2015",
        "endDate": "05/2017",
        "description": "Consistently surpassed the agency standard of 20 policies per month. Establish a referral network based on loan originators, real estate agents, new/used car and motorsports salesmen and my own personal network. Developed marketing and partnership campaigns using a mix of targeted mailers, telemarketing and email drip campaigns. Followed typical sales procedures on both internet and inbound sales leads. Probed for life and financial service opportunities for all customers. Provided customers with the utmost understanding during a loss and stood as a liaison between the customer and the claims department. Completed all customer service requests in a timely manner. Solved underwriting obstacles for customers and new business."
      },
      {
        "company": "Company Name",
        "position": "Business Development",
        "startDate": "03/2017",
        "endDate": "08/2017",
        "description": "Successfully implemented company wide business development process, which led to a 6% per month increase in gross revenue. (target set by CEO was 2.5%) Prospect for new retailers via outbound cold calls and email campaigns to decision makers. Met quota of on-boarding 2 new vendors per month. Strengthen existing accounts by proactively growing vendor product feed and improving pricing. Followed call and email cadence throughout the entire sales cycle. Demonstrate solution and configure website integration."
      },
      {
        "company": "Company Name",
        "position": "Success Management and Reporting Analyst",
        "startDate": "12/2012",
        "endDate": "02/2015",
        "description": "Documented new reports engine data dictionary and report content. Ran monthly and weekly adoption reports for upper management review. Ran reports and organized data into a presentable document for client meetings. Upload weekly reports to Salesforce.com for companywide viewing. Conducted classroom training on reporting system. Created web help videos."
      },
      {
        "company": "Company Name",
        "position": "Sales and Operations Support",
        "startDate": "",
        "endDate": "",
        "description": "Worked with minimal supervision on a variety of assignments across several departments. Completed all assignments accurately and ahead of deadlines. Organized SalesForce.com accounts into correct business categories and updated contact information from marketing campaigns. Managed SalesForce.com console and manage outbound calls to business directors and executives. Conducted telephone surveys via outbound calls to customers and industry workers. Created and maintained data for sales demo environment. Managed and assigned training courses for new employees. Researched customer data in new markets."
      }
    ],
    "projects": [
      {
        "name": "",
        "techStack": "",
        "description": "",
        "link": ""
      }
    ],
    "skills": [
      "MS Office Suite",
      "SalesForce.com",
      "Pipedrive.com",
      "Birst/Intradiem Reports",
      "CPR Certification",
      "Mailchimp.com",
      "agency",
      "com",
      "content",
      "client",
      "customer service",
      "data dictionary",
      "email",
      "financial",
      "marketing",
      "meetings",
      "network",
      "policies",
      "pricing",
      "real estate",
      "reporting",
      "Research",
      "Sales",
      "supervision",
      "surveys",
      "telemarketing",
      "telephone",
      "underwriting",
      "website"
    ],
    "licenses": [
      {
        "title": "CPR Certification",
        "description": "",
        "issueDate": "2012",
        "expiryDate": ""
      }
    ]
  }
}