{
  "resume_id": "R0041",
  "content": "BIOLOGY TEACHER\nExperience\n11/2016\n \nto \nCurrent\nBiology Teacher\n \nCompany Name\n \n\u00ef\u00bc\u200b \nCity\n \n, \nState\nExecute, implement, and modify lesson plans while incorporating differentiated instruction and multiple intelligences.\nDesign and align lessons, labs, and assessments incorporating STEM, problem based learning, Common Core and NGSS.\nVolunteer and participate in schools extracurricular activities such as selling tickets for the school talent show and participating in the\nLindenwold HS 5K for the scholarship fund.\nTeach and translate materials utilizing Sheltered Instruction techniques for English Language Learners.\nCo-teach with special education teachers while executing modifications in student IEP and 504 plans.\nPlan and present Google applications training for Lindenwold HS professional development.\n09/2011\n \nto \n11/2016\nBiology Teacher\n \nCompany Name\n \n\u00ef\u00bc\u200b \nCity\n \n, \nState\nSeek out of district professional development opportunities including but not limited to NJEA and NSTA Conventions, and addition\nprograms focused in science, standards, & STEM.\nSuccessfully fundraise money for incorporating additional technologies, TI Nspire CX graphing calculators, for the classroom through\nDonorsChoose.org.\nExecute, implement, and modify lesson plans while incorporating differentiated instruction and multiple intelligences.\nDesign and align lessons, labs, and assessments incorporating STEM, problem based learning, Common Core and NGSS.\nImplement ideas, practices, and theories from professional development workshops.\nTurn-Key for other teachers).\nCo-teach with special education teachers while executing modifications in student IEP and 504 plans.\nCommunicate with parents/guardians regarding student progress within the classroom.\nAchieve Level 1 Google Certified Educator status in October 2016.\n01/2011\n \nto \n03/2011\nStudent Teacher\n \nCompany Name\n \n\u00ef\u00bc\u200b \nCity\n \n, \nState\nDevelop labs, assignments, and projects to reinforce material taught previously encouraging deeper knowledge and understanding in\naddition to incorporate multiple disciplines, including writing, science, social sciences, and health.\nContinuous educational improvement by applying constructive criticism to lessons during student teaching experience.\nFormative and summative assessments of students on content related to the New Jersey State standards.\nExecute and implement lesson plans for the week while ensuring differentiated instruction.\nCommunicated with parents/guardians about student progress within the classroom.\n04/2007\n \nto \n04/2011\nClinical Lab Manager/Technologist\n \nCompany Name\n \n\u00ef\u00bc\u200b \nCity\n \n, \nState\nEducate and train Pathology Residents according to guidelines set forth in Molecular Diagnostic Laboratory Resident Manual, including\nobservation and hands on bench training of laboratory procedures and techniques.\nResearch and validate new laboratory tests by determining parameters for sample concentration, detection limits, and composition of\nprocedures for the laboratory.\nMaintain failed run, repeat testing, instrument/equipment maintenance & calibration, QC temperature, & T-A-T logs.\nPerform DNA extraction/quantitation, PCR, CE, interpretation, and reporting of results of molecular studies.\nManage and operate the laboratory and equipment according to the QA/QC Procedure and Protocol.\n08/2005\n \nto \n04/2007\nQuality Control Technician - TCA/E Coordinator\n \nCompany Name\n \n\u00ef\u00bc\u200b \nCity\n \n, \nState\nCoordinate monthly seminar with QC Director and attending laboratory technicians in addition to conducting 'Good Laboratory Practices'\nand orientation lectures for laboratory technicians.\nCompose and administer seminar quizzes and verifying technician credit by monitoring seminar attendance.\nAssemble and execute state reports for Department of Health in several states in which licenses are held.\nTroubleshoot and investigate pending specimens to ensure results are reported within a timely manner.\nManage Technician Competency Assessment (TCA) and Continuing Education (TCE) Programs.\nMaintain laboratory technician training records and schedule annual evaluations.\nAccumulate test result and testing comments for final report completion.\nCompose standard operations and procedure for pending specimens.\nVerify patient requisition forms to records in company database.\nCompile and maintained list of specimens pending.\n01/2005\n \nto \n08/2005\nClinical Laboratory Technician\n \nCompany Name\n \n\u00ef\u00bc\u200b \nCity\n \n, \nState\nPrepare gel agars and associated substrates from raw materials in large-scale electrophoresis testing platform.\nPrepare gel agars and associated substrates from raw materials in large-scale electrophoresis testing platform.\nProficient in aseptic techniques, 'Good Laboratory Practices', and proper pipetting practices.\nExtract raw samples for DNA purification utilizing aseptic techniques.\nExecute and analyze Real-Time and conventional PCR results.\nEducation\nAugust 2016\nDIG (Discoveries in Geosciences) Field School\nMarch 2011\nPost-Bachelors Teaching Certification Program\n",
  "enriched_profile": {
    "fullName": "John Doe",
    "email": "",
    "phone": "",
    "location": "City, State",
    "linkedin": "",
    "github": "",
    "portfolio": "",
    "summary": "Experienced Biology Teacher with a strong background in developing and implementing lesson plans, incorporating STEM, PBL, Common Core, and NGSS. Proficient in using Google applications and Sheltered Instruction techniques for English Language Learners. Achieved Level 1 Google Certified Educator status. Co-taught with special education teachers and communicated with parents/guardians regarding student progress.",
    "education": [
      {
        "school": "Drexel University School of Education",
        "degree": "Post-Bachelors Teaching Certification Program",
        "field": "Secondary Education",
        "startDate": "March 2011",
        "endDate": "",
        "gpa": ""
      },
      {
        "school": "University of Washington",
        "degree": "Secondary Education",
        "field": "",
        "startDate": "",
        "endDate": "",
        "gpa": ""
      },
      {
        "school": "Atlantic Cape Community College",
        "degree": "Bachelors of Sciences",
        "field": "Biological Sciences",
        "startDate": "January 2005",
        "endDate": "",
        "gpa": ""
      }
    ],
    "experience": [
      {
        "company": "Lindenwold HS",
        "position": "Biology Teacher",
        "startDate": "11/2016",
        "endDate": "Current",
        "description": "Execute, implement, and modify lesson plans while incorporating differentiated instruction and multiple intelligences. Design and align lessons, labs, and assessments incorporating STEM, problem based learning, Common Core and NGSS. Volunteer and participate in schools extracurricular activities. Teach and translate materials utilizing Sheltered Instruction techniques for English Language Learners. Co-teach with special education teachers while executing modifications in student IEP and 504 plans. Plan and present Google applications training for Lindenwold HS professional development."
      },
      {
        "company": "Company Name",
        "position": "Biology Teacher",
        "startDate": "09/2011",
        "endDate": "11/2016",
        "description": "Seek out of district professional development opportunities including but not limited to NJEA and NSTA Conventions, and addition programs focused in science, standards, & STEM. Successfully fundraise money for incorporating additional technologies, TI Nspire CX graphing calculators, for the classroom through DonorsChoose.org. Execute, implement, and modify lesson plans while incorporating differentiated instruction and multiple intelligences. Design and align lessons, labs, and assessments incorporating STEM, problem based learning, Common Core and NGSS. Implement ideas, practices, and theories from professional development workshops. Co-teach with special education teachers while executing modifications in student IEP and 504 plans. Communicate with parents/guardians regarding student progress within the classroom. Achieve Level 1 Google Certified Educator status in October 2016."
      },
      {
        "company": "Company Name",
        "position": "Student Teacher",
        "startDate": "01/2011",
        "endDate": "03/2011",
        "description": "Develop labs, assignments, and projects to reinforce material taught previously encouraging deeper knowledge and understanding in addition to incorporate multiple disciplines, including writing, science, social sciences, and health. Continuous educational improvement by applying constructive criticism to lessons during student teaching experience. Formative and summative assessments of students on content related to the New Jersey State standards. Execute and implement lesson plans for the week while ensuring differentiated instruction. Communicated with parents/guardians about student progress within the classroom."
      },
      {
        "company": "Company Name",
        "position": "Clinical Lab Manager/Technologist",
        "startDate": "04/2007",
        "endDate": "04/2011",
        "description": "Educate and train Pathology Residents according to guidelines set forth in Molecular Diagnostic Laboratory Resident Manual, including observation and hands on bench training of laboratory procedures and techniques. Research and validate new laboratory tests by determining parameters for sample concentration, detection limits, and composition of procedures for the laboratory. Maintain failed run, repeat testing, instrument/equipment maintenance & calibration, QC temperature, & T-A-T logs. Perform DNA extraction/quantitation, PCR, CE, interpretation, and reporting of results of molecular studies. Manage and operate the laboratory and equipment according to the QA/QC Procedure and Protocol."
      },
      {
        "company": "Company Name",
        "position": "Quality Control Technician - TCA/E Coordinator",
        "startDate": "08/2005",
        "endDate": "04/2007",
        "description": "Coordinate monthly seminar with QC Director and attending laboratory technicians in addition to conducting 'Good Laboratory Practices' and orientation lectures for laboratory technicians. Compose and administer seminar quizzes and verifying technician credit by monitoring seminar attendance. Assemble and execute state reports for Department of Health in several states in which licenses are held. Troubleshoot and investigate pending specimens to ensure results are reported within a timely manner. Manage Technician Competency Assessment (TCA) and Continuing Education (TCE) Programs. Maintain laboratory technician training records and schedule annual evaluations. Accumulate test result and testing comments for final report completion. Compose standard operations and procedure for pending specimens. Verify patient requisition forms to records in company database. Compile and maintained list of specimens pending."
      },
      {
        "company": "Company Name",
        "position": "Clinical Laboratory Technician",
        "startDate": "01/2005",
        "endDate": "08/2005",
        "description": "Prepare gel agars and associated substrates from raw materials in large-scale electrophoresis testing platform. Extract raw samples for DNA purification utilizing aseptic techniques. Execute and analyze Real-Time and conventional PCR results. Proficient in aseptic techniques, 'Good Laboratory Practices', and proper pipetting practices."
      }
    ],
    "projects": [],
    "skills": [
      "Anatomy",
      "aseptic techniques",
      "Bachelors",
      "Biology",
      "calculators",
      "calibration",
      "content",
      "credit",
      "database",
      "Department of Health",
      "DNA",
      "Educator",
      "English",
      "equipment maintenance",
      "forms",
      "forth",
      "Good Laboratory Practices",
      "instruction",
      "interpretation",
      "laboratory procedures",
      "laboratory tests",
      "lesson plans",
      "Director",
      "materials",
      "money",
      "Pathology",
      "PCR",
      "Physiology I",
      "progress",
      "QA",
      "Real-Time",
      "reporting",
      "Research",
      "selling",
      "workshops",
      "Composition I",
      "composition"
    ],
    "licenses": []
  }
}