{
  "resume_id": "R0046",
  "content": "INFORMATION TECHNOLOGY MANAGER\nSummary\nDedicated \nIT Manager\n \nwell-versed in analyzing and mitigating risk and finding cost-effective solutions. Excels at boosting performance and\nproductivity by establishing realistic goals and enforcing deadlines.\nHighlights\nOperations management\nProject tracking\u00c2 \nPerformance criteria tracking\nWaterfall framework\nScrum methodology\nEnterprise platforms\nSalary structure/compensation analysis\nCalm under pressure\nCompensation/benefits administration\nStaff development\nClient communication\nExperience\nInformation Technology Manager\n \n, \n03/2013\n \nto \nCurrent\n \nCompany Name\n \n\u00ef\u00bc\u200b \nCity\n \n, \nState\nManaged a four-person local IT team, allocating resources to ongoing projects and enforcing deadlines.\nDrove business KPIs through rapid iteration of customer-facing product features.\nLeveraged in-depth understanding of end-to-end customer experience to identify pain points and latent customer needs.\nCollaborated with the global team to resolve IT support cases.\nBuild and maintain a staff of five & terminate for cause one employee.\nCreate and audit processes interlocking with other teams, adjust as required.\nManage travel and budget for staff on-site visits.\nOwnership of SaaS customers in North America, Canada and Australia.\nDefined project deliverables and monitored status of tasks.\nExecuted proof of concept implementations to validate product feasibility.\nIT Administrator\n \n, \n06/2011\n \nto \n03/2013\n \nCompany Name\n \n\u00ef\u00bc\u200b \nCity\n \n, \nState\nDesigned and delivered mission critical infrastructure to ensure the highest levels of availability, performance and security.\nMaintained security, backup, and redundancy strategies.\nOwnership of IT Infrastructure and Client/Server management (Chicago, Houston, Montreal and Sydney).\nCollected, analyzed, and reported program metrics, including product technical performance measures and key performance parameters.\nManage North America production data center (SaaS) and disaster recovery applications.\nDeploy and manage VMware architecture.\nMonitor and created automatic actions related to hardware and web servers.\nEngineered IT infrastructure for reliable WAN and LAN connectivity.\nActive Directory and Group Policy configuration and deployment.\nProvided client support for production.\nSQL Administration.\nDeployed over 30 NEC phones and support for NEC PBX.\nResponsible for purchasing and product recommendations.\nNetwork Administrator\n \n, \n02/2010\n \nto \n05/2011\n \nCompany Name\n \n\u00ef\u00bc\u200b \nCity\n \n, \nState\nTested, configured and deployed Windows 7 operating system with Acronis Snap Deploy.\nDeployed and tested Microsoft Exchange 2010 in VMware.\nAdministered SQL 2005 database to run Dentrix and DEXIS software.\nConfiguration and implementation of Group Policies.\nInformation Technology Consultant\n \n, \n10/2008\n \nto \n05/2011\n \nCompany Name\n \n\u00ef\u00bc\u200b \nCity\n \n, \nState\nManaged and provided security administrative support for Paine Wetzel ONCOR International, Northridge Group, Rent Here Realty, and\nNorthwestern Dental Center.\nSupported Microsoft Windows 2003, XP, Vista and Mac operating systems.\nResponsible for purchase decisions to provide the best end point security solutions.\nObtained Milestone Advanced Certified Partner for video surveillance.\nNetwork Administrator\n \n, \n10/2008\n \nto \n05/2011\n \nCompany Name\n \n\u00ef\u00bc\u200b \nCity\n \n, \nState\nInstalled and configured LAN with Windows XP and Windows Vista clients.\nAdministration of Microsoft Active Directory.\nAdministration of Microsoft Exchange 2003 systems including backup and recovery.\nDeploy Symantec endpoint security solutions and implemented disaster recovery.\nManaged multiple desktop applications: Microsoft Office, Adobe Acrobat, ACT.\nAdministration of intranet.\nNetwork Administrator\n \n, \n10/2008\n \nto \n12/2009\n \nCompany Name\n \n\u00ef\u00bc\u200b \nCity\n \n, \nState\nProvided on-site technical support for Windows 2003 and 2008 servers, workstations, laptops, Blackberries, and iPhones.\nMigrated to Exchange 2007 SCR from Exchange 2003 with PowerShell and DAS.\nManaged Windows Server 2008 and Windows 7.\nCollege of Education Computer Technician\n \n, \n07/2006\n \nto \n06/2008\n \nCompany Name\n \n\u00ef\u00bc\u200b \nCity\n \n, \nState\nPerformed PC and Mac hardware and software configurations.\nTroubleshot general Novell Client issues.\nInstalled and maintained peripherals.\nBuilt images to be used with Symantec Ghost.\nEducation\nMaster of Science\n \n:\n \nBusiness Information Technology\n \n,\n \n2018\n \nDePaul University\n \n\u00ef\u00bc\u200b \nCity\n \n, \nState\nBachelor of Science\n \n:\n \nNetwork and Communications Management\n \n,\n \n2009\n \nDeVry University\n \n\u00ef\u00bc\u200b \nCity\n \n, \nState\nSkills\nActive Directory, administrative support, Adobe Acrobat, Architect, backup, budget, Client/Server, hardware, Concept, Client, clients, client\nsupport, DAS, database, disaster recovery, Ghost, LAN, laptops, Mac hardware, Mac, Exchange, Microsoft Exchange, Microsoft Exchange\n2003, Microsoft Office, Windows 7, Windows, Microsoft Windows 2003, Windows XP, NEC, Novell, operating systems, operating system,\nPBX, peripherals, Policies, processes",
  "enriched_profile": {
    "fullName": "Dedicated IT Manager",
    "email": "",
    "phone": "",
    "location": "City, State",
    "linkedin": "",
    "github": "",
    "portfolio": "",
    "summary": "IT Manager with expertise in operations management, project tracking, performance criteria tracking, and staff development. Skilled in waterfall framework, scrum methodology, and enterprise platforms. Calm under pressure and experienced in compensation/benefits administration.",
    "education": [
      {
        "school": "DeVry University",
        "degree": "Bachelor of Science",
        "field": "Network and Communications Management",
        "startDate": "2005",
        "endDate": "2009",
        "gpa": ""
      },
      {
        "school": "DePaul University",
        "degree": "Master of Science",
        "field": "Business Information Technology",
        "startDate": "2016",
        "endDate": "2018",
        "gpa": ""
      }
    ],
    "experience": [
      {
        "company": "Company Name",
        "position": "Information Technology Manager",
        "startDate": "03/2013",
        "endDate": "Present",
        "description": "Managed a four-person local IT team, allocating resources to ongoing projects and enforcing deadlines. Drove business KPIs through rapid iteration of customer-facing product features. Leveraged in-depth understanding of end-to-end customer experience to identify pain points and latent customer needs. Collaborated with the global team to resolve IT support cases. Created and audited processes interlocking with other teams, adjusted as required. Managed travel and budget for staff on-site visits. Ownership of SaaS customers in North America, Canada and Australia. Defined project deliverables and monitored status of tasks. Executed proof of concept implementations to validate product feasibility."
      },
      {
        "company": "Company Name",
        "position": "IT Administrator",
        "startDate": "06/2011",
        "endDate": "03/2013",
        "description": "Designed and delivered mission critical infrastructure to ensure the highest levels of availability, performance and security. Maintained security, backup, and redundancy strategies. Ownership of IT Infrastructure and Client/Server management (Chicago, Houston, Montreal and Sydney). Collected, analyzed, and reported program metrics, including product technical performance measures and key performance parameters. Managed North America production data center (SaaS) and disaster recovery applications. Deployed and managed VMware architecture. Monitored and created automatic actions related to hardware and web servers. Engineered IT infrastructure for reliable WAN and LAN connectivity. Provided client support for production. SQL Administration. Deployed over 30 NEC phones and support for NEC PBX. Responsible for purchasing and product recommendations."
      },
      {
        "company": "Company Name",
        "position": "Network Administrator",
        "startDate": "02/2010",
        "endDate": "05/2011",
        "description": "Tested, configured and deployed Windows 7 operating system with Acronis Snap Deploy. Deployed and tested Microsoft Exchange 2010 in VMware. Administered SQL 2005 database to run Dentrix and DEXIS software. Configuration and implementation of Group Policies. Managed multiple desktop applications: Microsoft Office, Adobe Acrobat, ACT. Administered intranet."
      },
      {
        "company": "Company Name",
        "position": "Information Technology Consultant",
        "startDate": "10/2008",
        "endDate": "05/2011",
        "description": "Managed and provided security administrative support for Paine Wetzel ONCOR International, Northridge Group, Rent Here Realty, and Northwestern Dental Center. Supported Microsoft Windows 2003, XP, Vista and Mac operating systems. Responsible for purchase decisions to provide the best end point security solutions. Obtained Milestone Advanced Certified Partner for video surveillance."
      },
      {
        "company": "Company Name",
        "position": "Network Administrator",
        "startDate": "10/2008",
        "endDate": "12/2009",
        "description": "Installed and configured LAN with Windows XP and Windows Vista clients. Administered Microsoft Active Directory. Administered Microsoft Exchange 2003 systems including backup and recovery. Deploy Symantec endpoint security solutions and implemented disaster recovery. Managed multiple desktop applications: Microsoft Office, Adobe Acrobat, ACT. Administered intranet."
      },
      {
        "company": "Company Name",
        "position": "College of Education Computer Technician",
        "startDate": "07/2006",
        "endDate": "06/2008",
        "description": "Performed PC and Mac hardware and software configurations. Troubleshot general Novell Client issues. Installed and maintained peripherals. Built images to be used with Symantec Ghost."
      }
    ],
    "projects": [],
    "skills": [
      "Active Directory",
      "administrative support",
      "Adobe Acrobat",
      "Architect",
      "backup",
      "budget",
      "Client/Server",
      "hardware",
      "Concept",
      "Client",
      "clients",
      "client support",
      "DAS",
      "database",
      "disaster recovery",
      "Ghost",
      "LAN",
      "laptops",
      "Mac hardware",
      "Mac",
      "Exchange",
      "Microsoft Exchange 2003",
      "Microsoft Office",
      "Windows 7",
      "Windows",
      "Microsoft Windows 2003",
      "Windows XP",
      "NEC",
      "Novell",
      "operating systems",
      "operating system",
      "PBX",
      "peripherals",
      "Policies",
      "processes",
      "purchasing",
      "servers",
      "SLA",
      "SQL",
      "Symantec",
      "technical support",
      "phones",
      "Video",
      "Vista",
      "web servers",
      "WAN",
      "Windows Server"
    ],
    "licenses": []
  }
}