{
  "resume_id": "R0056",
  "content": "IT MANAGEMENT\nCareer Overview\nDetail-oriented professional with extensive Information Technology experience in hardware and software troubleshooting/management. With\nadditional experience in networking, task automation, server technologies, digital graphic design, client + server side programming technologies and\npopular industry software packages including Microsoft Office and Adobe Creative Suite.\nQualifications\nEducation and certificates \nTroubleshooting q \nCompTIA A+ certified (2012) \nq \nAdvanced troubleshooting q \nCompTIA Net+ certification class \nq\nVirus and spyware removal q \nMCSA certification class \nq \nComputer diagnostics and repair q \nWeb Development I + II class \nq \nGaming console\nrepair and q \nDigital media manipulation class \nmodification q \nJava programming class \nq \nMobile device repair q \nHardware support and\nProgramming and Web \ntroubleshooting q \nHTML - HTML5 \nq \nOptimizing and performance tuning q \nXML \nq \nAudio and video technologies q\nCSS - CSS3 \nq \nMedical technology installation and q \nJavaScript \ntroubleshooting q \nCommand Line q \nJava \nManagement q \nActionScript \nq\nHardware and software upgrade q \nPHP \nplanning q \nDatabase servers \nq \nDocumentation q \nAndroid mobile application \nq \nOrganization\ndevelopment \nq \nMulti-project priority management q \nContent Management Systems (CMS) \nOperating Systems q \nWebsite enhancement \nq\nWindows 95 - 8 q \nStoryboarding \nq \nWindows Server 2003 - 8 q \nSearch Engine Optimization (SEO) \nq \nWindows Phone 7.0 - 8.0 q \nSocial\nMedia and marketing \nq \nMultiple Linux Distributions q \nUbuntu 10.04 LTS - 12.10 Networking \nq \nAndroid 1.0 - 4.0.4 q \nCloud computing \nq \nMac\nOS X v10.0 - v10.8 q \nServer management \nq \nIOS 1.0 - 6.1 q \nActive directory q \nRemote connection technologies \nPrograms q \nProficiency in\nnumerous protocols \nq \nMicrosoft Office 2010 including TCP/IP \nq \nSmall business management q \nInformation security \nsoftware (client and server)\nq \nWireless technologies \nq \nAdobe Creative Suite 5 q \nTelephony technologies q \nWiring and Network engineering \nGraphics and Media q \nPhoto\nenhancing Electronics \nq \nBrochure and newsletter formatting q \nElectronic circuits and components \nq \nAudio and video editing q \nCircuit diagrams\nand Prototyping \nq \nLogo and business card q \nLogic, electronic and computational algorithms q \nElectromagnetisms and waves q \nQuantum particle\nmechanics \nq \nAs well as many miscellaneous IT q \nEnergy and electrical alternatives \nskills. (Solar)\nAccomplishments\nRebuilt a client's website from the ground up and increased monthly hits from 3422 to 40884 in a matter of a few months.\nDesigned, priced, built, and installed a complete information system upgrade for a client; including networking devices, wiring, client\ncomputers, server and software.\nDiagrammed, prototyped, and assembled a portable USB phone charger outputting optimal voltage and amperage, with circuits and\ncomponents small enough to all fit in an Altoids tin.\nIt allows next to unlimited portable phone charging due to the device itself being recharged by a small solar panel on the top.\nAutomated and streamlined daily office tasks for client using Batch Scripting.\nTroubleshot medical technology including X-ray machines and medical industry client and server software (Eaglesoft).\nInformation Technology project management experience.\nProgrammed a cloud storage website allowing a client access to a shared home network drive from any browser, anywhere.\nIt includes security login, uploading and downloading.\nWork Experience\nIT management\n \nMarch 2012\n \nto \nNovember 2012\n \nCompany Name\n \n\u00ef\u00bc\u200b \nCity\n \n, \nState\nIn charge of planning, budgeting, and executing all IT projects.In addition to office troubleshooting, building/managing the company website\nand designing/updating the business's electronic newsletter.\nInformation Technology Consultant\n \nJuly 2011\n \nto \nFebruary 2012\n \nCompany Name\n \n\u00ef\u00bc\u200b \nState\nContracted IT consulting work from client computer repair to network expansion.\nMay 2011\n \nto \nJuly 2011\n \nCompany Name\n \n\u00ef\u00bc\u200b \nCity\n \n, \nState\nIn charge of company website management, social media administration, as well as assisting in administrative tasks.\nEducation and Training\nAssociate of Science\n \n: \nInformation Technology\n \n, \n2014\n \nLyons Township\n \n\u00ef\u00bc\u200b \nCity\n \n, \nState\n \n, \nUnited States\n \nInformation Technology\nHigh School Diploma\n \nGeneral Education\nCoursework in computer science all 4 years\n \nGPA: \nDiamond Achievement Academic award * Honor Roll\n \nDiamond Achievement Academic\naward * Honor Roll\nSkills\nA+ certified, ActionScript, Active directory, administrative, Adobe Creative Suite 5, Photo, Audio, Brochure, budgeting, business management,\nclient and server, CMS, Hardware, computer repair, consulting, Content Management, CSS, CSS3, client, Database, designing, Documentation,\nElectronics, XML, Graphics, Hardware support, HTML, HTML5, PHP, Information security, Java, Java programming, JavaScript, Linux, Logic,\nLogo, Mac OS, managing, marketing, Medical technology, Micros",
  "enriched_profile": {
    "fullName": "Detailed Professional",
    "email": "",
    "phone": "",
    "location": "City, State",
    "linkedin": "",
    "github": "",
    "portfolio": "",
    "summary": "Detail-oriented IT professional with extensive experience in hardware, software, networking, task automation, server technologies, digital graphic design, and client + server side programming. A+ certified, proficient in Microsoft Office, Adobe Creative Suite, and various protocols and operating systems.",
    "education": [
      {
        "school": "Lyons Township",
        "degree": "Associate of Science",
        "field": "Information Technology",
        "startDate": "",
        "endDate": "2014",
        "gpa": ""
      },
      {
        "school": "",
        "degree": "High School Diploma",
        "field": "General Education",
        "startDate": "",
        "endDate": "",
        "gpa": "",
        "additionalInfo": "Coursework in computer science all 4 years. Diamond Achievement Academic award * Honor Roll."
      }
    ],
    "experience": [
      {
        "company": "Company Name",
        "position": "IT Management",
        "startDate": "March 2012",
        "endDate": "November 2012",
        "description": "In charge of planning, budgeting, and executing all IT projects. In addition to office troubleshooting, building/managing the company website and designing/updating the business's electronic newsletter."
      },
      {
        "company": "Company Name",
        "position": "Information Technology Consultant",
        "startDate": "July 2011",
        "endDate": "February 2012",
        "description": "Contracted IT consulting work from client computer repair to network expansion."
      },
      {
        "company": "Company Name",
        "position": "IT Specialist",
        "startDate": "May 2011",
        "endDate": "July 2011",
        "description": "In charge of company website management, social media administration, as well as assisting in administrative tasks."
      }
    ],
    "projects": [
      {
        "name": "Client's Website",
        "techStack": "Web Development",
        "description": "Rebuilt a client's website from the ground up and increased monthly hits from 3422 to 40884 in a matter of a few months.",
        "link": ""
      },
      {
        "name": "Portable USB Phone Charger",
        "techStack": "Electronics, Circuit Diagrams, Prototyping",
        "description": "Diagrammed, prototyped, and assembled a portable USB phone charger outputting optimal voltage and amperage, with circuits and components small enough to all fit in an Altoids tin.",
        "link": ""
      },
      {
        "name": "Cloud Storage Website",
        "techStack": "Web Development, Cloud Computing",
        "description": "Programmed a cloud storage website allowing a client access to a shared home network drive from any browser, anywhere. Includes security login, uploading and downloading.",
        "link": ""
      }
    ],
    "skills": [
      "A+ certified",
      "ActionScript",
      "Active directory",
      "Adobe Creative Suite 5",
      "Photo",
      "Audio",
      "Brochure",
      "Budgeting",
      "Business management",
      "Client and server",
      "CMS",
      "Hardware",
      "Computer repair",
      "Consulting",
      "Content Management",
      "CSS",
      "CSS3",
      "Client",
      "Database",
      "Designing",
      "Documentation",
      "Electronics",
      "XML",
      "Graphics",
      "Hardware support",
      "HTML",
      "HTML5",
      "PHP",
      "Information security",
      "Java",
      "Java programming",
      "JavaScript",
      "Linux",
      "Logic",
      "Logo",
      "Mac OS",
      "Managing",
      "Marketing",
      "Medical technology",
      "Microsoft Office",
      "Office",
      "Windows",
      "Windows 95",
      "Network engineering",
      "Networking",
      "Network",
      "Newsletter",
      "Operating Systems",
      "Organization development",
      "Programming",
      "Protocols",
      "Prototyping",
      "Search Engine Optimization",
      "Servers",
      "Storyboarding",
      "TCP/IP",
      "Telephony",
      "Phone 7.0",
      "Troubleshooting",
      "Upgrade",
      "Video",
      "Video editing",
      "Web Development I",
      "Website",
      "Website management",
      "Windows Server",
      "Wiring"
    ],
    "licenses": []
  }
}