{
  "resume_id": "R0055",
  "content": "ENGINEERING OPERATIONS DIRECTOR\nExecutive Profile\nSenior Software Executive Senior Software Executive who is a key contributor to strategic planning and product development. Highly skilled at\ncreating and implementing key software improvements and process changes by uncovering major process limitations, maximizing profitability,\nscalability, and competition in the global marketplace. Accomplishments (over last 15 years +) Reported directly to C-level executives and Board\nmembers, successfully bridging the gap between the business and Engineering, implementing strategic plans and ensuring that the engineering teams\nare aligned to business goals. Agile expert and evangelist, running software development teams for over 17 years and specifically agile software\ndevelopment for more that 13 years. Reorganized and transitioned many teams and companies to become smooth running agile groups, drastically\nreducing delivery issues, making the work very transparent, empowering team members to become self-directed and accountable to their\ncommitments. Skilled at managing entire software development process and employees including QA, Project Management, Technical Support, on\nand offshore teams, contractors, subsidiaries, and merger/acquisitions. Successfully on-boarded the engineers and technology from an acquired\ncompany and quickly merged their intellectual property (IP) into the main product line. Advocate for strong Engineering Best Practices, including\ndesign & code reviews, paired programming, unit tests and continuous integration testing through automation. Including, establishing leading and\ntrailing engineering metrics, which provide strong indicators of product quality and delivery schedule. Managed globally distributed teams ranging\nfrom 15-60 people, with P&L responsibilities between $2M - $6M. Teams have been located in US, Germany, Hungary, Russia, China, and\nArgentina. Consistently an early adopter of critical trends in methodologies and practices, which transform and refine processes to increase the\ndelivery of business value.\nSkill Highlights\nTechnology \u00c2\u00b7 \nJava \n\u00c2\u00b7 \nAmazon \nAWS \n\u00c2\u00b7 \nHibernate \n\u00c2\u00b7 \nPHP \n\u00c2\u00b7 \nEC2 \n\u00c2\u00b7 \nElastic \nSearch \n\u00c2\u00b7 \nC++ \n\u00c2\u00b7 \nJSMVC \n\u00c2\u00b7 \nJUnit \n\u00c2\u00b7 \nC \n\u00c2\u00b7 \nHTML \n\u00c2\u00b7\nSelenium \n\u00c2\u00b7 \nCanJS \n\u00c2\u00b7 \nCSS \n\u00c2\u00b7 \nAurora \n\u00c2\u00b7 \nPL/SQL \n\u00c2\u00b7 \nBootstrap \n\u00c2\u00b7 \nJenkins \n\u00c2\u00b7 \nOracle \n\u00c2\u00b7 \nPython \n\u00c2\u00b7 \nPhabricator \n\u00c2\u00b7 \nMy/SQL \n\u00c2\u00b7 \nAJAX \n\u00c2\u00b7\nGitHub \n\u00c2\u00b7 \nJavaScript \n\u00c2\u00b7 \nCamel \n\u00c2\u00b7 \nJira \n\u00c2\u00b7 \nREST \nand \nSOAP \nservices \n\u00c2\u00b7 \nMongoDB \n\u00c2\u00b7 \nPerl\nProfessional Experience\nEngineering Operations Director\n \nJanuary 2014\n \nto \nCurrent\n \nCompany Name\n \n\u00ef\u00bc\u200b \nCity\n \n, \nState\nA high growth company, whose suite of services help researchers successfully communicate their work.\nIdentified misalignment between technical teams and business, reorganized the technical teams and aligned technical metrics to support\nbusiness KPIs, increasing revenue and cost savings.\nDoubled team to 20 people in 4 months, by introducing a new improved hiring process that quickly filtered out non-qualified candidates and\nincreased our acceptance rate to over 90%.\nAwarded Culture Champion Award.\nDirector of Software Development\n \nJanuary 2012\n \nto \nJanuary 2014\n \nCompany Name\n \n\u00ef\u00bc\u200b \nCity\n \n, \nState\nA non-profit organization devoted to the advancement and well-being of dogs.\nTurned around a multiyear software delivery failure, by re-architecting the approach taken, changing the technology used, and transitioning\nthe team to Agile; putting the software back on budget and on time.\nReduced technical dependency on old technologies by road mapping out a multiyear strategic technology plan, reducing number of\ntechnologies used throughout the department by 50%.\nResponsible for web based PCI compliant e-commerce software, connected to an enterprise database.\nChief Operating Officer\n \nJanuary 2010\n \nto \nJanuary 2012\n \nCompany Name\n \n\u00ef\u00bc\u200b \nCity\n \n, \nState\nPublic safety software and services company focused on enterprise-class software for Fire and EMS Departments.\nImplemented a SaaS solution, allowing smaller towns and cities the ability to use and integrate with the Fire and EMS software.\nReduced customer's server upgrade time from 4 days to 4 hours.\nRemoved the requirement, caused by software limitations, that hard mounted mobile computers be removed from fire trucks and brought\ninto the IT dept for upgrades.\nReduced a mobile computer's install and upgrade times from 1 day per machine to 2 hours.\nVice President of Engineering\n \nJanuary 2001\n \nto \nJanuary 2010\n \nCompany Name\n \n\u00ef\u00bc\u200b \nCity\n \n, \nState\nA mid-sized 3D software company for creating digital models of physical objects, including both 'off-the-shelf' and customized commercial\napplications.\nThe software is used globally in markets such as: rapid prototyping, reverse engineering, inspection, and healthcare.\nGrew revenue from $0 to over $16M with a CAGR greater than 30% for 6 consecutive years.\nIntegral in receiving 6 term sheets of similar valuation resulting in $8M in VC funds in 2008.\nExpanded company organically fro",
  "enriched_profile": {
    "fullName": "Senior Software Executive",
    "email": "",
    "phone": "",
    "location": "",
    "linkedin": "",
    "github": "",
    "portfolio": "",
    "summary": "Senior Software Executive with 15+ years of experience in strategic planning, product development, and Agile methodologies. Proven track record in bridging the gap between business and Engineering, increasing revenue, and reducing delivery issues. Managed globally distributed teams with P&L responsibilities.",
    "education": [
      {
        "school": "Boston University",
        "degree": "",
        "field": "Cognitive and Neural Systems",
        "startDate": "1991",
        "endDate": "",
        "gpa": ""
      },
      {
        "school": "Union College",
        "degree": "M. S",
        "field": "Computer Science",
        "startDate": "1989",
        "endDate": "",
        "gpa": ""
      },
      {
        "school": "Union College",
        "degree": "B. S",
        "field": "Computer Science",
        "startDate": "1988",
        "endDate": "",
        "gpa": ""
      }
    ],
    "experience": [
      {
        "company": "Company Name",
        "position": "Engineering Operations Director",
        "startDate": "January 2014",
        "endDate": "Present",
        "description": "Identified misalignment between technical teams and business, reorganized the technical teams and aligned technical metrics to support business KPIs, increasing revenue and cost savings."
      },
      {
        "company": "Company Name",
        "position": "Director of Software Development",
        "startDate": "January 2012",
        "endDate": "January 2014",
        "description": "Turned around a multiyear software delivery failure, by re-architecting the approach taken, changing the technology used, and transitioning the team to Agile; putting the software back on budget and on time."
      },
      {
        "company": "Company Name",
        "position": "Chief Operating Officer",
        "startDate": "January 2010",
        "endDate": "January 2012",
        "description": "Implemented a SaaS solution, allowing smaller towns and cities the ability to use and integrate with the Fire and EMS software."
      },
      {
        "company": "Company Name",
        "position": "Vice President of Engineering",
        "startDate": "January 2001",
        "endDate": "January 2010",
        "description": "Grew revenue from $0 to over $16M with a CAGR greater than 30% for 6 consecutive years."
      },
      {
        "company": "Company Name",
        "position": "Director of Software Development",
        "startDate": "January 2000",
        "endDate": "January 2001",
        "description": "Used patented lens system to project a standard 3D image into a 180 degree hemispherical screen."
      },
      {
        "company": "Company Name",
        "position": "Engineering Manager/Senior Software Engineer",
        "startDate": "January 1996",
        "endDate": "January 2000",
        "description": "Provided B2B and B2C real-time 3D solutions, via the Internet."
      },
      {
        "company": "Company Name",
        "position": "Software Engineer",
        "startDate": "January 1993",
        "endDate": "January 1996",
        "description": "Software Engineer"
      },
      {
        "company": "Company Name",
        "position": "Software Engineer",
        "startDate": "January 1989",
        "endDate": "January 1993",
        "description": "Software Engineer"
      }
    ],
    "projects": [],
    "skills": [
      "3D",
      "Agile",
      "AJAX",
      "B2B",
      "C",
      "C++",
      "Cognitive and Neural Systems",
      "CSS",
      "Database",
      "Delivery",
      "E-commerce",
      "Expert Systems",
      "Funds",
      "Hiring",
      "HTML",
      "Java",
      "JavaScript",
      "Marketing",
      "MongoDB",
      "Networks",
      "Neural",
      "Oracle",
      "PL/SQL",
      "PCI",
      "Perl",
      "Product Development",
      "Profit",
      "Prototyping",
      "Public safety",
      "Python",
      "Real-time 3D",
      "SOAP",
      "SQL",
      "Strategic",
      "Upgrades",
      "VC"
    ],
    "licenses": []
  }
}