{
  "resume_id": "R0059",
  "content": "STAFF ACCOUNTANT\nSummary\nHighly analytical and detail-oriented professional; possessing extensive financial statement background in quality assurance, compliance, auditing,\ncustomer service and regulatory requirements. Thorough knowledge of: financial reporting, cash and accrual basis accounting, fund basis reporting,\nGAAP and other accounting standards. Adapt quickly when new software and systems are installed. Proficient with: QuickBooks, MAS, ADP,\nCondo Manager, Adobe, and all Microsoft applications software. Excel in problem solving and strategic planning skills.\nHighlights\nDBA \nQuick Books MAS - Sage Software \nMicrosoft Excel ADP Drive \nMicrosoft Access Condo Manager \nMicrosoft Word\nEducation\nBachelor of Science\n \n: \nAccounting\n \n, \nMay 2010\n \nUniversity of North Carolina\n \n\u00ef\u00bc\u200b \nCity\n \n, \nState\n \nAccounting\nBachelor of Science\n \n: \nBusiness Administration Finance\n \n, \nMay 2010\n \nBusiness Administration Finance\nExperience\nStaff Accountant\n \nJanuary 2014\n \nto \nOctober 2014\n \nCompany Name\n \n\u00ef\u00bc\u200b \nCity\n \n, \nState\nPerformed all month end functions to produce financial statements.\nThe functions include: reconciliation of the operating and payroll bank accounts, recorded sales for the month, recorded payroll journals,\naccrued payroll, recorded sales tax, submitted sales tax to NC department of revenue, recorded inventory adjustments, and recorded\nbalance sheet month end entries.\nEntered all payables and receivables for the 7 franchise locations.\nWorked with vendors to resolve any situations that arose.\nReviewed and maintained that all needed franchise document were on file and up to date.\nWorked directly with controller on year-end review.\nAssembled all requested financial and legal documentation that was put into presentable formats.\nMaintained weekly spreadsheet on collected franchise royalties and advertising fees.\nThis spreadsheet is used for the year-end audit.\nManaged a company that owned and rented out 12 commercial properties of a shopping center to approved businesses.\nResponsible for: negotiating rent rates for new or renewing tenants, writing leases, collecting rent, cash flow management, payables, and\nresolving any tenant complaints or inquires.\nManaged a company that was a small farming entity.\nResponsible for maintaining cash flow, all payables, and setting up credit accounts with vendors.\nEntered all payroll journals and maintained cash flow for company that employed labor to work at farming entity.\nFiled North Carolina Annual Report for all companies managed by Cary Keisler Inc.\nand verified that all were current on their filings.\nStaff Accountant\n \nMarch 2013\n \nto \nJanuary 2014\n \nCompany Name\n \n\u00ef\u00bc\u200b \nCity\n \n, \nState\nCollect daily deposits for newly entered SOs as well the balance for any SO that has completed once a job status report has been ran.\nInteract directly with customers on outstanding deposits and balances due.\nResponsible for all PO and non PO payable entry/coding for all companies.\nWork directly with vendors to resolve and discrepancy with payables.\nPull weekly-unpaid bills reports that are used for cash flow projections.\nComplete weekly check run for all companies.\nReconcile monthly purchasing American Express credit card that ranges from $60,000.00 - $100,000.00+.\nHelped facilitate roll of purchasing manager during turnover period from September 2013 - December 2013.\nResponsible for ordering needed materials/supplies for factory production floor.\nWorked directly with VP of Finance and members of the production floor in collection of data to develop unit valuation.\nThis information combined with continued data collection is being used for future bills of materials and job costing.\nStaff Accountant\n \nApril 2012\n \nto \nMarch 2013\n \nCompany Name\n \n\u00ef\u00bc\u200b \nState\nLead reconciliation of Balance Sheet to ensure no discrepancy with General Ledger.\nResearch and resolve any transaction deviating from ordinary operations.\nRun Project Cost Reconciliation at month end to ensure all billable expenses are posted to a project.\nThis ensures all enries are posted to the correct project and General Ledger account.\nThis provides billing information as well as the correct bottom line for each project.\nDesign Excel Spreadsheet for prepaid employee benefits for EOM reconciliation purposes.\nReconcile American Express accounts for SDI and Battleware.\n10 Accounts) Responsible for all entry and custodial book keeping of SDI's fixed assets for depreciation purposes.\nDaily reconciliation SDI's Operating, Interest Sweep, and Line of Credit accounts for most accurate cash projections.\nResponsible for coding and entry of all Payables items for SDI and Battleware.\nPrepare monthly Sales and Use Tax.\nFinancial Management Partner\n \nJuly 2010\n \nto \nAugust 2011\n \nCompany Name\n \n\u00ef\u00bc\u200b \nCity\n \n, \nState\nIdentified, reported, tracked, and resolved subsidiary ledger discrepancies in all phases of the revenues and receivables accounting\nprocesses.\nProvide an end to end financial statement assurance and accurate presentation by aid",
  "enriched_profile": {
    "fullName": "Cary Keisler",
    "email": "",
    "phone": "",
    "location": "City, State",
    "linkedin": "",
    "github": "",
    "portfolio": "",
    "summary": "Highly analytical and detail-oriented Staff Accountant with extensive financial statement experience in quality assurance, compliance, auditing, customer service, and regulatory requirements. Proficient in QuickBooks, MAS, ADP, Condo Manager, Adobe, and Microsoft applications software.",
    "education": [
      {
        "school": "University of North Carolina",
        "degree": "Bachelor of Science",
        "field": "Accounting",
        "startDate": "May 2010",
        "endDate": "",
        "gpa": ""
      },
      {
        "school": "",
        "degree": "Bachelor of Science",
        "field": "Business Administration Finance",
        "startDate": "May 2010",
        "endDate": "",
        "gpa": ""
      }
    ],
    "experience": [
      {
        "company": "Cary Keisler Inc.",
        "position": "Staff Accountant",
        "startDate": "October 2014",
        "endDate": "",
        "description": "Managed a company that owned and rented out 12 commercial properties of a shopping center to approved businesses. Responsible for negotiating rent rates for new or renewing tenants, writing leases, collecting rent, cash flow management, payables, and resolving any tenant complaints or inquiries. Managed a company that was a small farming entity. Responsible for maintaining cash flow, all payables, and setting up credit accounts with vendors."
      },
      {
        "company": "Company Name",
        "position": "Staff Accountant",
        "startDate": "January 2014",
        "endDate": "October 2014",
        "description": "Performed all month end functions to produce financial statements. Entered all payables and receivables for the 7 franchise locations. Worked with vendors to resolve any situations that arose. Reviewed and maintained that all needed franchise documents were on file and up to date. Worked directly with controller on year-end review. Assembled all requested financial and legal documentation that was put into presentable formats. Maintained weekly spreadsheet on collected franchise royalties and advertising fees. This spreadsheet is used for the year-end audit."
      },
      {
        "company": "Company Name",
        "position": "Staff Accountant",
        "startDate": "March 2013",
        "endDate": "January 2014",
        "description": "Collected daily deposits for newly entered SOs as well the balance for any SO that has completed once a job status report has been ran. Interacted directly with customers on outstanding deposits and balances due. Responsible for all PO and non PO payable entry/coding for all companies. Worked directly with vendors to resolve and discrepancy with payables. Pulled weekly-unpaid bills reports that are used for cash flow projections. Completed weekly check run for all companies. Reconciled monthly purchasing American Express credit card that ranges from $60,000.00 - $100,000.00+. Helped facilitate roll of purchasing manager during turnover period from September 2013 - December 2013. Responsible for ordering needed materials/supplies for factory production floor. Worked directly with VP of Finance and members of the production floor in collection of data to develop unit valuation. This information combined with continued data collection is being used for future bills of materials and job costing."
      },
      {
        "company": "Company Name",
        "position": "Staff Accountant",
        "startDate": "April 2012",
        "endDate": "March 2013",
        "description": "Led reconciliation of Balance Sheet to ensure no discrepancy with General Ledger. Researched and resolved any transaction deviating from ordinary operations. Ran Project Cost Reconciliation at month end to ensure all billable expenses are posted to a project. Designed Excel Spreadsheet for prepaid employee benefits for EOM reconciliation purposes. Reconciled American Express accounts for SDI and Battleware. Responsible for all entry and custodial book keeping of SDI's fixed assets for depreciation purposes. Daily reconciliation SDI's Operating, Interest Sweep, and Line of Credit accounts for most accurate cash projections. Responsible for coding and entry of all Payables items for SDI and Battleware. Prepared monthly Sales and Use Tax."
      }
    ],
    "projects": [
      {
        "name": "",
        "techStack": "",
        "description": "",
        "link": ""
      }
    ],
    "skills": [
      "accounting",
      "accounts payable",
      "Accounts Receivable",
      "ADP",
      "advertising",
      "AR",
      "balance sheet",
      "balance",
      "bank reconciliations",
      "benefits",
      "billing",
      "book keeping",
      "budget",
      "cash flow projections",
      "cash flow",
      "controller",
      "Credit",
      "clients",
      "data collection",
      "delivery",
      "documentation",
      "email",
      "Finance",
      "financial",
      "financial reporting",
      "financial statements",
      "fixed assets",
      "General Ledger",
      "inventory",
      "job costing",
      "ledger",
      "legal",
      "materials",
      "meetings",
      "Microsoft Access",
      "Microsoft Excel",
      "Excel",
      "Microsoft Word",
      "negotiating",
      "DBA",
      "Payables",
      "payroll",
      "Peachtree",
      "processes",
      "purchasing",
      "Express",
      "Quick Books",
      "QuickBooks",
      "Research",
      "Sage",
      "Sales",
      "Spreadsheet",
      "Tax",
      "software support",
      "valuation",
      "year-end"
    ],
    "licenses": [
      {
        "title": "",
        "description": "",
        "issueDate": "",
        "expiryDate": ""
      }
    ]
  }
}