{
  "resume_id": "R0052",
  "content": "MANAGER / FITNESS INSTRUCTOR\nSummary\nEnthusiastic customer service/telesales representative with in-depth knowledge of sales, account management and training. Results-driven Manager\nwith proven ability to establish rapport with clients. A very hands-on, hardworking, and highly motivated individual. Results-driven specialist who\ncan multi-task, while staying organized and focused.Energetic, motivated specialist who is highly organized and skilled at balancing the needs of\nclients in both personal and professional capacities. Customer service and sales expert who identifies customer needs and delivers solutions to\nproblems. Talented Customer Service Associate skilled at balancing customer needs and company demands. Effectively builds loyalty and long-\nterm relationships with customers while achieving all individual sales goals. Customer Service Representative who maintains a high level of\nprofessionalism, patience and efficiency to minimize customer dissatisfaction and increase customer loyalty.\nHighlights\nHigh customer service standards\nDedicated to process improvement\nStrong problem solving ability\nStrong organizational skills\nActive listening skills\nSeasoned in conflict resolution\nEnergetic work attitude\nAdaptive team player\nSelf-motivated\nExcellent communication skills\nNatural leader\nThrives under pressure\nFast learning\nCustomer friendly\nCoordination skills\nExperience\nManager / Fitness Instructor\n \nJanuary 2014\n \nto \nCurrent\n \nCompany Name\n \n\u00ef\u00bc\u200b \nCity\n \n, \nState\nCultivated positive relationships with participants by interacting with them during group fitness classes.\nExplained the use of exercise equipment to all participants, prioritizing safety at all times.\nGreeted all members in a professional and friendly manner.\nImmediately reported any damaged or broken equipment.\nExplained class objectives and rules.\nExtensively trained new and existing employees.\nEducated clients on effective ways to exercise while on business travel, at home and on vacation.\nPromoted a safe and interactive environment for club clients and members.\nInstructed gym members about correct use of weight resistance and cardiovascular equipment.\nWorked with clients to improve their overall endurance, strength, flexibility and balance.\nReviewed weekly sales numbers and club statistics to identify areas for improvement.\nCocktail Waitress\n \nJuly 2013\n \nto \nOctober 2013\n \nCompany Name\n \n\u00ef\u00bc\u200b \nCity\n \n, \nState\nMaintained updated knowledge of all menu items, specials, liquor brands, beers and non-alcoholic selections.\nContinually provided exceptional service to customers by being friendly, knowledgeable and accommodating.\nEffectively and calmly resolved situations with intoxicated guests.\nImmediately informed supervisors of any problems or unusual situations and took appropriate action.\nDisplayed friendly, outgoing and energetic behavior to create a warm, fun atmosphere for guests.\nBuilt guest satisfaction and enjoyment.\nUpsold products when appropriate.\nWaitress\n \nFebruary 2013\n \nto \nJuly 2013\n \nCompany Name\n \n\u00ef\u00bc\u200b \nCity\n \n, \nState\nContinually monitored dining rooms for seating availability, service, safety and well-being of guests.\nEffectively listened to, understood and clarified guest concerns and issues.\nMaintained complete knowledge of restaurant menu, including daily specials.\nMonitored guest for intoxication and immediately reported concerns to management.\nMaintained high standards of cleanliness and sanitation.\nConsistently provided professional, friendly and engaging service.\nSkillfully promoted items on beverage lists and restaurant specials.\nWaitress\n \nJanuary 2013\n \nto \nJuly 2013\n \nCompany Name\n \n\u00ef\u00bc\u200b \nCity\n \n, \nState\nConsistently provided professional, friendly and engaging service.\nSkillfully promoted items on beverage lists and restaurant specials.\nDisplayed enthusiasm and knowledge about the restaurant's menu and products.\nDeveloped and maintained positive working relationships with others to reach business goals.\nProvided attentive service.\nAssertively uphold alcoholic beverages, appetizers and desserts.\nAssisted co-workers whenever possible.\nWaitress / Cocktail Server / Beer Tub\n \nMay 2012\n \nto \nDecember 2012\n \nCompany Name\n \n\u00ef\u00bc\u200b \nCity\n \n, \nState\nDelivered exceptional service by greeting and serving customers in a timely, friendly manner.\nMaintained knowledge of current menu items, garnishes, ingredients and preparation methods.\nAppropriately suggested additional items to customers to increase restaurant sales.\nDelivered exceptional, friendly and fast service.\nParticipated in bar incentives and contests to drive sales and promote the venue.\nMaintained a positive working relationship with fellow staff and management.\nDisplayed friendly, outgoing and energetic behavior to create a warm, fun atmosphere for guests.\nEducation\nHigh School Diploma\n \n: \n2011\n \nEagan High School\n \n\u00ef\u00bc\u200b \nCity\n \n, \nState\nSkills\nbalance, clients, fast, safety, sales, statistics",
  "enriched_profile": {
    "fullName": "Enthusiastic Customer Service Representative",
    "email": "",
    "phone": "",
    "location": "City, State",
    "linkedin": "",
    "github": "",
    "portfolio": "",
    "summary": "Results-driven Manager and Fitness Instructor with a passion for customer service, sales, and process improvement. High customer service standards, strong problem-solving skills, and adaptive team player. Natural leader who thrives under pressure and is dedicated to continuous learning.",
    "education": [
      {
        "school": "Eagan High School",
        "degree": "",
        "field": "",
        "startDate": "2007",
        "endDate": "2011",
        "gpa": ""
      }
    ],
    "experience": [
      {
        "company": "Company Name",
        "position": "Manager / Fitness Instructor",
        "startDate": "January 2014",
        "endDate": "Present",
        "description": "Cultivate positive relationships with participants by interacting with them during group fitness classes. Explain the use of exercise equipment to all participants, prioritizing safety at all times. Greet all members in a professional and friendly manner. Report any damaged or broken equipment immediately. Explain class objectives and rules. Train new and existing employees extensively. Educate clients on effective ways to exercise while on business travel, at home and on vacation. Promote a safe and interactive environment for club clients and members. Instruct gym members about correct use of weight resistance and cardiovascular equipment. Work with clients to improve their overall endurance, strength, flexibility and balance. Review weekly sales numbers and club statistics to identify areas for improvement."
      },
      {
        "company": "Company Name",
        "position": "Cocktail Waitress",
        "startDate": "July 2013",
        "endDate": "October 2013",
        "description": "Maintain updated knowledge of all menu items, specials, liquor brands, beers and non-alcoholic selections. Provide exceptional service to customers by being friendly, knowledgeable and accommodating. Resolve situations with intoxicated guests effectively and calmly. Inform supervisors of any problems or unusual situations and take appropriate action. Display friendly, outgoing and energetic behavior to create a warm, fun atmosphere for guests. Upsell products when appropriate."
      },
      {
        "company": "Company Name",
        "position": "Waitress",
        "startDate": "February 2013",
        "endDate": "July 2013",
        "description": "Monitor dining rooms for seating availability, service, safety and well-being of guests. Listen to, understand and clarify guest concerns and issues effectively. Maintain complete knowledge of restaurant menu, including daily specials. Monitor guest for intoxication and immediately report concerns to management. Maintain high standards of cleanliness and sanitation. Provide professional, friendly and engaging service. Promote items on beverage lists and restaurant specials skillfully."
      },
      {
        "company": "Company Name",
        "position": "Waitress / Cocktail Server / Beer Tub",
        "startDate": "May 2012",
        "endDate": "December 2012",
        "description": "Deliver exceptional service by greeting and serving customers in a timely, friendly manner. Maintain knowledge of current menu items, garnishes, ingredients and preparation methods. Suggest additional items to customers to increase restaurant sales appropriately. Deliver exceptional, friendly and fast service. Participate in bar incentives and contests to drive sales and promote the venue. Maintain a positive working relationship with fellow staff and management. Display friendly, outgoing and energetic behavior to create a warm, fun atmosphere for guests."
      }
    ],
    "projects": [],
    "skills": [
      "balance",
      "clients",
      "sales",
      "safety",
      "statistics",
      "process improvement",
      "problem-solving",
      "adaptability",
      "leadership",
      "communication",
      "fast learning",
      "coordination"
    ],
    "licenses": []
  }
}