{
  "resume_id": "R0051",
  "content": "MEDICAL SUPPORT ASSISTANT (OA) GS-5 STEP 2\nSummary\nCommitted and motivated medical support assistant with exceptional customer service and decision making skills. Strong work ethic, professional\ndemeanor and great initiative. Proficient at quickly learning new procedures and taking ownership of diverse projects.\nHighlights\nPatient scheduling abilities\nExcellent communication and interpersonal skills\n\u00c2 Flexibility\nReception area management\nDetail-oriented\n\u00c2 Self-starter\nTeam player\nAccomplishments\nCertificate of Acheivement\nExperience\n12/2015\n \nto \nCurrent\nMedical Support Assistant (OA) GS-5 Step 2\n \nCompany Name\n \n\u00ef\u00bc\u200b \nCity\n \n, \nState\nSalary: $32,918 per year 40 hours/week \u00c2 \nSupervisor: Dwight Huddleston \u00c2 \u00c2 \nService over 20000 military/civilian personnel and their dependents\nEnters, manipulates and/or retrieves information and data from automated systems\nmaintains and monitors patient appointment schedules for the clinic/practice, coordinates and/or schedules patient appointments with other\nclinics or specialties, receives patients and visitors as the initial point of contact, in person or telephonically\nrecords and relays messages and/or redirect calls\nexperienced in providing technical advice and assist managers\u00c2 \nprovides information regarding the practice, clinic, and hospital policies, procedures, and locations to patients, family members, staff, etc\nmaintains all patients' records, both electronic and paper\nresponsible for the clerical duties inherent to the in processing (reception), care, and out processing (transition) of outpatients,\nfamilies/caregivers and guests.\u00c2 \nScreen patients to determine eligibility of care for their treatment\nAlways keep medical assistants informed regarding the policies, procedures,and goals of the organization\npasses on the supervisor's instructions on work assignment, priorities, and deadlines.\nManages templates for 3 providers\n \nsubstitutes for absent medical support assistants to ensure there is coverage\u00c2 \nProvide on the job training to newly assigned employees\nmaintain appointment calendars to schedule and/or cancel appointments.\u00c2 \nKnowledgeable of \u00c2 Defense Civilian Payroll System (DCPS), Automated Time and Attendance Production System (ATAAPS), Civilian\nPersonnel OnLine (CPOL)\nprovide clerical/administrative and automation support using multiple computer systems and technologies, including Microsoft office (MS\nAccess, MS Powerpoint, MS Excel, MS Word and MS) Well versed to systems such as Composite Health Care System (CHCS), Allied\nHealth Longitudinal Technology Application (AHLTA), Defense Manpower Human Resource System Information (DMHRSI).\n10/2013\n \nto \n12/2014\nHealthcare Assistant Rep\n \nCompany Name\n \n\u00ef\u00bc\u200b \nCity\n \n, \nState\nSalary: $18,000 per year 40 hours/ week.\nSupervisor: America Gurrero may be contacted 915-204-1116.\nDuties: assisted with FSA/HRA benefits\nadministered Cobra benefits\nrespond to telephone inquiries and complaints using standard scripts and procedures\nfiled personal information\nresearches/resolves inquires and logs customer calls\ncommunicates appropriate options for resolution in a timely matter\ninforms customers about services available and assesses customer needs\nprovides functional guidance training and assistance to lower level staff\nassists in planning and implementing department goals and makes recommendations to management to improve efficiency and effectiveness\n\u00c2 operates word processing equipment in order to produce a variety of narrative and tabular materials, including labels, graphics,\ncorrespondence, memorandums, promotion recommendations, award recommendations, evaluations, meeting minutes, extensive updated\ndepartmental policies, procedures and reports.\n01/2003\n \nto \n08/2012\nAccount Adjuster II\n \nCompany Name\n \n\u00ef\u00bc\u200b \nCity\n \n, \nState\nSalary: $34,000.00 per year 40 hours/week.\nSupervisor: Tomeka Haddock -may be contacted (252) 493-4081.\nDuties: contacted customers to collect past due payments\nmade acceptable payment arrangements with customer\nfiled personal information,\nperform skip tracing as needed\nsent appropriate correspondence to customers\nscheduled appointments for designated personnel and remind them of such commitments, collected, selected, rearranged, tabulated, and\nconsolidated data from numerous source documents.\n08/2002\n \nto \n12/2002\nTechnical Representative\n \nCompany Name\n \n\u00ef\u00bc\u200b \nCity\n \n, \nState\nSalary: 18,000 per year 40 hours/week.\nSupervisor: Shana Jones.\nDuties: Accepted inbound calls from customers regarding satellite radios, Activated new satellite service, resolved customer complaints and\nprocessed refunds, Arranged for defective satellite equipment to be repaired, replaced or refunded.\n01/2001\n \nto \n12/2001\nPharmacy Technician\n \nCompany Name\n \n\u00ef\u00bc\u200b \nCity\n \n, \nState\nSalary: $15,000 per year 40 hours/week.\nSupervisor: Tiffany Bowman.\nDuties: Received and stored incoming pharmacy supplies, verified stock and entered data into the computer to maintain inventory records,\nEntered customer information and prescription",
  "enriched_profile": {
    "fullName": "Committed Medical Support Assistant",
    "email": "",
    "phone": "",
    "location": "City, State",
    "linkedin": "",
    "github": "",
    "portfolio": "",
    "summary": "Committed and motivated medical support assistant with exceptional customer service and decision making skills. Strong work ethic, professional demeanor and great initiative. Proficient at quickly learning new procedures and taking ownership of diverse projects. Highlights include patient scheduling abilities, excellent communication and interpersonal skills, flexibility, reception area management, detail-oriented, self-starter, and team player.",
    "education": [
      {
        "school": "University of Phoenix",
        "degree": "Bachelor of Science",
        "field": "Healthcare Administration/Healthcare Management",
        "startDate": "2016",
        "endDate": "",
        "gpa": "3.7"
      },
      {
        "school": "Fayetteville Tech Community College",
        "degree": "Associates",
        "field": "Medical Office Administration",
        "startDate": "2011",
        "endDate": "",
        "gpa": "3.0"
      }
    ],
    "experience": [
      {
        "company": "Medical Support Assistant (OA) GS-5 Step 2 Company Name",
        "position": "Medical Support Assistant (OA) GS-5 Step 2",
        "startDate": "12/2015",
        "endDate": "Current",
        "description": "Service over 20000 military/civilian personnel and their dependents. Enters, manipulates and/or retrieves information and data from automated systems. Maintains and monitors patient appointment schedules for the clinic/practice, coordinates and/or schedules patient appointments with other clinics or specialties, receives patients and visitors as the initial point of contact, in person or telephonically. Records and relays messages and/or redirect calls. Experienced in providing technical advice and assist managers. Provides information regarding the practice, clinic, and hospital policies, procedures, and locations to patients, family members, staff, etc. Maintains all patients' records, both electronic and paper. Responsible for the clerical duties inherent to the in processing (reception), care, and out processing (transition) of outpatients, families/caregivers and guests. Screens patients to determine eligibility of care for their treatment. Always keeps medical assistants informed regarding the policies, procedures,and goals of the organization. Passes on the supervisor's instructions on work assignment, priorities, and deadlines. Manages templates for 3 providers. Substitutes for absent medical support assistants to ensure there is coverage. Provides on the job training to newly assigned employees. Maintains appointment calendars to schedule and/or cancel appointments. Knowledgeable of Defense Civilian Payroll System (DCPS), Automated Time and Attendance Production System (ATAAPS), Civilian Personnel OnLine (CPOL), Composite Health Care System (CHCS), Allied Health Longitudinal Technology Application (AHLTA), Defense Manpower Human Resource System Information (DMHRSI)."
      },
      {
        "company": "Healthcare Assistant Rep Company Name",
        "position": "Healthcare Assistant Rep",
        "startDate": "10/2013",
        "endDate": "12/2014",
        "description": "Assisted with FSA/HRA benefits. Administered Cobra benefits. Responded to telephone inquiries and complaints using standard scripts and procedures. Filed personal information. Researched/resolved inquires and logged customer calls. Communicated appropriate options for resolution in a timely matter. Informed customers about services available and assessed customer needs. Provided functional guidance training and assistance to lower level staff. Assisted in planning and implementing department goals and makes recommendations to management to improve efficiency and effectiveness. Operated word processing equipment in order to produce a variety of narrative and tabular materials, including labels, graphics, correspondence, memorandums, promotion recommendations, award recommendations, evaluations, meeting minutes, extensive updated departmental policies, procedures and reports."
      },
      {
        "company": "Account Adjuster II Company Name",
        "position": "Account Adjuster II",
        "startDate": "01/2003",
        "endDate": "08/2012",
        "description": "Contacted customers to collect past due payments. Made acceptable payment arrangements with customer. Filed personal information. Performed skip tracing as needed. Sent appropriate correspondence to customers. Scheduled appointments for designated personnel and remind them of such commitments. Collected, selected, rearranged, tabulated, and consolidated data from numerous source documents."
      },
      {
        "company": "Technical Representative Company Name",
        "position": "Technical Representative",
        "startDate": "08/2002",
        "endDate": "12/2002",
        "description": "Accepted inbound calls from customers regarding satellite radios. Activated new satellite service. Resolved customer complaints and processed refunds. Arranged for defective satellite equipment to be repaired, replaced or refunded."
      },
      {
        "company": "Pharmacy Technician Company Name",
        "position": "Pharmacy Technician",
        "startDate": "01/2001",
        "endDate": "12/2001",
        "description": "Received and stored incoming pharmacy supplies. Verified stock and entered data into the computer to maintain inventory records. Entered customer information and prescriptions company database. Dispensed medical prescriptions operation. Helped health care providers and patients by greeting them in person and by phone; answering questions and requests; referring inquiries to the pharmacist. Maintained pharmacy inventory by checking pharmaceutical stock to determine inventory level; anticipating needed medications and supplies; placing and expediting orders; verifying receipt; removing outdated drugs. Maintained a safe and clean pharmacy by complying with procedures, rules, and regulations. Protected patients and employees by adhering to infection-control policies and protocols. Organized medications for pharmacist to dispense by reading medication orders and prescriptions; preparing labels; calculating quantities; assembling intravenous solutions and other pharmaceutical therapies. Maintained records by recording and filing physicians' orders and prescriptions. Generated revenues by calculating, recording, and issuing charges. Ensured medication availability by delivering medications to patients and departments. Prepared reports by collecting and summarizing information."
      }
    ],
    "projects": [],
    "skills": [
      "patient scheduling",
      "communication",
      "interpersonal skills",
      "flexibility",
      "reception area management",
      "detail-oriented",
      "self-starter",
      "team player",
      "data entry",
      "record keeping",
      "customer service",
      "training",
      "appointment scheduling",
      "Microsoft Office",
      "Composite Health Care System (CHCS)",
      "Allied Health Longitudinal Technology Application (AHLTA)",
      "Defense Manpower Human Resource System Information (DMHRSI)"
    ],
    "licenses": []
  }
}