{
  "resume_id": "R0069",
  "content": "EXPRESS SCRIPTS\nSummary\nResponsible and mature Retail Sales Consultant who thrives in fast-paced environments. Enjoys working as part of a team to achieve sales goals.\nAccomplishments\nFulfilled all supervisory duties when Store Manager was on vacation.\nNamed \"Employee of the Month\".\nReceived numerous \u00e2\u20ac\u0153exceeds expectations\u00e2\u20ac\u200b ratings on performance reviews.\nMet monthly sales goals for numerous months.\nSupervised team of three staff members.\nExperience\nExpress Scripts\n \nSeptember 2015\n \nto \nCurrent\n \nCompany Name\n \n\u00ef\u00bc\u200b \nCity\n \n, \nState\nExercises sound judgment in issuing credits and making exceptions to customer policies to maintain high levels of customer satisfaction.\nFielded an average of [number] customer service calls per day.\nManaged wide variety of customer service and administrative tasks to resolve customer issues quickly and efficiently.\nPrime Communication (AT&T Authorized Retailer)\n \nJanuary 2015\n \nto \nSeptember 2015\n \nCompany Name\n \n\u00ef\u00bc\u200b \nCity\n \n, \nState\nCreated strategies to develop and expand existing customer sales, which resulted in a 20% increase in monthly sales.\nInitiated daily store counts, orders and acquired proper products\nMaintained knowledge of current promotions, policies regarding payment and exchanges, and security practices.\nRadio Shack\n \nNovember 2013\n \nto \nJanuary 2015\n \nCompany Name\n \n\u00ef\u00bc\u200b \nCity\n \n, \nState\nOperated a cash register to process cash, check and credit card transactions.\nComputed sales prices, total purchases and processed payments.\nDescribed merchandise and explain operation of merchandise to customers.\nReplenished floor stock and processed shipments to ensure product availability for customers.\nFacilitated monthly and quarterly physical inventory counts.\nAdministered all point of sale opening and closing procedures.\nOpened and closed the store, including counting cash, opening and closing cash registers and creating staff assignments.\nWorked as a team member to provide the highest level of service to customers.\nMaintained friendly and professional customer interactions.\nEducation\nHigh School Diploma\n \n: \nBusiness/ Computers\n \nCamden County High School\n \n\u00ef\u00bc\u200b \nCity\n \n, \nState\nSkills\nAdministrative\nCash handling\nExcellent communication\ninterpersonal skills\nDetail-oriented merchandising\nSelf-motivated\n70 WPM",
  "enriched_profile": {
    "fullName": "Retail Sales Consultant",
    "email": "",
    "phone": "",
    "location": "City, State",
    "linkedin": "",
    "github": "",
    "portfolio": "",
    "summary": "Responsible and mature Retail Sales Consultant with a proven track record in achieving sales goals and providing excellent customer service. Skilled in team supervision, communication, and cash handling.",
    "education": [
      {
        "school": "Camden County High School",
        "degree": "High School Diploma",
        "field": "Business/ Computers",
        "startDate": "",
        "endDate": "",
        "gpa": ""
      }
    ],
    "experience": [
      {
        "company": "Express Scripts",
        "position": "Retail Sales Consultant",
        "startDate": "September 2015",
        "endDate": "Present",
        "description": "Exercise sound judgment in issuing credits and making exceptions to customer policies to maintain high levels of customer satisfaction. Field an average of [number] customer service calls per day. Manage wide variety of customer service and administrative tasks to resolve customer issues quickly and efficiently."
      },
      {
        "company": "Prime Communication (AT&T Authorized Retailer)",
        "position": "Sales Associate",
        "startDate": "January 2015",
        "endDate": "September 2015",
        "description": "Created strategies to develop and expand existing customer sales, resulting in a 20% increase in monthly sales. Initiated daily store counts, orders and acquired proper products. Maintained knowledge of current promotions, policies regarding payment and exchanges, and security practices."
      },
      {
        "company": "Radio Shack",
        "position": "Sales Associate",
        "startDate": "November 2013",
        "endDate": "January 2015",
        "description": "Operated a cash register to process cash, check and credit card transactions. Computed sales prices, total purchases and processed payments. Described merchandise and explain operation of merchandise to customers. Replenished floor stock and processed shipments to ensure product availability for customers. Facilitated monthly and quarterly physical inventory counts. Administered all point of sale opening and closing procedures. Opened and closed the store, including counting cash, opening and closing cash registers and creating staff assignments. Worked as a team member to provide the highest level of service to customers. Maintained friendly and professional customer interactions."
      }
    ],
    "projects": [],
    "skills": [
      "Administrative",
      "Cash handling",
      "Excellent communication",
      "interpersonal skills",
      "Detail-oriented merchandising",
      "Self-motivated",
      "70 WPM"
    ],
    "licenses": []
  }
}