{
  "resume_id": "R0060",
  "content": "HR BENEFITS/LEAVE COORDINATOR\nSummary\n13 years of Human Resources experience and 27 years of administrative experience working in various settings *Professional, detail-oriented,\nexcellent time-management skills, team player, open and honest communicator, effective at maintaining confidentiality and multi-tasker.\nSkills\nProficient in all Microsoft applications and HRIS systems (Banner, PeopleAdmin, Personnel Management Information (PMIS) System and\nBenefits Eligibility System (BES), VRS Navigator (VNAV))\nExperience\nDecember 2016\nto\nCurrent\nCompany Name\n \nCity\n \n, \nState\n \nHR Benefits/Leave Coordinator\nProvide consultation and assistance for all employee benefits.\nAssist Retirement/Benefits Manager in counseling employees on retirements as well as generate retirement calculations.\nAssist Retirement/Benefits Manager with retirement trainings.\nPromote and coordinate all aspects of the Highlander Wellness Watch program.\nAdvise faculty/staff regarding leave policies and procedures.\nInterpret and apply policies, procedures and guidelines.\nDevelop and present leave trainings for employees and supervisors.\nContent editor for the HR newsletter and HR website committee.\nAnalyze and reconcile leave discrepancies.\nProcess and maintain Workers Compensation claims, short term disability claims and FMLA requests.\nCoordinate return to work for employees on short term disability, FMLA and WC.\nMaintain OSHA logs and reporting to include OSHA 301 and OSHA 300A reports.\nProcess employees leave corrections.\nProcess leave share requests and coordinate payments with payroll.\nCalculate leave payouts for separating employees for payment.\nProcess reports in Banner (HRIS) to ensure leave policies and procedures are being adhered to and applied in regards to FLSA\nregulations.\nPerform leave audits.\nProvide programmatic support to employees and supervisors for the on-line leave reporting system.\nAssist with other HR duties as needed to include job fairs, benefits fair, etc.\nMaintain confidential and sensitive information.\nNovember 2008\nto\nNovember 2016\nCompany Name\n \nCity\n \n, \nState\n \nHR Leave Coordinator\nAdvise faculty/staff regarding leave policies and procedures.\nInterpret and apply policies, procedures and guidelines.\nDevelop and present leave trainings for employees and supervisors.\nAnalyze and reconcile leave discrepancies.\nProcess and maintain Workers Compensation claims, short term disability claims and FMLA requests.\nCoordinate return to work for employees on short term disability, FMLA and WC.\nMaintain OSHA logs and reporting to include OSHA 301 and OSHA 300A reports.\nProcess employees leave corrections.\nProcess leave share requests and coordinate payments with payroll.\nCalculate leave payouts for separating employees for payment.\nProcess reports in Banner (HRIS) to ensure leave policies and procedures are being adhered to and applied in regards to FLSA\nregulations.\nAssist with coordination of CommonHealth wellness program.\nPerform leave audits.\nProvide programmatic support to employees and supervisors for the on-line leave reporting system.\nAssist with other HR duties as needed to include screening job applicants, new hire orientation, exit interviews, open enrollment for health\ninsurance and flexible spending accounts, job fairs, benefits fair, etc.\nMaintain confidential and sensitive information.\nJune 2004\nto\nNovember 2008\nCompany Name\n \nCity\n \n, \nState\n \nPersonnel Transaction Specialist/Human Resource Assistant\nProcess new hires, transfers, promotions into Banner and PMIS systems.\nPerform audits for payroll processing.\nProcess short term disability claims and FMLA requests.\nProcess leave share requests.\nCoordinate docks with payroll.\nPerform other duties and tasks as needed.\nMaintain confidential and sensitive information.\nAugust 2002\nto\nJune 2004\nCompany Name\n \nCity\n \n, \nState\n \nCommunications Operator\nRefer patients to appropriate areas for treatment.\nAssist patients with questions and concerns via phone or walk-ins.\nAnswer incoming calls on a seven-line phone system.\nPage doctors in a timely manner.\nUpdate call schedules as changes occur.\nFile.\nOverhead all codes in a timely manner.\nMaintain patient confidentiality.\nEducation and Training\nBluefield College\n \nCity\n \n, \nState\n \nBachelor of Science\n \n: \nOrganizational Management and Leadership\n \nOrganizational Management and Leadership\nNew River Community College\n \nAssociate of Applied Science\n \n: \nBusiness Management\n \nBusiness Management\nActivities and Honors\nSociety for Human Resources Management (SHRM) Colleges and Universities Professional Association for Human Resources (CUPA-HR)\nSkills\nBenefits, consultation, Content, counseling, editor, HRIS, HR, insurance, all Microsoft, Navigator, newsletter, Page, Assist patients, payroll,\npayroll processing, Personnel Management, phone system, policies, reporting, research, phone, website",
  "enriched_profile": {
    "fullName": "HR Benefits/Leave Coordinator",
    "email": "",
    "phone": "",
    "location": "",
    "linkedin": "",
    "github": "",
    "portfolio": "",
    "summary": "13 years of Human Resources experience, 27 years of administrative experience, proficient in Microsoft applications and HRIS systems (Banner, PeopleAdmin, PMIS System, BES, VRS Navigator). Skilled in benefits consultation, retirement calculations, wellness program promotion, leave policy advising, and training development.",
    "education": [
      {
        "school": "Bluefield College",
        "degree": "Bachelor of Science",
        "field": "Organizational Management and Leadership",
        "startDate": "",
        "endDate": "",
        "gpa": ""
      },
      {
        "school": "New River Community College",
        "degree": "Associate of Applied Science",
        "field": "Business Management",
        "startDate": "",
        "endDate": "",
        "gpa": ""
      }
    ],
    "experience": [
      {
        "company": "Company Name",
        "position": "HR Benefits/Leave Coordinator",
        "startDate": "December 2016",
        "endDate": "Current",
        "description": "Provide consultation and assistance for all employee benefits, generate retirement calculations, assist in retirement trainings, promote wellness program, advise on leave policies, develop and present leave trainings, analyze and reconcile leave discrepancies, process and maintain Workers Compensation claims, short term disability claims and FMLA requests, coordinate return to work for employees on short term disability, FMLA and WC, maintain OSHA logs, process leave corrections, process leave share requests, calculate leave payouts, perform leave audits, provide programmatic support for online leave reporting system, assist with HR duties as needed, maintain confidential information."
      },
      {
        "company": "Company Name",
        "position": "HR Leave Coordinator",
        "startDate": "November 2008",
        "endDate": "November 2016",
        "description": "Advise faculty/staff regarding leave policies and procedures, interpret and apply policies, develop and present leave trainings, analyze and reconcile leave discrepancies, process and maintain Workers Compensation claims, short term disability claims and FMLA requests, coordinate return to work for employees on short term disability, FMLA and WC, maintain OSHA logs, process leave corrections, process leave share requests, calculate leave payouts, perform leave audits, provide programmatic support for online leave reporting system, assist with HR duties as needed, maintain confidential information."
      },
      {
        "company": "Company Name",
        "position": "Personnel Transaction Specialist/Human Resource Assistant",
        "startDate": "June 2004",
        "endDate": "November 2008",
        "description": "Process new hires, transfers, promotions into Banner and PMIS systems, perform audits for payroll processing, process short term disability claims and FMLA requests, process leave share requests, coordinate docks with payroll, maintain confidential information."
      },
      {
        "company": "Company Name",
        "position": "Communications Operator",
        "startDate": "August 2002",
        "endDate": "June 2004",
        "description": "Refer patients to appropriate areas for treatment, assist patients with questions and concerns via phone or walk-ins, answer incoming calls on a seven-line phone system, page doctors in a timely manner, update call schedules as changes occur, file, overhead all codes in a timely manner, maintain patient confidentiality."
      }
    ],
    "projects": [],
    "skills": [
      "Benefits",
      "consultation",
      "Content",
      "counseling",
      "editor",
      "HRIS",
      "HR",
      "insurance",
      "Microsoft",
      "Navigator",
      "newsletter",
      "Page",
      "assist patients",
      "payroll",
      "payroll processing",
      "Personnel Management",
      "reporting",
      "research",
      "phone",
      "website"
    ],
    "licenses": []
  }
}