{
  "resume_id": "R0068",
  "content": "GROUP FITNESS COORDINATOR\nProfessional Summary\nHighly motivated, wellness professional seeking an opportunity to advance my career with a position providing the community with programs and\nservices to further their knowledge and involvement in wellness activities. Ability to design, develop, implement, and evaluate health and wellness\nprograms Strong interpersonal skills with experience in educating members and community about health related topics Innovative in designing and\ncarrying out projects \nAdvanced understanding and experience with the wellness industry Maintain high level of organizational, communication and\nservice oriented skills Basic understanding of fitness testing and evaluation concepts\nProfessional Experience\nGroup Fitness Coordinator\n \n05/2012\n \nto \n10/2015\n \nCompany Name\nDirected and supervised the Group Fitness Program which included staffing and evaluation of 30+ instructors.\nDeveloped educational seminars for active adults and members, providing wellness and health information.\nDeveloped health education events, incentive programs, and seminars for all employees.\nResponsible for P&L for the Group Fitness Program.\nDeveloped and ran annual community support campaign to bring in $10,000+ per year to department.\nDevised and implemented progressive and individualized exercise recommendations and programs.\nCreated and successfully held monthly healthy lifestyle events/ presentations.\nMarketed the group fitness classes to members as well as all fitness related events.\nPrivate Childcare Provider\n \n11/2011\n \nto \nCurrent\n \nCity\n \n, \nState\nCreated and carried out daily schedules that meet the physical and emotional needs of children.\nMet with parents on a weekly basis to discuss the week's plans, as well as any disciplinary problems.\nScheduled activities to ensure proper development of social interaction with others as well as personal development.\nEffectively handled interventions between children when disagreements arise.\nFitness Instructor\n \n08/2011\n \nto \nCurrent\nYMCA of the Suncoast, Highland Recreation Complex \nResponsibilities Developed, organized, and maintained fitness classes for members\nin an effective, efficient, and professional manner through personal recognition, relationship building, and safe execution.\nAdvised members on items related to fitness, exercise principles, and wellness.\nKept and maintained up-to-date trends in the fitness industry.\nEncouraged members to reach their fitness and wellness goals.\nEducation and Training\nBachelor's Degree\n \n: \nPsychology/ Government\n \nDecember 2011\n \nUniversity of Tampa\n \nPsychology/ Government Healthy Lifestyle Principles\nFoundations of Strength and Conditioning \nCPR, First Aid, AED Les Mills Bodypump Guardian ad Litem volunteer and advocacy training\nSkills\nad, CPR, First Aid, Guardian, health education, presentations, relationship building, seminars, staffing",
  "enriched_profile": {
    "fullName": "Highly motivated Wellness Professional",
    "email": "",
    "phone": "",
    "location": "",
    "linkedin": "",
    "github": "",
    "portfolio": "",
    "summary": "Highly motivated wellness professional seeking to advance my career by providing communities with programs and services to further their knowledge and involvement in wellness activities. Skilled in designing, developing, implementing, and evaluating health and wellness programs; educating members and community about health related topics; and maintaining organizational, communication, and service oriented skills.",
    "education": [
      {
        "school": "University of Tampa",
        "degree": "Bachelor's Degree",
        "field": "Psychology/ Government",
        "startDate": "",
        "endDate": "December 2011",
        "gpa": ""
      }
    ],
    "experience": [
      {
        "company": "Company Name",
        "position": "Group Fitness Coordinator",
        "startDate": "05/2012",
        "endDate": "10/2015",
        "description": "Directed and supervised the Group Fitness Program which included staffing and evaluation of 30+ instructors. Developed educational seminars for active adults and members, providing wellness and health information. Developed health education events, incentive programs, and seminars for all employees. Responsible for P&L for the Group Fitness Program. Developed and ran annual community support campaign to bring in $10,000+ per year to department. Devised and implemented progressive and individualized exercise recommendations and programs. Created and successfully held monthly healthy lifestyle events/ presentations. Marketed the group fitness classes to members as well as all fitness related events."
      },
      {
        "company": "City, State",
        "position": "Private Childcare Provider",
        "startDate": "11/2011",
        "endDate": "",
        "description": "Created and carried out daily schedules that meet the physical and emotional needs of children. Met with parents on a weekly basis to discuss the week's plans, as well as any disciplinary problems. Scheduled activities to ensure proper development of social interaction with others as well as personal development. Effectively handled interventions between children when disagreements arise."
      },
      {
        "company": "YMCA of the Suncoast, Highland Recreation Complex",
        "position": "Fitness Instructor",
        "startDate": "08/2011",
        "endDate": "",
        "description": "Developed, organized, and maintained fitness classes for members in an effective, efficient, and professional manner through personal recognition, relationship building, and safe execution. Advised members on items related to fitness, exercise principles, and wellness. Kept and maintained up-to-date trends in the fitness industry. Encouraged members to reach their fitness and wellness goals."
      }
    ],
    "projects": [],
    "skills": [
      "health education",
      "presentations",
      "relationship building",
      "seminars",
      "staffing",
      "CPR",
      "First Aid",
      "Guardian",
      "ad",
      "fitness",
      "wellness"
    ],
    "licenses": [
      {
        "title": "Les Mills Bodypump",
        "description": "",
        "issueDate": "",
        "expiryDate": ""
      },
      {
        "title": "CPR, First Aid, AED",
        "description": "",
        "issueDate": "",
        "expiryDate": ""
      },
      {
        "title": "Guardian ad Litem volunteer and advocacy training",
        "description": "",
        "issueDate": "",
        "expiryDate": ""
      }
    ]
  }
}