{
  "resume_id": "R0066",
  "content": "LIGHTING DESIGNER\nProfessional Summary\nComputer savvy and proficient with design tools for Architecture and Electro-Mechanical Design \n[Job Title]\n \nwho continually searches for new\ninspiration and stays savvy on current design trends. Proficient in Adobe InDesign, SketchUp and Rhino. \n[Job Title]\n \nwhose multi-faceted specialty\nranges from design of accessories and furniture to lighting design. Motivated Visual Merchandising Designer involved in all stages of design from\nproduct inception and development to production. Results-oriented \n[Job Title]\n \nwho delivers cutting edge and creative designs within strict time\nframes. Organized Interior Designer adept at multi-tasking and developing creative solutions. Successfully coordinates with vendors and manages\nconstruction teams with ease.\nSkills\nBuilding codes knowledge\n \nComplex problem solving\nStrong analytical ability\nExcellent attention to detail\nCommercial interior design\nWorking drawings and procedures\nSpace planning methodology\nDesign process\nCarpentry\nSketching\nRendering\nDigital drafting\n3D rendering software\nProficient in SketchUp\nWork History\nLighting Designer\n \n12/2013\n \nto \n11/2014\n \nCompany Name\n \n\u00e2\u20ac\u201c \nCity\n \n, \nState\n \nInterfaced with design team members, including contractors, consultants, fabricators, architects and regulatory agencies.\nSpecified proper products and materials for each project.\nCarefully reviewed contractor submittals of finish materials.\nSpecified proper products and materials for each project.\nPrepared construction documents and details to implement design concepts.\nOriginated and developed creative design concepts.\nArchitectural and Electrical Design/Drafter\n \n03/2008\n \nto \n12/2013\n \nCompany Name\n \n\u00e2\u20ac\u201c \nCity\n \n, \nState\n \nArchitectural and Electrical Design/Drafting.\nSuccessfully resolved complex technical design issues.\nInterfaced with design team members, including contractors, consultants, fabricators, architects and regulatory agencies.\nCarefully reviewed contractor submittals of finish materials.\nSpecified proper products and materials for each project.\nOriginated and developed creative design concepts.\nPrepared construction documents and details to implement design concepts.\nArchitecture Intern\n \n05/2007\n \nto \n02/2008\n \nCompany Name\n \n\u00e2\u20ac\u201c \nCity\n \n, \nState\n \nConsulted with clients to determine architectural preference to meet overall design goals.\nInterfaced with design team members, including contractors, consultants, fabricators, architects and regulatory agencies.\nCarefully reviewed contractor submittals of finish materials.\nSpecified proper products and materials for each project.\nFacilitated requests regarding product information, installation methods and product upgrade options.\nOriginated and developed creative design concepts.\nPrepared construction documents and details to implement design concepts.\nSenior Electro-Mechanical Designer & CEO\n \n01/1990\n \nto \n01/2005\n \nCompany Name\n \n\u00e2\u20ac\u201c \nCity\n \n, \nState\n \nRaytheon E-Systems.\nMotorola.\nCadence.\nConsulted with clients to determine architectural preference to meet overall design goals.\nResearched industry in the area of green building and environmental design.\nAssisted clients with budget considerations regarding products and materials.\nSuccessfully resolved complex technical design issues.\nInterfaced with design team members, including contractors, consultants, fabricators, architects and regulatory agencies.\nFacilitated requests regarding product information, installation methods and product upgrade options.\nOriginated and developed creative design concepts.\nPrepared construction documents and details to implement design concepts.\nSenior Electro-Mechanical Designer\n \n02/1986\n \nto \n11/1989\n \nCompany Name\n \n\u00e2\u20ac\u201c \nCity\n \n, \nState\n \nSuccessfullyresolved complex technical design issues.\nInterfaced with design team members, including contractors, consultants, fabricators, architects and regulatory agencies.\nSpecified proper products and materials for each project.\nOriginated and developed creative design concepts.\nPrepared construction documents and details to implement design concepts.\nDesign/Drafter\n \n05/1980\n \nto \n01/1986\n \nCompany Name\n \n\u00e2\u20ac\u201c \nCity\n \n, \nState\n \nConsulted with clients to determine architectural preference to meet overall design goals.\nSuccessfully resolved complex technical design issues.\nInterfaced with design team members, including contractors, consultants, fabricators, architects and regulatory agencies.\nSpecified proper products and materials for each project.\nOriginated and developed creative design concepts.\nPrepared construction documents and details to implement design concepts.\nEducation\nBachelor of Fine Arts\n \n: \nInterior Architecture\n \n2013\n \nThe University of North Carolina\n \n- \nCity\n \nInterior Architecture\nBIM and Design Graphics coursework\nContinuing coursework in Sustainable Design\nArchitecture coursework\nColor Theory and Perspective course\nHistoric Conservation \n& Adaptive Re-use Sustainable Design Practices Energy Efficiency in the Build",
  "enriched_profile": {
    "fullName": "Lighting Designer",
    "email": "",
    "phone": "",
    "location": "",
    "linkedin": "",
    "github": "",
    "portfolio": "",
    "summary": "Computer savvy Lighting Designer with proficiency in design tools for Architecture and Electro-Mechanical Design. Skilled in Adobe InDesign, SketchUp, and Rhino. Delivers creative and cutting-edge designs within strict time frames. Proficient in space planning methodology, digital drafting, and 3D rendering software.",
    "education": [
      {
        "school": "The University of North Carolina",
        "degree": "Bachelor of Fine Arts",
        "field": "Interior Architecture",
        "startDate": "2013",
        "endDate": "",
        "gpa": ""
      },
      {
        "school": "Wake Technical Community College",
        "degree": "Associates",
        "field": "Applied Science Architecture Technology",
        "startDate": "",
        "endDate": "",
        "gpa": ""
      },
      {
        "school": "Island Drafting & Technical Institute",
        "degree": "Drafting Certificate",
        "field": "Electrical and Mechanical",
        "startDate": "1980",
        "endDate": "",
        "gpa": ""
      }
    ],
    "experience": [
      {
        "company": "Company Name",
        "position": "Lighting Designer",
        "startDate": "12/2013",
        "endDate": "11/2014",
        "description": "Interfaced with design team members, specified proper products and materials, prepared construction documents, and developed creative design concepts."
      },
      {
        "company": "Company Name",
        "position": "Architectural and Electrical Design/Drafter",
        "startDate": "03/2008",
        "endDate": "12/2013",
        "description": "Architectural and Electrical Design/Drafting. Interfaced with design team members, reviewed contractor submittals, specified proper products and materials, and prepared construction documents."
      },
      {
        "company": "Company Name",
        "position": "Architecture Intern",
        "startDate": "05/2007",
        "endDate": "02/2008",
        "description": "Consulted with clients, interfaced with design team members, reviewed contractor submittals, specified proper products and materials, and prepared construction documents."
      },
      {
        "company": "Company Name",
        "position": "Senior Electro-Mechanical Designer & CEO",
        "startDate": "01/1990",
        "endDate": "01/2005",
        "description": "Consulted with clients, researched green building and environmental design, assisted clients with budget considerations, interfaced with design team members, and facilitated requests regarding product information, installation methods, and product upgrade options."
      },
      {
        "company": "Company Name",
        "position": "Senior Electro-Mechanical Designer",
        "startDate": "02/1986",
        "endDate": "11/1989",
        "description": "Successfully resolved complex technical design issues, interfaced with design team members, specified proper products and materials, and prepared construction documents."
      },
      {
        "company": "Company Name",
        "position": "Design/Drafter",
        "startDate": "05/1980",
        "endDate": "01/1986",
        "description": "Consulted with clients, successfully resolved complex technical design issues, interfaced with design team members, specified proper products and materials, and prepared construction documents."
      }
    ],
    "projects": [],
    "skills": [
      "Building codes knowledge",
      "Complex problem solving",
      "Strong analytical ability",
      "Excellent attention to detail",
      "Commercial interior design",
      "Working drawings and procedures",
      "Space planning methodology",
      "Design process",
      "Carpentry",
      "Sketching",
      "Rendering",
      "Digital drafting",
      "3D rendering software",
      "Proficient in SketchUp",
      "AutoCAD",
      "Cadence",
      "Client",
      "Documentation",
      "Drafting",
      "Estimating",
      "Leadership",
      "Team lead",
      "Lighting",
      "Materials",
      "meetings",
      "Motorola",
      "presentations",
      "Press",
      "Project Management"
    ],
    "licenses": []
  }
}