{
  "resume_id": "R0064",
  "content": "CONSTRUCTION\nSummary\nThe purpose of submitting my resume to your company is to obtain a position with the opportunity to utilize my training and skills in the technician\nindustry. I am experienced in warehouse and technician field -wiring 508 A UL soft starters, hard starters while assuring a high level of excellent\ncustomer service and satisfaction with maximum productivity; and maintaining a clean and safe warehouse. Also with security experience with skills\nin Microsoft Office Applications including Word, Excel, CCTV and PowerPoint; I am also competent in customer service satisfaction for installing\ndirect TV and having the ability to gain knowledge of certain products and being able to sell them to the public. I have solid leadership and\ncommunication skills. I am also a positive person willing to take on different tasks and eager to learn. These skills are exemplified in my previous\nemployment with Sprecher + Schuh. As a Wire-man and a Warehouse worker my duties ranged from being able to sale products to answering\ninquires or repair and wiring enclosures. By applying for this position will allow me to expand professionally and develop and learn new skills. I am\na team player-I enjoy being a positive outlet for my fellow co-workers and contributed to the success of others. I would like to thank you all, for\nyour time and consideration. Enclosed is a copy of my resume containing my contact information and my work history. Thanks to all again.\nSincerely, Edgardo M. Dubose To secure a position that will utilize my training and skills in the manufacturing \nindustry to contribute to the success\nof the organization. Managing employees and projects \u00c2\u00b7 Competent in Microsoft Applications-Word, Excel, PowerPoint \u00c2\u00b7 Maintain solid\ncommunication skills-oral and written \u00c2\u00b7 Ability t remain focus and productive daily while managing repetitive tasks \u00c2\u00b7 Knowledge of chemical\nlabeling and mixing \u00c2\u00b7 Quality control \n\u00c2\u00b7 Manufacturing work place \u00c2\u00b7 Operating sit-down Forklift\nHighlights\nImmaculate Customer Service\u00c2 \nDriver Safety Test Certificate\nCertified to work with Autistic Individuals\nSecurity Certification- Levels 1, 2, 3\nForklift and Pallet Jack Certificate\nEbiz, Management, professional\nTeam lead training\nHvac, Emergency\nLife crisis building evacuation skills\nChemicals Understanding and reaction\nExperience\n01/2014\n \nto \n01/2015\nConstruction\n \nCompany Name\n \n\u00ef\u00bc\u200b \nCity\n \n, \nState\nConstruction of houses.\nSubcontract with Aslide.\nApplying Sofit, Siding.\nUse of saw, hammer, drill, tape measure etc.\nCovers up wood on home exterior.\n01/2014\n \nto \n01/2014\nWire-man Assembler\n \nCompany Name\n \n\u00ef\u00bc\u200b \nCity\n \n, \nState\nAssemble Chromatograph.\nBuild product from scratch.\nInspect all products before use.\nApply circuit board.\nSoldering.\nWire.\nInspect for shipping.\nUsed power tools.\n01/2011\n \nto \n01/2013\nWire-man\n \nCompany Name\n \n\u00ef\u00bc\u200b \nCity\n \n, \nState\nRead electronic circuits schematics.\nCircuit board and soldering.\nWire.\nMulti-task using voltage reading for assembly production.\nUse of power tools and understand the basic of mechanics with tools.\nInstall and repair electric wire.\nBuild soft starters, hard starters.\nDrill and Tap.\nAssemble Enclosure.\n01/2011\n \nto \n01/2012\nSecurity Guard\n \nCompany Name\n \n\u00ef\u00bc\u200b \nCity\n \n, \nState\nFront desk answer phones supplying customer service.\nFront desk answer phones supplying customer service.\nHVAC systems, elevators.\nSecurity cameras.\nPatrol building secure.\n01/2010\n \nto \n01/2012\nTechnician\n \nCompany Name\n \n\u00ef\u00bc\u200b \nCity\n \n, \nState\nConsult helping customers plan for direct TV.\nMulti-tasking building satellites while installing,.\nAssigning membership and handling account information.\nInstall wire outlets, cut wire, ground wire, check for output of wire.\nUse of power tools drills, saws etc.\nBirddogs used to find signals.\n01/2009\n \nto \n01/2009\nSupervisor\n \nCompany Name\n \n\u00ef\u00bc\u200b \nCity\n \n, \nState\nProvided excellent customer service and satisfaction.\nFielded phone calls and emails.\nManaged inventory.\nMaintained building equipment.\nSupervised employees.\nTrack incoming and outgoing packages.\nAssemble appliances and furniture.\n01/2004\n \nto \n01/2008\nSales Representative/Care Provider\n \nCompany Name\n \n\u00ef\u00bc\u200b \nCity\n \n, \nState\nSale Representative for incoming patients.\nScheduled appointments for potential clients to visit the site.\nAnswered inquires about the benefits and services of the site.\nProvided potential clients with different services and packages.\nResponded and directed all complex incoming calls.\nMaintain a daily log of appointments.\nMaintain clean, working and livable environment for patients.\nResolved customer service inquires regarding: Billing and payments schedules and Benefits.\nAuthorization for treatments and medicine.\nEducation\nFire Science\n \nBAKERSFIELD COLLEGE\n \n\u00ef\u00bc\u200b \nCity\n \n, \nState\n \nFire Science\nHOUSTON COMMUNITY COLLEGE\n \n\u00ef\u00bc\u200b \nCity\n \n, \nState\nSkills\nbasic, Benefits, Billing, clients, excellent customer service, customer service, Forklift, hammer, HVAC, Inspect, inventory, Team lead, Multi-\ntasking, ",
  "enriched_profile": {
    "fullName": "Edgardo M. Dubose",
    "email": "",
    "phone": "",
    "location": "",
    "linkedin": "",
    "github": "",
    "portfolio": "",
    "summary": "Seeking a position in the manufacturing industry to utilize my training and skills, and contribute to the organization's success. Experienced in construction, wire-man assembler, wire-man, security guard, technician, and supervisor roles. Skilled in customer service, Microsoft Applications, leadership, and manufacturing processes. Certified in Forklift and Pallet Jack operation, security levels 1, 2, 3, and working with Autistic Individuals.",
    "education": [
      {
        "school": "Bakersfield College",
        "degree": "",
        "field": "Fire Science",
        "startDate": "",
        "endDate": "",
        "gpa": ""
      },
      {
        "school": "Houston Community College",
        "degree": "",
        "field": "Fire Science",
        "startDate": "",
        "endDate": "",
        "gpa": ""
      }
    ],
    "experience": [
      {
        "company": "Construction Company Name",
        "position": "Construction",
        "startDate": "01/2014",
        "endDate": "01/2015",
        "description": "Construction of houses. Subcontract with Aslide. Applying Sofit, Siding. Use of saw, hammer, drill, tape measure etc. Covers up wood on home exterior."
      },
      {
        "company": "Wire-man Assembler Company Name",
        "position": "Wire-man Assembler",
        "startDate": "01/2014",
        "endDate": "01/2014",
        "description": "Assemble Chromatograph. Build product from scratch. Inspect all products before use. Apply circuit board. Soldering. Wire. Inspect for shipping. Used power tools."
      },
      {
        "company": "Wire-man Company Name",
        "position": "Wire-man",
        "startDate": "01/2011",
        "endDate": "01/2013",
        "description": "Read electronic circuits schematics. Circuit board and soldering. Wire. Multi-task using voltage reading for assembly production. Use of power tools and understand the basic of mechanics with tools. Install and repair electric wire. Build soft starters, hard starters. Drill and Tap. Assemble Enclosure."
      },
      {
        "company": "Security Guard Company Name",
        "position": "Security Guard",
        "startDate": "01/2011",
        "endDate": "01/2012",
        "description": "Front desk answer phones supplying customer service. HVAC systems, elevators. Security cameras. Patrol building secure."
      },
      {
        "company": "Technician Company Name",
        "position": "Technician",
        "startDate": "01/2010",
        "endDate": "01/2012",
        "description": "Consult helping customers plan for direct TV. Multi-tasking building satellites while installing. Assigning membership and handling account information. Install wire outlets, cut wire, ground wire, check for output of wire. Use of power tools drills, saws etc. Birddogs used to find signals."
      },
      {
        "company": "Supervisor Company Name",
        "position": "Supervisor",
        "startDate": "01/2009",
        "endDate": "01/2009",
        "description": "Provided excellent customer service and satisfaction. Fielded phone calls and emails. Managed inventory. Maintained building equipment. Supervised employees. Track incoming and outgoing packages. Assemble appliances and furniture."
      },
      {
        "company": "Sales Representative/Care Provider Company Name",
        "position": "Sales Representative/Care Provider",
        "startDate": "01/2004",
        "endDate": "01/2008",
        "description": "Sale Representative for incoming patients. Scheduled appointments for potential clients to visit the site. Answered inquires about the benefits and services of the site. Provided potential clients with different services and packages. Responded and directed all complex incoming calls. Maintain a daily log of appointments. Maintain clean, working and livable environment for patients. Resolved customer service inquires regarding: Billing and payments schedules and Benefits. Authorization for treatments and medicine."
      }
    ],
    "projects": [],
    "skills": [
      "basic",
      "Benefits",
      "Billing",
      "clients",
      "excellent customer service",
      "customer service",
      "Forklift",
      "hammer",
      "HVAC",
      "Inspect",
      "inventory",
      "Team lead",
      "Multi-tasking",
      "Pallet Jack",
      "cameras",
      "power tools",
      "reading",
      "Read",
      "Safety",
      "schematics",
      "shipping",
      "Soldering",
      "tape measure",
      "answer phones",
      "phone",
      "TV"
    ],
    "licenses": [
      {
        "title": "Driver Safety Test Certificate",
        "description": "",
        "issueDate": "",
        "expiryDate": ""
      },
      {
        "title": "Certified to work with Autistic Individuals",
        "description": "",
        "issueDate": "",
        "expiryDate": ""
      },
      {
        "title": "Security Certification- Levels 1, 2, 3",
        "description": "",
        "issueDate": "",
        "expiryDate": ""
      },
      {
        "title": "Forklift and Pallet Jack Certificate",
        "description": "",
        "issueDate": "",
        "expiryDate": ""
      }
    ]
  }
}