{
  "resume_id": "R0079",
  "content": "MASTER TEACHER\nHighlights\nHome schooling knowledge\nCalm and patient\nCertified in Early Childhood Education\nHead Start programs\nStrong communicator\nToddler and preschool curricula\nClassroom management\nClassroom management\nSkills\nI have a lot patience, I communicate really well with children, \nI can usually calm a stressful situation quickly.\nEducation\nEarly Childhood Education\n \n2000\n \nSan Jacinto College\n \n\u00ef\u00bc\u200b \nCity\n \n, \nState\n \n, \nUSA\nCoursework in Child NutritionChild Abuse Awareness trainingCoursework in Emergency PreparednessCoursework in Behavior\nManagementEmphasis in Child Development\nHigh School Diploma\n \n, \nGeneral\n \n1991\n \nBeaumont High School\n \n\u00ef\u00bc\u200b \nCity\n \n, \nState\n \n, \nUSA\nEmphasis in Child Development\nExperience\nMaster Teacher\n \nSep 2010\n \nto \nApr 2013\n \nCompany Name\n \n\u00ef\u00bc\u200b \nCity\n \n, \nState\nConducted small group and individual classroom activities based on differentiated learning needs.Encouraged students to be understanding of and\nhelpful to others.Observed students to supply teachers with feedback regarding potential learning blocks and opportunities for support.Physically\nand verbally interacted with students throughout the day to keep them engaged.Supported students in developing strategies for individual needs\nand classroom group dynamics.Organized field trips to local parks, fire stations and zoos.Helped prepare daily lesson plans for activities and\nlessons.Implemented emergent curriculum to encourage student participation.Supplied one-on-one attention to each student, while maintaining\noverall focus on the entire group.Wrote daily and weekly lesson plans.Administered minor first aid to injured students.Applied the positive\nreinforcement method to redirect negative behaviors.Promoted language development skills through reading and storytelling. implemented family\nstyle meals. conducting parent/teacher conferences. and kept personal profiles of each child.\nTeachers Associate \nAug 2004\n \nto \nNov 2009\n \nCompany Name\n \n\u00ef\u00bc\u200b \nCity\n \n, \nState\nPromoted language development skills through reading and storytelling.Applied the positive reinforcement method to redirect negative\nbehaviors.Conducted small group and individual classroom activities based on differentiated learning needs.Assisted 5-6 children per station during\nsmall group learning periods. Organized field trips to Encouraged students to be understanding of and helpful to others.Observed students to\nsupply teachers with feedback regarding potential learning blocks and opportunities for support.Physically and verbally interacted with students\nthroughout the day to keep them engaged.Helped prepare daily lesson plans for activities and lessons.Implemented emergent curriculum Supplied\none-on-one attention to each student, while maintaining overall focus on the entire group.Physically and verbally interacted with students throughout\nthe day to keep them engaged.Communicated effectively with educators from various grade levels.Wrote daily and weekly lesson\nplans.Administered minor first aid to injured students.to encourage student participation.Organized field trips to local parks, fire stations and\nzoos.Maintained daily records of children's individual activities, behaviors, meals and naps. Established a safe play environment for the\nchildren.Distributed quarterly educational assessments, similar to report cards, to each parent.Developed professional relationships with parents,\nteachers, directors and therapists.Observed children for signs of illness, injury, emotional disturbance, learning disorders and speech\nproblems.Maintained daily records of children's individual activities, behaviors, meals and naps.\nTeacher aide\n \nAug 1999\n \nto \nMar 2001\n \nCompany Name\n \n\u00ef\u00bc\u200b \nCity\n \n, \nState\nPromoted language development skills through reading and storytelling.Applied the positive reinforcement method to redirect negative\nbehaviors.Conducted small group and individual classroom activities based on differentiated learning needs. Organized field trips to local parks, fire\nstations and zoos. Assisted 5-6 children per station during small group learning periods.Encouraged students to be understanding of and helpful to\nothers.Observed students to supply teachers with feedback regarding potential learning blocks and opportunities for support.Physically and\nverbally interacted with students throughout the day to keep them engaged.Supported students in developing strategies for individual needs and\nclassroom group dynamics.Helped prepare daily lesson plans for activities and lessons. Implemented emergent curriculum to encourage student\nparticipation. Supplied one-on-one attention to each student, while maintaining overall focus on the entire group.Communicated effectively with\neducators from various grade levels.Wrote daily and weekly lesson plans.Administered minor first aid to injured students.Maintained daily records\nof children's individual activities, behaviors, meals and naps.Established a safe play environment for the children.Created and implemented\ndeve",
  "enriched_profile": {
    "fullName": "MASTER TEACHER",
    "email": "",
    "phone": "",
    "location": "",
    "linkedin": "",
    "github": "",
    "portfolio": "",
    "summary": "Talented early education professional with diverse experience in planning and implementing various activities for promoting physical, social, emotional and intellectual growth of children.",
    "education": [
      {
        "school": "San Jacinto College",
        "degree": "",
        "field": "Early Childhood Education",
        "startDate": "2000",
        "endDate": "",
        "gpa": ""
      },
      {
        "school": "Beaumont High School",
        "degree": "High School Diploma",
        "field": "",
        "startDate": "1991",
        "endDate": "",
        "gpa": ""
      }
    ],
    "experience": [
      {
        "company": "Company Name",
        "position": "Master Teacher",
        "startDate": "Sep 2010",
        "endDate": "Apr 2013",
        "description": "Conducted small group and individual classroom activities based on differentiated learning needs. Encouraged students to be understanding of and helpful to others. Observed students to supply teachers with feedback regarding potential learning blocks and opportunities for support. Physically and verbally interacted with students throughout the day to keep them engaged. Supported students in developing strategies for individual needs and classroom group dynamics. Organized field trips to local parks, fire stations and zoos. Helped prepare daily lesson plans for activities and lessons. Implemented emergent curriculum to encourage student participation. Supplied one-on-one attention to each student, while maintaining overall focus on the entire group. Wrote daily and weekly lesson plans. Administered minor first aid to injured students. Applied the positive reinforcement method to redirect negative behaviors. Promoted language development skills through reading and storytelling. Implemented family style meals. Conducted parent/teacher conferences and kept personal profiles of each child."
      },
      {
        "company": "Company Name",
        "position": "Teachers Associate",
        "startDate": "Aug 2004",
        "endDate": "Nov 2009",
        "description": "Promoted language development skills through reading and storytelling. Applied the positive reinforcement method to redirect negative behaviors. Conducted small group and individual classroom activities based on differentiated learning needs. Assisted 5-6 children per station during small group learning periods. Organized field trips to local parks, fire stations and zoos. Encouraged students to be understanding of and helpful to others. Observed students to supply teachers with feedback regarding potential learning blocks and opportunities for support. Physically and verbally interacted with students throughout the day to keep them engaged. Helped prepare daily lesson plans for activities and lessons. Implemented emergent curriculum. Supplied one-on-one attention to each student, while maintaining overall focus on the entire group. Physically and verbally interacted with students throughout the day to keep them engaged. Communicated effectively with educators from various grade levels. Wrote daily and weekly lesson plans. Administered minor first aid to injured students. Maintained daily records of children's individual activities, behaviors, meals and naps. Established a safe play environment for the children. Developed professional relationships with parents, teachers, directors and therapists. Observed children for signs of illness, injury, emotional disturbance, learning disorders and speech problems. Maintained daily records of children's individual activities, behaviors, meals and naps."
      },
      {
        "company": "Company Name",
        "position": "Teacher aide",
        "startDate": "Aug 1999",
        "endDate": "Mar 2001",
        "description": "Promoted language development skills through reading and storytelling. Applied the positive reinforcement method to redirect negative behaviors. Conducted small group and individual classroom activities based on differentiated learning needs. Organized field trips to local parks, fire stations and zoos. Assisted 5-6 children per station during small group learning periods. Encouraged students to be understanding of and helpful to others. Observed students to supply teachers with feedback regarding potential learning blocks and opportunities for support. Physically and verbally interacted with students throughout the day to keep them engaged. Supported students in developing strategies for individual needs and classroom group dynamics. Helped prepare daily lesson plans for activities and lessons. Implemented emergent curriculum to encourage student participation. Supplied one-on-one attention to each student, while maintaining overall focus on the entire group. Communicated effectively with educators from various grade levels. Wrote daily and weekly lesson plans. Administered minor first aid to injured students. Maintained daily records of children's individual activities, behaviors, meals and naps. Established a safe play environment for the children. Created and implemented developmentally-appropriate curriculum that addressed all learning styles. Distributed quarterly educational assessments, similar to report cards, to each parent. Maintained a child-friendly environment with access to outdoor activities. Completed all required documentation for the National Head Start program."
      }
    ],
    "projects": [],
    "skills": [
      "planning activities",
      "implementing activities",
      "classroom management",
      "student support",
      "first aid",
      "reading",
      "storytelling",
      "communication",
      "parent/teacher conferences"
    ],
    "licenses": []
  }
}