{
  "resume_id": "R0074",
  "content": "ACCOUNT MANAGER\nHighlights\nExcellent verbal and written communication skills\nAbility to successfully complete multiple tasks concurrently\nSuperior organization skills\nExemplary interpersonal skills\nPunctual and reliable\nExceptional Computer Proficiency\nMicrosoft Office (Word, Access, PowerPoint, Excel)\nInternet Research\nSocial Media\nCisionPoint\nEVENTS: \nPROGRAMS:\n2012 Academy Award Gifting Suite\nExperience\nAccount Manager\n \nFebruary 2013\n \nto \nCurrent\n \nCompany Name\n \n\u00ef\u00bc\u200b \nCity\n \n, \nState\nEnter advertising insertion orders into online systems (Salesforce & Fattail) Create monthly advertiser reports - reporting advertisement\nmetrics Schedule online advertisements and Newsletters throughout the year Manage forecast and budget reports Travel to Tradeshows\nand represent the brand Assist with monthly billing Work on advertising proposals and competitive reports Manage distribution and\ncirculation of Print Pull online advertisement data from database (IMS) Create Presentations, Event invites & Product Decks.\nMedia Coordinator\n \nJune 2012\n \nto \nJanuary 2013\n \nCompany Name\n \n\u00ef\u00bc\u200b \nCity\n \n, \nState\nCoordinate, review, and edit various portions of 50+ domestic and international medical trade digital publications, including e-newsletters,\nproduct showcases, supplier bulletins, trade-show advisories, etc.\nManage ad materials for newsletters with advertisers, including requesting ad materials from advertisers and ensuring deadlines are met\nconsidering review, edit and deployment schedules Coordinate all advertisements including text, copy and digital medial for all e-newsletters\nto ready for production/publication Process and log ad materials into internal ad tracking and production computer program for newsletter\nassembly Review ad materials and test newsletters to ensure they are functional before deployment Assemble monthly ad close reports for\neach newsletter at the end of the month via excel to facilitate production of newsletter Provide diverse customer service and assistance as\ncompany liaison with advertisers Check and edit ad materials against ad specifications for accurate size, copy, image resolution and\nhyperlinks.\nSupervising Production Coordinator\n \nJuly 2011\n \nto \nJune 2012\n \nCompany Name\n \n\u00ef\u00bc\u200b \nCity\n \n, \nState\nResponsible for creative development and execution of product placement in film & television Read and develop script breakdowns for\nclient product placement opportunities Accountable for organization and documentation of client placement activity through update reports\nLead in developing and presenting monthly product placement presentations Digitally create \"Set Still\" reports, client brochures, and event\ninvitations Key liaison between clientele and studio; provide complete script to product analysis and placement Manage delivery and\nconfirmation of effective product placements to the appropriate studios (including Warner Bros., Paramount, Universal, CBS-Radford, etc.)\nAssist in planning and execution of delivered product support for high-profile celebrity events; develop celebrity relationship to product\ncreatively and logistically.\nProduction Intern\n \nFebruary 2011\n \nto \nJune 2011\n \nCompany Name\n \n\u00ef\u00bc\u200b \nCity\n \n, \nState\nPerform diverse administrative and organizational tasks Organize the production and distribution of scripts Conduct online research Type up\ncamera scripts and shot cards Support staff on projects for development and/or distribution.\nPublic Relations Intern\n \nFebruary 2010\n \nto \nJune 2010\n \nCompany Name\n \n\u00ef\u00bc\u200b \nCity\n \n, \nState\nResponsible for social networking (Twitter) Distribute product pitches to press (newspapers, magazines, bloggers) Research\nenvironmentally friendly (\"green\") beauty companies Obtain, update and organize client contact information Compile and review expense\nreports for accuracy and completeness Compile and distribute client press clips Organize and distribute product samples and press releases\nto media outlets.\nMarketing Intern\n \nSeptember 2009\n \nto \nJanuary 2010\n \nCompany Name\n \n\u00ef\u00bc\u200b \nCity\n \n, \nState\nDiverse marketing assistance for fast growing internet radio station with 11 premium radio stations Responsible for social networking\n(Twitter, Facebook, and blogs) updates for all 11 stations Upload, mix, qualification tags, album art, etc.\nfor online music library Record commercial spots and promos broadcasted during music breaks Help organize and create play list for\nvarious online radio stations Develop pitch ideas for potential sponsors.\nAdmissions Assistant\n \nSeptember 2008\n \nto \nJune 2010\n \nCompany Name\n \n\u00ef\u00bc\u200b \nCity\n \n, \nState\nAssist students, faculty and university administration with various admission policies, procedures and activities.\nAccountable for organization and administration of student applications.\nResponsible for scanning and indexing documents into database.\nEducation\nBachelor of Arts\n \n: \nPublic Relations and Journalism\n \nSeton Hall University\n \n\u00ef\u00bc\u200b \nCity\n \n, \nState\n \nGPA: \nCum Laude\n \nPublic Relations and Journalism Cum\nLaude\nSkills\nadministrat",
  "enriched_profile": {
    "fullName": "John Doe",
    "email": "",
    "phone": "",
    "location": "City, State",
    "linkedin": "",
    "github": "",
    "portfolio": "",
    "summary": "Highly skilled professional with excellent verbal and written communication skills, superior organization skills, and exemplary interpersonal skills. Proficient in Microsoft Office, Internet Research, and Social Media. Experienced in advertising, marketing, public relations, and account management.",
    "education": [
      {
        "school": "Seton Hall University",
        "degree": "Bachelor of Arts",
        "field": "Public Relations and Journalism",
        "startDate": "2006",
        "endDate": "2010",
        "gpa": "Cum Laude"
      }
    ],
    "experience": [
      {
        "company": "Company Name",
        "position": "Account Manager",
        "startDate": "February 2013",
        "endDate": "Present",
        "description": "Enter advertising insertion orders into online systems (Salesforce & Fattail) Create monthly advertiser reports - reporting advertisement metrics Schedule online advertisements and Newsletters throughout the year Manage forecast and budget reports Travel to Tradeshows and represent the brand Assist with monthly billing Work on advertising proposals and competitive reports"
      },
      {
        "company": "Company Name",
        "position": "Media Coordinator",
        "startDate": "June 2012",
        "endDate": "January 2013",
        "description": "Coordinate, review, and edit various portions of 50+ domestic and international medical trade digital publications, including e-newsletters, product showcases, supplier bulletins, trade-show advisories, etc. Manage ad materials for newsletters with advertisers, including requesting ad materials from advertisers and ensuring deadlines are met Coordinate all advertisements including text, copy and digital medial for all e-newsletters to ready for production/publication Process and log ad materials into internal ad tracking and production computer program for newsletter assembly Review ad materials and test newsletters to ensure they are functional before deployment Assemble monthly ad close reports for each newsletter at the end of the month via excel to facilitate production of newsletter Provide diverse customer service and assistance as company liaison with advertisers Check and edit ad materials against ad specifications for accurate size, copy, image resolution and hyperlinks."
      },
      {
        "company": "Company Name",
        "position": "Supervising Production Coordinator",
        "startDate": "July 2011",
        "endDate": "June 2012",
        "description": "Responsible for creative development and execution of product placement in film & television Read and develop script breakdowns for client product placement opportunities Accountable for organization and documentation of client placement activity through update reports Lead in developing and presenting monthly product placement presentations Digitally create 'Set Still' reports, client brochures, and event invitations Key liaison between clientele and studio; provide complete script to product analysis and placement Manage delivery and confirmation of effective product placements to the appropriate studios (including Warner Bros., Paramount, Universal, CBS-Radford, etc.) Assist in planning and execution of delivered product support for high-profile celebrity events; develop celebrity relationship to product creatively and logistically."
      },
      {
        "company": "Company Name",
        "position": "Production Intern",
        "startDate": "February 2011",
        "endDate": "June 2011",
        "description": "Perform diverse administrative and organizational tasks Organize the production and distribution of scripts Conduct online research Type up camera scripts and shot cards Support staff on projects for development and/or distribution."
      },
      {
        "company": "Company Name",
        "position": "Public Relations Intern",
        "startDate": "February 2010",
        "endDate": "June 2010",
        "description": "Responsible for social networking (Twitter) Distribute product pitches to press (newspapers, magazines, bloggers) Research environmentally friendly ('green') beauty companies Obtain, update and organize client contact information Compile and review expense reports for accuracy and completeness Compile and distribute client press clips Organize and distribute product samples and press releases to media outlets."
      },
      {
        "company": "Company Name",
        "position": "Marketing Intern",
        "startDate": "September 2009",
        "endDate": "January 2010",
        "description": "Diverse marketing assistance for fast growing internet radio station with 11 premium radio stations Responsible for social networking (Twitter, Facebook, and blogs) updates for all 11 stations Upload, mix, qualification tags, album art, etc. for online music library Record commercial spots and promos broadcasted during music breaks Help organize and create play list for various online radio stations Develop pitch ideas for potential sponsors."
      }
    ],
    "projects": [
      {
        "name": "",
        "techStack": "",
        "description": "",
        "link": ""
      }
    ],
    "skills": [
      "administrative",
      "Adobe Photoshop",
      "Premiere",
      "ad",
      "advertisements",
      "advertising",
      "product analysis",
      "art",
      "assembly",
      "billing",
      "brochures",
      "budget",
      "interpersonal skills",
      "competitive",
      "clientele",
      "client",
      "customer service",
      "database",
      "delivery",
      "creative development",
      "documentation",
      "edit",
      "fast",
      "film",
      "functional",
      "image",
      "IMS",
      "indexing",
      "marketing",
      "materials",
      "Access",
      "Excel",
      "Microsoft Office",
      "PowerPoint",
      "Word",
      "networking",
      "Newsletters",
      "newsletter",
      "newspapers",
      "Internet Research",
      "online research",
      "Oracle",
      "organizational",
      "organization skills",
      "camera",
      "policies",
      "presenting",
      "Presentations",
      "press",
      "press releases",
      "proposals",
      "publications",
      "publication",
      "radio",
      "Read",
      "reporting",
      "Research",
      "scanning",
      "scripts",
      "script",
      "television",
      "Type",
      "video",
      "written communication skills"
    ],
    "licenses": [
      {
        "title": "",
        "description": "",
        "issueDate": "",
        "expiryDate": ""
      }
    ]
  }
}