{
  "resume_id": "R0078",
  "content": "VICE PRESIDENT\nSummary\nSeeking a Program/Project Management position to utilize and expand my talents, knowledge and experience.\nExperience\nVice President\n \n01/2011\n \nto \nCurrent\n \nCompany Name\n \nCity\n \n, \nState\nManage cross functional and cross business unit projects to reduce expenses and best utilitize company resources Site Strategies\nDivestitures Create repeatable reporting processes of data to support current and future projects Designed project plan templates for future\nproject managers to board new consumer customers in 120 days or 90 days or less depending on the size of the prospective customer.\nCreated a document repository for future project managers Create and maintain strategic reports for senior management.\nRisk Management Analyst, Vice President\n \n01/2007\n \nto \n01/2011\n \nCompany Name\n \nCity\n \n, \nState\nManaged cross functional and cross business unit projects.\nIdentify Consumer loans in the Commercial Bank; work with the business to ensure coding is correct and taking any necessary steps to have\nthese loans exit.\nDevelop credit file checklists, product specific coding matrices, Green Light Memo and other tools to streamline and assist the business in\nmeeting Risk requirements.\nParticipated in writing several chapters for the Commercial Banking - Decentralized Policies and Procedures (Annual Reviews, ACH\nFacilities, GFCIDs, GFPIDs, CAGIDs, Continuity of Business and PSE Guidelines).\nDeveloped an Annual Review process for CBTX and worked with the business to bring all loans into compliance.\nDeveloped training on GFCID, GFPIDs and CAGIDs for business and worked closely with RMs and RSOs to ensure all classifiably\nmanaged loans had proper Global Risk Reporting identifications.\nManaged derivative facility process for CBTX and then Decentralized Central Region including documentation, system input and reporting.\nRe-engineered the derivative process for all regions in the US Local Commercial Bank.\nUpdated the coding and programming for the Facility Data Input Template for CRMS.\nManaged data quality initiatives for US-Citi Commercial Bank (CCB) systems.\nRe-engineered the Credit Authority Delegation process for CBTX and later for all regions in the US Local Commercial Bank.\nMaintain Credit Authority Delegation database and reporting and documentation for US-LCB.\nPresently the COB Coordinator for Risk Organizations in Texas and California.\nCreate various monthly Risk reports for management.\nProject Manager, Vice President\n \n01/2003\n \nto \n01/2007\n \nCompany Name\n \nCity\n \n, \nState\nManaged large scale projects (over 40 hours of effort and budgets greater than $200K).\nFacilitated requirements gathering with business partners and documentation.\nCreated Project documentation following (Software Development Life Cycle) SDLC guidelines.\nLiaison between business partners and technology teams.\nReported status updates to senior management for both technology and commercial businesses.\nAnalyzed and resolved target problems with effective solutions.\nComplied with project policy and procedures and use of Mystic system.\nWrote compliance initiatives for corporate security policies.\nProvided application support for Saratoga, TCL, PCFS2000, Stucky, Davox and NICE.\nDesigned and supported reports in Crystal Reports.\nBusiness System Analyst, Associate Vice President\n \n01/2000\n \nto \n01/2003\n \nCompany Name\n \nCity\n \n, \nState\nResearched technology business solutions to increase efficiency and revenues.\nLiaison between business partners and technology teams for commercial business lending, small business finance, public finance and\nmanufactured home finance customers.\nReported and communicated status with senior management.\nManaged a conversion project from DOS based TCL to Windows TCL for commercial lending customer.\nCreated and/or modified numerous Crystal Reports for commercial lending customer improving efficiency.\nProvided support and maintenance for Saratoga, TCL, PCFS 2000, T Soft, Laser Pro Lending, and Micro Soft desktop programs.\nManaged and organized moves for business partners.\nAnalyzed and resolved target problems with effective solutions.\nEducation\nBCIS degree\n \nNorthlake College\n \nCity\n \n, \nState\n \nGPA: \nGPA: 3.0\n \nGPA: 3.0\nBCIS degree\n \nNorth Central Texas College\n \nCity\n \n, \nState\n \nGPA: \nGPA: 3.35\n \nGPA: 3.35\nInterests\nChurch activities, Baseball and Football spectator, Gardening, Community Leader. Volunteer Organizations 1998 - 2001 \nBoard Member and\nCommissioner for Lewisville Baseball \nAssociation 2004 - Present \nCASA of Denton County - advisory board member 2009 - Present \nLewisville\nTask Force - founding board member 2010 - Present \nLewisville Independent School District Board of Trustees 2015 - Present \nDenton County\nAppraisal District Board\nAdditional Information\nInterests Church activities, Baseball and Football spectator, Gardening, Community Leader. Volunteer Organizations 1998 - 2001 \nBoard\nInterests Church activities, Baseball and Football spectator, Gardening, Community Leader. Volunteer Organizati",
  "enriched_profile": {
    "fullName": "Jane Doe",
    "email": "",
    "phone": "",
    "location": "City, State",
    "linkedin": "",
    "github": "",
    "portfolio": "",
    "summary": "Seeking a Program/Project Management position to utilize and expand my talents, knowledge and experience.",
    "education": [
      {
        "school": "Northlake College",
        "degree": "BCIS",
        "field": "",
        "startDate": "",
        "endDate": "",
        "gpa": "3.0"
      },
      {
        "school": "North Central Texas College",
        "degree": "BCIS",
        "field": "",
        "startDate": "",
        "endDate": "",
        "gpa": "3.35"
      }
    ],
    "experience": [
      {
        "company": "Company Name",
        "position": "Vice President",
        "startDate": "01/2011",
        "endDate": "Present",
        "description": "Manage cross functional and cross business unit projects to reduce expenses and best utilize company resources. Site Strategies, Divestitures, Create repeatable reporting processes of data to support current and future projects. Designed project plan templates for future project managers to board new consumer customers in 120 days or 90 days or less depending on the size of the prospective customer. Created a document repository for future project managers. Create and maintain strategic reports for senior management. Risk Management."
      },
      {
        "company": "Company Name",
        "position": "Risk Management Analyst, Vice President",
        "startDate": "01/2007",
        "endDate": "01/2011",
        "description": "Managed cross functional and cross business unit projects. Identify Consumer loans in the Commercial Bank; work with the business to ensure coding is correct and taking any necessary steps to have these loans exit. Develop credit file checklists, product specific coding matrices, Green Light Memo and other tools to streamline and assist the business in meeting Risk requirements. Participated in writing several chapters for the Commercial Banking - Decentralized Policies and Procedures (Annual Reviews, ACH Facilities, GFCIDs, GFPIDs, CAGIDs, Continuity of Business and PSE Guidelines). Developed an Annual Review process for CBTX and worked with the business to bring all loans into compliance. Developed training on GFCID, GFPIDs and CAGIDs for business and worked closely with RMs and RSOs to ensure all classifiably managed loans had proper Global Risk Reporting identifications. Managed derivative facility process for CBTX and then Decentralized Central Region including documentation, system input and reporting. Re-engineered the derivative process for all regions in the US Local Commercial Bank. Updated the coding and programming for the Facility Data Input Template for CRMS. Managed data quality initiatives for US-Citi Commercial Bank (CCB) systems. Re-engineered the Credit Authority Delegation process for CBTX and later for all regions in the US Local Commercial Bank. Maintain Credit Authority Delegation database and reporting and documentation for US-LCB. Presently the COB Coordinator for Risk Organizations in Texas and California. Create various monthly Risk reports for management."
      },
      {
        "company": "Company Name",
        "position": "Project Manager, Vice President",
        "startDate": "01/2003",
        "endDate": "01/2007",
        "description": "Managed large scale projects (over 40 hours of effort and budgets greater than $200K). Facilitated requirements gathering with business partners and documentation. Created Project documentation following (Software Development Life Cycle) SDLC guidelines. Liaison between business partners and technology teams. Reported status updates to senior management for both technology and commercial businesses. Analyzed and resolved target problems with effective solutions. Complied with project policy and procedures and use of Mystic system. Wrote compliance initiatives for corporate security policies. Provided application support for Saratoga, TCL, PCFS2000, Stucky, Davox and NICE. Designed and supported reports in Crystal Reports."
      },
      {
        "company": "Company Name",
        "position": "Business System Analyst, Associate Vice President",
        "startDate": "01/2000",
        "endDate": "01/2003",
        "description": "Researched technology business solutions to increase efficiency and revenues. Liaison between business partners and technology teams for commercial business lending, small business finance, public finance and manufactured home finance customers. Reported and communicated status with senior management. Managed a conversion project from DOS based TCL to Windows TCL for commercial lending customer. Created and/or modified numerous Crystal Reports for commercial lending customer improving efficiency. Provided support and maintenance for Saratoga, TCL, PCFS 2000, T Soft, Laser Pro Lending, and Micro Soft desktop programs. Managed and organized moves for business partners. Analyzed and resolved target problems with effective solutions."
      }
    ],
    "projects": [],
    "skills": [
      "streamline",
      "Banking",
      "budgets",
      "business solutions",
      "commercial lending",
      "conversion",
      "Credit",
      "Crystal Reports",
      "database",
      "documentation",
      "DOS",
      "senior management",
      "finance",
      "functional",
      "Laser",
      "Windows",
      "2000",
      "NICE",
      "Policies",
      "processes",
      "coding",
      "programming",
      "quality",
      "reporting",
      "requirements gathering",
      "RMs",
      "SDLC",
      "Software Development",
      "strategic",
      "TCL"
    ],
    "licenses": []
  }
}