{
  "resume_id": "R0076",
  "content": "LEAD COOK (COOK III)\nSummary\nCharles Hundley has well over nine years of overall cooking and kitchen experience. Four years of lead cook experience. Three years as a\ncertified trainer. He has gained various amounts of knowledge in the culinary industry and has taken his career to many different levels throughout\nhis cooking career, though he only has minimal school training Charles has learned from various top of the line chefs including the top three chefs of\nThe Norwegian Cruise Line's Pride Of America Executive Chef Frank D. Chef David Lilllis, and Chef Alan) These great chefs have taught Charles\nvarious skills in the kitchen including learning of the mother sauces, knife skills, and even new kitchen terminology. Charles Has also worked with\nIron Chef Michael Symon on a couple different occasions and has learned various techniques with smoking meats, using herbs and spices, as well\nas manage cooking time and work different items all at once. WIth an Associates degree in Business Management and a strong understanding of\nbusiness concepts, Charles can combine the knowledge of business management and culinary to become a very outstanding chef, and has done so\nthus far in his career in the culinary field. Able to deliver quality dishes in a timely matter. Superior culinary art skills and techniques. Willingness to\nlearn while retaining a positive attitude, and ability to understand guests want and needs. Charles has the drive, passion, and heart to be a great\nchef. Core Qualifications Knowledge of Mother Sauces, Produce orders, Knife Skills, Menu organization, Kitchen Management skills, Employee\nmanagement, Scheduling management, very fast learner. Learned new skills and knowledge with each company I worked for, and learned how to\nbetter serve our guests wants and needs therefore I would base most of my menus off that.\nExperience\nLead Cook (Cook III)\n \n06/2012\n \nto \nCurrent\n \nCompany Name\n \nCity\n \n, \nState\nPrep menu for the day service.\nHelp all our cooks in my area with dinner setup.\nDelegate all our breaks throughout the shift.\nAssist our Sous Chefs and Executive Chef with running dinner service.\nMaintain cleanliness throughout each shift.\nPositive interactions with all guests throughout service Started out as a prep cook and moved to Cook Lead/Cook III within six months.\nCook Lead\n \n11/2009\n \nto \n05/2012\n \nCompany Name\n \nCity\n \n, \nState\nPrep our menu for each shift.\nMake sure we cook all the food for each station to operate in time for service.\nManage our assigned station making sure we are stocked with the proper items throughout each shift Work with the Sous Chefs, and\nExecutive Sous chefs, and cooks to run shifts smoothly.\nAbide by the USPH Standards Galley Steward (305) 436-400 (Ronald Strode.\nAssistant Cook\n \n09/2008\n \nto \n11/2009\n \nCompany Name\n \nCity\n \n, \nState\nMake sure our assigned kitchen has the proper cook-ware each shift Responsible for the cleanliness of our assigned station as well as\nkitchen we are working at Provide our cooks and chefs with clean and sanitized equipment throughout each shift Responsible for knowing\nwhat chemicals we are working with and all safety procedures that accompany them.\nAbide by the USPH Standards Promoted after my second contract with the cruise ship.\nLead Cook\n \n04/2007\n \nto \n09/2008\n \nCompany Name\n \nCity\n \n, \nState\nPut in product orders for the Restaurant.\nSet the kitchen schedules.\nMonitored our cooks while they prepped for the day.\nHired new cooks.\nConducted monthly restaurant inspections.\nWorked as the window man on busy nights (Call out order times, and completed plates with garnishes, as well as double checked recipes\nbefore servers took them to our guest) Maintained menu items and the recipes.\nLead Cook/Kitchen Trainer Kitchen Manager\n \n07/2006\n \nto \n09/2008\n \nCompany Name\n \nCity\n \n, \nState\nCook and Prepare meals for our guest.\nResponsible to train all new kitchen cooks and dishwashers.\nKeep control of the night shifts in the kitchen.\nTrain new kitchen employees at the 4 locations around Cleveland (Strongsville, Westlake, Downtown Cleveland, And Beachwood OH)\nDiscuss and review our cook assistants with our sous chef and Kitchen manager and General Manager I started out as a prep cook in the\nback learning the menu for about two months then moved up to line cook for six months before I became a Lead Cook.\nEducation\nAssociate of Arts\n \n: \nBusiness Management\n \n2007\n \nLakeland Community College\n \nCity\n \n, \nState\n \n, \nUSA\nBusiness Management\nHigh School Diploma\n \n: \nHigh school\n \n2005\n \nCharles F Brush High School\n \nCity\n \n, \nState\n \n, \nUSA\nI also Attended Beechwood High school my junior and senior years of high school as part of the Vocational program where I studied Culinary\nI also Attended Beechwood High school my junior and senior years of high school as part of the Vocational program where I studied Culinary\nArts.\nPersonal Information\nLakeland College Kirtland, OH, United States Although it is not a degree for the culinary field, I have been able to appl",
  "enriched_profile": {
    "fullName": "Charles Hundley",
    "email": "",
    "phone": "",
    "location": "City, State",
    "linkedin": "",
    "github": "",
    "portfolio": "",
    "summary": "Charles Hundley is an experienced lead cook with over nine years of overall cooking and kitchen experience. He has expertise in kitchen management, produce orders, knife skills, and menu organization. Charles has worked with top chefs and learned various culinary skills and techniques, including working with Iron Chef Michael Symon. He combines his culinary skills with an Associate's degree in Business Management to deliver quality dishes in a timely manner.",
    "education": [
      {
        "school": "Lakeland Community College",
        "degree": "Associate of Arts",
        "field": "Business Management",
        "startDate": "2007",
        "endDate": "",
        "gpa": ""
      },
      {
        "school": "Charles F Brush High School",
        "degree": "High School Diploma",
        "field": "High School",
        "startDate": "2005",
        "endDate": "",
        "gpa": ""
      }
    ],
    "experience": [
      {
        "company": "Company Name",
        "position": "Lead Cook (Cook III)",
        "startDate": "06/2012",
        "endDate": "Present",
        "description": "Prep menu for the day service, help all cooks in the area with dinner setup, delegate all breaks throughout the shift, assist Sous Chefs and Executive Chef with running dinner service, and maintain cleanliness throughout each shift."
      },
      {
        "company": "Company Name",
        "position": "Cook Lead (Cook II)",
        "startDate": "11/2009",
        "endDate": "05/2012",
        "description": "Prep menu for each shift, make sure all food for each station is cooked in time for service, manage assigned station making sure it is stocked with proper items throughout each shift, work with Sous Chefs, Executive Sous Chefs, and cooks to run shifts smoothly, and abide by the USPH Standards."
      },
      {
        "company": "Company Name",
        "position": "Assistant Cook",
        "startDate": "09/2008",
        "endDate": "11/2009",
        "description": "Make sure the assigned kitchen has proper cookware each shift, responsible for the cleanliness of the assigned station and kitchen, provide cooks and chefs with clean and sanitized equipment throughout each shift, responsible for knowing what chemicals are being used and all safety procedures, and abide by the USPH Standards."
      }
    ],
    "projects": [],
    "skills": [
      "Kitchen Management",
      "Knife Skills",
      "Mother Sauce Knowledgeable",
      "Leadership skills",
      "Employee Development",
      "Fast Pace and efficient"
    ],
    "licenses": []
  }
}