{
  "resume_id": "R0072",
  "content": "INFORMATION TECHNOLOGY SPECIALIST\nProfessional Summary\nSeeking to obtain a career in Information Assurance with a focus on Cyber Network Defense\nSeeking to obtain a career in Information Assurance with a focus on Cyber Network Defense\nSeeking to obtain a career in Information Assurance with a focus on Cyber Network Defense\nSkills\nDesktops,\nEthernet cables\nCisco routers\nVideo & Sound Cards\nCD-ROM Drives\nMultiplexors\nScanners\nMonitors\nSwitches\nTCP/IP Configuration\nInstalling, adding and deleting user accounts with Active Directory\nStrong software and application knowledge such as Avaya, Microsoft Office, and Remedy\nExperience with Information Technology Service Management (ITSM)\nDesktops,\nEthernet cables\nCisco routers\nVideo & Sound Cards\nCD-ROM Drives\nMultiplexors\nScanners\nMonitors\nSwitches\nTCP/IP Configuration\nInstalling, adding and deleting user accounts with Active\nDirectory\nStrong software and application knowledge such as Avaya,\nMicrosoft Office, and Remedy\nExperience with Information Technology Service Management\n(ITSM)\nExperience with Information Technology\u00c2 \nStrong \u00c2 software and application knowledge such as\nAvaya,Microsoft Office,and Remedy\nInstalling,adding and deleting user accounts with Active Directory\nEthernet cables\nVideo & Sound Cards\nCD-ROM Drives\nMultiplexors\nScanners\nMonitors\nSwitches\nTCP/IP Configuration\nInstalling, adding and deleting user accounts with Active\nDirectory\nStrong software and application knowledge such as Avaya,\nMicrosoft Office, and Remedy\nExperience with Information Technology Service Management\n(ITSM)\nExperience with Information Technology\u00c2 \nStrong \u00c2 software and application knowledge such as\nAvaya,Microsoft Office,and Remedy\nInstalling,adding and deleting user accounts with Active Directory\nExperience with Information Technology Service Managment\n(ITSM)\nEthernet cables\nCD-ROM Drives\nScanners\nTCP/IP Configuration\nInstalling, adding and deleting user accounts with Active\nDirectory\nStrong software and application knowledge such as Avaya,\nExperience with Information Technology\u00c2 \nStrong \u00c2 software and application knowledge such as\nAvaya,Microsoft Office,and Remedy\nInstalling,adding and deleting user accounts with Active Directory\nExperience with Information Technology Service Managment\n(ITSM)\nMicrosoft Office, and Remedy\nExperience with Information Technology Service Management\n(ITSM)\nWork History\nInformation Technology Specialist\n \n, \n02/2018\n \nto \nCurrent\n \nCompany Name\n \nDefines scope, plans and deliverables for assigned projects Coordinates and collaborates with others in analyzing collected requirements to\nensure plans and identified solutions meet customer needs and expectations Confirms and prioritizes project plans and deliverables with the\ncustomer, participates in business and technical information technology solution implementations, upgrades, enhancement and conversions\nUnderstands and uses appropriate tools to analyze, identify and resolve business and or technical problems Applies metrics to monitor\nperformance and measure key project criteria Performs maintenance and troubleshoots network connectivity, printer, and other hardware\nissues for both uses on site and those that are remote Assists users with deployment and maintenance of desktop workstations.\n06/2016\n \nto \n01/2018\n \nCompany Name\n \nDiplomatic Security Service for the Department of State Protected U.S.\ndiplomats while visiting foreign dignitaries for diplomatic missions Maintained security awareness in a federal environment Assisted in\nemployee management Interacted with VIP personnel such as members of the Senate, foreign and domestic diplomats, and the Secretary of\nState.\nInformation Technology Interpreter\n \n, \n08/2010\n \nto \n03/2016\n \nCompany Name\n \nAssisted United States military in training foreign nationals on information technology such as basic troubleshooting and basic system set up\nDiagnosed computer errors and provided technical support Backed up and restored organizational data files and systems Installed,\nconfigured and upgraded PC software and operating systems Created and updated IT support tickets per Standard Operating Procedures\nProvided customer support for email, hosted applications, desktop, system and network problems within defined Service Level\nAgreements.\nLanguages\nFluent in Dari, Dutch, and Russian",
  "enriched_profile": {
    "fullName": "Information Technology Specialist",
    "email": "",
    "phone": "",
    "location": "",
    "linkedin": "",
    "github": "",
    "portfolio": "",
    "summary": "Seeking a career in Information Assurance with a focus on Cyber Network Defense. Skilled in IT service management and various hardware and software tools.",
    "education": [],
    "experience": [
      {
        "company": "Company Name",
        "position": "Information Technology Specialist",
        "startDate": "02/2018",
        "endDate": "Present",
        "description": "Defines scope, plans and deliverables for assigned projects. Coordinates and collaborates with others in analyzing collected requirements. Confirms and prioritizes project plans and deliverables with the customer. Participates in business and technical information technology solution implementations, upgrades, enhancement and conversions. Understands and uses appropriate tools to analyze, identify and resolve business and or technical problems. Applies metrics to monitor performance and measure key project criteria. Performs maintenance and troubleshoots network connectivity, printer, and other hardware issues for both on-site and remote users. Assists users with deployment and maintenance of desktop workstations."
      },
      {
        "company": "Company Name",
        "position": "Diplomatic Security Service for the Department of State",
        "startDate": "06/2016",
        "endDate": "01/2018",
        "description": "Protected U.S. diplomats while visiting foreign dignitaries for diplomatic missions. Maintained security awareness in a federal environment. Assisted in employee management. Interacted with VIP personnel such as members of the Senate, foreign and domestic diplomats, and the Secretary of State."
      },
      {
        "company": "Company Name",
        "position": "Information Technology Interpreter",
        "startDate": "08/2010",
        "endDate": "03/2016",
        "description": "Assisted United States military in training foreign nationals on information technology such as basic troubleshooting and basic system set up. Diagnosed computer errors and provided technical support. Backed up and restored organizational data files and systems. Installed, configured and upgraded PC software and operating systems. Created and updated IT support tickets per Standard Operating Procedures. Provided customer support for email, hosted applications, desktop, system and network problems within defined Service Level Agreements."
      }
    ],
    "projects": [],
    "skills": [
      "Desktops",
      "Ethernet cables",
      "Cisco routers",
      "Video & Sound Cards",
      "CD-ROM Drives",
      "Multiplexors",
      "Scanners",
      "Monitors",
      "Switches",
      "TCP/IP Configuration",
      "Active Directory",
      "Avaya",
      "Microsoft Office",
      "Remedy",
      "Information Technology Service Management (ITSM)"
    ],
    "licenses": []
  }
}