{
  "resume_id": "R0084",
  "content": "PROCESS CONSULTANT\nProfessional Summary\nExperienced operations manager and entrepreneur who built 4.5 million dollar company without start up capital or outside investment. Supremely\norganized with ability to identify and solve challenges in growth environment, performing at peak when boundaries are in constant state of change.\nVisionary professional excels at recognition and anticipation, coupling ability to diagnose with skill to execute. Confident negotiator who\nunderstands nuances of variables, timing, and leverage in negotiation.\nStrength Finders: Analytical/Context/Command/Futuristic/Relator\nKey Skills\nNegotiations\nStrategic thinker\nTeam building\nDriven\nAdvanced problem solving skills\nOperations analysis\nProcess development and execution\nEmployee training, support, \nand development\nProject management\nProfessional Experience\nProcess Consultant\n \nJanuary 2014\n \nto \nCurrent\n \nCompany Name\n \n\u00ef\u00bc\u200b \nCity\n \n, \nState\nDevelop processes that allow company use of business metrics to provide both macro and micro analysis of company performance. Provide\nstructure from which to scale operations, identifying productive and unproductive work activity.\nDetermine then deploy management practices for small and medium sized business to operate with increased financial clarity and operational\nefficiency. \nProcess requires macro understanding of a given business's primary economic driver. \nOnce identified, modify processes to\nsimplify the execution of that driver.\nFull conversion to objective business practices, eliminating management decisions made in a vacuum. \nObjective is often met by defining strict\ndata entry process and schedule, returning data faster and more accurately, then requiring all decision making be originated from the most\ncurrent information available.\nImplement and deploy procurement processes to optimize cost savings, ensuring proper leveraging of organizational buying power.\nDirector of Operations\n \nJanuary 2012\n \nto \nJanuary 2014\n \nCompany Name\n \n\u00ef\u00bc\u200b \nCity\n \n, \nState\nConverted company culture from subjective management driven by opinion to objective management driven by data.\nStreamlined accounting system to be deployed as management tool, thereby changing organizational behavior to respond to financial goals.\nAchieved 14% savings in operational costs by applying line item approach to attacking costs, starting from highest cost to lowest. \nHigh to\nlow formula proved cost effective as buying power leverage and ROI were optimized.\nRecognized changing business climate required more nimble communications, researched available solutions, negotiated cost effective\npricing, then deployed \"cloud\" management of company data and IT processes.\nAuthored and deployed best practices for hiring of employee and sub contracted labor resources, exposing corporate strength and\nweakness points in human resource management.\nProvided general and accurate understanding of company cash flow needs in a volatile revenue environment.\nFounder, President and CEO\n \nJanuary 2002\n \nto \nJanuary 2011\n \nCompany Name\n \n\u00ef\u00bc\u200b \nCity\n \n, \nState\nFounded company which provided corporate housing services to corporate clients and relocating individuals. \nManaged sales volume growth\nfrom $52,000 in 2002 to sustained volume of 2,000,000 in 2004, with company revenues reaching $4,500,000 in fiscal 2011.\nManaged temp housing procurement for Toyota Motor Manufacturing expansion into Blue Springs, Mississippi. \nDemand for apartments far\nexceeded local supply, requiring swift and creative negotiation to inspect and procure all available apartment space in a condensed time\nperiod. \nThrough complex acquisition of both apartment and hotel supply all team members were placed on the ground on time and in line\nwith cost budget. \nProject generated $2.3 million in revenue at targeted gross margin and doubled company apartment inventory.\nExpanded and managed operations in Cincinnati, OH and Lexington, KY. \nProvided service to customers in other area markets, including\nLouisville, KY, Columbus OH, and Dayton, OH.\nRecognized that gross margins were damaged by ineffective leasing policies, and aggressively adjusted lease procurement practices to\ndecrease leasing costs without compromising sales volume or raising overhead. \nThe results were dramatically improved margins and\ncompany profitability. \nMaintained high margins by proactive management of apartment inventory, strategically matching customer demand to\navailable space.\nTwice negotiated deals to double company revenue by expanding to out of state markets.\nProvided daily operational support to out of market employees, directing activities by intelligent use of market performance data.\nSuccessfully developed co-branding relationships with vendor partners to supply Vesta customers with no cost products in exchange for\nmarket exposure.\nRecognized in Entrepreneur magazine for fast \"no excuses\" growth.\nConsistently sold apartment inventory to industry competitors due to high service standards and effective quality ",
  "enriched_profile": {
    "fullName": "John Doe",
    "email": "",
    "phone": "",
    "location": "City, State",
    "linkedin": "",
    "github": "",
    "portfolio": "",
    "summary": "Experienced operations manager and entrepreneur who built a 4.5 million dollar company without start-up capital or outside investment. Supremely organized with the ability to identify and solve challenges in a growth environment, performing at peak when boundaries are in a constant state of change. Visionary professional who excels at recognition and anticipation, coupling the ability to diagnose with the skill to execute. Confident negotiator who understands the nuances of variables, timing, and leverage in negotiation.",
    "education": [
      {
        "school": "University of Wisconsin Green Bay",
        "degree": "BA",
        "field": "",
        "startDate": "1987",
        "endDate": "",
        "gpa": "3.47"
      }
    ],
    "experience": [
      {
        "company": "Company Name",
        "position": "Process Consultant",
        "startDate": "January 2014",
        "endDate": "Present",
        "description": "Develop processes that allow company use of business metrics to provide both macro and micro analysis of company performance. Provide structure from which to scale operations, identifying productive and unproductive work activity. Determine then deploy management practices for small and medium-sized businesses to operate with increased financial clarity and operational efficiency. Implement and deploy procurement processes to optimize cost savings, ensuring proper leveraging of organizational buying power."
      },
      {
        "company": "Company Name",
        "position": "Director of Operations",
        "startDate": "January 2012",
        "endDate": "January 2014",
        "description": "Converted company culture from subjective management driven by opinion to objective management driven by data. Streamlined accounting system to be deployed as a management tool, thereby changing organizational behavior to respond to financial goals. Achieved 14% savings in operational costs by applying a line item approach to attacking costs, starting from the highest cost to the lowest. Recognized changing business climate required more nimble communications, researched available solutions, negotiated cost-effective pricing, then deployed 'cloud' management of company data and IT processes."
      },
      {
        "company": "Company Name",
        "position": "Founder, President and CEO",
        "startDate": "January 2002",
        "endDate": "January 2011",
        "description": "Founded company which provided corporate housing services to corporate clients and relocating individuals. Managed sales volume growth from $52,000 in 2002 to sustained volume of 2,000,000 in 2004, with company revenues reaching $4,500,000 in fiscal 2011. Managed temp housing procurement for Toyota Motor Manufacturing expansion into Blue Springs, Mississippi. Expanded and managed operations in Cincinnati, OH and Lexington, KY. Provided service to customers in other area markets, including Louisville, KY, Columbus OH, and Dayton, OH. Recognized that gross margins were damaged by ineffective leasing policies, and aggressively adjusted lease procurement practices to decrease leasing costs without compromising sales volume or raising overhead."
      }
    ],
    "projects": [],
    "skills": [
      "Negotiations",
      "Strategic thinker",
      "Team building",
      "Driven",
      "Advanced problem solving skills",
      "Operations analysis",
      "Process development and execution",
      "Employee training, support, and development",
      "Project management"
    ],
    "licenses": []
  }
}