{
  "resume_id": "R0082",
  "content": "RN STAFF NURSE\nProfessional Experience\nRN Staff Nurse\n \nAugust 2008\n \nto \nApril 2014\n \nCompany Name\n \n\u00ef\u00bc\u200b \nCity\n \n, \nState\nParticipate in multidisciplinary plan of care.\nFollow Best Practice Protocols, Evidence based practice as well as patient-centered and team-based care.\nIdentify barriers to successful treatment and share with team.\nMonitor,measure and report/document progress of interventions and outcomes.\nTimely and effective communication of newly implemented changes to unit based methods of practice.\nAccomplishments Management of Aggressive Behavior (MOAB) in house Certified Instructor, Patient Experience Champion, Shared\nGovernance Chair of Policy & Procedure Committee, Oncology Certification, Implementation of unit Bedside Report and hourly rounding.\nSkills Used Therapeutic touch/communication, teach back communication,assessments, IV care, telemetry care, wound care including\nwound vacs, dressing changes.\nAge-based plan of care.\nExcellent organizational skills.\nCollaborative working relationship with unit team members as well as physicians, technicians, pharmacy, housekeeping and other ancillary\nteam members.\nRN- Resident Care Manager\n \nJuly 2007\n \nto \nJuly 2008\n \nCompany Name\n \n\u00ef\u00bc\u200b \nCity\n \n, \nState\nResponsibilities Care Management of adult and senior patient population.\nKnowledge of care levels including SNF, ECF, ICF, ALF, rehab and hospice.\nAttending and participating in care conferences.\nDevelopment and distribution of expected outcomes to interdisciplinary team.\nAssignment and direction of care provided by licensed staff across 24 hour schedule.\nReconciliation of monthly MAR's.\nDisposal of out-dated/discontinued medications.\nDevelopment and monitoring of appropriate care plans, Accomplishments Created, communicated and modeled a unit Mission Statement.\nDeveloped effective teamwork model for licensed staff and caregivers.\nSkills Used Effective oral and written communication and organizational skills.\nAbility to determine and direct appropriate care.\nAbility to navigate electronic medical records and effectively utilize basic computer programs.\nProvide compassionate and effective communication to family members in times of crisis.\nRN Charge Nurse\n \nJuly 2000\n \nto \nJune 2007\n \nCompany Name\n \n\u00ef\u00bc\u200b \nCity\n \n, \nState\nAssessment of acuity, asignment of staff, Review of charts, obtaining and signing off orders.\nGuidance/monitoring and assistance to team members to balance work load throughout shift.\nAttend and participate in staff meetings and hospital wide agendas.\nIn the Geriatric Assessment Center (GAC), I performed total body assessments including hearing, vision, labs and Accomplishments\nGeriatric Resource Nurse (GRN) certification 2003-2008.\nHospital based NICHE member.\nPain Management Resource team member.\nParticipant in Evidence Based Practice implementation.\nGeriatric Assessment Center on call RN.\nNote: During my tenure at Providence Milwaukie, I worked in the ECF/ICF/SNF unit, the Med/Surg unit, Womens Health/Mother-Baby\nunit, the Geriatric Assessment Center and the Emergency Dept.\nI was a charge nurse in all except the GAC and ED.\nSkills Used Open and effective communication.\nExcellent organizational skills.\nTelemetry, IV, wound care, physical, mental and emotional assessment.\nAppropriate and effective care plans.\nMedication reconciliation and monitoring for therapeutic effectiveness.\nAdministrative Assistant\n \nApril 1990\n \nto \nApril 1996\n \nCompany Name\n \n\u00ef\u00bc\u200b \nCity\n \n, \nState\nMaintaining informational material and application packets availability.\nAssisting applicants accurately complete and provide information required form application completion.\nCompile information for reports.\nSetting up and maintaining supervised bank accounts monthly.\nReconcileing local office concentrated banking system.\nServicing delinquent accounts, Prepares tax vouchers as applicable.\nWeekly back up of computer files and secure storage of files.\nEducation and Training\nBSN\n \n: \nNursing\n \n, \n1 2007\n \nWashington State University\n \n\u00ef\u00bc\u200b \nCity\n \n, \nState\n \nNursing\nADN\n \n: \nNursing\n \n, \n1 2000\n \nClark College\n \n\u00ef\u00bc\u200b \nCity\n \n, \nState\n \nNursing\nAA\n \n: \nGeneral Studies\n \n, \n1 1987\n \nClark College\n \n\u00ef\u00bc\u200b \nCity\n \n, \nState\n \nGeneral Studies Medical Admin. Assistant in Front/back office Med. Ass't.\n1 1982\n \nWestern Business College\n \n\u00ef\u00bc\u200b \nCity\n \n, \nState\nPersonal Information\nI also worked this role in a temporary position during the 1996-1997 fiscal year while I worked on my nursing prerequisites.\nSkills\nbalance, banking, basic, charts, oral, Basic computer skills, conferences, direction, Instructor, meetings, office, organizational skills, progress,\nProtocols, tax, teamwork, Telemetry, vision, written communication\nAdditional Information\nNote: I also worked this role in a temporary position during the 1996-1997 fiscal year while I worked on my nursing prerequisites.\nFacebook LinkedIn Twitter Your resume is visible to anyone. Your contact details are hidden but employers can contact you via Indeed.\nPublic Your resume is visible to",
  "enriched_profile": {
    "fullName": "RN Staff Nurse",
    "email": "",
    "phone": "",
    "location": "",
    "linkedin": "",
    "github": "",
    "portfolio": "",
    "summary": "Experienced RN Staff Nurse with expertise in multidisciplinary plan of care, best practice protocols, and evidence-based practice. Strong therapeutic touch and communication skills, with a proven track record in wound care, telemetry care, and IV care.",
    "education": [
      {
        "school": "Washington State University",
        "degree": "BSN",
        "field": "Nursing",
        "startDate": "2004",
        "endDate": "2007",
        "gpa": ""
      },
      {
        "school": "Clark College",
        "degree": "ADN",
        "field": "Nursing",
        "startDate": "1998",
        "endDate": "2000",
        "gpa": ""
      },
      {
        "school": "Clark College",
        "degree": "AA",
        "field": "General Studies",
        "startDate": "1985",
        "endDate": "1987",
        "gpa": ""
      },
      {
        "school": "Western Business College",
        "degree": "",
        "field": "General Studies Medical Admin. Assistant in Front/back office Med. Ass't.",
        "startDate": "1981",
        "endDate": "1982",
        "gpa": ""
      }
    ],
    "experience": [
      {
        "company": "Company Name",
        "position": "RN Charge Nurse",
        "startDate": "July 2000",
        "endDate": "June 2007",
        "description": "Assessment of acuity, assignment of staff, review of charts, obtaining and signing off orders. Guidance/monitoring and assistance to team members to balance work load throughout shift. Attendance and participation in staff meetings and hospital wide agendas. Participation in Geriatric Assessment Center (GAC), Geriatric Resource Nurse (GRN) certification 2003-2008, Hospital based NICHE member, Pain Management Resource team member, and participant in Evidence Based Practice implementation. Geriatric Assessment Center on call RN."
      },
      {
        "company": "Company Name",
        "position": "RN- Resident Care Manager",
        "startDate": "July 2007",
        "endDate": "July 2008",
        "description": "Care Management of adult and senior patient population. Knowledge of care levels including SNF, ECF, ICF, ALF, rehab and hospice. Attendance and participation in care conferences. Development and distribution of expected outcomes to interdisciplinary team. Assignment and direction of care provided by licensed staff across 24 hour schedule. Reconciliation of monthly MAR's. Disposal of out-dated/discontinued medications. Development and monitoring of appropriate care plans."
      },
      {
        "company": "Company Name",
        "position": "RN Staff Nurse",
        "startDate": "August 2008",
        "endDate": "April 2014",
        "description": "Participate in multidisciplinary plan of care. Follow Best Practice Protocols, Evidence based practice as well as patient-centered and team-based care. Identify barriers to successful treatment and share with team. Monitor, measure and report/document progress of interventions and outcomes. Timely and effective communication of newly implemented changes to unit based methods of practice."
      }
    ],
    "projects": [],
    "skills": [
      "balance",
      "banking",
      "basic",
      "charts",
      "oral",
      "Basic computer skills",
      "conferences",
      "direction",
      "Instructor",
      "meetings",
      "office",
      "organizational skills",
      "progress",
      "Protocols",
      "tax",
      "teamwork",
      "Telemetry",
      "vision",
      "written communication"
    ],
    "licenses": []
  }
}