{
  "resume_id": "R0081",
  "content": "GLOBAL IT PROJECT MANAGER\nSummary\nMy background is in Information Technology and I have over 20 years experience working in the Aviation Ground Handling sector performing\nseveral IT roles. From Support to System Administration and most recently in Project Management\nSkills\nWindows , Windows Office Suites, Citrix, Active Directory, JIRA and Trello Project Management Applications, Service Now ITSM\nPersonal Information\nDate of Birth: 8th October 1973\nMarital Status: Married\nExperience\nGlobal IT Project Manager\n \n05/2013\n \nto \nCurrent\n \nCompany Name\n \nCity\n \n, \nState\n \nAir Menzies International Limited \n\u00c2  \nGlobal IT Project Manager \u00e2\u20ac\u201c\nMay 2013 to Present \n\u00c2  \nA wholesale Freight Agent providing Cargo and Express services in Europe, North America, South Africa and Oceania.\nMy role, based in Wood Dale, IL is primarily to manage the Internal system around our global network. Managing the in-house Java Development\nTeam to offer internal, back of house solutions as well as Customer facing web portals to our Freight Agent community. I also manage the Support\nNetwork across our four regions ensuring the end user is supported by local key users or from members of my UK, US and South Pac based\nteams. \n\u00c2  \nMy role is to gather business knowledge and process in order to provide requirements to my Development Team that allows them to\nwork to an agreed scope. Development would then be handed over to myself and my Support team to provide UAT before approving and\nplanning Live deployments. \n\u00c2  \nAs the senior IT representative in AMI, I also work closely with the parent company's IT Team around the globe to\nensure our business is supported 24/7. I also play a role in the expansion of our network when the business opens up new locations in our regions.\n\u00c2  \nI am also currently involved in a Data Centre transformation project where are applications are being migrated to a new Enterprise Cloud\nService with a third party supplier.\nIT Project Manager \n06/2007\n \nto \n05/2013\n \nCompany Name\n \nCity\n \n, \nState\n \nMy previous role was as an IT Project Manager with Menzies Aviation.\nFirstly working out of the Menzies Aviation Head Office at Heathrow Airport in the UK and from 2012 to May 2013, based out of the Menzies\nAviation Cargo facility at O'Hare Airport. During the six year in this role, I was responsible or heavily involved in several major projects. \nThese\nincluded Project Managing the IT Infrastructure required for our green field Station start-ups for our Joint Ventures in Hyderabad and Bangalore in\n2007 and 2008. Where I oversaw the implementation of the Network, IT Hardware acquisition and key systems at both of these new Airports up\nto the go-live in the Spring of 2008. \nFollowing on from that I was heavily involved in the expansion of the Menzies Aviation Ground Handling\nbusiness in the UK and the rest of Europe. \nOther key projects and responsibilities have included Project Managing the implementation of IT\nsystems and infrastructure for the easyJet Station start-up in Bristol in January 2009 as well as other easyJet start-ups in Tenerife, Ibiza and most\nrecently Barcelona in November 2009\nSupport Analyst and System Administrator\n \n05/2001\n \nto \n05/2007\n \nCompany Name\n \nCity\n \n, \nState\n \nPrior to taking a full-time Project Management role,\nI Project Managed the implementation of the Global Cargo System in to Prague in 2006 while also working in the IT Technical Department based\nin London Heathrow Airport. This support role also involved administrating and assisting in the installation of various Menzies' IT systems run from\nthe Global Data Centre located in the UK. \nOn a daily basis, I provided front line (on site and remote) support to all UK Cargo Terminals,\nIncluding PC support and maintenance, network administration, exchange server administration and answering user enquiries.\u00c2 \nBusiness Analyst \n05/1998\n \nto \n05/2001\n \nCompany Name\n \nCity\n \n, \nState\n \nBefore integrating in to the Menzies Aviation IT structure, I was part of the\nOgden Cargo System and Support team that looked after the three UK Cargo terminals. I also assisted in administering, with the Quality Manager,\nOgden Cargo's ISO 9002 Certified Quality System. \nI was also responsible for developing via a Business Intelligence tool called IQ Objects, all\nreports generated from the core Cargo Handling System. \n\u00c2 \nInterests\nI regularly play Golf most weekends at various courses around the south west suburbs. I am also a member of a gym and workout 2 to 3 times a\nweek. I am an avid sports fan and have a passion for English Soccer, Rugby, Collage Football and watching theCubs.\nEducation and Training\nBachelor of Science\n \n: \nMathematics\n \n1996\n \nUniversity of Glamorgan\n \nCity\n \n, \nState\n \n, \nUK\nA Levels\n \n1992\n \nCardinal Newman R.C. School\n \nCity\n \n, \nState\n \n, \nUK\nMathematics & Geography\nGSCEs\n \n1992\n \nCardinal Newman R.C. School\n \nCity\n \n, \nState\n \n, \nUK\nMathematics, Geography, Biology, English, French & Physics",
  "enriched_profile": {
    "fullName": "GLOBAL IT PROJECT MANAGER",
    "email": "",
    "phone": "",
    "location": "Wood Dale, IL",
    "linkedin": "",
    "github": "",
    "portfolio": "",
    "summary": "Over 20 years of experience in Information Technology, specializing in Aviation Ground Handling sector. Strong background in IT Support, System Administration, and Project Management.",
    "education": [
      {
        "school": "University of Glamorgan",
        "degree": "Bachelor of Science",
        "field": "Mathematics",
        "startDate": "1996",
        "endDate": "",
        "gpa": ""
      },
      {
        "school": "Cardinal Newman R.C. School",
        "degree": "A Levels",
        "field": "Mathematics & Geography",
        "startDate": "1992",
        "endDate": "",
        "gpa": ""
      },
      {
        "school": "Cardinal Newman R.C. School",
        "degree": "GSCEs",
        "field": "Mathematics, Geography, Biology, English, French & Physics",
        "startDate": "1992",
        "endDate": "",
        "gpa": ""
      }
    ],
    "experience": [
      {
        "company": "Air Menzies International Limited",
        "position": "Global IT Project Manager",
        "startDate": "May 2013",
        "endDate": "Present",
        "description": "Manage the Internal system around the global network. Oversee the in-house Java Development Team for internal, back of house solutions and Customer facing web portals. Manage the Support Network across four regions. Gather business knowledge and process to provide requirements to the Development Team. Plan Live deployments. Work closely with the parent company's IT Team around the globe. Involved in a Data Centre transformation project."
      },
      {
        "company": "Menzies Aviation",
        "position": "IT Project Manager",
        "startDate": "June 2007",
        "endDate": "May 2013",
        "description": "Project Managed the IT Infrastructure required for green field Station start-ups for Joint Ventures in Hyderabad and Bangalore. Oversaw the implementation of the Network, IT Hardware acquisition and key systems at both new Airports. Involved in the expansion of the Menzies Aviation Ground Handling business in the UK and the rest of Europe. Project Managed the implementation of IT systems and infrastructure for easyJet Station start-ups."
      },
      {
        "company": "Menzies Aviation",
        "position": "Support Analyst and System Administrator",
        "startDate": "May 2001",
        "endDate": "May 2007",
        "description": "Project Managed the implementation of the Global Cargo System in Prague in 2006. Worked in the IT Technical Department based in London Heathrow Airport. Provided front line support to all UK Cargo Terminals. Assisted in the installation of various Menzies' IT systems run from the Global Data Centre located in the UK."
      },
      {
        "company": "Ogden Cargo System and Support team",
        "position": "Business Analyst",
        "startDate": "May 1998",
        "endDate": "May 2001",
        "description": "Assisted in administering Ogden Cargo's ISO 9002 Certified Quality System. Developed reports via a Business Intelligence tool called IQ Objects."
      }
    ],
    "projects": [],
    "skills": [
      "Windows",
      "Windows Office Suites",
      "Citrix",
      "Active Directory",
      "JIRA",
      "Trello Project Management Applications",
      "Service Now ITSM"
    ],
    "licenses": []
  }
}