{
  "resume_id": "R0083",
  "content": "CONCIERGE\nProfessional Summary\nI am looking for a job where I can put my positive strengths and abilities to good use. I am an efficient and cheerful worker who relates to people\nwith compassion and understanding. I am discreet, trustworthy, and dedicated. Authorized to work in the US for any employer.\nLicenses\nCertified Nursing Assistant\nSkill Highlights\nHighly organized\nProfessional behavior and telephone manner\nComputer literate\nAble to perform without close supervision\nAble to prioritize\nAble to work under stress\nPatient care and safety\nMedical terminology\nElectronic medical records\nVital signs and patient monitoring\nPrivacy/Hippa regulations\nPatient advocacy and support\nProfessional Experience\nCompany Name\n \nCity\n \n, \nState\n \nConcierge\n \n02/2016\n \nto \nCurrent\nWelcome owners and vendors upon entrance\nAct as point of reference for those who need assistance or information and attend to their wishes and requirements\nUnderstand the owner's needs and provide them with personalized solutions by suggesting activities and facilities provided\nProvide extensive knowledge of the premises and the nearby venues and businesses to make the most suitable recommendations\nArrange events, excursions, transportation etc.\nupon request Answer the phone and make reservations, take and distribute messages, mail, and packages and redirect calls\nRespond to complaints and find the appropriate solutions\nMonitor a very extensive security system to maintain the owner's privacy and safety.\nCompany Name\n \nCity\n \n, \nState\n \nHealth Unit Coordinator / Certified Nurse Assistant\n \n02/2009\n \nto \n02/2016\nPerforming various activities to support the provision of patient care and clerical duties under the supervision and/or direction of Staff Nurse\nand assists RN/LVNs in treatment and care of patients.\nPerforming numerous personal care and clerical services to ensure patient's safety, comfort, cleanliness, and to support patient activities.\nTraining new employees\nEnsure Hippa compliance\nScheduling lab tests\nRegistering patients\nEnsure patient safety and comfort while providing transfer, or assisting with mobility, from one location to another in accordance with\nestablished procedures\nAssists with the proper nutrition and accurately records meal and nourishment intake and calorie count\nPromptly answers all patient call lights\nInitiates, and assembles and maintains patient chart/Kardex in accordance with established procedures\nUses Epic computer charting accurately and promptly transcribes physician orders\nProcesses ordered tests, medications, procedures, and appointments appropriately and coordinates appropriate transportation\nProcesses admits/transfers/discharges\nMonitors and records patient's vital signs, intake and output and other measurements in accordance with unit routines as directed\nMonitors patients and reports patients' conditions at regular intervals and promptly reports any signs or symptoms of concern to appropriate\nparty\nHelping patients with toilet and bathroom needs\nPeri and catheter care on ante partum, laboring, and postpartum women\nMaintains unit equipment in good working order and notifies the appropriate parties promptly when requires service or repairs\nPrepared patient rooms prior to their arrival.\nEnsuring a safe and healthy environment for nursing staff and patients.\nEnsuring compliance with hospital rules and regulations.\nCompany Name\n \nCity\n \n, \nState\n \nHousekeeping\n \n02/2008\n \nto \n02/2009\nEnvironmental Services Labor and Delivery\nPerformed routine cleaning and sanitizing in offices, exam rooms, procedure rooms, stairs, restrooms, elevators, and other ancillary areas.\nPerformed discharge cleaning of patient rooms\nChanged bed lines and cleaned patients rooms\nTerminal clean of labor beds and operating rooms\nCleaned equipment properly and distributed based on patient needs\nFollowed infection control\nMaintained all assigned rooms, areas, and spaces in a clean, neat, and sanitary manner using the chemicals and process required by the EVS\nDepartment.\nCompany Name\n \nCity\n \n, \nState\n \nCertified Fitness Instructor/Circuit Coach\n \n02/2002\n \nto \n02/2008\nTrained and motivated ladies in the use of the 30 minute Curves Circuit\nConducted nutrition meetings on a 1:1 basis and group setting\nCompleted monthly fitness goals for members\nGave assistance, instruction, and motivation of members on the Curves Weight Loss Program\nParticipated in new member campaigns, guest production, and sales Marketing of Curves gym and obtaining new members\nVarious Club administration activities.\nEducation and Training\nHigh School Diploma\n \n:\n \nGeneral\n \n1988\n \nBelton High School\n \n, \nCity\n \n, \nState\nSkills\nPatient-focused care, \nExcellent interpersonal skills, \nCompassionate and trustworthy caregiver, \nDetail-oriented, \nMedical terminology",
  "enriched_profile": {
    "fullName": "Connierge",
    "email": "",
    "phone": "",
    "location": "",
    "linkedin": "",
    "github": "",
    "portfolio": "",
    "summary": "Seeking a job where I can utilize my positive strengths and abilities. I am an efficient, cheerful, and compassionate worker who is trustworthy, dedicated, and authorized to work in the US. Highly organized with professional behavior and telephone manner, computer literate, able to perform tasks without close supervision, prioritize, and work under stress. Skilled in patient care and safety, medical terminology, electronic medical records, vital signs and patient monitoring, privacy/Hippa regulations, and patient advocacy and support.",
    "education": [
      {
        "school": "Belton High School",
        "degree": "High School Diploma",
        "field": "General",
        "startDate": "1988",
        "endDate": "",
        "gpa": ""
      }
    ],
    "experience": [
      {
        "company": "Company Name",
        "position": "Concierge",
        "startDate": "02/2016",
        "endDate": "Present",
        "description": "Welcome owners and vendors upon entrance, act as a point of reference, understand owner's needs, provide personalized solutions, arrange events, answer phone calls, respond to complaints, monitor security system, and maintain owner's privacy and safety."
      },
      {
        "company": "Company Name",
        "position": "Health Unit Coordinator / Certified Nurse Assistant",
        "startDate": "02/2009",
        "endDate": "02/2016",
        "description": "Perform various activities to support patient care and clerical duties under the supervision of Staff Nurse, assist RN/LVNs in treatment and care of patients, ensure patient safety and comfort, train new employees, ensure Hippa compliance, schedule lab tests, register patients, provide transfer assistance, maintain patient charts, process ordered tests, appointments, and transportation, monitor patients' vital signs, intake and output, and report any signs or symptoms of concern."
      },
      {
        "company": "Company Name",
        "position": "Housekeeping",
        "startDate": "02/2008",
        "endDate": "02/2009",
        "description": "Perform routine cleaning and sanitizing in offices, exam rooms, procedure rooms, stairs, restrooms, elevators, and other ancillary areas, change bed lines, clean patient rooms, perform discharge cleaning, terminal clean of labor beds and operating rooms, clean equipment, maintain assigned rooms, areas, and spaces in a clean, neat, and sanitary manner."
      },
      {
        "company": "Company Name",
        "position": "Certified Fitness Instructor/Circuit Coach",
        "startDate": "02/2002",
        "endDate": "02/2008",
        "description": "Train and motivate ladies in the use of the 30 minute Curves Circuit, conduct nutrition meetings, complete monthly fitness goals for members, give assistance, instruction, and motivation of members on the Curves Weight Loss Program, participate in new member campaigns, guest production, and sales Marketing of Curves gym and obtaining new members, perform various club administration activities."
      }
    ],
    "projects": [],
    "skills": [
      "Patient-focused care",
      "Excellent interpersonal skills",
      "Compassionate and trustworthy caregiver",
      "Detail-oriented",
      "Medical terminology"
    ],
    "licenses": [
      {
        "title": "Certified Nursing Assistant",
        "description": "",
        "issueDate": "",
        "expiryDate": ""
      }
    ]
  }
}