{
  "resume_id": "R0089",
  "content": "BUSINESS DEVELOPMENT MANAGER\nExperience\nJanuary 2014\nto\nCurrent\nCompany Name\n \nCity\n \n, \nState\n \nBusiness Development Manager\nPlatform for video content and targeted native video ads Report to COO and CRO with new business initiatives and business strategies for\npublishers and advertisers.\nLaunched Cinema6's first campaigns, with a premium spirits brand and athletic brand resulting in 100% profit Negotiated contracts with 3rd\nparty vendors (Jun Group, Veeseo, Adblade, Bidtellect).\nAdding clients to partner with by phone, email and meetings resulting in the creation of a pipeline for Cinema6 Compose weekly reports on\nnew business, campaigns and other daily tasks.\nJanuary 2013\nto\nJanuary 2014\nCompany Name\n \nCity\n \n, \nState\n \nSales and Service Desk Specialist\nPrivate Wealth Management - Alternative Investments Supported and managed relationships with Financial Advisors in the Pacific\nNorthwest and Mid-America regions, as well as throughout the country and internationally.\nEducated Financial Advisors on specific Alternative Investment products on the Merrill Lynch platform, including strategies, fee structure,\nand purchase and redemption schedules.\nIdentified as the Sales and Service Desk Specialist with the highest and most consistent call record, leading the team in services provided to\nFinancial Advisors that called on the Alternative Investments Service Desk.\nDeveloped and helped launch the Best Practitioner program for Financial Advisors geared towards generating new business on the\nAlternative Investment platform.\nAwarded 2013 Alternative Investments Most Net Sales to Budget for the Pacific Northwest Region.\nJanuary 2010\nto\nJanuary 2013\nCompany Name\n \nCity\n \n, \nState\n \nNew Business Director\nProvided financial solutions for client that reduced cash flow expenditures and realized losses on assets by utilizing those underperforming\nassets to offset media expenditures.\nResponsible for introducing ORION Trading to 75-150 accounts with annual media budgets in excess of $4mm on advertising including, but\nnot limited to television, radio, digital print, and OOH, nationally and locally.\nSourced and maintained relationships with corporate executives at Fortune 1000 organizations.\nResponsible for sourcing and brokering new business with significant clients including Vail Resorts, Cargill, Pergo, Black and Decker, and\nColonial Williamsburg.\nResponsible for production of monthly newsletters for ORION clients and employees on current innovations that provided creative solutions\nto business problems.\nJanuary 2008\nto\nJanuary 2009\nCompany Name\n \nCity\n \n, \nState\n \nSales Manager\nMaximized Showtime Networks subscriber growth and revenue in affiliate customer service centers in the Mid-West and Western\nterritories.\nManaged 10 accounts in the cable industry sector with $894,623 of combined revenue and maintained a 1% account net growth, in a\ntelevision advertising environment that exhibited significant declines in growth.\nLed on-site training by educating and motivating affiliated Customer Contact Personnel, which included 15-20 people per training on\nproduct, sales, retention, new product introduction, and created and implemented motivational methods to influence sales.\nLed new business development initiatives in Seneca, SC and Seattle, WA, territories that directly resulted in increased revenue from\nlocations that previously generated zero advertising revenue.\nEstablished and maintained an extensive network of clients through calls, meetings, and designed client management events.\nJuly 2006\nCompany Name\n \nCity\n \n, \nState\n \nSummer Analyst\nConducted research for Portfolio Managers on portfolio investments including analyses of 10-K and 10-Q reports.\nTracked the trading volume and prices of key stocks for institutional and private clients, producing weekly reports to various Portfolio\nManagers and assisted the trading desk with market database analysis on prospective trades.\nEducation\n2007\nHOBART COLLEGE\n \nCity\n \n, \nState\n \nBachelor of Arts\n \n: \nEnglish\n \nEnglish\nMay 2007\nMedia and Society\n \nMedia and Society\nInterests\nMember, Men's Club Ice Hockey (2003 - 2007), devoted 12 hours per week in practice and competition Volunteer, Political Activism House\n(2004), organized and conducted voter registration drives for college students 1999-2003 THE DELBARTON SCHOOL Morristown, NJ\nMember, Men's Varsity Ice Hockey (NJ State Champions - 2002) New Jersey Hockey Hall of Fame inductee - 2014\nAdditional Information\nMember, Men's Club Ice Hockey (2003 - 2007), devoted 12 hours per week in practice and competition Volunteer, Political Activism\nHouse (2004), organized and conducted voter registration drives for college students 1999-2003 THE DELBARTON SCHOOL\nMorristown, NJ Member, Men's Varsity Ice Hockey (NJ State Champions - 2002) New Jersey Hockey Hall of Fame inductee - 2014\nSkills\nads, advertising, Avid, budgets, Budget, business strategies, cable, cash flow, coach, client management, content, contracts, SC, client, clients,\ncustomer serv",
  "enriched_profile": {
    "fullName": "John Doe",
    "email": "",
    "phone": "",
    "location": "City, State",
    "linkedin": "",
    "github": "",
    "portfolio": "",
    "summary": "Experienced Business Development Manager with a demonstrated history of working in the media, financial services, and advertising industries. Skilled in sales, business development, customer service, and financial solutions.",
    "education": [
      {
        "school": "Hobart College",
        "degree": "Bachelor of Arts",
        "field": "English",
        "startDate": "2003",
        "endDate": "2007",
        "gpa": ""
      }
    ],
    "experience": [
      {
        "company": "Company Name",
        "position": "Business Development Manager",
        "startDate": "January 2014",
        "endDate": "Current",
        "description": "Report to COO and CRO with new business initiatives and business strategies for publishers and advertisers. Launched Cinema6's first campaigns with a premium spirits brand and athletic brand resulting in 100% profit. Negotiated contracts with 3rd party vendors. Adding clients to partner with by phone, email and meetings resulting in the creation of a pipeline for Cinema6. Compose weekly reports on new business, campaigns and other daily tasks."
      },
      {
        "company": "Company Name",
        "position": "Sales and Service Desk Specialist",
        "startDate": "January 2013",
        "endDate": "January 2014",
        "description": "Supported and managed relationships with Financial Advisors in the Pacific Northwest and Mid-America regions, as well as throughout the country and internationally. Educated Financial Advisors on specific Alternative Investment products on the Merrill Lynch platform. Identified as the Sales and Service Desk Specialist with the highest and most consistent call record, leading the team in services provided to Financial Advisors that called on the Alternative Investments Service Desk. Developed and helped launch the Best Practitioner program for Financial Advisors geared towards generating new business on the Alternative Investment platform. Awarded 2013 Alternative Investments Most Net Sales to Budget for the Pacific Northwest Region."
      },
      {
        "company": "Company Name",
        "position": "New Business Director",
        "startDate": "January 2010",
        "endDate": "January 2013",
        "description": "Provided financial solutions for clients that reduced cash flow expenditures and realized losses on assets by utilizing those underperforming assets to offset media expenditures. Responsible for introducing ORION Trading to 75-150 accounts with annual media budgets in excess of $4mm on advertising including, but not limited to television, radio, digital print, and OOH, nationally and locally. Sourced and maintained relationships with corporate executives at Fortune 1000 organizations. Responsible for sourcing and brokering new business with significant clients including Vail Resorts, Cargill, Pergo, Black and Decker, and Colonial Williamsburg. Responsible for production of monthly newsletters for ORION clients and employees on current innovations that provided creative solutions to business problems."
      },
      {
        "company": "Company Name",
        "position": "Sales Manager",
        "startDate": "January 2008",
        "endDate": "January 2009",
        "description": "Maximized Showtime Networks subscriber growth and revenue in affiliate customer service centers in the Mid-West and Western territories. Managed 10 accounts in the cable industry sector with $894,623 of combined revenue and maintained a 1% account net growth, in a television advertising environment that exhibited significant declines in growth. Led on-site training by educating and motivating affiliated Customer Contact Personnel, which included 15-20 people per training on product, sales, retention, new product introduction, and created and implemented motivational methods to influence sales. Led new business development initiatives in Seneca, SC and Seattle, WA, territories that directly resulted in increased revenue from locations that previously generated zero advertising revenue. Established and maintained an extensive network of clients through calls, meetings, and designed client management events."
      }
    ],
    "projects": [],
    "skills": [
      "ads",
      "advertising",
      "Avid",
      "budgets",
      "Budget",
      "business strategies",
      "cable",
      "cash flow",
      "coach",
      "client management",
      "content",
      "contracts",
      "SC",
      "client",
      "clients",
      "customer service",
      "database analysis",
      "email",
      "Financial",
      "Investments",
      "market",
      "meetings",
      "Microsoft Excel",
      "Power Point",
      "Microsoft Word",
      "network",
      "Networks",
      "new business development",
      "newsletters",
      "Personnel",
      "producing",
      "profit",
      "radio",
      "Research",
      "Sales",
      "phone",
      "television",
      "video"
    ],
    "licenses": []
  }
}