{
  "resume_id": "R0087",
  "content": "CONSULTANT\nProfessional Profile\nHighly motivated and self-driven Systems Analyst with vast experience in various environments and technologies in support of multiple departments\nacross the enterprise. \nExpertise in Software Development Lifecycle (SDLC) and Computer Systems Validation (CSV). \nLooking for an\nopportunity to apply and develop strong analytical skills and problem solving techniques.\nQualifications\nDocumentum DCM and Documentum D2, MS Access, VBA, C, C++,\nsome HTML, Assembly language programming.\nProject leadership, strong technical skills, analytical skills, problem-solving\nskills, organizational skills and communication skills\nSystems analyst, general application support, software development, data\ncommunications, System administration\nExpertise in SDLC on small to large projects\nProficient in SDLC and Computer Systems Validation\nRequirements and Documentation\nExperience\nConsultant\n \nJanuary 1999\n \nto \nNovember 2015\n \nCompany Name\n \n\u00ef\u00bc\u200b \nCity\n \n, \nState\nProvides consultant expertise in various roles supporting McNeil Consumer Healthcare including but not limited to the following applications:\nshop floor application, document management application, timekeeper application, business process applications.\nKnowledgeable in the SDLC process and GxP, SOX compliant applications.\nMost supported applications have been FDA validated applications requiring significant Computer System Validation experience.\nProject Leadership roles in several projects including application upgrades.\nProvides support to a GxP compliant document management application based on Documentum D2 as well as older Documentum DCM\nenvironments.\nSupport includes detailed analysis of issues including document transformation, printing issues, reporting and general user troubleshooting.\nProviding Level 2 Production Application support, attend to user requests through ITSM and emails Monitoring the Support Mailbox during\nthe Support hours Generating Scheduled and Adhoc Reports for Users Daily Consistency Checks to ensure proper functioning of the\nservers, services and Documentum jobs and other related activities Bug fixing in the application supported that may require Change\nRequests Providing solutions to minor Enhancements in the Application that requires Change Requests Responsible for Doing Root cause\nanalysis for recurring issues.\nEscalating to Level 3 Support/ application Core Team where issue is out of scope of Level 2.\nFollow up with different support groups like Windows Team, DBA Team as and when needed Monitoring the Validation Environment to\nensure proper functioning.\nMonitoring the Training Environment to ensure User Training can run smoothly.\nProvides support to SOX compliant payroll application which tracks the hourly wage employees times and reports into the J&J corporate\nsystem.\nProvides support to multiple Microsoft Access database and applications.\nPrior support including designing, developing and testing VBA code in the databases and Excel spreadsheets.\nProvided support to FDA-validated manufacturing application that aided the shop floor in reporting activities involved in the manufacturing\nprocess as well as creating, managing and reporting on non-conformances.\nInvolved in various roles and projects to support IT rollouts and upgrades of the Windows operating system.\nConsultant\n \nJanuary 1990\n \nto \nJanuary 1999\n \nCompany Name\nProvided consultant expertise to customers in various roles and expertise including but not limited to the following responsibilities: Provided\ndesign, development, testing and support for Client/server messaging application to provide the communication between VAX and IBM\nsystems for a large steel company.\nProvided design, development, testing and support for and electronic batch record application within a large team consisting of consultants\nand customer.\nProvided relational database expertise on multiple projects for various applications and technologies.\nProvided training for several Digital products to customers.\nProvided system administration support to several customers.\nSystems Programmer\n \nJanuary 1985\n \nto \nJanuary 1990\n \nCompany Name\n \n\u00ef\u00bc\u200b \nCity\n \n, \nState\nDesigned, developed, tested and supported a real-time client/server application to provide messaging.\ncommunications from a VAX/VMS application to an IBM application.\nThe application tracked the movement if trains.\nand locations.\nThe application was originally written in assembly language and later converted to C.\nProvided general system and network administration support.\nEducation\nM.S\n \n: \nComputer Science Data Communications\n \n, \n1996\n \nVillanova University\n \n\u00ef\u00bc\u200b \nCity\n \n, \nState\n \nComputer Science Data Communications\nB.A\n \n: \nComputer Science\n \n, \n1985\n \nLaSalle University\n \n\u00ef\u00bc\u200b \nCity\n \n, \nState\n \nComputer Science\nSkills\nanalytical skills, Assembly language, C, C++, Client/server, communication skills, consultant, Data communications, database and applications,\nDBA, databases, designing, document management, Documentation, Docume",
  "enriched_profile": {
    "fullName": "Highly motivated Systems Analyst",
    "email": "",
    "phone": "",
    "location": "",
    "linkedin": "",
    "github": "",
    "portfolio": "",
    "summary": "Highly motivated and self-driven Systems Analyst with vast experience in various environments and technologies in support of multiple departments across the enterprise. Expertise in Software Development Lifecycle (SDLC) and Computer Systems Validation (CSV). Looking for an opportunity to apply and develop strong analytical skills and problem-solving techniques.",
    "education": [
      {
        "school": "Villanova University",
        "degree": "M.S",
        "field": "Computer Science Data Communications",
        "startDate": "1996",
        "endDate": "",
        "gpa": ""
      },
      {
        "school": "LaSalle University",
        "degree": "B.A",
        "field": "Computer Science",
        "startDate": "1985",
        "endDate": "",
        "gpa": ""
      }
    ],
    "experience": [
      {
        "company": "Company Name",
        "position": "Consultant",
        "startDate": "January 1999",
        "endDate": "November 2015",
        "description": "Provides consultant expertise in various roles supporting McNeil Consumer Healthcare including but not limited to the following applications: shop floor application, document management application, timekeeper application, business process applications. Knowledgeable in the SDLC process and GxP, SOX compliant applications. Most supported applications have been FDA validated applications requiring significant Computer System Validation experience. Project Leadership roles in several projects including application upgrades. Provides support to a GxP compliant document management application based on Documentum D2 as well as older Documentum DCM environments. Support includes detailed analysis of issues including document transformation, printing issues, reporting and general user troubleshooting. Providing Level 2 Production Application support, attend to user requests through ITSM and emails Monitoring the Support Mailbox during the Support hours Generating Scheduled and Adhoc Reports for Users Daily Consistency Checks to ensure proper functioning of the servers, services and Documentum jobs and other related activities Bug fixing in the application supported that may require Change Requests Providing solutions to minor Enhancements in the Application that requires Change Requests Responsible for Doing Root cause analysis for recurring issues. Escalating to Level 3 Support/ application Core Team where issue is out of scope of Level 2. Follow up with different support groups like Windows Team, DBA Team as and when needed Monitoring the Validation Environment to ensure proper functioning. Monitoring the Training Environment to ensure User Training can run smoothly. Provides support to SOX compliant payroll application which tracks the hourly wage employees times and reports into the J&J corporate system. Provides support to multiple Microsoft Access database and applications. Prior support including designing, developing and testing VBA code in the databases and Excel spreadsheets. Provided support to FDA-validated manufacturing application that aided the shop floor in reporting activities involved in the manufacturing process as well as creating, managing and reporting on non-conformances. Involved in various roles and projects to support IT rollouts and upgrades of the Windows operating system."
      },
      {
        "company": "Company Name",
        "position": "Consultant",
        "startDate": "January 1990",
        "endDate": "January 1999",
        "description": "Provided consultant expertise to customers in various roles and expertise including but not limited to the following responsibilities: Provided design, development, testing and support for Client/server messaging application to provide the communication between VAX and IBM systems for a large steel company. Provided design, development, testing and support for and electronic batch record application within a large team consisting of consultants and customer. Provided relational database expertise on multiple projects for various applications and technologies. Provided training for several Digital products to customers. Provided system administration support to several customers."
      },
      {
        "company": "Company Name",
        "position": "Systems Programmer",
        "startDate": "January 1985",
        "endDate": "January 1990",
        "description": "Designed, developed, tested and supported a real-time client/server application to provide messaging. communications from a VAX/VMS application to an IBM application. The application tracked the movement if trains. and locations. The application was originally written in assembly language and later converted to C. Provided general system and network administration support."
      }
    ],
    "projects": [
      {
        "name": "",
        "techStack": "Assembly language, C, C++, Client/server, Data communications, database and applications, DBA, databases, designing, document management, Documentation, Documentum, some HTML, IBM, managing, manufacturing process, messaging, Microsoft Access, MS Access, Excel spreadsheets, Windows operating system, Windows, Windows 2000, Windows XP, network administration, Operating Systems, programming, Project Leadership, real-time, relational database, reporting, SDLC, servers, System administration, User Training, troubleshooting, upgrades, Validation, VAX, VAX/VMS, Vista, VBA, Windows Server, written",
        "description": "",
        "link": ""
      }
    ],
    "skills": [
      "analytical skills",
      "Assembly language",
      "C",
      "C++",
      "Client/server",
      "communication skills",
      "consultant",
      "Data communications",
      "database and applications",
      "DBA",
      "databases",
      "designing",
      "document management",
      "Documentation",
      "Documentum",
      "some HTML",
      "IBM",
      "managing",
      "manufacturing process",
      "messaging",
      "Microsoft Access",
      "MS Access",
      "Excel spreadsheets",
      "Windows operating system",
      "Windows",
      "Windows 2000",
      "Windows XP",
      "network administration",
      "Operating Systems",
      "organizational skills",
      "payroll",
      "programming",
      "Project Leadership",
      "real-time",
      "relational database",
      "reporting",
      "SDLC",
      "servers",
      "System administration",
      "User Training",
      "troubleshooting",
      "upgrades",
      "Validation",
      "VAX",
      "VAX/VMS",
      "Vista",
      "VBA",
      "Windows Server",
      "written"
    ],
    "licenses": []
  }
}