{
  "resume_id": "R0098",
  "content": "RN / ASST. HEAD NURSE PRACTICE LEADER\nSkills\ncare planning, Case Management, Home Health, Hospice, Infection control, injections, Nurse Manager, Oncology, scheduling, staff development,\nTrauma, triage, tutoring, Urology\nExperience\n09/2010\n \nto \n12/2011\nCompany Name\nHired as ADON (Assistant Director of Nursing) for an 85 to 90 bed long term care of Mentally and Physically disabled children from 2\nyears to upper 20's with a few older individuals.\nMy job there included staffing of all the nurses monthly, setting up transportation for all outside MD office visits of the residents, monitoring\nthe 3 nursing units of day to day care and documentation of the residents, taking call as needed and twice a month being MOD for the entire\nbuilding ,I conducted in-services for the nursing staff and answered all pages during the day with questions or to oversee any critical changes\nof residents and helped with decisions to transfer out to a hospital after speaking with the MD.Helped with staff nursing as needed.\nSecured a Home Health position at ResCare \nlocated in Oak Park Illinois in 2015.\nI made home visits overseeing clients overall health.\nDid basic assessments and listened for any new complaints or change of status.\nWould call \nclients doctor if needed or to inform him of a change in status.\nGave injections/ infusions as needed and participated in one clinical trial where all aspects of visit were timed and documented as per\nprotocal.\nI am still registered with this agency but they have very few clients in need of an RN visit.\nMost of their clients only need part time CAN visits.\nSecured an RN position in July 2016 at Best Home Health where I did home visits part time.\nThe jobs that were available for part time were minimal so took myself off their roster.\nIn the fall of 2016 worked for Maxim Home Health asking for part time for Infusion cases.\nAgain I was promised infusion cases but what were available Were ones 40 miles away and they didn't cover milage.\nI still am on their roster but rarely called.\nCurrently looking for Part Time RN on line or going into a facility not more than 30 minute drive to do tutoring or online triage or willing to\nlearn Case Management or PT Oncology/Hospice Additional professional activities Was OCN certified in past Was Med / Surg certified in\npast and plan to recertify in future.\nWas team nurse of North Shore Youth Baseball League for \n4 years References Dr.\nEmil Totonchi MD.\nAdvocate Illinois Masonic Med.\nCenter** Dr.\nMichael Friedman MD.\nAdvocate Illinois Masonic Med.\nCenter** Beverly Bohus RN, Nurse Manager \nAdvocate Illinois Masonic Med.\nCenter** Lorel Hedges Nurse Practioner.\nAdvocate Illinois Masonic Med.\nCenter now works in Tennessee Uma Kelkar Director of Rehab Manor Care of Northbrook Jean Gavina Director of MDS, Manor Care\nof Northbrook Elma Ramos RN , Evening Nursing Supervisor, Manor Care of Northbrook Contact information available upon request.\n06/2009\n \nto \n07/2010\nCompany Name\nStarted out as a Supervisor but was promoted to DCD (Director of Care Delivery) managing a 40 bed Locked Dementia Unit and later a\n60 bed Long Term Care Unit and recently back to the Dementia Unit along with the Long Term Care Unit.\nDuties included: Leading the nursing unit, setting priorities, staff development ,upholding Corporate Standards, communicating through\nexisting information systems, and material management, Clinical Management: Infection control, QA, understanding Professional issues,\nvaluing every employee, supporting and leading company policies, attending interdisciplinary meetings twice daily, weekly and monthly\nmeetings such as Medicare meetings, investigation of all falls and skin injuries, and new admissions care planning.\nMonthly Staff Meetings.\nAssists with hiring and disciplinary actions.\nResigned July 2010 Want to take some vacation time, and to find a Long Term Care Management position somewhat closer to my home.\n01/1977\n \nto \n01/2009\nRN / Asst. Head Nurse Practice Leader\n \nCompany Name\n \n\u00ef\u00bc\u200b \nCity\n \n, \nState\nResponsible for management of Unit on 24 hr basis including staffing, scheduling, and payroll.\nMonitor staff of RN's, NCT's, and Unit Clerks for daily assignments on going learning needs, and occasionally fill staff RN voids.\nReported to Nurse Manager on daily basis for any additional tasks and to keep her current to Units activities and problems.\nHelped Nurse Manager in interview process and in both disciplinary activity and in employee terminations .Sought out and scheduled in-\nservices for staff \nand made sure all staff attended required hospital mandatories yearly and when required.\n01/1977\n \nto \n01/2009\nCompany Name\n \n\u00ef\u00bc\u200b \nCity\n \n, \nState\nStarted nursing career as RN on general Med / Surg Unit for 2 years.\nRecruited by MD Chairman of Oncology to be part of staff to open 1st Oncology inpatient Unit.\nPromoted also to Assistant Head Nurse.\nWorked there for next 20 years.\nEarned OCN certificate.\nHelped instruct all RNs on unit to become certified to mix Chemo drugs via",
  "enriched_profile": {
    "fullName": "RN / ASST. HEAD NURSE PRACTICE LEADER",
    "email": "",
    "phone": "",
    "location": "",
    "linkedin": "",
    "github": "",
    "portfolio": "",
    "summary": "Experienced RN with expertise in care planning, case management, and oncology. Proven track record in staff development, infection control, and triage. Seeking part-time opportunities in home health, tutoring, or online triage.",
    "education": [
      {
        "school": "Illinois Masonic School of Nursing",
        "degree": "RN Diploma",
        "field": "",
        "startDate": "1976",
        "endDate": "",
        "gpa": ""
      }
    ],
    "experience": [
      {
        "company": "Best Home Health",
        "position": "RN",
        "startDate": "July 2016",
        "endDate": "",
        "description": "Performed part-time home visits, administered injections/infusions, and participated in clinical trials."
      },
      {
        "company": "Maxim Home Health",
        "position": "RN",
        "startDate": "Fall 2016",
        "endDate": "",
        "description": "Requested part-time infusion cases but received cases that were 40 miles away without mileage coverage. Still on roster but rarely called."
      },
      {
        "company": "Hired as ADON (Assistant Director of Nursing)",
        "position": "",
        "startDate": "09/2010",
        "endDate": "12/2011",
        "description": "Managed staffing, transportation, monitoring of nursing units, conducted in-services, and took call for an 85 to 90 bed long term care facility for mentally and physically disabled children and adults."
      },
      {
        "company": "ResCare",
        "position": "Home Health",
        "startDate": "2015",
        "endDate": "",
        "description": "Made home visits to oversee clients' overall health, conducted basic assessments, and communicated with clients' doctors as needed."
      },
      {
        "company": "Director of Care Delivery",
        "position": "",
        "startDate": "06/2009",
        "endDate": "07/2010",
        "description": "Managed a 40 bed Locked Dementia Unit and later a 60 bed Long Term Care Unit, led nursing unit, set priorities, developed staff, upheld corporate standards, and attended interdisciplinary meetings."
      },
      {
        "company": "RN / Asst. Head Nurse Practice Leader",
        "position": "",
        "startDate": "01/1977",
        "endDate": "01/2009",
        "description": "Managed unit on a 24-hour basis, staffing, scheduling, payroll, monitored staff, reported to Nurse Manager, helped in interview process, disciplinary activity, and employee terminations, and sought out and scheduled in-services for staff."
      }
    ],
    "projects": [],
    "skills": [
      "care planning",
      "Case Management",
      "Home Health",
      "Hospice",
      "Infection control",
      "injections",
      "Nurse Manager",
      "Oncology",
      "scheduling",
      "staff development",
      "Trauma",
      "triage",
      "tutoring",
      "Urology"
    ],
    "licenses": []
  }
}