{
  "resume_id": "R0097",
  "content": "FIELD PROJECT SUPERVISOR\nSummary\nAdministrative aviation logistics professional with 26 years' experience working in the military sector including 20 years' operating in a supervisory\nposition. Tracked and managed U.S. Navy and Marine Corps aeronautical logistics assets performing above and beyond the requirements of the\nMilitary Occupational Specialty (6046/6047). \nAdditional roles include management, personnel development, and quality assurance. \nOutstanding\nleader and team builder; established and managed programs; coached and mentored personnel. \nExceptional technical and technology skills. \nBA in\nHuman Resources Management.\nSkills\nSecret Clearance.\nE-commerce\nSupply Chain Management\nLogistics Management\nMicrosoft Office Suite\nNTCSS\nSAP\nTechnical Publications\nTechnical Writing\nSix Sigma Green Belt\nMaintenance Administration\nExperience\n01/2015\n \nto \nCurrent\nField Project Supervisor\n \nCompany Name\nManaged U.S.\nNaval Aviation Logistics Command Management Information System, Optimized-Organizational Maintenance Activity (NALCOMIS\nOOMA) implementations, operation, and training for 7 diverse tactical aviation units comprised of more than 48,400 Naval aircraft systems,\nparts and publications worth more than 11 billion dollars.\nOrganized and managed compliance, inspections, and repairs for more than 19,500 logistic components installed on 130 U.S.\nNaval aircraft and ejection seats and 260 engines.\nGenerated and released over 400 critical U.S.\nNaval aircraft, engine, and summary analysis reports for 130 aircraft, ejections seats, and 260 engines to assist higher headquarters in\nstrategic planning.\nDeveloped numerous spreadsheets that assisted the Marine Corps Aviation Branch to streamline the in-service repair process for 130 U.S.\nNaval aircraft and increase asset readiness goals by 20%.\nSuccessfully managed 7 critical aviation programs completing 12 logistics inspections necessary to conduct combat operations.\nDemonstrates up-to-date expertise and applies this to the development, execution, and improvement of action plans.\nDevelops and directs one or more work streams of cross-functional store planning projects in all formats.\nDirects Associates, including managers, on process and procedures for Facility set-up projects, including \nreviewing new modular plans,\nplanning merchandise placement based on modular requirements, and advising on \nassigning additional staff to assist to ensure Company and\nFacility goals are met.\nDrives and monitors sales and project budget.\nDrives the implementation of real estate plans for project facilities (for example, remodels, new stores, \nrelocations, new formats,\nexpansions).\nModels compliance with company policies and procedures and supports company mission, values, and standards of ethics and integrity.\nModels, enforces, and provides direction and guidance to Associates on proper Customer service approaches and \ntechniques to ensure\nCustomer needs, complaints, and issues are successfully resolved within Company \nguidelines and standards.\nAdditional Information U.S Marine Corps.\n01/2012\n \nto \n01/2015\nAviation Implementation Manager Master Sergeant\n \nCompany Name\n \n\u00ef\u00bc\u200b \nCity\n \n, \nState\nManaged project logistics for Naval aviation and ship software system assets.\nSupervised project staff.\nMonitored project progress.\nPrepared status reports.\nManaged project deliverable documentation for compliance and accuracy.\nProvided functional and follow-on support for software systems and assets tracked U.S.\nMarine Corps.\n01/2002\n \nto \n01/2012\nAviation Administration Manager Staff Sergeant Gunnery Sergeant\n \nCompany Name\n \n\u00ef\u00bc\u200b \nCity\n \n, \nState\nMaintained Government Aviation Logistics Information Systems and databases.\nScheduled, tracked, and requisitioned aircraft components and systems for Naval Aviation compliance.\nPerformed data entry screening for compliance of U.S.\nNaval aircraft, ejection seat, and engine repair compliance.\nDeveloped and maintained aviation metrics, logistic reports, process documentation, and safety records to support unit operations and\nplanning.\nGathered, organized, and analyzed aircraft logistics component discrepancies to develop solutions.\nDeveloped logistical training procedures, guides, and course materials, such as handouts or visual aids.\nOversaw all safety standards, occupational safety, and safety affairs on the job.\n01/1987\n \nto \n01/2012\nAviation Administration Program Manager/Data Analyst Sergeant Staff Sergeant Gunnery Sergeant\nMaintained Government Aviation Logistics Information Systems and databases.\nDistributed maintenance schedules and logistics work orders to the maintenance departments.\nVerified source logistics data for completeness and accuracy.\nComputed and analyzed aviation logistics data, using statistical formulas, computers, and calculators.\nCompleted configuration management actions such as compliance discrepancies during flight operations, special logistics inspections, and\nconditional inspections relevant to aircraft systems and components.",
  "enriched_profile": {
    "fullName": "Administrative aviation logistics professional",
    "email": "",
    "phone": "",
    "location": "City, State",
    "linkedin": "",
    "github": "",
    "portfolio": "",
    "summary": "Administrative aviation logistics professional with 26 years' experience in the military sector, including 20 years in a supervisory position. Tracked and managed U.S. Navy and Marine Corps aeronautical logistics assets, performing above requirements. Demonstrated skills in management, personnel development, quality assurance, leadership, and team building. Holds a BA in Human Resources Management.",
    "education": [
      {
        "school": "Ashford University",
        "degree": "Bachelor of Arts",
        "field": "Human Resources Management, Business Administration",
        "startDate": "2015",
        "endDate": "",
        "gpa": "3.8"
      }
    ],
    "experience": [
      {
        "company": "U.S. Naval Aviation Logistics Command",
        "position": "Field Project Supervisor",
        "startDate": "01/2015",
        "endDate": "Present",
        "description": "Managed U.S. Naval Aviation Logistics Command Management Information System, Optimized-Organizational Maintenance Activity (NALCOMIS OOMA) implementations, operation, and training for 7 diverse tactical aviation units. Organized and managed compliance, inspections, and repairs for logistic components, engines, and aircraft. Generated and released critical U.S. Naval aircraft, engine, and summary analysis reports. Developed spreadsheets to streamline the in-service repair process and increase asset readiness goals. Successfully managed 7 critical aviation programs and 12 logistics inspections."
      },
      {
        "company": "U.S. Marine Corps",
        "position": "Aviation Implementation Manager Master Sergeant",
        "startDate": "01/2012",
        "endDate": "01/2015",
        "description": "Managed project logistics for Naval aviation and ship software system assets. Supervised project staff, monitored project progress, and prepared status reports. Managed project deliverable documentation for compliance and accuracy. Provided functional and follow-on support for software systems and assets tracked."
      },
      {
        "company": "U.S. Marine Corps",
        "position": "Aviation Administration Manager Staff Sergeant Gunnery Sergeant",
        "startDate": "01/2002",
        "endDate": "01/2012",
        "description": "Maintained Government Aviation Logistics Information Systems and databases. Scheduled, tracked, and requisitioned aircraft components and systems for Naval Aviation compliance. Performed data entry screening for compliance of U.S. Naval aircraft, ejection seat, and engine repair compliance. Developed and maintained aviation metrics, logistic reports, process documentation, and safety records to support unit operations and planning."
      },
      {
        "company": "U.S. Marine Corps",
        "position": "Aviation Administration Program Manager/Data Analyst Sergeant Staff Sergeant Gunnery Sergeant",
        "startDate": "01/1987",
        "endDate": "01/2002",
        "description": "Maintained Government Aviation Logistics Information Systems and databases. Distributed maintenance schedules and logistics work orders to the maintenance departments. Verified source logistics data for completeness and accuracy. Completed configuration management actions such as compliance discrepancies during flight operations, special logistics inspections, and conditional inspections relevant to aircraft systems and components."
      }
    ],
    "projects": [],
    "skills": [
      "Secret Clearance",
      "E-commerce",
      "Supply Chain Management",
      "Logistics Management",
      "Microsoft Office Suite",
      "NTCSS",
      "SAP",
      "Technical Publications",
      "Technical Writing",
      "Six Sigma Green Belt",
      "Maintenance Administration"
    ],
    "licenses": []
  }
}