{
  "resume_id": "R0096",
  "content": "ACCOUNTANT\nProfessional Summary\nTo obtain a position in a fast-paced business office environment, demanding a strong organizational, technical, and interpersonal position utilizing\nmy skills and attributes. Attributes Self-motivated and honest; good work ethic Effective working alone or as a cooperative team member Reliable\nand hard-working; thorough in completing projects Committed to excellent customer service\nCore Qualifications\nIntermediate Word \nAdvanced Excel \nPowerPoint Intermediate Access \nAccounts Receivable \nAccounts Payable \nQuickBooks Enterprise \nOutlook\nCustomer Service\nExperience\nAccountant\n \nJanuary 2011\n \nto \nNovember 2015\n \nCompany Name\n \n\u00ef\u00bc\u200b \nCity\n \n, \nState\nProcessed accounts receivables payments received by ACH, Lockbox, Credit Card and Checks.\nMaintained all banking activity.\nDocumented all loan and other payments to the proper G/L Accounts.\nReview and maintain all positive pay processing with the bank.\nReview and processed accounts payables reports.\nProcessed all accounts payables by check, domestic and international wires, ACH, and credit card.\nReconcile all bank statements.\nMaintained all credit card activity for all credit card holders, documented transactions to the proper G/L Accounts.\nCalculate and process all Sales quarterly commission reports.\nReview and complete all credit checks and reference checks on new customers.\nMaintain and file the quarterly reports for the Job Development Credit with the State of South Carolina.\nOrder passports and Visa's for international travel.\nAccounts Receivable Clerk\n \nJanuary 2008\n \nto \nJanuary 2010\n \nCompany Name\n \n\u00ef\u00bc\u200b \nCity\n \n, \nState\nPerformed data entry.\nProcessed accounts receivable payments.\nReconciled delivery driver's cash and checks with daily invoices.\nCorresponded with customers through email and phone calls on overdue invoices.\nSent bi-weekly and monthly statements.\nCreated and maintained monthly inventory depletion and sales reports to suppliers.\nBalanced and solved problems with customer's accounts.\nFiled customer and suppliers invoices.\nRan daily trial balance.\nRan the end of day closing reports.\nMortgage Underwriter\n \nJanuary 2006\n \nto \nJanuary 2008\n \nCompany Name\n \n\u00ef\u00bc\u200b \nCity\n \n, \nState\nProcessed new residential mortgage loan submissions.\nProvided clear and consistent written and verbal communications with customers/clients.\nProvided a strong analytical aptitude for reviewing credit reports, bank statements, preliminary title reports and appraisals.\nCorresponded with customers, loan officers, and account managers for information needed.\nCommercial Auto Underwriter\n \nJanuary 2004\n \nto \nJanuary 2006\n \nCompany Name\n \n\u00ef\u00bc\u200b \nCity\n \n, \nState\nProcessed new business commercial auto applications and issued endorsements.\nPerformed data entry, reviewed applications, loss runs and driving records.\nProvided clear and consistent written and verbal communications with customers/brokers.\nGail L.\nLugo \nPage 2 864-472-7092.\nPersonal Auto Underwriter\n \nJanuary 2001\n \nto \nJanuary 2004\n \nCompany Name\n \n\u00ef\u00bc\u200b \nCity\n \n, \nState\nProcessed new business, renewals and endorsements.\nPerformed data entry, reviewed applications, loss runs and driving records.\nProcessed account receivable premium checks for insurance premiums.\nConsistently resolved and answered customer concerns and questions by properly and promptly reviewing policies, endorsements and\npremium payments.\nClaims Examiner\n \nJanuary 1983\n \nto \nJanuary 2001\n \nCompany Name\n \n\u00ef\u00bc\u200b \nCity\n \n, \nState\nTrained coworkers on multiple tasks and administrative functions.\nReviewed medical records and made decisions regarding disability payments.\nPerformed data entry.\nCreated, designed and maintained various insurance documents which complied with Truth and Lending regulations.\nResponded to and resolved all customer inquiries via telecommunications and written correspondence.\nDeveloped and maintained measures of self-directed team performance which improved workflow.\nConsistently exceeded company goal of required number of paid claims per hour.\nPerformed journal entries and ledger postings.\nReconciled bank statements, budget accounts, and accounts receivable/payable records.\nRapidly promoted from Level I to Level III within a one-year period due to excellent work performance.\nEducation\nComputer Applications Specialist Certificate Program\n \n: \n2008\n \nMartinez Adult Education, Business Training Center\n \n\u00ef\u00bc\u200b \nCity\n \n, \nState\nSkills\naccounts payables, accounts receivables, Accounts Payable, Accounts Receivable, administrative functions, trial balance, banking, budget, bi,\nclosing, Computer Applications, Credit, clients, Customer Service, data entry, delivery, driving, email, insurance, inventory, ledger, Access, Excel,\nOutlook, PowerPoint, Word, mortgage loan, Enterprise, policies, QuickBooks, Sales, sales reports, telecommunications, phone, workflow,\nwritten",
  "enriched_profile": {
    "fullName": "Gail L. Lugo",
    "email": "",
    "phone": "864-472-7092",
    "location": "",
    "linkedin": "",
    "github": "",
    "portfolio": "",
    "summary": "Self-motivated and honest professional with a strong work ethic, effective in teamwork and individually. Committed to excellent customer service. Skilled in various business areas, including accounts receivable, accounts payable, and customer service.",
    "education": [
      {
        "school": "Martinez Adult Education, Business Training Center",
        "degree": "",
        "field": "Computer Applications Specialist Certificate Program",
        "startDate": "2008",
        "endDate": "",
        "gpa": ""
      }
    ],
    "experience": [
      {
        "company": "Company Name",
        "position": "Accountant",
        "startDate": "January 2011",
        "endDate": "November 2015",
        "description": "Processed accounts receivables payments, maintained banking activity, documented loan and other payments, reviewed positive pay processing, reconciled bank statements, maintained credit card activity, calculated sales commission reports, and completed credit checks."
      },
      {
        "company": "Company Name",
        "position": "Accounts Receivable Clerk",
        "startDate": "January 2008",
        "endDate": "January 2010",
        "description": "Performed data entry, processed accounts receivable payments, reconciled delivery driver's cash and checks, corresponded with customers, created and maintained inventory reports, balanced and solved problems with customer's accounts, and filed invoices."
      },
      {
        "company": "Company Name",
        "position": "Mortgage Underwriter",
        "startDate": "January 2006",
        "endDate": "January 2008",
        "description": "Processed new residential mortgage loan submissions, reviewed credit reports, bank statements, preliminary title reports and appraisals, corresponded with customers and loan officers, and provided analytical aptitude."
      },
      {
        "company": "Company Name",
        "position": "Commercial Auto Underwriter",
        "startDate": "January 2004",
        "endDate": "January 2006",
        "description": "Processed new business commercial auto applications, issued endorsements, performed data entry, reviewed applications, loss runs and driving records, and provided clear and consistent written and verbal communications."
      },
      {
        "company": "Company Name",
        "position": "Personal Auto Underwriter",
        "startDate": "January 2001",
        "endDate": "January 2004",
        "description": "Processed new business, renewals and endorsements, performed data entry, reviewed applications, loss runs and driving records, and resolved customer concerns and questions."
      },
      {
        "company": "Company Name",
        "position": "Claims Examiner",
        "startDate": "January 1983",
        "endDate": "January 2001",
        "description": "Trained coworkers, reviewed medical records, performed data entry, created and maintained insurance documents, responded to and resolved customer inquiries, developed and maintained team performance measures, and reconciled accounts."
      }
    ],
    "projects": [],
    "skills": [
      "accounts payables",
      "accounts receivables",
      "administrative functions",
      "trial balance",
      "banking",
      "budget",
      "bi",
      "closing",
      "computer applications",
      "credit",
      "clients",
      "customer service",
      "data entry",
      "delivery",
      "driving",
      "email",
      "insurance",
      "inventory",
      "ledger",
      "access",
      "excel",
      "outlook",
      "powerpoint",
      "word",
      "mortgage loan",
      "enterprise",
      "policies",
      "quickbooks",
      "sales",
      "sales reports",
      "telecommunications",
      "phone",
      "workflow",
      "written"
    ],
    "licenses": []
  }
}