{
  "resume_id": "R0105",
  "content": "GENERAL LIABILITY CLAIM REPRESENTATIVE\nSummary\nClaims Representative who is highly motivated, success driven with several years experience in the insurance industry.\u00c2 \nSkills\nClaims file management processes\nLitigation resolution\nStrong interpersonal and communication skills\nSelf-directed\nTeam player\nCritical thinker\nExperience\n01/2008\n \nto \n02/2013\nGeneral Liability Claim Representative\n \nCompany Name\n \n\u00ef\u00bc\u200b \nCity\n \n, \nState\nRecognized for continued outstanding customer service - nominated for In-Synch Award Successfully determine coverage and communicate\nwith insured based on application of policy information, facts and allegations of each case.\nAggressively investigate, evaluate, reserve, and negotiate assigned claims in accordance with Best Practices.\nOrganize workflow to maintain efficiency and productivity.\nRecognized for successfully indentifying resources for activities required to properly investigate claims involving Subrogation, Risk Control,\nand fraud.\nEffectively manage litigated claims.\nMaintain accounts with business partners to ensure and sustain quality results.\n07/2005\n \nto \n01/2008\nAuto Claims Unit Manager\n \nCompany Name\n \n\u00ef\u00bc\u200b \nCity\n \n, \nState\nMonitor the performance of a team of eight automobile claim representatives, using the tools and techniques available, and implement plans\nto improve performance timely and effectively.\nCommunicate expectations and hold unit meetings.\nOrganize workflow to maintain efficiency and productivity.\nCoach and develop technically and professionally in order to improve business results, and maintain positive morale in the office.\nProactively understand, plan and communicate the objectives and philosophy of the company, unit goals, expectations and changes in\nworkflows.\nAbility to analyze team results independently, create, and implement appropriate action plans in order to achieve needed results.\n01/2004\n \nto \n07/2005\nAutomobile Liability Claims Representative\n \nCompany Name\n \n\u00ef\u00bc\u200b \nCity\n \n, \nState\nDetermine coverage.\nSupervise the investigation of automobile accidents over the telephone and on site to determine liability.\nDirect auto claims representatives to pay property damage claims once liability has been determined adverse.\nManaged uninsured/underinsured motorist property/injury claims.\nManage reported claims to special investigations and completed reports as to the outcome of these investigations.\nAwarded at home work privileges due to superior time management skills.\nSupervise litigated claims with support of company legal counsel.\n07/2000\n \nto \n01/2004\nSenior General Liability Claims Representative\n \nCompany Name\n \n\u00ef\u00bc\u200b \nCity\n \n, \nState\nDirectly responsible for investigating general liability claims, such as slip and falls, municipality claims involving wrongful death allegations.\nRequired to work closely with clients to complete the investigation of claims, determine liability, and evaluate settlements.\nRequired to understand services offered to assist in outside sales presentations.\nIn conjunction with Risk Management General Counsel supervised litigated claims.\nManaged multimillion dollar settlements in conjunction with Risk Management partners \nand Defense Counsel.\nEducation and Training\nB.S\n \n: \nJournalism\n \nSouthern Illinois University\n \n\u00ef\u00bc\u200b \nCity\n \n, \nState\n \nJournalism\nSkills\nCoverage analysis, Customer service, presentations, litigation management, claim investigations and time management.\u00c2 ",
  "enriched_profile": {
    "fullName": "John Doe",
    "email": "",
    "phone": "",
    "location": "City, State",
    "linkedin": "",
    "github": "",
    "portfolio": "",
    "summary": "Claims Representative with several years of experience in the insurance industry, recognized for outstanding customer service and strong interpersonal skills.",
    "education": [
      {
        "school": "Southern Illinois University",
        "degree": "B.S.",
        "field": "Journalism",
        "startDate": "",
        "endDate": "",
        "gpa": ""
      }
    ],
    "experience": [
      {
        "company": "Company Name",
        "position": "Senior General Liability Claims Representative",
        "startDate": "07/2000",
        "endDate": "01/2004",
        "description": "Directly responsible for investigating general liability claims, such as slip and falls, municipality claims involving wrongful death allegations. Required to work closely with clients to complete the investigation of claims, determine liability, and evaluate settlements. In conjunction with Risk Management General Counsel supervised litigated claims. Managed multimillion dollar settlements in conjunction with Risk Management partners and Defense Counsel."
      },
      {
        "company": "Company Name",
        "position": "Automobile Liability Claims Representative",
        "startDate": "01/2004",
        "endDate": "07/2005",
        "description": "Determine coverage. Supervise the investigation of automobile accidents over the telephone and on site to determine liability. Direct auto claims representatives to pay property damage claims once liability has been determined adverse. Managed uninsured/underinsured motorist property/injury claims. Manage reported claims to special investigations and completed reports as to the outcome of these investigations. Supervise litigated claims with support of company legal counsel. Awarded at-home work privileges due to superior time management skills."
      },
      {
        "company": "Company Name",
        "position": "Auto Claims Unit Manager",
        "startDate": "07/2005",
        "endDate": "01/2008",
        "description": "Monitor the performance of a team of eight automobile claim representatives, using the tools and techniques available, and implement plans to improve performance timely and effectively. Communicate expectations and hold unit meetings. Organize workflow to maintain efficiency and productivity. Coach and develop technically and professionally in order to improve business results, and maintain positive morale in the office. Proactively understand, plan and communicate the objectives and philosophy of the company, unit goals, expectations and changes in workflows. Ability to analyze team results independently, create, and implement appropriate action plans in order to achieve needed results."
      },
      {
        "company": "Company Name",
        "position": "General Liability Claim Representative",
        "startDate": "01/2008",
        "endDate": "02/2013",
        "description": "Recognized for continued outstanding customer service - nominated for In-Synch Award. Successfully determine coverage and communicate with insured based on application of policy information, facts and allegations of each case. Aggressively investigate, evaluate, reserve, and negotiate assigned claims in accordance with Best Practices. Organize workflow to maintain efficiency and productivity. Recognized for successfully indentifying resources for activities required to properly investigate claims involving Subrogation, Risk Control, and fraud. Effectively manage litigated claims. Maintain accounts with business partners to ensure and sustain quality results."
      }
    ],
    "projects": [],
    "skills": [
      "Coverage analysis",
      "Customer service",
      "Presentations",
      "Litigation management",
      "Claim investigations",
      "Time management"
    ],
    "licenses": []
  }
}