{
  "resume_id": "R0102",
  "content": "PLANT PROTECTION AND QUARANTINE TECHNICIAN\nSummary\nEnvironmental Biologist and experienced researcher with expertise in data collection and study. Analytical and detail-oriented.\nHighlights\nCertificate study in Wetlands\nIdentification and Delineation\nProficient in Microsoft Office suite\nExcellent verbal and written\ncommunication skills\nKnowledgeable about invasive insects and plant hosts\nUndergraduate thesis study \"Species Diversity of Lepidoptera in Oak Hickory and Northern\nHardwood Forests of Luzerne County, PA\nAccomplishments\nKeystone College Academic Honor Award -Dean's List Spring 2011 and Fall 2008\nMildred Wrigley Ryder Scholarship Fall 2009 and Spring 2010\nJoseph Sirotnak '66, Esq., Memorial Scholarship Fall 2007 and Spring 2009\nExperience\nPlant Protection and Quarantine Technician\n \nMay 2011\n \nto \nAugust 2011\n \nCompany Name\n \n\u00ef\u00bc\u200b \nCity\n \n, \nState\nRegional specialist independently conducting Asian Long-Horned Beetle and Emerald Ash Borer ground based visual surveys in eight northeastern\nPennsylvania counties.\nImplemented PPQ standards which safeguards agriculture and natural resources from risks associated with plant pests to ensure an abundant,\nhigh-quality forest canopy.\nEmployed industry standards effectively collecting forest and insect field data and reporting results in a timely manner.\nForest Insect Pest Aide I\n \nMay 2009\n \nto \nAugust 2009\n \nCompany Name\n \n\u00ef\u00bc\u200b \nCity\n \n, \nState\nForest Insect Pest Aide\n \nMay 2008\n \nto \nAugust 2008\n \nCompany Name\n \n\u00ef\u00bc\u200b \nCity\n \n, \nState\nEmerald Ash Borer, Asian Longhorn Beetle, Sirex Wood wasp and apiarian surveys in Lackawanna County, PA (2008) and 10 northeastern\nPennsylvania counties (2009).\nAccurately identified plant hosts utilizing a dichotomous key, enabling placement, baiting and monitoring of Lindgren Funnel, sugar bait, IPM Tech\npanel and purple panel insect traps.\nOperated and maintained PDA owned 4x4 pickup truck and Panasonic Toughbook computer with Global Mapper and Microsoft Office\nsoftware.\nTrail Steward and Workshop Staff Member\n \nMay 2007\n \nto \nAugust 2007\n \nCompany Name\n \n\u00ef\u00bc\u200b \nCity\n \n, \nState\nTrail maintenance of Keystone College's 160-acre Woodland Campus and Lake Manataka Environmental Field Station, hazardous tree removal\nand firewood harvest.\nProvided field support at Watershed Explorers Workshop performing water quality monitoring of local lakes and streams utilizing Secchi depth,\ntemperature, conductivity, oxygen depth profile, benthic macro invertebrates, taxa richness and fish indices.\nEmploying methods of electro fishing, seining and kick nets; collection and identification of macrophytes.\nFlammulated Owl Research Lab Technician\n \nSeptember 1998\n \nto \nJanuary 1999\n \nCompany Name\n \n\u00ef\u00bc\u200b \nCity\n \n, \nState\nLaboratory analysis and documentation of Flammulated Owl prey delivery video, operating video editing equipment. Field data analysis of nest site\nforaging habits to determine regional insectivorous dietary selection, consumption, prey density and diversity.\nOrganized insect collections with stereomicroscope, and invertebrate field guide.\nAnalysis of insect energy content, utilizing caloric centrifuge, to determine caloric requirements of individual nests.\nResults provided support of undergraduate independent study at the University of Nevada-Reno and David P. Arsenault's unpublished thesis for\nthe Degree of Masters of Science in Environmental and Natural Resource Science.\nWildlife Biology Field Assistant\n \nMay 1998\n \nto \nSeptember 1998\n \nCompany Name\n \n\u00ef\u00bc\u200b \nCity\n \n, \nState\nAssisted in avian field surveys utilizing research data analysis to determine the condition of the current population of Flammulated Owls in western\nNew Mexico.\nCollected nest site and microhabitat forest density measurements with Garmin GPS unit, fiberglass tape, spherical densitometer, clinometer,\ntelescoping pinhole camera and video recording equipment during constant monitoring of survey routes along the Continental Divide, New Mexico.\nParticipated in broadcast surveys, observed nest site selection, flight patterns, observed and collected foraging rates and prey selection data, used\ntargeted mist nets to capture, band and take blood samples for DNA fingerprinting, observed nest and brood habits and fledgling success.\nEducation\nCertificate\n \n: \nWetland Delineation and Identification\n \n, \n2012\n \nRutgers, The State University of New Jersey\n \n\u00ef\u00bc\u200b \nCity\n \n, \nState\n \n, \nUS\n \nBachelor of Science\n \n: \nEnvironmental Biology\n \n, \n2011\n \nKeystone College\n \n\u00ef\u00bc\u200b \nCity\n \n, \nState\n \n, \nUS\n \nAffiliations\nKeystone College Eco Club\nNorth American Bird Phenology Program\nCertifications\nAmerican Red Cross First Aid and CPR training\nFEMA Federal Emergency Management Training\nSkills\nSkillful application of bench chemistry in a lab setting by adhering to standard operating procedures.\nAbility to analyze and test basic wet and dry chemistry obtaining qualitative and quantitative chemical measurements.\nCapacity to follow recipes and formulate mixtures based on manufacturer's specifications.\nK",
  "enriched_profile": {
    "fullName": "Environmental Biologist",
    "email": "",
    "phone": "",
    "location": "Pennsylvania, US",
    "linkedin": "",
    "github": "",
    "portfolio": "",
    "summary": "Experienced researcher with expertise in data collection and study. Analytical and detail-oriented. Proficient in Microsoft Office suite and excellent verbal and written communication skills. Knowledgeable about invasive insects and plant hosts.",
    "education": [
      {
        "school": "Rutgers, The State University of New Jersey",
        "degree": "Certificate",
        "field": "Wetland Delineation and Identification",
        "startDate": "2012",
        "endDate": "",
        "gpa": ""
      },
      {
        "school": "Keystone College",
        "degree": "Bachelor of Science",
        "field": "Environmental Biology",
        "startDate": "",
        "endDate": "2011",
        "gpa": ""
      }
    ],
    "experience": [
      {
        "company": "Company Name",
        "position": "Plant Protection and Quarantine Technician",
        "startDate": "May 2011",
        "endDate": "August 2011",
        "description": "Regional specialist independently conducting Asian Long-Horned Beetle and Emerald Ash Borer ground based visual surveys in eight northeastern Pennsylvania counties. Implemented PPQ standards which safeguards agriculture and natural resources from risks associated with plant pests to ensure an abundant, high-quality forest canopy. Employed industry standards effectively collecting forest and insect field data and reporting results in a timely manner."
      },
      {
        "company": "Company Name",
        "position": "Forest Insect Pest Aide I",
        "startDate": "May 2009",
        "endDate": "August 2009",
        "description": "Conducted Emerald Ash Borer, Asian Longhorn Beetle, Sirex Wood wasp and apiarian surveys in Lackawanna County, PA. Accurately identified plant hosts utilizing a dichotomous key, enabling placement, baiting and monitoring of Lindgren Funnel, sugar bait, IPM Tech panel and purple panel insect traps. Operated and maintained PDA owned 4x4 pickup truck and Panasonic Toughbook computer with Global Mapper and Microsoft Office software."
      },
      {
        "company": "Company Name",
        "position": "Forest Insect Pest Aide",
        "startDate": "May 2008",
        "endDate": "August 2008",
        "description": "Conducted Emerald Ash Borer, Asian Longhorn Beetle, Sirex Wood wasp and apiarian surveys in 10 northeastern Pennsylvania counties. Accurately identified plant hosts utilizing a dichotomous key, enabling placement, baiting and monitoring of Lindgren Funnel, sugar bait, IPM Tech panel and purple panel insect traps. Operated and maintained PDA owned 4x4 pickup truck and Panasonic Toughbook computer with Global Mapper and Microsoft Office software."
      },
      {
        "company": "Company Name",
        "position": "Trail Steward and Workshop Staff Member",
        "startDate": "May 2007",
        "endDate": "August 2007",
        "description": "Performed trail maintenance of Keystone College's 160-acre Woodland Campus and Lake Manataka Environmental Field Station, hazardous tree removal and firewood harvest. Provided field support at Watershed Explorers Workshop performing water quality monitoring of local lakes and streams utilizing Secchi depth, temperature, conductivity, oxygen depth profile, benthic macro invertebrates, taxa richness and fish indices. Employing methods of electro fishing, seining and kick nets; collection and identification of macrophytes."
      }
    ],
    "projects": [],
    "skills": [
      "Data Collection",
      "Research",
      "Microsoft Office Suite",
      "Wetland Delineation and Identification",
      "Invasive Insects and Plant Hosts",
      "Field Data Collection",
      "Forest and Insect Field Data Reporting",
      "Industry Standards",
      "Trail Maintenance",
      "Water Quality Monitoring",
      "Flammulated Owl Research",
      "Laboratory Analysis",
      "Field Data Analysis",
      "Insect Collection",
      "Insect Energy Content Analysis",
      "Bench Chemistry",
      "Wet and Dry Chemistry",
      "Recipe Formulation",
      "Technical and Mechanical Ability",
      "Strong Work Ethic",
      "Collaboration",
      "Independent Work"
    ],
    "licenses": []
  }
}